Workbook
Name Slicer_COLLECTION: #N/A
Name Slicer_COUNTRY: #N/A
Name Slicer_MODE: #N/A
Name Slicer_REGION: #N/A
Name Slicer_TYPE: #N/A

Sheet Overview
B2: FY2026 MASTER BUDGET MODEL
B4: This workbook plans FY2026 revenue, cost, and margin from the ground up, by country, collection, and channel, starting from actual 2025 performance and letting you adjust the assumptions to plan for the new fiscal year.
B6: Data
B7: Every gray 'Query Data' cell in this workbook was pulled via Power Query from meridian.db / SQL Server on 2026-07-20. It is correct as of that date, not live. Two source facts, fact_boutique_sales (direct/boutique channel) and fact_sell_in (wholesale shipments), are each merged with their supporting dimensions (store or wholesale customer to geography, SKU to collection, date to month/year), then appended into one consolidated actuals table, tagged by channel. That table is grouped down to Month x Channel x Collection x Country, which is the grain the Model tab works at.
B11: Workbook structure:
B12: Inputs | C12: Every editable assumption in one place: units per country, price and cost per SKU, collection mix by country, planned new store openings for 2026, and the Boutique/Wholesale and Retail/Online channel splits. Blue is input, black is formula, green is cross-sheet link.
B15: Model | C15: Takes 2025 actuals and 2026 Inputs assumptions and builds FY2026 at Type x Collection x Country x Month grain: a statistical shape (FORECAST.ETS, floored at zero) blended with your manual overrides, priced and costed per SKU, rolled into budgeted units, revenue, COGS, and margin.
B18: Income Statement | C18: The Model's output consolidated into a full P&L, 2025 Actual vs 2026 Budget, monthly and quarterly, down to net income.
B19: Summary | C19: Budget sliced interactively by Mode, Collection, Type, Region, and Country. Topline or detailed view without touching the Model tab.
B20: Budget Export | C20: The Model's output reshaped to match fact_budget's schema exactly, splitting each row into its four channel_id values (Boutique/Wholesale x Retail/Online) using each Country/Collection's Channel Mix shares. This table is used at the end of the process to update the Database with the Official Budget for 2026

Sheet Summary
B2: =IF(E5='Income Statement'!D8,"","INPUTS CHANGED - REFRESH PIVOT TABLE") | D2: OVERVIEW | N2: REGIONAL SPLIT
E4: Revenue | F4: vs LY | G4: Margin vs LY | I4: Mix LY | J4: Mix TY | O4: Revenue | P4: vs LY | Q4: Margin vs LY | S4: Mix LY | T4: Mix TY
D5: TOPLINE | E5: =_xlfn.XLOOKUP($D5,Pivot!$A:$A,Pivot!H:H) -> 1.0443122e+09 | F5: =IFERROR(_xlfn.XLOOKUP($D5,Pivot!$A:$A,Pivot!M:M,0),0) -> 0.096060053 | G5: =IFERROR(_xlfn.XLOOKUP($D5,Pivot!$A:$A,Pivot!N:N,0),0) -> 71 bpts | I5: =IFERROR(_xlfn.XLOOKUP($D5,Pivot!$A:$A,Pivot!O:O,0),0) -> 1 | J5: =IFERROR(_xlfn.XLOOKUP($D5,Pivot!$A:$A,Pivot!P:P,0),0) -> 1 | N5: =IFERROR(Pivot!B37,"") -> EMEA | O5: =IFERROR(_xlfn.XLOOKUP($N5,Pivot!$B:$B,Pivot!H:H,0),0) -> 4.9486286e+08 | P5: =IFERROR(_xlfn.XLOOKUP($N5,Pivot!$B:$B,Pivot!M:M,0),0) -> 0.091014936 | Q5: =IFERROR(_xlfn.XLOOKUP($N5,Pivot!$B:$B,Pivot!N:N,0),0) -> 55 bpts | S5: =IFERROR(_xlfn.XLOOKUP($N5,Pivot!$B:$B,Pivot!O:O,0),0) -> 0.47605615 | T5: =IFERROR(_xlfn.XLOOKUP($N5,Pivot!$B:$B,Pivot!P:P,0),0) -> 0.47386488
N6: =IFERROR(Pivot!B38,"") -> APAC | O6: =IFERROR(_xlfn.XLOOKUP($N6,Pivot!$B:$B,Pivot!H:H,0),0) -> 3.097853e+08 | P6: =IFERROR(_xlfn.XLOOKUP($N6,Pivot!$B:$B,Pivot!M:M,0),0) -> 0.10007617 | Q6: =IFERROR(_xlfn.XLOOKUP($N6,Pivot!$B:$B,Pivot!N:N,0),0) -> 90 bpts | S6: =IFERROR(_xlfn.XLOOKUP($N6,Pivot!$B:$B,Pivot!O:O,0),0) -> 0.29555755 | T6: =IFERROR(_xlfn.XLOOKUP($N6,Pivot!$B:$B,Pivot!P:P,0),0) -> 0.29664052
N7: =IFERROR(Pivot!B39,"") -> NA | O7: =IFERROR(_xlfn.XLOOKUP($N7,Pivot!$B:$B,Pivot!H:H,0),0) -> 1.6842559e+08 | P7: =IFERROR(_xlfn.XLOOKUP($N7,Pivot!$B:$B,Pivot!M:M,0),0) -> 0.087231977 | Q7: =IFERROR(_xlfn.XLOOKUP($N7,Pivot!$B:$B,Pivot!N:N,0),0) -> 56 bpts | S7: =IFERROR(_xlfn.XLOOKUP($N7,Pivot!$B:$B,Pivot!O:O,0),0) -> 0.16258852 | T7: =IFERROR(_xlfn.XLOOKUP($N7,Pivot!$B:$B,Pivot!P:P,0),0) -> 0.16127897
E8: Revenue | F8: vs LY | G8: Margin vs LY | I8: Mix LY | J8: Mix TY | N8: =IFERROR(Pivot!B40,"") -> LATAM | O8: =IFERROR(_xlfn.XLOOKUP($N8,Pivot!$B:$B,Pivot!H:H,0),0) -> 71238416 | P8: =IFERROR(_xlfn.XLOOKUP($N8,Pivot!$B:$B,Pivot!M:M,0),0) -> 0.13633664 | Q8: =IFERROR(_xlfn.XLOOKUP($N8,Pivot!$B:$B,Pivot!N:N,0),0) -> 143 bpts | S8: =IFERROR(_xlfn.XLOOKUP($N8,Pivot!$B:$B,Pivot!O:O,0),0) -> 0.065797783 | T8: =IFERROR(_xlfn.XLOOKUP($N8,Pivot!$B:$B,Pivot!P:P,0),0) -> 0.068215634
D9: Wholesale | E9: =IFERROR(_xlfn.XLOOKUP($D9,Pivot!$B:$B,Pivot!H:H,0),0) -> 7.7447927e+08 | F9: =IFERROR(_xlfn.XLOOKUP($D9,Pivot!$B:$B,Pivot!M:M,0),0) -> 0.067665178 | G9: =IFERROR(_xlfn.XLOOKUP($D9,Pivot!$B:$B,Pivot!N:N,0),0) -> 54 bpts | I9: =IFERROR(_xlfn.XLOOKUP($D9,Pivot!$B:$B,Pivot!O:O,0),0) -> 0.76134015 | J9: =IFERROR(_xlfn.XLOOKUP($D9,Pivot!$B:$B,Pivot!P:P,0),0) -> 0.74161663
D10: Boutique | E10: =IFERROR(_xlfn.XLOOKUP($D10,Pivot!$B:$B,Pivot!H:H,0),0) -> 2.6983289e+08 | F10: =IFERROR(_xlfn.XLOOKUP($D10,Pivot!$B:$B,Pivot!M:M,0),0) -> 0.18664152 | G10: =IFERROR(_xlfn.XLOOKUP($D10,Pivot!$B:$B,Pivot!N:N,0),0) -> 25 bpts | I10: =IFERROR(_xlfn.XLOOKUP($D10,Pivot!$B:$B,Pivot!O:O,0),0) -> 0.23865985 | J10: =IFERROR(_xlfn.XLOOKUP($D10,Pivot!$B:$B,Pivot!P:P,0),0) -> 0.25838337 | O10: Revenue | P10: vs LY | Q10: Margin vs LY | S10: Mix LY | T10: Mix TY
N11: =IFERROR(Pivot!B46,"") -> United States | O11: =IFERROR(_xlfn.XLOOKUP($N11,Pivot!$B:$B,Pivot!H:H,0),0) -> 92133696 | P11: =IFERROR(_xlfn.XLOOKUP($N11,Pivot!$B:$B,Pivot!M:M,0),0) -> 0.08783294 | Q11: =IFERROR(_xlfn.XLOOKUP($N11,Pivot!$B:$B,Pivot!N:N,0),0) -> 55 bpts | S11: =IFERROR(_xlfn.XLOOKUP($N11,Pivot!$B:$B,Pivot!O:O,0),0) -> 0.088891514 | T11: =IFERROR(_xlfn.XLOOKUP($N11,Pivot!$B:$B,Pivot!P:P,0),0) -> 0.088224287
E12: Revenue | F12: vs LY | G12: Margin vs LY | I12: Mix LY | J12: Mix TY | N12: =IFERROR(Pivot!B47,"") -> Switzerland | O12: =IFERROR(_xlfn.XLOOKUP($N12,Pivot!$B:$B,Pivot!H:H,0),0) -> 79478848 | P12: =IFERROR(_xlfn.XLOOKUP($N12,Pivot!$B:$B,Pivot!M:M,0),0) -> 0.092765755 | Q12: =IFERROR(_xlfn.XLOOKUP($N12,Pivot!$B:$B,Pivot!N:N,0),0) -> 55 bpts | S12: =IFERROR(_xlfn.XLOOKUP($N12,Pivot!$B:$B,Pivot!O:O,0),0) -> 0.076335843 | T12: =IFERROR(_xlfn.XLOOKUP($N12,Pivot!$B:$B,Pivot!P:P,0),0) -> 0.076106409
D13: Retail | E13: =IFERROR(_xlfn.XLOOKUP($D13,Pivot!$B:$B,Pivot!H:H,0),0) -> 7.6467998e+08 | F13: =IFERROR(_xlfn.XLOOKUP($D13,Pivot!$B:$B,Pivot!M:M,0),0) -> 0.10122784 | G13: =IFERROR(_xlfn.XLOOKUP($D13,Pivot!$B:$B,Pivot!N:N,0),0) -> 74 bpts | I13: =IFERROR(_xlfn.XLOOKUP($D13,Pivot!$B:$B,Pivot!O:O,0),0) -> 0.72879696 | J13: =IFERROR(_xlfn.XLOOKUP($D13,Pivot!$B:$B,Pivot!P:P,0),0) -> 0.73223314 | N13: =IFERROR(Pivot!B48,"") -> United Kingdom | O13: =IFERROR(_xlfn.XLOOKUP($N13,Pivot!$B:$B,Pivot!H:H,0),0) -> 79547549 | P13: =IFERROR(_xlfn.XLOOKUP($N13,Pivot!$B:$B,Pivot!M:M,0),0) -> 0.096283286 | Q13: =IFERROR(_xlfn.XLOOKUP($N13,Pivot!$B:$B,Pivot!N:N,0),0) -> 55 bpts | S13: =IFERROR(_xlfn.XLOOKUP($N13,Pivot!$B:$B,Pivot!O:O,0),0) -> 0.076156684 | T13: =IFERROR(_xlfn.XLOOKUP($N13,Pivot!$B:$B,Pivot!P:P,0),0) -> 0.076172195
D14: Online | E14: =IFERROR(_xlfn.XLOOKUP($D14,Pivot!$B:$B,Pivot!H:H,0),0) -> 2.7963219e+08 | F14: =IFERROR(_xlfn.XLOOKUP($D14,Pivot!$B:$B,Pivot!M:M,0),0) -> 0.082172807 | G14: =IFERROR(_xlfn.XLOOKUP($D14,Pivot!$B:$B,Pivot!N:N,0),0) -> 61 bpts | I14: =IFERROR(_xlfn.XLOOKUP($D14,Pivot!$B:$B,Pivot!O:O,0),0) -> 0.27120304 | J14: =IFERROR(_xlfn.XLOOKUP($D14,Pivot!$B:$B,Pivot!P:P,0),0) -> 0.26776686 | N14: =IFERROR(Pivot!B49,"") -> Germany | O14: =IFERROR(_xlfn.XLOOKUP($N14,Pivot!$B:$B,Pivot!H:H,0),0) -> 75904894 | P14: =IFERROR(_xlfn.XLOOKUP($N14,Pivot!$B:$B,Pivot!M:M,0),0) -> 0.096069509 | Q14: =IFERROR(_xlfn.XLOOKUP($N14,Pivot!$B:$B,Pivot!N:N,0),0) -> 59 bpts | S14: =IFERROR(_xlfn.XLOOKUP($N14,Pivot!$B:$B,Pivot!O:O,0),0) -> 0.072683477 | T14: =IFERROR(_xlfn.XLOOKUP($N14,Pivot!$B:$B,Pivot!P:P,0),0) -> 0.072684104
N15: =IFERROR(Pivot!B50,"") -> Japan | O15: =IFERROR(_xlfn.XLOOKUP($N15,Pivot!$B:$B,Pivot!H:H,0),0) -> 74351402 | P15: =IFERROR(_xlfn.XLOOKUP($N15,Pivot!$B:$B,Pivot!M:M,0),0) -> 0.086274869 | Q15: =IFERROR(_xlfn.XLOOKUP($N15,Pivot!$B:$B,Pivot!N:N,0),0) -> 64 bpts | S15: =IFERROR(_xlfn.XLOOKUP($N15,Pivot!$B:$B,Pivot!O:O,0),0) -> 0.071837869 | T15: =IFERROR(_xlfn.XLOOKUP($N15,Pivot!$B:$B,Pivot!P:P,0),0) -> 0.07119653
E16: Revenue | F16: vs LY | G16: Margin vs LY | I16: Mix LY | J16: Mix TY | N16: =IFERROR(Pivot!B51,"") -> France | O16: =IFERROR(_xlfn.XLOOKUP($N16,Pivot!$B:$B,Pivot!H:H,0),0) -> 71167772 | P16: =IFERROR(_xlfn.XLOOKUP($N16,Pivot!$B:$B,Pivot!M:M,0),0) -> 0.086084972 | Q16: =IFERROR(_xlfn.XLOOKUP($N16,Pivot!$B:$B,Pivot!N:N,0),0) -> 54 bpts | S16: =IFERROR(_xlfn.XLOOKUP($N16,Pivot!$B:$B,Pivot!O:O,0),0) -> 0.068773889 | T16: =IFERROR(_xlfn.XLOOKUP($N16,Pivot!$B:$B,Pivot!P:P,0),0) -> 0.068147988
D17: =IFERROR(Pivot!B22,"") -> Atelier | E17: =IFERROR(_xlfn.XLOOKUP($D17,Pivot!$B:$B,Pivot!H:H,0),0) -> 1.8825674e+08 | F17: =IFERROR(_xlfn.XLOOKUP($D17,Pivot!$B:$B,Pivot!M:M,0),0) -> 0.097934948 | G17: =IFERROR(_xlfn.XLOOKUP($D17,Pivot!$B:$B,Pivot!N:N,0),0) -> 67 bpts | I17: =IFERROR(_xlfn.XLOOKUP($D17,Pivot!$B:$B,Pivot!O:O,0),0) -> 0.17996081 | J17: =IFERROR(_xlfn.XLOOKUP($D17,Pivot!$B:$B,Pivot!P:P,0),0) -> 0.18026865 | N17: =IFERROR(Pivot!B52,"") -> China | O17: =IFERROR(_xlfn.XLOOKUP($N17,Pivot!$B:$B,Pivot!H:H,0),0) -> 68853049 | P17: =IFERROR(_xlfn.XLOOKUP($N17,Pivot!$B:$B,Pivot!M:M,0),0) -> 0.12458861 | Q17: =IFERROR(_xlfn.XLOOKUP($N17,Pivot!$B:$B,Pivot!N:N,0),0) -> 151 bpts | S17: =IFERROR(_xlfn.XLOOKUP($N17,Pivot!$B:$B,Pivot!O:O,0),0) -> 0.064258933 | T17: =IFERROR(_xlfn.XLOOKUP($N17,Pivot!$B:$B,Pivot!P:P,0),0) -> 0.065931483
D18: =IFERROR(Pivot!B23,"") -> Grand Complication | E18: =IFERROR(_xlfn.XLOOKUP($D18,Pivot!$B:$B,Pivot!H:H,0),0) -> 1.6983548e+08 | F18: =IFERROR(_xlfn.XLOOKUP($D18,Pivot!$B:$B,Pivot!M:M,0),0) -> 0.095573067 | G18: =IFERROR(_xlfn.XLOOKUP($D18,Pivot!$B:$B,Pivot!N:N,0),0) -> 66 bpts | I18: =IFERROR(_xlfn.XLOOKUP($D18,Pivot!$B:$B,Pivot!O:O,0),0) -> 0.16270133 | J18: =IFERROR(_xlfn.XLOOKUP($D18,Pivot!$B:$B,Pivot!P:P,0),0) -> 0.16262904 | N18: =IFERROR(Pivot!B53,"") -> Mexico | O18: =IFERROR(_xlfn.XLOOKUP($N18,Pivot!$B:$B,Pivot!H:H,0),0) -> 46863360 | P18: =IFERROR(_xlfn.XLOOKUP($N18,Pivot!$B:$B,Pivot!M:M,0),0) -> 0.086703873 | Q18: =IFERROR(_xlfn.XLOOKUP($N18,Pivot!$B:$B,Pivot!N:N,0),0) -> 57 bpts | S18: =IFERROR(_xlfn.XLOOKUP($N18,Pivot!$B:$B,Pivot!O:O,0),0) -> 0.045261217 | T18: =IFERROR(_xlfn.XLOOKUP($N18,Pivot!$B:$B,Pivot!P:P,0),0) -> 0.044874858
D19: =IFERROR(Pivot!B24,"") -> Celeste | E19: =IFERROR(_xlfn.XLOOKUP($D19,Pivot!$B:$B,Pivot!H:H,0),0) -> 1.5011745e+08 | F19: =IFERROR(_xlfn.XLOOKUP($D19,Pivot!$B:$B,Pivot!M:M,0),0) -> 0.096821085 | G19: =IFERROR(_xlfn.XLOOKUP($D19,Pivot!$B:$B,Pivot!N:N,0),0) -> 61 bpts | I19: =IFERROR(_xlfn.XLOOKUP($D19,Pivot!$B:$B,Pivot!O:O,0),0) -> 0.14364794 | J19: =IFERROR(_xlfn.XLOOKUP($D19,Pivot!$B:$B,Pivot!P:P,0),0) -> 0.14374768 | N19: =IFERROR(Pivot!B54,"") -> UAE | O19: =IFERROR(_xlfn.XLOOKUP($N19,Pivot!$B:$B,Pivot!H:H,0),0) -> 45173303 | P19: =IFERROR(_xlfn.XLOOKUP($N19,Pivot!$B:$B,Pivot!M:M,0),0) -> 0.090190389 | Q19: =IFERROR(_xlfn.XLOOKUP($N19,Pivot!$B:$B,Pivot!N:N,0),0) -> 54 bpts | S19: =IFERROR(_xlfn.XLOOKUP($N19,Pivot!$B:$B,Pivot!O:O,0),0) -> 0.04348941 | T19: =IFERROR(_xlfn.XLOOKUP($N19,Pivot!$B:$B,Pivot!P:P,0),0) -> 0.043256514
D20: =IFERROR(Pivot!B25,"") -> Heritage | E20: =IFERROR(_xlfn.XLOOKUP($D20,Pivot!$B:$B,Pivot!H:H,0),0) -> 1.3310787e+08 | F20: =IFERROR(_xlfn.XLOOKUP($D20,Pivot!$B:$B,Pivot!M:M,0),0) -> 0.09493213 | G20: =IFERROR(_xlfn.XLOOKUP($D20,Pivot!$B:$B,Pivot!N:N,0),0) -> 71 bpts | I20: =IFERROR(_xlfn.XLOOKUP($D20,Pivot!$B:$B,Pivot!O:O,0),0) -> 0.12759115 | J20: =IFERROR(_xlfn.XLOOKUP($D20,Pivot!$B:$B,Pivot!P:P,0),0) -> 0.12745985 | N20: =IFERROR(Pivot!B55,"") -> South Korea | O20: =IFERROR(_xlfn.XLOOKUP($N20,Pivot!$B:$B,Pivot!H:H,0),0) -> 43348060 | P20: =IFERROR(_xlfn.XLOOKUP($N20,Pivot!$B:$B,Pivot!M:M,0),0) -> 0.085022881 | Q20: =IFERROR(_xlfn.XLOOKUP($N20,Pivot!$B:$B,Pivot!N:N,0),0) -> 57 bpts | S20: =IFERROR(_xlfn.XLOOKUP($N20,Pivot!$B:$B,Pivot!O:O,0),0) -> 0.041930958 | T20: =IFERROR(_xlfn.XLOOKUP($N20,Pivot!$B:$B,Pivot!P:P,0),0) -> 0.041508719
D21: =IFERROR(Pivot!B26,"") -> Lumina | E21: =IFERROR(_xlfn.XLOOKUP($D21,Pivot!$B:$B,Pivot!H:H,0),0) -> 1.0227366e+08 | F21: =IFERROR(_xlfn.XLOOKUP($D21,Pivot!$B:$B,Pivot!M:M,0),0) -> 0.095326389 | G21: =IFERROR(_xlfn.XLOOKUP($D21,Pivot!$B:$B,Pivot!N:N,0),0) -> 65 bpts | I21: =IFERROR(_xlfn.XLOOKUP($D21,Pivot!$B:$B,Pivot!O:O,0),0) -> 0.097999591 | J21: =IFERROR(_xlfn.XLOOKUP($D21,Pivot!$B:$B,Pivot!P:P,0),0) -> 0.097933993 | N21: =IFERROR(Pivot!B56,"") -> Brazil | O21: =IFERROR(_xlfn.XLOOKUP($N21,Pivot!$B:$B,Pivot!H:H,0),0) -> 39604826 | P21: =IFERROR(_xlfn.XLOOKUP($N21,Pivot!$B:$B,Pivot!M:M,0),0) -> 0.19133061 | Q21: =IFERROR(_xlfn.XLOOKUP($N21,Pivot!$B:$B,Pivot!N:N,0),0) -> 220 bpts | S21: =IFERROR(_xlfn.XLOOKUP($N21,Pivot!$B:$B,Pivot!O:O,0),0) -> 0.034891515 | T21: =IFERROR(_xlfn.XLOOKUP($N21,Pivot!$B:$B,Pivot!P:P,0),0) -> 0.037924318
D22: =IFERROR(Pivot!B27,"") -> Nautique | E22: =IFERROR(_xlfn.XLOOKUP($D22,Pivot!$B:$B,Pivot!H:H,0),0) -> 87971574 | F22: =IFERROR(_xlfn.XLOOKUP($D22,Pivot!$B:$B,Pivot!M:M,0),0) -> 0.093541517 | G22: =IFERROR(_xlfn.XLOOKUP($D22,Pivot!$B:$B,Pivot!N:N,0),0) -> 73 bpts | I22: =IFERROR(_xlfn.XLOOKUP($D22,Pivot!$B:$B,Pivot!O:O,0),0) -> 0.084432782 | J22: =IFERROR(_xlfn.XLOOKUP($D22,Pivot!$B:$B,Pivot!P:P,0),0) -> 0.084238772 | N22: =IFERROR(Pivot!B57,"") -> Hong Kong | O22: =IFERROR(_xlfn.XLOOKUP($N22,Pivot!$B:$B,Pivot!H:H,0),0) -> 37213204 | P22: =IFERROR(_xlfn.XLOOKUP($N22,Pivot!$B:$B,Pivot!M:M,0),0) -> 0.097369051 | Q22: =IFERROR(_xlfn.XLOOKUP($N22,Pivot!$B:$B,Pivot!N:N,0),0) -> 58 bpts | S22: =IFERROR(_xlfn.XLOOKUP($N22,Pivot!$B:$B,Pivot!O:O,0),0) -> 0.03559167 | T22: =IFERROR(_xlfn.XLOOKUP($N22,Pivot!$B:$B,Pivot!P:P,0),0) -> 0.035634177
D23: =IFERROR(Pivot!B28,"") -> Sportivo | E23: =IFERROR(_xlfn.XLOOKUP($D23,Pivot!$B:$B,Pivot!H:H,0),0) -> 86284486 | F23: =IFERROR(_xlfn.XLOOKUP($D23,Pivot!$B:$B,Pivot!M:M,0),0) -> 0.096890948 | G23: =IFERROR(_xlfn.XLOOKUP($D23,Pivot!$B:$B,Pivot!N:N,0),0) -> 88 bpts | I23: =IFERROR(_xlfn.XLOOKUP($D23,Pivot!$B:$B,Pivot!O:O,0),0) -> 0.082560684 | J23: =IFERROR(_xlfn.XLOOKUP($D23,Pivot!$B:$B,Pivot!P:P,0),0) -> 0.082623271 | N23: =IFERROR(Pivot!B58,"") -> Netherlands | O23: =IFERROR(_xlfn.XLOOKUP($N23,Pivot!$B:$B,Pivot!H:H,0),0) -> 35176261 | P23: =IFERROR(_xlfn.XLOOKUP($N23,Pivot!$B:$B,Pivot!M:M,0),0) -> 0.086111064 | Q23: =IFERROR(_xlfn.XLOOKUP($N23,Pivot!$B:$B,Pivot!N:N,0),0) -> 54 bpts | S23: =IFERROR(_xlfn.XLOOKUP($N23,Pivot!$B:$B,Pivot!O:O,0),0) -> 0.033992214 | T23: =IFERROR(_xlfn.XLOOKUP($N23,Pivot!$B:$B,Pivot!P:P,0),0) -> 0.033683665
D24: =IFERROR(Pivot!B29,"") -> Terra | E24: =IFERROR(_xlfn.XLOOKUP($D24,Pivot!$B:$B,Pivot!H:H,0),0) -> 50051302 | F24: =IFERROR(_xlfn.XLOOKUP($D24,Pivot!$B:$B,Pivot!M:M,0),0) -> 0.097987764 | G24: =IFERROR(_xlfn.XLOOKUP($D24,Pivot!$B:$B,Pivot!N:N,0),0) -> 84 bpts | I24: =IFERROR(_xlfn.XLOOKUP($D24,Pivot!$B:$B,Pivot!O:O,0),0) -> 0.047843385 | J24: =IFERROR(_xlfn.XLOOKUP($D24,Pivot!$B:$B,Pivot!P:P,0),0) -> 0.04792753 | N24: =IFERROR(Pivot!B59,"") -> Italy | O24: =IFERROR(_xlfn.XLOOKUP($N24,Pivot!$B:$B,Pivot!H:H,0),0) -> 32110359 | P24: =IFERROR(_xlfn.XLOOKUP($N24,Pivot!$B:$B,Pivot!M:M,0),0) -> 0.092314649 | Q24: =IFERROR(_xlfn.XLOOKUP($N24,Pivot!$B:$B,Pivot!N:N,0),0) -> 51 bpts | S24: =IFERROR(_xlfn.XLOOKUP($N24,Pivot!$B:$B,Pivot!O:O,0),0) -> 0.030853285 | T24: =IFERROR(_xlfn.XLOOKUP($N24,Pivot!$B:$B,Pivot!P:P,0),0) -> 0.030747855
D25: =IFERROR(Pivot!B30,"") -> Meridian Classic | E25: =IFERROR(_xlfn.XLOOKUP($D25,Pivot!$B:$B,Pivot!H:H,0),0) -> 43126677 | F25: =IFERROR(_xlfn.XLOOKUP($D25,Pivot!$B:$B,Pivot!M:M,0),0) -> 0.092692426 | G25: =IFERROR(_xlfn.XLOOKUP($D25,Pivot!$B:$B,Pivot!N:N,0),0) -> 87 bpts | I25: =IFERROR(_xlfn.XLOOKUP($D25,Pivot!$B:$B,Pivot!O:O,0),0) -> 0.041424004 | J25: =IFERROR(_xlfn.XLOOKUP($D25,Pivot!$B:$B,Pivot!P:P,0),0) -> 0.04129673 | N25: =IFERROR(Pivot!B60,"") -> Australia | O25: =IFERROR(_xlfn.XLOOKUP($N25,Pivot!$B:$B,Pivot!H:H,0),0) -> 30718394 | P25: =IFERROR(_xlfn.XLOOKUP($N25,Pivot!$B:$B,Pivot!M:M,0),0) -> 0.094645885 | Q25: =IFERROR(_xlfn.XLOOKUP($N25,Pivot!$B:$B,Pivot!N:N,0),0) -> 56 bpts | S25: =IFERROR(_xlfn.XLOOKUP($N25,Pivot!$B:$B,Pivot!O:O,0),0) -> 0.029452955 | T25: =IFERROR(_xlfn.XLOOKUP($N25,Pivot!$B:$B,Pivot!P:P,0),0) -> 0.029414954
D26: =IFERROR(Pivot!B31,"") -> Aventus | E26: =IFERROR(_xlfn.XLOOKUP($D26,Pivot!$B:$B,Pivot!H:H,0),0) -> 33286916 | F26: =IFERROR(_xlfn.XLOOKUP($D26,Pivot!$B:$B,Pivot!M:M,0),0) -> 0.097305006 | G26: =IFERROR(_xlfn.XLOOKUP($D26,Pivot!$B:$B,Pivot!N:N,0),0) -> 91 bpts | I26: =IFERROR(_xlfn.XLOOKUP($D26,Pivot!$B:$B,Pivot!O:O,0),0) -> 0.031838325 | J26: =IFERROR(_xlfn.XLOOKUP($D26,Pivot!$B:$B,Pivot!P:P,0),0) -> 0.031874488 | N26: =IFERROR(Pivot!B61,"") -> Canada | O26: =IFERROR(_xlfn.XLOOKUP($N26,Pivot!$B:$B,Pivot!H:H,0),0) -> 29428532 | P26: =IFERROR(_xlfn.XLOOKUP($N26,Pivot!$B:$B,Pivot!M:M,0),0) -> 0.086193922 | Q26: =IFERROR(_xlfn.XLOOKUP($N26,Pivot!$B:$B,Pivot!N:N,0),0) -> 58 bpts | S26: =IFERROR(_xlfn.XLOOKUP($N26,Pivot!$B:$B,Pivot!O:O,0),0) -> 0.028435786 | T26: =IFERROR(_xlfn.XLOOKUP($N26,Pivot!$B:$B,Pivot!P:P,0),0) -> 0.028179823
N27: =IFERROR(Pivot!B62,"") -> Saudi Arabia | O27: =IFERROR(_xlfn.XLOOKUP($N27,Pivot!$B:$B,Pivot!H:H,0),0) -> 26604173 | P27: =IFERROR(_xlfn.XLOOKUP($N27,Pivot!$B:$B,Pivot!M:M,0),0) -> 0.09151387 | Q27: =IFERROR(_xlfn.XLOOKUP($N27,Pivot!$B:$B,Pivot!N:N,0),0) -> 46 bpts | S27: =IFERROR(_xlfn.XLOOKUP($N27,Pivot!$B:$B,Pivot!O:O,0),0) -> 0.025581413 | T27: =IFERROR(_xlfn.XLOOKUP($N27,Pivot!$B:$B,Pivot!P:P,0),0) -> 0.025475307
N28: =IFERROR(Pivot!B63,"") -> Singapore | O28: =IFERROR(_xlfn.XLOOKUP($N28,Pivot!$B:$B,Pivot!H:H,0),0) -> 25004398 | P28: =IFERROR(_xlfn.XLOOKUP($N28,Pivot!$B:$B,Pivot!M:M,0),0) -> 0.079140806 | Q28: =IFERROR(_xlfn.XLOOKUP($N28,Pivot!$B:$B,Pivot!N:N,0),0) -> 56 bpts | S28: =IFERROR(_xlfn.XLOOKUP($N28,Pivot!$B:$B,Pivot!O:O,0),0) -> 0.024318809 | T28: =IFERROR(_xlfn.XLOOKUP($N28,Pivot!$B:$B,Pivot!P:P,0),0) -> 0.023943413
N29: =IFERROR(Pivot!B64,"") -> Spain | O29: =IFERROR(_xlfn.XLOOKUP($N29,Pivot!$B:$B,Pivot!H:H,0),0) -> 21095213 | P29: =IFERROR(_xlfn.XLOOKUP($N29,Pivot!$B:$B,Pivot!M:M,0),0) -> 0.081145919 | Q29: =IFERROR(_xlfn.XLOOKUP($N29,Pivot!$B:$B,Pivot!N:N,0),0) -> 65 bpts | S29: =IFERROR(_xlfn.XLOOKUP($N29,Pivot!$B:$B,Pivot!O:O,0),0) -> 0.020478758 | T29: =IFERROR(_xlfn.XLOOKUP($N29,Pivot!$B:$B,Pivot!P:P,0),0) -> 0.020200102
N30: =IFERROR(Pivot!B65,"") -> Peru | O30: =IFERROR(_xlfn.XLOOKUP($N30,Pivot!$B:$B,Pivot!H:H,0),0) -> 11872331 | P30: =IFERROR(_xlfn.XLOOKUP($N30,Pivot!$B:$B,Pivot!M:M,0),0) -> 0.073704896 | Q30: =IFERROR(_xlfn.XLOOKUP($N30,Pivot!$B:$B,Pivot!N:N,0),0) -> 78 bpts | S30: =IFERROR(_xlfn.XLOOKUP($N30,Pivot!$B:$B,Pivot!O:O,0),0) -> 0.011605266 | T30: =IFERROR(_xlfn.XLOOKUP($N30,Pivot!$B:$B,Pivot!P:P,0),0) -> 0.011368565
N31: =IFERROR(Pivot!B66,"") -> Vietnam | O31: =IFERROR(_xlfn.XLOOKUP($N31,Pivot!$B:$B,Pivot!H:H,0),0) -> 12312228 | P31: =IFERROR(_xlfn.XLOOKUP($N31,Pivot!$B:$B,Pivot!M:M,0),0) -> 0.30320566 | Q31: =IFERROR(_xlfn.XLOOKUP($N31,Pivot!$B:$B,Pivot!N:N,0),0) -> 275 bpts | S31: =IFERROR(_xlfn.XLOOKUP($N31,Pivot!$B:$B,Pivot!O:O,0),0) -> 0.0099157991 | T31: =IFERROR(_xlfn.XLOOKUP($N31,Pivot!$B:$B,Pivot!P:P,0),0) -> 0.011789797
N32: =IFERROR(Pivot!B67,"") -> Chile | O32: =IFERROR(_xlfn.XLOOKUP($N32,Pivot!$B:$B,Pivot!H:H,0),0) -> 8954264.8 | P32: =IFERROR(_xlfn.XLOOKUP($N32,Pivot!$B:$B,Pivot!M:M,0),0) -> 0.095070348 | Q32: =IFERROR(_xlfn.XLOOKUP($N32,Pivot!$B:$B,Pivot!N:N,0),0) -> 71 bpts | S32: =IFERROR(_xlfn.XLOOKUP($N32,Pivot!$B:$B,Pivot!O:O,0),0) -> 0.0085820676 | T32: =IFERROR(_xlfn.XLOOKUP($N32,Pivot!$B:$B,Pivot!P:P,0),0) -> 0.0085743183
N33: =IFERROR(Pivot!B68,"") -> Taiwan | O33: =IFERROR(_xlfn.XLOOKUP($N33,Pivot!$B:$B,Pivot!H:H,0),0) -> 8349498.7 | P33: =IFERROR(_xlfn.XLOOKUP($N33,Pivot!$B:$B,Pivot!M:M,0),0) -> 0.078238345 | Q33: =IFERROR(_xlfn.XLOOKUP($N33,Pivot!$B:$B,Pivot!N:N,0),0) -> 71 bpts | S33: =IFERROR(_xlfn.XLOOKUP($N33,Pivot!$B:$B,Pivot!O:O,0),0) -> 0.0081273627 | T33: =IFERROR(_xlfn.XLOOKUP($N33,Pivot!$B:$B,Pivot!P:P,0),0) -> 0.0079952135
N34: =IFERROR(Pivot!B69,"") -> Argentina | O34: =IFERROR(_xlfn.XLOOKUP($N34,Pivot!$B:$B,Pivot!H:H,0),0) -> 7486142.6 | P34: =IFERROR(_xlfn.XLOOKUP($N34,Pivot!$B:$B,Pivot!M:M,0),0) -> 0.091932959 | Q34: =IFERROR(_xlfn.XLOOKUP($N34,Pivot!$B:$B,Pivot!N:N,0),0) -> 63 bpts | S34: =IFERROR(_xlfn.XLOOKUP($N34,Pivot!$B:$B,Pivot!O:O,0),0) -> 0.0071955854 | T34: =IFERROR(_xlfn.XLOOKUP($N34,Pivot!$B:$B,Pivot!P:P,0),0) -> 0.0071684912
N35: =IFERROR(Pivot!B70,"") -> Greece | O35: =IFERROR(_xlfn.XLOOKUP($N35,Pivot!$B:$B,Pivot!H:H,0),0) -> 7250288.3 | P35: =IFERROR(_xlfn.XLOOKUP($N35,Pivot!$B:$B,Pivot!M:M,0),0) -> 0.05655251 | Q35: =IFERROR(_xlfn.XLOOKUP($N35,Pivot!$B:$B,Pivot!N:N,0),0) -> 37 bpts | S35: =IFERROR(_xlfn.XLOOKUP($N35,Pivot!$B:$B,Pivot!O:O,0),0) -> 0.0072022502 | T35: =IFERROR(_xlfn.XLOOKUP($N35,Pivot!$B:$B,Pivot!P:P,0),0) -> 0.0069426447
N36: =IFERROR(Pivot!B71,"") -> Belgium | O36: =IFERROR(_xlfn.XLOOKUP($N36,Pivot!$B:$B,Pivot!H:H,0),0) -> 7101675.1 | P36: =IFERROR(_xlfn.XLOOKUP($N36,Pivot!$B:$B,Pivot!M:M,0),0) -> 0.103428 | Q36: =IFERROR(_xlfn.XLOOKUP($N36,Pivot!$B:$B,Pivot!N:N,0),0) -> 57 bpts | S36: =IFERROR(_xlfn.XLOOKUP($N36,Pivot!$B:$B,Pivot!O:O,0),0) -> 0.0067549294 | T36: =IFERROR(_xlfn.XLOOKUP($N36,Pivot!$B:$B,Pivot!P:P,0),0) -> 0.0068003375
N37: =IFERROR(Pivot!B72,"") -> Portugal | O37: =IFERROR(_xlfn.XLOOKUP($N37,Pivot!$B:$B,Pivot!H:H,0),0) -> 6598666.2 | P37: =IFERROR(_xlfn.XLOOKUP($N37,Pivot!$B:$B,Pivot!M:M,0),0) -> 0.097555628 | Q37: =IFERROR(_xlfn.XLOOKUP($N37,Pivot!$B:$B,Pivot!N:N,0),0) -> 47 bpts | S37: =IFERROR(_xlfn.XLOOKUP($N37,Pivot!$B:$B,Pivot!O:O,0),0) -> 0.0063100621 | T37: =IFERROR(_xlfn.XLOOKUP($N37,Pivot!$B:$B,Pivot!P:P,0),0) -> 0.0063186722
N38: =IFERROR(Pivot!B73,"") -> Thailand | O38: =IFERROR(_xlfn.XLOOKUP($N38,Pivot!$B:$B,Pivot!H:H,0),0) -> 5800820.7 | P38: =IFERROR(_xlfn.XLOOKUP($N38,Pivot!$B:$B,Pivot!M:M,0),0) -> -0.056489799 | Q38: =IFERROR(_xlfn.XLOOKUP($N38,Pivot!$B:$B,Pivot!N:N,0),0) -> 35 bpts | S38: =IFERROR(_xlfn.XLOOKUP($N38,Pivot!$B:$B,Pivot!O:O,0),0) -> 0.00645278 | T38: =IFERROR(_xlfn.XLOOKUP($N38,Pivot!$B:$B,Pivot!P:P,0),0) -> 0.0055546808
... N42: =IFERROR(Pivot!B77,"") -> Colombia | O42: =IFERROR(_xlfn.XLOOKUP($N42,Pivot!$B:$B,Pivot!H:H,0),0) -> 3320851.4 | P42: =IFERROR(_xlfn.XLOOKUP($N42,Pivot!$B:$B,Pivot!M:M,0),0) -> -0.010768989 | Q42: =IFERROR(_xlfn.XLOOKUP($N42,Pivot!$B:$B,Pivot!N:N,0),0) -> 59 bpts | S42: =IFERROR(_xlfn.XLOOKUP($N42,Pivot!$B:$B,Pivot!O:O,0),0) -> 0.0035233495 | T42: =IFERROR(_xlfn.XLOOKUP($N42,Pivot!$B:$B,Pivot!P:P,0),0) -> 0.0031799413

Sheet Income Statement
B2: INCOME STATEMENT
C4: 2025 ACTUALS | D4: 2026 BUDGET | E4: % | G4: JAN | H4: FEB | I4: MAR | J4: APR | K4: MAY | L4: JUN | M4: JUL | N4: AUG | O4: SEP | P4: OCT | Q4: NOV | R4: DEC | T4: Q1 | U4: Q2 | V4: Q3 | W4: Q4
B5: Revenue
B6: Boutique Revenue | C6: =SUMIFS(tbl_Model[Revenue2025],tbl_Model[Type],"Boutique") -> 2.2739209e+08 | D6: =SUM(T6,U6,V6,W6) -> 2.6983289e+08 | E6: =D6/C6-1 -> 0.18664152 | G6: =SUMIFS(Model!CF$7:CF$566,tbl_Model[Type],"Boutique") -> 21111266 | H6: =SUMIFS(Model!CG$7:CG$566,tbl_Model[Type],"Boutique") -> 21277833 | I6: =SUMIFS(Model!CH$7:CH$566,tbl_Model[Type],"Boutique") -> 21673857 | J6: =SUMIFS(Model!CI$7:CI$566,tbl_Model[Type],"Boutique") -> 21642805 | K6: =SUMIFS(Model!CJ$7:CJ$566,tbl_Model[Type],"Boutique") -> 22421323 | L6: =SUMIFS(Model!CK$7:CK$566,tbl_Model[Type],"Boutique") -> 22064843 | M6: =SUMIFS(Model!CL$7:CL$566,tbl_Model[Type],"Boutique") -> 22197469 | N6: =SUMIFS(Model!CM$7:CM$566,tbl_Model[Type],"Boutique") -> 22218509 | ... R6: =SUMIFS(Model!CQ$7:CQ$566,tbl_Model[Type],"Boutique") -> 24717392 | T6: =SUM(G6:I6) -> 64062957 | U6: =SUM(J6:L6) -> 66128971 | V6: =SUM(M6:O6) -> 67467387 | W6: =SUM(P6:R6) -> 72173576
B7: Wholesale Revenue | C7: =SUMIFS(tbl_Model[Revenue2025],tbl_Model[Type],"Wholesale") -> 7.2539527e+08 | D7: =SUM(T7,U7,V7,W7) -> 7.7447927e+08 | E7: =D7/C7-1 -> 0.067665178 | G7: =SUMIFS(Model!CF$7:CF$566,tbl_Model[Type],"Wholesale") -> 61271179 | H7: =SUMIFS(Model!CG$7:CG$566,tbl_Model[Type],"Wholesale") -> 60276319 | I7: =SUMIFS(Model!CH$7:CH$566,tbl_Model[Type],"Wholesale") -> 62023811 | J7: =SUMIFS(Model!CI$7:CI$566,tbl_Model[Type],"Wholesale") -> 61542597 | K7: =SUMIFS(Model!CJ$7:CJ$566,tbl_Model[Type],"Wholesale") -> 63624093 | L7: =SUMIFS(Model!CK$7:CK$566,tbl_Model[Type],"Wholesale") -> 63936474 | M7: =SUMIFS(Model!CL$7:CL$566,tbl_Model[Type],"Wholesale") -> 62250855 | N7: =SUMIFS(Model!CM$7:CM$566,tbl_Model[Type],"Wholesale") -> 63075452 | ... R7: =SUMIFS(Model!CQ$7:CQ$566,tbl_Model[Type],"Wholesale") -> 72355199 | T7: =SUM(G7:I7) -> 1.8357131e+08 | U7: =SUM(J7:L7) -> 1.8910316e+08 | V7: =SUM(M7:O7) -> 1.8965225e+08 | W7: =SUM(P7:R7) -> 2.1215255e+08
B8: Total Net Revenue | C8: =SUM(C6:C7) -> 9.5278736e+08 | D8: =SUM(T8,U8,V8,W8) -> 1.0443122e+09 | E8: =D8/C8-1 -> 0.096060053 | G8: =G6+G7 -> 82382445 | H8: =H6+H7 -> 81554153 | I8: =I6+I7 -> 83697668 | J8: =J6+J7 -> 83185401 | K8: =K6+K7 -> 86045416 | L8: =L6+L7 -> 86001317 | M8: =M6+M7 -> 84448323 | N8: =N6+N7 -> 85293961 | ... R8: =R6+R7 -> 97072592 | T8: =SUM(G8:I8) -> 2.4763427e+08 | U8: =SUM(J8:L8) -> 2.5523213e+08 | V8: =SUM(M8:O8) -> 2.5711964e+08 | W8: =SUM(P8:R8) -> 2.8432612e+08
B10: Cost of Goods Sold
B11: Boutique COGS | C11: =SUMIFS(tbl_Model[COGS2025],tbl_Model[Type],"Boutique") -> 55404604 | D11: =SUM(T11,U11,V11,W11) -> 65078881 | E11: =D11/C11-1 -> 0.17461143 | G11: =SUMIFS(Model!CR$7:CR$566,tbl_Model[Type],"Boutique") -> 5098033.4 | H11: =SUMIFS(Model!CS$7:CS$566,tbl_Model[Type],"Boutique") -> 5137872.9 | I11: =SUMIFS(Model!CT$7:CT$566,tbl_Model[Type],"Boutique") -> 5225728.8 | J11: =SUMIFS(Model!CU$7:CU$566,tbl_Model[Type],"Boutique") -> 5218313.1 | K11: =SUMIFS(Model!CV$7:CV$566,tbl_Model[Type],"Boutique") -> 5408822.3 | L11: =SUMIFS(Model!CW$7:CW$566,tbl_Model[Type],"Boutique") -> 5321719.6 | M11: =SUMIFS(Model!CX$7:CX$566,tbl_Model[Type],"Boutique") -> 5349866.6 | N11: =SUMIFS(Model!CY$7:CY$566,tbl_Model[Type],"Boutique") -> 5354404.3 | ... R11: =SUMIFS(Model!DC$7:DC$566,tbl_Model[Type],"Boutique") -> 5958548.1 | T11: =SUM(G11:I11) -> 15461635 | U11: =SUM(J11:L11) -> 15948855 | V11: =SUM(M11:O11) -> 16265582 | W11: =SUM(P11:R11) -> 17402808
B12: Wholesale COGS | C12: =SUMIFS(tbl_Model[COGS2025],tbl_Model[Type],"Wholesale") -> 2.6689593e+08 | D12: =SUM(T12,U12,V12,W12) -> 2.807715e+08 | E12: =D12/C12-1 -> 0.051988713 | G12: =SUMIFS(Model!CR$7:CR$566,tbl_Model[Type],"Wholesale") -> 22220540 | H12: =SUMIFS(Model!CS$7:CS$566,tbl_Model[Type],"Wholesale") -> 21878046 | I12: =SUMIFS(Model!CT$7:CT$566,tbl_Model[Type],"Wholesale") -> 22562637 | J12: =SUMIFS(Model!CU$7:CU$566,tbl_Model[Type],"Wholesale") -> 22326642 | K12: =SUMIFS(Model!CV$7:CV$566,tbl_Model[Type],"Wholesale") -> 23091755 | L12: =SUMIFS(Model!CW$7:CW$566,tbl_Model[Type],"Wholesale") -> 23220122 | M12: =SUMIFS(Model!CX$7:CX$566,tbl_Model[Type],"Wholesale") -> 22548010 | N12: =SUMIFS(Model!CY$7:CY$566,tbl_Model[Type],"Wholesale") -> 22879122 | ... R12: =SUMIFS(Model!DC$7:DC$566,tbl_Model[Type],"Wholesale") -> 26183585 | T12: =SUM(G12:I12) -> 66661223 | U12: =SUM(J12:L12) -> 68638519 | V12: =SUM(M12:O12) -> 68748643 | W12: =SUM(P12:R12) -> 76723117
B13: Total COGS | C13: =SUM(C11:C12) -> 3.2230053e+08 | D13: =SUM(T13,U13,V13,W13) -> 3.4585038e+08 | E13: =D13/C13-1 -> 0.073067993 | G13: =G11+G12 -> 27318573 | H13: =H11+H12 -> 27015919 | I13: =I11+I12 -> 27788366 | J13: =J11+J12 -> 27544955 | K13: =K11+K12 -> 28500577 | L13: =L11+L12 -> 28541842 | M13: =M11+M12 -> 27897876 | N13: =N11+N12 -> 28233526 | ... R13: =R11+R12 -> 32142133 | T13: =SUM(G13:I13) -> 82122858 | U13: =SUM(J13:L13) -> 84587374 | V13: =SUM(M13:O13) -> 85014226 | W13: =SUM(P13:R13) -> 94125926
B15: Gross Profit
B16: Gross Profit | C16: =C8-C13 -> 6.3048682e+08 | D16: =SUM(G16:R16) -> 6.9846178e+08 | E16: =D16/C16-1 -> 0.10781344 | G16: =G8-G13 -> 55063871 | H16: =H8-H13 -> 54538234 | I16: =I8-I13 -> 55909302 | J16: =J8-J13 -> 55640446 | K16: =K8-K13 -> 57544838 | L16: =L8-L13 -> 57459476 | M16: =M8-M13 -> 56550447 | N16: =N8-N13 -> 57060435 | ... R16: =R8-R13 -> 64930459 | T16: =SUM(G16:I16) -> 1.6551141e+08 | U16: =SUM(J16:L16) -> 1.7064476e+08 | V16: =SUM(M16:O16) -> 1.7210541e+08 | W16: =SUM(P16:R16) -> 1.902002e+08
B17: Gross Margin % | C17: =IF(C8=0,0,C16/C8) -> 0.66172879 | D17: =IF(D8=0,0,D16/D8) -> 0.66882471 | E17: =_xlfn.CONCAT(ROUND((D17-C17)*10000,0),"pp") -> 71pp | G17: =IF(G8=0,0,G16/G8) -> 0.66839327 | H17: =IF(H8=0,0,H16/H8) -> 0.66873644 | I17: =IF(I8=0,0,I16/I8) -> 0.66799115 | J17: =IF(J8=0,0,J16/J8) -> 0.66887272 | K17: =IF(K8=0,0,K16/K8) -> 0.66877286 | L17: =IF(L8=0,0,L16/L8) -> 0.6681232 | M17: =IF(M8=0,0,M16/M8) -> 0.66964558 | N17: =IF(N8=0,0,N16/N8) -> 0.66898564 | ... R17: =IF(R8=0,0,R16/R8) -> 0.6688856 | T17: =IF(T8=0,0,T16/T8) -> 0.66837038 | U17: =IF(U8=0,0,U16/U8) -> 0.6685865 | V17: =IF(V8=0,0,V16/V8) -> 0.66935927 | W17: =IF(W8=0,0,W16/W8) -> 0.66895083
B19: Operating Expenses
B20: Ammortisation & Depreciation | C20: =-C8*0.06 -> -57167241 | D20: =SUM(G20:R20) -> -52215608 | E20: =D20/C20-1 -> -0.086616622 | G20: =-G8*0.05 -> -4119122.2 | H20: =-H8*0.05 -> -4077707.6 | I20: =-I8*0.05 -> -4184883.4 | J20: =-J8*0.05 -> -4159270.1 | K20: =-K8*0.05 -> -4302270.8 | L20: =-L8*0.05 -> -4300065.9 | M20: =-M8*0.05 -> -4222416.2 | N20: =-N8*0.05 -> -4264698 | ... R20: =-R8*0.05 -> -4853629.6 | T20: =SUM(G20:I20) -> -12381713 | U20: =SUM(J20:L20) -> -12761607 | V20: =SUM(M20:O20) -> -12855982 | W20: =SUM(P20:R20) -> -14216306
B21: Marketing | C21: =-C8*0.09 -> -85750862 | D21: =SUM(G21:R21) -> -1.0443122e+08 | E21: =D21/C21-1 -> 0.2178445 | G21: =-G8*0.1 -> -8238244.5 | H21: =-H8*0.1 -> -8155415.3 | I21: =-I8*0.1 -> -8369766.8 | J21: =-J8*0.1 -> -8318540.1 | K21: =-K8*0.1 -> -8604541.6 | L21: =-L8*0.1 -> -8600131.7 | M21: =-M8*0.1 -> -8444832.3 | N21: =-N8*0.1 -> -8529396.1 | ... R21: =-R8*0.1 -> -9707259.2 | T21: =SUM(G21:I21) -> -24763427 | U21: =SUM(J21:L21) -> -25523213 | V21: =SUM(M21:O21) -> -25711964 | W21: =SUM(P21:R21) -> -28432612
B22: General & Administrative | C22: =-C8*0.05 -> -47639368 | D22: =SUM(G22:R22) -> -52215608 | E22: =D22/C22-1 -> 0.096060053 | G22: =-G8*0.05 -> -4119122.2 | H22: =-H8*0.05 -> -4077707.6 | I22: =-I8*0.05 -> -4184883.4 | J22: =-J8*0.05 -> -4159270.1 | K22: =-K8*0.05 -> -4302270.8 | L22: =-L8*0.05 -> -4300065.9 | M22: =-M8*0.05 -> -4222416.2 | N22: =-N8*0.05 -> -4264698 | ... R22: =-R8*0.05 -> -4853629.6 | T22: =SUM(G22:I22) -> -12381713 | U22: =SUM(J22:L22) -> -12761607 | V22: =SUM(M22:O22) -> -12855982 | W22: =SUM(P22:R22) -> -14216306
B23: Salaries & Benefits | C23: =-C8*0.2 -> -1.9055747e+08 | D23: =SUM(G23:R23) -> -2.0886243e+08 | E23: =D23/C23-1 -> 0.096060053 | G23: =-G8*0.2 -> -16476489 | H23: =-H8*0.2 -> -16310831 | I23: =-I8*0.2 -> -16739534 | J23: =-J8*0.2 -> -16637080 | K23: =-K8*0.2 -> -17209083 | L23: =-L8*0.2 -> -17200263 | M23: =-M8*0.2 -> -16889665 | N23: =-N8*0.2 -> -17058792 | ... R23: =-R8*0.2 -> -19414518 | T23: =SUM(G23:I23) -> -49526853 | U23: =SUM(J23:L23) -> -51046427 | V23: =SUM(M23:O23) -> -51423928 | W23: =SUM(P23:R23) -> -56865225
B25: Operating Result
B26: Operating Result | C26: =C16+SUM(C20:C23) -> 2.4937188e+08 | D26: =SUM(G26:R26) -> 2.8073691e+08 | E26: =D26/C26-1 -> 0.12577613 | G26: =G16+SUM(G20:G23) -> 22110894 | H26: =H16+SUM(H20:H23) -> 21916573 | I26: =I16+SUM(I20:I23) -> 22430235 | J26: =J16+SUM(J20:J23) -> 22366285 | K26: =K16+SUM(K20:K23) -> 23126672 | L26: =L16+SUM(L20:L23) -> 23058949 | M26: =M16+SUM(M20:M23) -> 22771118 | N26: =N16+SUM(N20:N23) -> 22942851 | ... R26: =R16+SUM(R20:R23) -> 26101422 | T26: =SUM(G26:I26) -> 66457701 | U26: =SUM(J26:L26) -> 68551906 | V26: =SUM(M26:O26) -> 69257557 | W26: =SUM(P26:R26) -> 76469748
B27: Operating Margin % | C27: =IF(C8=0,0,C26/C8) -> 0.26172879 | D27: =IF(D8=0,0,D26/D8) -> 0.26882471 | E27: =_xlfn.CONCAT(ROUND((D27-C27)*10000,0),"pp") -> 71pp | G27: =IF(G8=0,0,G26/G8) -> 0.26839327 | H27: =IF(H8=0,0,H26/H8) -> 0.26873644 | I27: =IF(I8=0,0,I26/I8) -> 0.26799115 | J27: =IF(J8=0,0,J26/J8) -> 0.26887272 | K27: =IF(K8=0,0,K26/K8) -> 0.26877286 | L27: =IF(L8=0,0,L26/L8) -> 0.2681232 | M27: =IF(M8=0,0,M26/M8) -> 0.26964558 | N27: =IF(N8=0,0,N26/N8) -> 0.26898564 | ... R27: =IF(R8=0,0,R26/R8) -> 0.2688856 | T27: =IF(T8=0,0,T26/T8) -> 0.26837038 | U27: =IF(U8=0,0,U26/U8) -> 0.2685865 | V27: =IF(V8=0,0,V26/V8) -> 0.26935927 | W27: =IF(W8=0,0,W26/W8) -> 0.26895083
B29: Interests & Taxes
B30: Net Interests Expenses | C30: =-C26*0.1 -> -24937188 | D30: =-D26*0.09 -> -25266322 | E30: =D30/C30-1 -> 0.013198514 | G30: =-G26*0.09 -> -1989980.4 | H30: =-H26*0.09 -> -1972491.5 | I30: =-I26*0.09 -> -2018721.1 | J30: =-J26*0.09 -> -2012965.7 | K30: =-K26*0.09 -> -2081400.5 | L30: =-L26*0.09 -> -2075305.4 | M30: =-M26*0.09 -> -2049400.6 | N30: =-N26*0.09 -> -2064856.6 | ... R30: =-R26*0.09 -> -2349128 | T30: =-T26*0.09 -> -5981193.1 | U30: =-U26*0.09 -> -6169671.6 | V30: =-V26*0.09 -> -6233180.1 | W30: =-W26*0.09 -> -6882277.3
B31: Corporate Tax | C31: =-(C26-C30)*0.25 -> -68577268 | D31: =-(D26-D30)*0.25 -> -76500809 | E31: =D31/C31-1 -> 0.1155418 | G31: =-(G26-G30)*0.25 -> -6025218.5 | H31: =-(H26-H30)*0.25 -> -5972266.1 | I31: =-(I26-I30)*0.25 -> -6112238.9 | J31: =-(J26-J30)*0.25 -> -6094812.8 | K31: =-(K26-K30)*0.25 -> -6302018.1 | L31: =-(L26-L30)*0.25 -> -6283563.5 | M31: =-(M26-M30)*0.25 -> -6205129.5 | N31: =-(N26-N30)*0.25 -> -6251926.8 | ... R31: =-(R26-R30)*0.25 -> -7112637.4 | T31: =-(T26-T30)*0.25 -> -18109723 | U31: =-(U26-U30)*0.25 -> -18680394 | V31: =-(V26-V30)*0.25 -> -18872684 | W31: =-(W26-W30)*0.25 -> -20838006
B33: Net Income
B34: =B33 -> Net Income | C34: =C26+C30+C31 -> 1.5585743e+08 | D34: =D26+D30+D31 -> 1.7896978e+08 | E34: =D34/C34-1 -> 0.14829165 | G34: =G26+G30+G31 -> 14095695 | H34: =H26+H30+H31 -> 13971815 | I34: =I26+I30+I31 -> 14299275 | J34: =J26+J30+J31 -> 14258507 | K34: =K26+K30+K31 -> 14743253 | L34: =L26+L30+L31 -> 14700080 | M34: =M26+M30+M31 -> 14516587 | N34: =N26+N30+N31 -> 14626067 | ... R34: =R26+R30+R31 -> 16639656 | T34: =T26+T30+T31 -> 42366784 | U34: =U26+U30+U31 -> 43701840 | V34: =V26+V30+V31 -> 44151693 | W34: =W26+W30+W31 -> 48749464
B35: Net Income Margin % | C35: =IF(C8=0,0,C34/C8) -> 0.16358049 | D35: =IF(D8=0,0,D34/D8) -> 0.17137575 | E35: =_xlfn.CONCAT(ROUND((D35-C35)*10000,0),"pp") -> 78pp | G35: =IF(G8=0,0,G34/G8) -> 0.17110071 | H35: =IF(H8=0,0,H34/H8) -> 0.17131948 | I35: =IF(I8=0,0,I34/I8) -> 0.17084436 | J35: =IF(J8=0,0,J34/J8) -> 0.17140636 | K35: =IF(K8=0,0,K34/K8) -> 0.1713427 | L35: =IF(L8=0,0,L34/L8) -> 0.17092854 | M35: =IF(M8=0,0,M34/M8) -> 0.17189906 | N35: =IF(N8=0,0,N34/N8) -> 0.17147834 | ... R35: =IF(R8=0,0,R34/R8) -> 0.17141457 | T35: =IF(T8=0,0,T34/T8) -> 0.17108611 | U35: =IF(U8=0,0,U34/U8) -> 0.1712239 | V35: =IF(V8=0,0,V34/V8) -> 0.17171653 | W35: =IF(W8=0,0,W34/W8) -> 0.17145616

Sheet Inputs
B2: INPUTS | AN2: SUPPORTING TABLES
B4: Color Convention
B5: Blue | C5: Manual planning input. Safe and expected to edit. | N5: X | O5: X | T5: X | W5: X | X5: X | AC5: X | AG5: X | AK5: X
B6: Black | C6: Calculated cell. Don't type over these. | AD6: X | AE6: X | AH6: X | AI6: X | AL6: X
B7: Green | C7: Formula that pulls from another tab.
B8: Gray Italic | C8: 2025 actual, reference only, not editable. | I8: X | J8: X | K8: X | L8: X | M8: X | S8: X | AB8: X | AF8: X | AJ8: X | AP8: X | AS8: X
A11: 1 | B11: Units per Country | F11: Price per SKU | Q11: Collection Mix | V11: Planned New Stores 2026 | Z11: Channel Mix — Boutique vs Wholesale split & Retail vs Online | AD11: Boutique vs Wholesale | AH11: Boutique: Retail vs Online | AK11: Wholesale: Retail vs Online | AN11: Regional Grouping | AR11: Wholesale Margin by Country
B12: Country | C12: Units2025Actual | D12: Units2026 | F12: SKU | G12: SKU_name | H12: Collection | I12: ListPrice2023 | J12: ListPrice2024 | K12: ListPrice2025 | L12: StandardCost2025 | M12: Units2025Actual | N12: BudgetedPrice2026 | O12: BudgetedCost2026 | Q12: country | R12: collection | S12: Mix2025Actual | T12: Mix2026 | V12: Country | W12: PlannedOpening | X12: ModeShiftAssumption | Z12: Country | AA12: Collection | AB12: BoutiqueShare_2025Actual | AC12: BoutiqueShare_2026 | AD12: BoutiqueShare_2026_Effective | AE12: WhlsShare_2026_Effective | AF12: BoutiqueRetailShare_2025Actual | AG12: BoutiqueRetailShare_2026 | AH12: BoutiqueRetailShare_2026_Effective | AI12: BoutiqueOnlineShare_2026_Effective | AJ12: WholesaleRetailShare_2025Actual | AK12: WholesaleRetailShare_2026 | AL12: WholesaleOnlineShare_2026 | AN12: Country | AO12: geo_id | AP12: Region | AR12: Country | AS12: WholesaleMarginPct
B13: Argentina | C13: 468 | D13: 490 | F13: SKU0001 | G13: Nautique Rose Gold 40mm Salmon | H13: Nautique | I13: 19917.05 | J13: 20773.48 | K13: 21666.74 | L13: 5667.97 | M13: 488 | N13: 22300 | O13: 5800 | Q13: Argentina | R13: Atelier | S13: 0.08547 | T13: 0.085470085 | V13: Thailand | W13: 1 | X13: 0.25 | Z13: Argentina | AA13: Atelier | AB13: 0.65 | AC13: 0.6825 | AD13: =MIN(1,MAX(0,tbl_ChannelMix[[#This Row],[BoutiqueShare_2026]]+IF(IFERROR(_xlfn.XLOOKUP(tbl_ChannelMix[[#This Row],[Country]],tbl_PlannedNewStores2026[Country],tbl_PlannedNewStores2026[PlannedOpening],0),0)=1,IFERROR(_xlfn.XLOOKUP(tbl_ChannelMix[[#This Row],[Country]],tbl_PlannedNewStores2026[Country],tbl_PlannedNewStores2026[ModeShiftAssumption],0),0),0))) -> 0.6825 | AE13: =1-tbl_ChannelMix[[#This Row],[BoutiqueShare_2026_Effective]] -> 0.3175 | AF13: 0 | AG13: 0 | AH13: =MIN(1,MAX(0,tbl_ChannelMix[[#This Row],[BoutiqueRetailShare_2026]]+IF(IFERROR(_xlfn.XLOOKUP(tbl_ChannelMix[[#This Row],[Country]],tbl_PlannedNewStores2026[Country],tbl_PlannedNewStores2026[PlannedOpening],0),0)=1,IFERROR(_xlfn.XLOOKUP(tbl_ChannelMix[[#This Row],[Country]],tbl_PlannedNewStores2026[Country],tbl_PlannedNewStores2026[ModeShiftAssumption],0),0),0))) -> 0 | AI13: =1-tbl_ChannelMix[[#This Row],[BoutiqueRetailShare_2026_Effective]] -> 1 | AJ13: 1 | AK13: 1 | AL13: =1-tbl_ChannelMix[[#This Row],[WholesaleRetailShare_2026]] -> 0 | AN13: Switzerland | AO13: 1 | AP13: EMEA | AR13: Switzerland | AS13: 0.305
B14: Australia | C14: 2055 | D14: 2160 | F14: SKU0002 | G14: Nautique Titanium 42mm Salmon | H14: Nautique | I14: 13070.56 | J14: 13632.6 | K14: 14218.8 | L14: 3572.8 | M14: 545 | N14: 14600 | O14: 3600 | Q14: Argentina | R14: Nautique | S14: 0.047008 | T14: 0.047008547 | V14: Colombia | W14: 1 | X14: 0.25 | Z14: Australia | AA14: Atelier | AB14: 0.255395 | AC14: 0.26816547 | AD14: =MIN(1,MAX(0,tbl_ChannelMix[[#This Row],[BoutiqueShare_2026]]+IF(IFERROR(_xlfn.XLOOKUP(tbl_ChannelMix[[#This Row],[Country]],tbl_PlannedNewStores2026[Country],tbl_PlannedNewStores2026[PlannedOpening],0),0)=1,IFERROR(_xlfn.XLOOKUP(tbl_ChannelMix[[#This Row],[Country]],tbl_PlannedNewStores2026[Country],tbl_PlannedNewStores2026[ModeShiftAssumption],0),0),0))) -> 0.26816547 | AE14: =1-tbl_ChannelMix[[#This Row],[BoutiqueShare_2026_Effective]] -> 0.73183453 | AF14: 0.436619 | AG14: 0.43661972 | AH14: =MIN(1,MAX(0,tbl_ChannelMix[[#This Row],[BoutiqueRetailShare_2026]]+IF(IFERROR(_xlfn.XLOOKUP(tbl_ChannelMix[[#This Row],[Country]],tbl_PlannedNewStores2026[Country],tbl_PlannedNewStores2026[PlannedOpening],0),0)=1,IFERROR(_xlfn.XLOOKUP(tbl_ChannelMix[[#This Row],[Country]],tbl_PlannedNewStores2026[Country],tbl_PlannedNewStores2026[ModeShiftAssumption],0),0),0))) -> 0.43661972 | AI14: =1-tbl_ChannelMix[[#This Row],[BoutiqueRetailShare_2026_Effective]] -> 0.56338028 | AJ14: 0.628019 | AK14: 0.62801932 | AL14: =1-tbl_ChannelMix[[#This Row],[WholesaleRetailShare_2026]] -> 0.37198068 | AN14: Germany | AO14: 2 | AP14: EMEA | AR14: Germany | AS14: 0.35
B15: Austria | C15: 264 | D15: 280 | F15: SKU0003 | G15: Nautique Two-Tone 44mm Black | H15: Nautique | I15: 14315.38 | J15: 14930.94 | K15: 15572.97 | L15: 4045.02 | M15: 544 | N15: 16000 | O15: 4100 | Q15: Argentina | R15: Aventus | S15: 0.081196 | T15: 0.081196581 | V15: Vietnam | W15: 1 | X15: 0.15 | Z15: Argentina | AA15: Aventus | AB15: 0.315789 | AC15: 0.33157895 | AD15: =MIN(1,MAX(0,tbl_ChannelMix[[#This Row],[BoutiqueShare_2026]]+IF(IFERROR(_xlfn.XLOOKUP(tbl_ChannelMix[[#This Row],[Country]],tbl_PlannedNewStores2026[Country],tbl_PlannedNewStores2026[PlannedOpening],0),0)=1,IFERROR(_xlfn.XLOOKUP(tbl_ChannelMix[[#This Row],[Country]],tbl_PlannedNewStores2026[Country],tbl_PlannedNewStores2026[ModeShiftAssumption],0),0),0))) -> 0.33157895 | AE15: =1-tbl_ChannelMix[[#This Row],[BoutiqueShare_2026_Effective]] -> 0.66842105 | AF15: 0 | AG15: 0 | AH15: =MIN(1,MAX(0,tbl_ChannelMix[[#This Row],[BoutiqueRetailShare_2026]]+IF(IFERROR(_xlfn.XLOOKUP(tbl_ChannelMix[[#This Row],[Country]],tbl_PlannedNewStores2026[Country],tbl_PlannedNewStores2026[PlannedOpening],0),0)=1,IFERROR(_xlfn.XLOOKUP(tbl_ChannelMix[[#This Row],[Country]],tbl_PlannedNewStores2026[Country],tbl_PlannedNewStores2026[ModeShiftAssumption],0),0),0))) -> 0 | AI15: =1-tbl_ChannelMix[[#This Row],[BoutiqueRetailShare_2026_Effective]] -> 1 | AJ15: 1 | AK15: 1 | AL15: =1-tbl_ChannelMix[[#This Row],[WholesaleRetailShare_2026]] -> 0 | AN15: United Kingdom | AO15: 3 | AP15: EMEA | AR15: United Kingdom | AS15: 0.337
B16: Belgium | C16: 508 | D16: 530 | F16: SKU0004 | G16: Nautique Titanium 40mm Green | H16: Nautique | I16: 13070.56 | J16: 13632.6 | K16: 14218.8 | L16: 3658.12 | M16: 552 | N16: 14600 | O16: 3700 | Q16: Argentina | R16: Lumina | S16: 0.09188 | T16: 0.091880342 | V16: Brazil | W16: 1 | X16: 0.075 | Z16: Argentina | AA16: Celeste | AB16: 0.40909 | AC16: 0.42954545 | AD16: =MIN(1,MAX(0,tbl_ChannelMix[[#This Row],[BoutiqueShare_2026]]+IF(IFERROR(_xlfn.XLOOKUP(tbl_ChannelMix[[#This Row],[Country]],tbl_PlannedNewStores2026[Country],tbl_PlannedNewStores2026[PlannedOpening],0),0)=1,IFERROR(_xlfn.XLOOKUP(tbl_ChannelMix[[#This Row],[Country]],tbl_PlannedNewStores2026[Country],tbl_PlannedNewStores2026[ModeShiftAssumption],0),0),0))) -> 0.42954545 | AE16: =1-tbl_ChannelMix[[#This Row],[BoutiqueShare_2026_Effective]] -> 0.57045455 | AF16: 0 | AG16: 0 | AH16: =MIN(1,MAX(0,tbl_ChannelMix[[#This Row],[BoutiqueRetailShare_2026]]+IF(IFERROR(_xlfn.XLOOKUP(tbl_ChannelMix[[#This Row],[Country]],tbl_PlannedNewStores2026[Country],tbl_PlannedNewStores2026[PlannedOpening],0),0)=1,IFERROR(_xlfn.XLOOKUP(tbl_ChannelMix[[#This Row],[Country]],tbl_PlannedNewStores2026[Country],tbl_PlannedNewStores2026[ModeShiftAssumption],0),0),0))) -> 0 | AI16: =1-tbl_ChannelMix[[#This Row],[BoutiqueRetailShare_2026_Effective]] -> 1 | AJ16: 1 | AK16: 1 | AL16: =1-tbl_ChannelMix[[#This Row],[WholesaleRetailShare_2026]] -> 0 | AN16: France | AO16: 4 | AP16: EMEA | AR16: France | AS16: 0.318
B17: Brazil | C17: 2709 | D17: 3000 | F17: SKU0005 | G17: Nautique White Gold 42mm Silver | H17: Nautique | I17: 19917.05 | J17: 20773.48 | K17: 21666.74 | L17: 5782.74 | M17: 561 | N17: 22300 | O17: 5900 | Q17: Argentina | R17: Terra | S17: 0.1047 | T17: 0.10470085 | V17: China | W17: 1 | X17: 0.05 | Z17: Austria | AA17: Atelier | AB17: 0 | AC17: 0 | AD17: =MIN(1,MAX(0,tbl_ChannelMix[[#This Row],[BoutiqueShare_2026]]+IF(IFERROR(_xlfn.XLOOKUP(tbl_ChannelMix[[#This Row],[Country]],tbl_PlannedNewStores2026[Country],tbl_PlannedNewStores2026[PlannedOpening],0),0)=1,IFERROR(_xlfn.XLOOKUP(tbl_ChannelMix[[#This Row],[Country]],tbl_PlannedNewStores2026[Country],tbl_PlannedNewStores2026[ModeShiftAssumption],0),0),0))) -> 0 | AE17: =1-tbl_ChannelMix[[#This Row],[BoutiqueShare_2026_Effective]] -> 1 | AF17: 0.843 | AG17: 0.843 | AH17: =MIN(1,MAX(0,tbl_ChannelMix[[#This Row],[BoutiqueRetailShare_2026]]+IF(IFERROR(_xlfn.XLOOKUP(tbl_ChannelMix[[#This Row],[Country]],tbl_PlannedNewStores2026[Country],tbl_PlannedNewStores2026[PlannedOpening],0),0)=1,IFERROR(_xlfn.XLOOKUP(tbl_ChannelMix[[#This Row],[Country]],tbl_PlannedNewStores2026[Country],tbl_PlannedNewStores2026[ModeShiftAssumption],0),0),0))) -> 0.843 | AI17: =1-tbl_ChannelMix[[#This Row],[BoutiqueRetailShare_2026_Effective]] -> 0.157 | AJ17: 0 | AK17: 0 | AL17: =1-tbl_ChannelMix[[#This Row],[WholesaleRetailShare_2026]] -> 1 | AN17: Italy | AO17: 5 | AP17: EMEA | AR17: Italy | AS17: 0.319
B18: Canada | C18: 1988 | D18: 2090 | F18: SKU0006 | G18: Nautique White Gold 40mm Silver | H18: Nautique | I18: 19917.05 | J18: 20773.48 | K18: 21666.74 | L18: 5795.9 | M18: 496 | N18: 22300 | O18: 5900 | Q18: Argentina | R18: Meridian Classic | S18: 0.079059 | T18: 0.079059829 | V18: PlannedOpening: 1 | Z18: Argentina | AA18: Grand Complication | AB18: 0.537313 | AC18: 0.5641791 | AD18: =MIN(1,MAX(0,tbl_ChannelMix[[#This Row],[BoutiqueShare_2026]]+IF(IFERROR(_xlfn.XLOOKUP(tbl_ChannelMix[[#This Row],[Country]],tbl_PlannedNewStores2026[Country],tbl_PlannedNewStores2026[PlannedOpening],0),0)=1,IFERROR(_xlfn.XLOOKUP(tbl_ChannelMix[[#This Row],[Country]],tbl_PlannedNewStores2026[Country],tbl_PlannedNewStores2026[ModeShiftAssumption],0),0),0))) -> 0.5641791 | AE18: =1-tbl_ChannelMix[[#This Row],[BoutiqueShare_2026_Effective]] -> 0.4358209 | AF18: 0 | AG18: 0 | AH18: =MIN(1,MAX(0,tbl_ChannelMix[[#This Row],[BoutiqueRetailShare_2026]]+IF(IFERROR(_xlfn.XLOOKUP(tbl_ChannelMix[[#This Row],[Country]],tbl_PlannedNewStores2026[Country],tbl_PlannedNewStores2026[PlannedOpening],0),0)=1,IFERROR(_xlfn.XLOOKUP(tbl_ChannelMix[[#This Row],[Country]],tbl_PlannedNewStores2026[Country],tbl_PlannedNewStores2026[ModeShiftAssumption],0),0),0))) -> 0 | AI18: =1-tbl_ChannelMix[[#This Row],[BoutiqueRetailShare_2026_Effective]] -> 1 | AJ18: 1 | AK18: 1 | AL18: =1-tbl_ChannelMix[[#This Row],[WholesaleRetailShare_2026]] -> 0 | AN18: Spain | AO18: 6 | AP18: EMEA | AR18: Spain | AS18: 0.336
B19: Chile | C19: 540 | D19: 570 | F19: SKU0007 | G19: Nautique Titanium 38mm Black | H19: Nautique | I19: 13070.56 | J19: 13632.6 | K19: 14218.8 | L19: 3652.62 | M19: 457 | N19: 14600 | O19: 3700 | Q19: Argentina | R19: Celeste | S19: 0.141025 | T19: 0.14102564 | V19: ModeShiftAssumption: assumed pp increase to Boutique channel | Z19: Argentina | AA19: Heritage | AB19: 0.484848 | AC19: 0.50909091 | AD19: =MIN(1,MAX(0,tbl_ChannelMix[[#This Row],[BoutiqueShare_2026]]+IF(IFERROR(_xlfn.XLOOKUP(tbl_ChannelMix[[#This Row],[Country]],tbl_PlannedNewStores2026[Country],tbl_PlannedNewStores2026[PlannedOpening],0),0)=1,IFERROR(_xlfn.XLOOKUP(tbl_ChannelMix[[#This Row],[Country]],tbl_PlannedNewStores2026[Country],tbl_PlannedNewStores2026[ModeShiftAssumption],0),0),0))) -> 0.50909091 | AE19: =1-tbl_ChannelMix[[#This Row],[BoutiqueShare_2026_Effective]] -> 0.49090909 | AF19: 0 | AG19: 0 | AH19: =MIN(1,MAX(0,tbl_ChannelMix[[#This Row],[BoutiqueRetailShare_2026]]+IF(IFERROR(_xlfn.XLOOKUP(tbl_ChannelMix[[#This Row],[Country]],tbl_PlannedNewStores2026[Country],tbl_PlannedNewStores2026[PlannedOpening],0),0)=1,IFERROR(_xlfn.XLOOKUP(tbl_ChannelMix[[#This Row],[Country]],tbl_PlannedNewStores2026[Country],tbl_PlannedNewStores2026[ModeShiftAssumption],0),0),0))) -> 0 | AI19: =1-tbl_ChannelMix[[#This Row],[BoutiqueRetailShare_2026_Effective]] -> 1 | AJ19: 1 | AK19: 1 | AL19: =1-tbl_ChannelMix[[#This Row],[WholesaleRetailShare_2026]] -> 0 | AN19: Netherlands | AO19: 7 | AP19: EMEA | AR19: Netherlands | AS19: 0.332
B20: China | C20: 4710 | D20: 5000 | F20: SKU0008 | G20: Nautique Titanium 44mm White | H20: Nautique | I20: 13070.56 | J20: 13632.6 | K20: 14218.8 | L20: 3737.09 | M20: 495 | N20: 14600 | O20: 3800 | Q20: Argentina | R20: Heritage | S20: 0.070512 | T20: 0.070512821 | Z20: Belgium | AA20: Atelier | AB20: 0 | AC20: 0 | AD20: =MIN(1,MAX(0,tbl_ChannelMix[[#This Row],[BoutiqueShare_2026]]+IF(IFERROR(_xlfn.XLOOKUP(tbl_ChannelMix[[#This Row],[Country]],tbl_PlannedNewStores2026[Country],tbl_PlannedNewStores2026[PlannedOpening],0),0)=1,IFERROR(_xlfn.XLOOKUP(tbl_ChannelMix[[#This Row],[Country]],tbl_PlannedNewStores2026[Country],tbl_PlannedNewStores2026[ModeShiftAssumption],0),0),0))) -> 0 | AE20: =1-tbl_ChannelMix[[#This Row],[BoutiqueShare_2026_Effective]] -> 1 | AF20: 0.843 | AG20: 0.843 | AH20: =MIN(1,MAX(0,tbl_ChannelMix[[#This Row],[BoutiqueRetailShare_2026]]+IF(IFERROR(_xlfn.XLOOKUP(tbl_ChannelMix[[#This Row],[Country]],tbl_PlannedNewStores2026[Country],tbl_PlannedNewStores2026[PlannedOpening],0),0)=1,IFERROR(_xlfn.XLOOKUP(tbl_ChannelMix[[#This Row],[Country]],tbl_PlannedNewStores2026[Country],tbl_PlannedNewStores2026[ModeShiftAssumption],0),0),0))) -> 0.843 | AI20: =1-tbl_ChannelMix[[#This Row],[BoutiqueRetailShare_2026_Effective]] -> 0.157 | AJ20: 1 | AK20: 1 | AL20: =1-tbl_ChannelMix[[#This Row],[WholesaleRetailShare_2026]] -> 0 | AN20: UAE | AO20: 8 | AP20: EMEA | AR20: UAE | AS20: 0.326
B21: Colombia | C21: 280 | D21: 350 | F21: SKU0009 | G21: Nautique White Gold 40mm Black | H21: Nautique | I21: 19917.05 | J21: 20773.48 | K21: 21666.74 | L21: 5466.87 | M21: 559 | N21: 22300 | O21: 5600 | Q21: Argentina | R21: Sportivo | S21: 0.155982 | T21: 0.15598291 | Z21: Argentina | AA21: Lumina | AB21: 0.44186 | AC21: 0.46395349 | AD21: =MIN(1,MAX(0,tbl_ChannelMix[[#This Row],[BoutiqueShare_2026]]+IF(IFERROR(_xlfn.XLOOKUP(tbl_ChannelMix[[#This Row],[Country]],tbl_PlannedNewStores2026[Country],tbl_PlannedNewStores2026[PlannedOpening],0),0)=1,IFERROR(_xlfn.XLOOKUP(tbl_ChannelMix[[#This Row],[Country]],tbl_PlannedNewStores2026[Country],tbl_PlannedNewStores2026[ModeShiftAssumption],0),0),0))) -> 0.46395349 | AE21: =1-tbl_ChannelMix[[#This Row],[BoutiqueShare_2026_Effective]] -> 0.53604651 | AF21: 0 | AG21: 0 | AH21: =MIN(1,MAX(0,tbl_ChannelMix[[#This Row],[BoutiqueRetailShare_2026]]+IF(IFERROR(_xlfn.XLOOKUP(tbl_ChannelMix[[#This Row],[Country]],tbl_PlannedNewStores2026[Country],tbl_PlannedNewStores2026[PlannedOpening],0),0)=1,IFERROR(_xlfn.XLOOKUP(tbl_ChannelMix[[#This Row],[Country]],tbl_PlannedNewStores2026[Country],tbl_PlannedNewStores2026[ModeShiftAssumption],0),0),0))) -> 0 | AI21: =1-tbl_ChannelMix[[#This Row],[BoutiqueRetailShare_2026_Effective]] -> 1 | AJ21: 1 | AK21: 1 | AL21: =1-tbl_ChannelMix[[#This Row],[WholesaleRetailShare_2026]] -> 0 | AN21: Saudi Arabia | AO21: 9 | AP21: EMEA | AR21: Saudi Arabia | AS21: 0.342
B22: Estonia | C22: 248 | D22: 260 | F22: SKU0010 | G22: Nautique Yellow Gold 42mm Black | H22: Nautique | I22: 19917.05 | J22: 20773.48 | K22: 21666.74 | L22: 5412.89 | M22: 494 | N22: 22300 | O22: 5500 | Q22: Argentina | R22: Grand Complication | S22: 0.143162 | T22: 0.14316239 | Z22: Argentina | AA22: Meridian Classic | AB22: 0.378378 | AC22: 0.3972973 | AD22: =MIN(1,MAX(0,tbl_ChannelMix[[#This Row],[BoutiqueShare_2026]]+IF(IFERROR(_xlfn.XLOOKUP(tbl_ChannelMix[[#This Row],[Country]],tbl_PlannedNewStores2026[Country],tbl_PlannedNewStores2026[PlannedOpening],0),0)=1,IFERROR(_xlfn.XLOOKUP(tbl_ChannelMix[[#This Row],[Country]],tbl_PlannedNewStores2026[Country],tbl_PlannedNewStores2026[ModeShiftAssumption],0),0),0))) -> 0.3972973 | AE22: =1-tbl_ChannelMix[[#This Row],[BoutiqueShare_2026_Effective]] -> 0.6027027 | AF22: 0 | AG22: 0 | AH22: =MIN(1,MAX(0,tbl_ChannelMix[[#This Row],[BoutiqueRetailShare_2026]]+IF(IFERROR(_xlfn.XLOOKUP(tbl_ChannelMix[[#This Row],[Country]],tbl_PlannedNewStores2026[Country],tbl_PlannedNewStores2026[PlannedOpening],0),0)=1,IFERROR(_xlfn.XLOOKUP(tbl_ChannelMix[[#This Row],[Country]],tbl_PlannedNewStores2026[Country],tbl_PlannedNewStores2026[ModeShiftAssumption],0),0),0))) -> 0 | AI22: =1-tbl_ChannelMix[[#This Row],[BoutiqueRetailShare_2026_Effective]] -> 1 | AJ22: 1 | AK22: 1 | AL22: =1-tbl_ChannelMix[[#This Row],[WholesaleRetailShare_2026]] -> 0 | AN22: Belgium | AO22: 10 | AP22: EMEA | AR22: Belgium | AS22: 0.312
B23: France | C23: 4904 | D23: 5150 | F23: SKU0011 | G23: Nautique White Gold 42mm Green | H23: Nautique | I23: 19917.05 | J23: 20773.48 | K23: 21666.74 | L23: 5673.38 | M23: 532 | N23: 22300 | O23: 5800 | Q23: Australia | R23: Celeste | S23: 0.1236 | T23: 0.12360097 | Z23: Brazil | AA23: Atelier | AB23: 0.094512 | AC23: 0.099237805 | AD23: =MIN(1,MAX(0,tbl_ChannelMix[[#This Row],[BoutiqueShare_2026]]+IF(IFERROR(_xlfn.XLOOKUP(tbl_ChannelMix[[#This Row],[Country]],tbl_PlannedNewStores2026[Country],tbl_PlannedNewStores2026[PlannedOpening],0),0)=1,IFERROR(_xlfn.XLOOKUP(tbl_ChannelMix[[#This Row],[Country]],tbl_PlannedNewStores2026[Country],tbl_PlannedNewStores2026[ModeShiftAssumption],0),0),0))) -> 0.1742378 | AE23: =1-tbl_ChannelMix[[#This Row],[BoutiqueShare_2026_Effective]] -> 0.8257622 | AF23: 1 | AG23: 1 | AH23: =MIN(1,MAX(0,tbl_ChannelMix[[#This Row],[BoutiqueRetailShare_2026]]+IF(IFERROR(_xlfn.XLOOKUP(tbl_ChannelMix[[#This Row],[Country]],tbl_PlannedNewStores2026[Country],tbl_PlannedNewStores2026[PlannedOpening],0),0)=1,IFERROR(_xlfn.XLOOKUP(tbl_ChannelMix[[#This Row],[Country]],tbl_PlannedNewStores2026[Country],tbl_PlannedNewStores2026[ModeShiftAssumption],0),0),0))) -> 1 | AI23: =1-tbl_ChannelMix[[#This Row],[BoutiqueRetailShare_2026_Effective]] -> 0 | AJ23: 0.703703 | AK23: 0.7037037 | AL23: =1-tbl_ChannelMix[[#This Row],[WholesaleRetailShare_2026]] -> 0.2962963 | AN23: Austria | AO23: 11 | AP23: EMEA | AR23: Austria | AS23: 0.311
B24: Germany | C24: 5124 | D24: 5380 | F24: SKU0012 | G24: Nautique Steel 38mm Black | H24: Nautique | I24: 12448.15 | J24: 12983.42 | K24: 13541.71 | L24: 3412.18 | M24: 504 | N24: 13900 | O24: 3500 | Q24: Australia | R24: Terra | S24: 0.102189 | T24: 0.10218978 | Z24: Argentina | AA24: Nautique | AB24: 0.590909 | AC24: 0.62045455 | AD24: =MIN(1,MAX(0,tbl_ChannelMix[[#This Row],[BoutiqueShare_2026]]+IF(IFERROR(_xlfn.XLOOKUP(tbl_ChannelMix[[#This Row],[Country]],tbl_PlannedNewStores2026[Country],tbl_PlannedNewStores2026[PlannedOpening],0),0)=1,IFERROR(_xlfn.XLOOKUP(tbl_ChannelMix[[#This Row],[Country]],tbl_PlannedNewStores2026[Country],tbl_PlannedNewStores2026[ModeShiftAssumption],0),0),0))) -> 0.62045455 | AE24: =1-tbl_ChannelMix[[#This Row],[BoutiqueShare_2026_Effective]] -> 0.37954545 | AF24: 0 | AG24: 0 | AH24: =MIN(1,MAX(0,tbl_ChannelMix[[#This Row],[BoutiqueRetailShare_2026]]+IF(IFERROR(_xlfn.XLOOKUP(tbl_ChannelMix[[#This Row],[Country]],tbl_PlannedNewStores2026[Country],tbl_PlannedNewStores2026[PlannedOpening],0),0)=1,IFERROR(_xlfn.XLOOKUP(tbl_ChannelMix[[#This Row],[Country]],tbl_PlannedNewStores2026[Country],tbl_PlannedNewStores2026[ModeShiftAssumption],0),0),0))) -> 0 | AI24: =1-tbl_ChannelMix[[#This Row],[BoutiqueRetailShare_2026_Effective]] -> 1 | AJ24: 1 | AK24: 1 | AL24: =1-tbl_ChannelMix[[#This Row],[WholesaleRetailShare_2026]] -> 0 | AN24: Portugal | AO24: 12 | AP24: EMEA | AR24: Portugal | AS24: 0.309
B25: Greece | C25: 521 | D25: 550 | F25: SKU0013 | G25: Heritage Steel 44mm Black | H25: Heritage | I25: 19971.49 | J25: 20798.31 | K25: 21659.36 | L25: 4930.98 | M25: 844 | N25: 22300 | O25: 5000 | Q25: Australia | R25: Sportivo | S25: 0.108029 | T25: 0.1080292 | Z25: Argentina | AA25: Sportivo | AB25: 0.452054 | AC25: 0.47465753 | AD25: =MIN(1,MAX(0,tbl_ChannelMix[[#This Row],[BoutiqueShare_2026]]+IF(IFERROR(_xlfn.XLOOKUP(tbl_ChannelMix[[#This Row],[Country]],tbl_PlannedNewStores2026[Country],tbl_PlannedNewStores2026[PlannedOpening],0),0)=1,IFERROR(_xlfn.XLOOKUP(tbl_ChannelMix[[#This Row],[Country]],tbl_PlannedNewStores2026[Country],tbl_PlannedNewStores2026[ModeShiftAssumption],0),0),0))) -> 0.47465753 | AE25: =1-tbl_ChannelMix[[#This Row],[BoutiqueShare_2026_Effective]] -> 0.52534247 | AF25: 0 | AG25: 0 | AH25: =MIN(1,MAX(0,tbl_ChannelMix[[#This Row],[BoutiqueRetailShare_2026]]+IF(IFERROR(_xlfn.XLOOKUP(tbl_ChannelMix[[#This Row],[Country]],tbl_PlannedNewStores2026[Country],tbl_PlannedNewStores2026[PlannedOpening],0),0)=1,IFERROR(_xlfn.XLOOKUP(tbl_ChannelMix[[#This Row],[Country]],tbl_PlannedNewStores2026[Country],tbl_PlannedNewStores2026[ModeShiftAssumption],0),0),0))) -> 0 | AI25: =1-tbl_ChannelMix[[#This Row],[BoutiqueRetailShare_2026_Effective]] -> 1 | AJ25: 1 | AK25: 1 | AL25: =1-tbl_ChannelMix[[#This Row],[WholesaleRetailShare_2026]] -> 0 | AN25: Estonia | AO25: 13 | AP25: EMEA | AR25: Estonia | AS25: 0.305
B26: Hong Kong | C26: 2613 | D26: 2740 | F26: SKU0014 | G26: Heritage Steel 40mm Salmon | H26: Heritage | I26: 19971.49 | J26: 20798.31 | K26: 21659.36 | L26: 4713.77 | M26: 757 | N26: 22300 | O26: 4800 | Q26: Australia | R26: Aventus | S26: 0.081265 | T26: 0.081265207 | Z26: Canada | AA26: Atelier | AB26: 0.089843 | AC26: 0.094335938 | AD26: =MIN(1,MAX(0,tbl_ChannelMix[[#This Row],[BoutiqueShare_2026]]+IF(IFERROR(_xlfn.XLOOKUP(tbl_ChannelMix[[#This Row],[Country]],tbl_PlannedNewStores2026[Country],tbl_PlannedNewStores2026[PlannedOpening],0),0)=1,IFERROR(_xlfn.XLOOKUP(tbl_ChannelMix[[#This Row],[Country]],tbl_PlannedNewStores2026[Country],tbl_PlannedNewStores2026[ModeShiftAssumption],0),0),0))) -> 0.094335938 | AE26: =1-tbl_ChannelMix[[#This Row],[BoutiqueShare_2026_Effective]] -> 0.90566406 | AF26: 1 | AG26: 1 | AH26: =MIN(1,MAX(0,tbl_ChannelMix[[#This Row],[BoutiqueRetailShare_2026]]+IF(IFERROR(_xlfn.XLOOKUP(tbl_ChannelMix[[#This Row],[Country]],tbl_PlannedNewStores2026[Country],tbl_PlannedNewStores2026[PlannedOpening],0),0)=1,IFERROR(_xlfn.XLOOKUP(tbl_ChannelMix[[#This Row],[Country]],tbl_PlannedNewStores2026[Country],tbl_PlannedNewStores2026[ModeShiftAssumption],0),0),0))) -> 1 | AI26: =1-tbl_ChannelMix[[#This Row],[BoutiqueRetailShare_2026_Effective]] -> 0 | AJ26: 0.579399 | AK26: 0.57939914 | AL26: =1-tbl_ChannelMix[[#This Row],[WholesaleRetailShare_2026]] -> 0.42060086 | AN26: Greece | AO26: 14 | AP26: EMEA | AR26: Greece | AS26: 0.316
B27: Italy | C27: 2123 | D27: 2230 | F27: SKU0015 | G27: Heritage Two-Tone 36mm Blue | H27: Heritage | I27: 22967.22 | J27: 23918.06 | K27: 24908.27 | L27: 5336.29 | M27: 776 | N27: 25700 | O27: 5400 | Q27: Australia | R27: Nautique | S27: 0.082238 | T27: 0.082238443 | Z27: Argentina | AA27: Terra | AB27: 0.55102 | AC27: 0.57857143 | AD27: =MIN(1,MAX(0,tbl_ChannelMix[[#This Row],[BoutiqueShare_2026]]+IF(IFERROR(_xlfn.XLOOKUP(tbl_ChannelMix[[#This Row],[Country]],tbl_PlannedNewStores2026[Country],tbl_PlannedNewStores2026[PlannedOpening],0),0)=1,IFERROR(_xlfn.XLOOKUP(tbl_ChannelMix[[#This Row],[Country]],tbl_PlannedNewStores2026[Country],tbl_PlannedNewStores2026[ModeShiftAssumption],0),0),0))) -> 0.57857143 | AE27: =1-tbl_ChannelMix[[#This Row],[BoutiqueShare_2026_Effective]] -> 0.42142857 | AF27: 0 | AG27: 0 | AH27: =MIN(1,MAX(0,tbl_ChannelMix[[#This Row],[BoutiqueRetailShare_2026]]+IF(IFERROR(_xlfn.XLOOKUP(tbl_ChannelMix[[#This Row],[Country]],tbl_PlannedNewStores2026[Country],tbl_PlannedNewStores2026[PlannedOpening],0),0)=1,IFERROR(_xlfn.XLOOKUP(tbl_ChannelMix[[#This Row],[Country]],tbl_PlannedNewStores2026[Country],tbl_PlannedNewStores2026[ModeShiftAssumption],0),0),0))) -> 0 | AI27: =1-tbl_ChannelMix[[#This Row],[BoutiqueRetailShare_2026_Effective]] -> 1 | AJ27: 1 | AK27: 1 | AL27: =1-tbl_ChannelMix[[#This Row],[WholesaleRetailShare_2026]] -> 0 | AN27: United States | AO27: 15 | AP27: NA | AR27: United States | AS27: 0.323
B28: Japan | C28: 5228 | D28: 5490 | F28: SKU0016 | G28: Heritage Two-Tone 36mm Green | H28: Heritage | I28: 22967.22 | J28: 23918.06 | K28: 24908.27 | L28: 5488.74 | M28: 838 | N28: 25700 | O28: 5600 | Q28: Australia | R28: Grand Complication | S28: 0.113868 | T28: 0.11386861 | Z28: Chile | AA28: Atelier | AB28: 0.542857 | AC28: 0.57 | AD28: =MIN(1,MAX(0,tbl_ChannelMix[[#This Row],[BoutiqueShare_2026]]+IF(IFERROR(_xlfn.XLOOKUP(tbl_ChannelMix[[#This Row],[Country]],tbl_PlannedNewStores2026[Country],tbl_PlannedNewStores2026[PlannedOpening],0),0)=1,IFERROR(_xlfn.XLOOKUP(tbl_ChannelMix[[#This Row],[Country]],tbl_PlannedNewStores2026[Country],tbl_PlannedNewStores2026[ModeShiftAssumption],0),0),0))) -> 0.57 | AE28: =1-tbl_ChannelMix[[#This Row],[BoutiqueShare_2026_Effective]] -> 0.43 | AF28: 1 | AG28: 1 | AH28: =MIN(1,MAX(0,tbl_ChannelMix[[#This Row],[BoutiqueRetailShare_2026]]+IF(IFERROR(_xlfn.XLOOKUP(tbl_ChannelMix[[#This Row],[Country]],tbl_PlannedNewStores2026[Country],tbl_PlannedNewStores2026[PlannedOpening],0),0)=1,IFERROR(_xlfn.XLOOKUP(tbl_ChannelMix[[#This Row],[Country]],tbl_PlannedNewStores2026[Country],tbl_PlannedNewStores2026[ModeShiftAssumption],0),0),0))) -> 1 | AI28: =1-tbl_ChannelMix[[#This Row],[BoutiqueRetailShare_2026_Effective]] -> 0 | AJ28: 1 | AK28: 1 | AL28: =1-tbl_ChannelMix[[#This Row],[WholesaleRetailShare_2026]] -> 0 | AN28: Canada | AO28: 16 | AP28: NA | AR28: Canada | AS28: 0.315
B29: Malaysia | C29: 293 | D29: 310 | F29: SKU0017 | G29: Heritage Titanium 38mm Salmon | H29: Heritage | I29: 20970.07 | J29: 21838.23 | K29: 22742.33 | L29: 4803.22 | M29: 835 | N29: 23400 | O29: 4900 | Q29: Australia | R29: Heritage | S29: 0.100729 | T29: 0.10072993 | Z29: Australia | AA29: Aventus | AB29: 0.191616 | AC29: 0.2011976 | AD29: =MIN(1,MAX(0,tbl_ChannelMix[[#This Row],[BoutiqueShare_2026]]+IF(IFERROR(_xlfn.XLOOKUP(tbl_ChannelMix[[#This Row],[Country]],tbl_PlannedNewStores2026[Country],tbl_PlannedNewStores2026[PlannedOpening],0),0)=1,IFERROR(_xlfn.XLOOKUP(tbl_ChannelMix[[#This Row],[Country]],tbl_PlannedNewStores2026[Country],tbl_PlannedNewStores2026[ModeShiftAssumption],0),0),0))) -> 0.2011976 | AE29: =1-tbl_ChannelMix[[#This Row],[BoutiqueShare_2026_Effective]] -> 0.7988024 | AF29: 0.4375 | AG29: 0.4375 | AH29: =MIN(1,MAX(0,tbl_ChannelMix[[#This Row],[BoutiqueRetailShare_2026]]+IF(IFERROR(_xlfn.XLOOKUP(tbl_ChannelMix[[#This Row],[Country]],tbl_PlannedNewStores2026[Country],tbl_PlannedNewStores2026[PlannedOpening],0),0)=1,IFERROR(_xlfn.XLOOKUP(tbl_ChannelMix[[#This Row],[Country]],tbl_PlannedNewStores2026[Country],tbl_PlannedNewStores2026[ModeShiftAssumption],0),0),0))) -> 0.4375 | AI29: =1-tbl_ChannelMix[[#This Row],[BoutiqueRetailShare_2026_Effective]] -> 0.5625 | AJ29: 0.659259 | AK29: 0.65925926 | AL29: =1-tbl_ChannelMix[[#This Row],[WholesaleRetailShare_2026]] -> 0.34074074 | AN29: Mexico | AO29: 17 | AP29: NA | AR29: Mexico | AS29: 0.31
B30: Mexico | C30: 3111 | D30: 3270 | F30: SKU0018 | G30: Heritage Steel 42mm Green | H30: Heritage | I30: 19971.49 | J30: 20798.31 | K30: 21659.36 | L30: 4934.25 | M30: 788 | N30: 22300 | O30: 5000 | Q30: Australia | R30: Meridian Classic | S30: 0.076885 | T30: 0.076885645 | Z30: Australia | AA30: Celeste | AB30: 0.200787 | AC30: 0.21082677 | AD30: =MIN(1,MAX(0,tbl_ChannelMix[[#This Row],[BoutiqueShare_2026]]+IF(IFERROR(_xlfn.XLOOKUP(tbl_ChannelMix[[#This Row],[Country]],tbl_PlannedNewStores2026[Country],tbl_PlannedNewStores2026[PlannedOpening],0),0)=1,IFERROR(_xlfn.XLOOKUP(tbl_ChannelMix[[#This Row],[Country]],tbl_PlannedNewStores2026[Country],tbl_PlannedNewStores2026[ModeShiftAssumption],0),0),0))) -> 0.21082677 | AE30: =1-tbl_ChannelMix[[#This Row],[BoutiqueShare_2026_Effective]] -> 0.78917323 | AF30: 0.509803 | AG30: 0.50980392 | AH30: =MIN(1,MAX(0,tbl_ChannelMix[[#This Row],[BoutiqueRetailShare_2026]]+IF(IFERROR(_xlfn.XLOOKUP(tbl_ChannelMix[[#This Row],[Country]],tbl_PlannedNewStores2026[Country],tbl_PlannedNewStores2026[PlannedOpening],0),0)=1,IFERROR(_xlfn.XLOOKUP(tbl_ChannelMix[[#This Row],[Country]],tbl_PlannedNewStores2026[Country],tbl_PlannedNewStores2026[ModeShiftAssumption],0),0),0))) -> 0.50980392 | AI30: =1-tbl_ChannelMix[[#This Row],[BoutiqueRetailShare_2026_Effective]] -> 0.49019608 | AJ30: 0.773399 | AK30: 0.77339901 | AL30: =1-tbl_ChannelMix[[#This Row],[WholesaleRetailShare_2026]] -> 0.22660099 | AN30: Brazil | AO30: 18 | AP30: LATAM | AR30: Brazil | AS30: 0.391
B31: Netherlands | C31: 2517 | D31: 2640 | F31: SKU0019 | G31: Heritage Steel 42mm Blue | H31: Heritage | I31: 19971.49 | J31: 20798.31 | K31: 21659.36 | L31: 4748.54 | M31: 787 | N31: 22300 | O31: 4800 | Q31: Australia | R31: Lumina | S31: 0.075912 | T31: 0.075912409 | Z31: China | AA31: Atelier | AB31: 0.227598 | AC31: 0.23897849 | AD31: =MIN(1,MAX(0,tbl_ChannelMix[[#This Row],[BoutiqueShare_2026]]+IF(IFERROR(_xlfn.XLOOKUP(tbl_ChannelMix[[#This Row],[Country]],tbl_PlannedNewStores2026[Country],tbl_PlannedNewStores2026[PlannedOpening],0),0)=1,IFERROR(_xlfn.XLOOKUP(tbl_ChannelMix[[#This Row],[Country]],tbl_PlannedNewStores2026[Country],tbl_PlannedNewStores2026[ModeShiftAssumption],0),0),0))) -> 0.28897849 | AE31: =1-tbl_ChannelMix[[#This Row],[BoutiqueShare_2026_Effective]] -> 0.71102151 | AF31: 0.440944 | AG31: 0.44094488 | AH31: =MIN(1,MAX(0,tbl_ChannelMix[[#This Row],[BoutiqueRetailShare_2026]]+IF(IFERROR(_xlfn.XLOOKUP(tbl_ChannelMix[[#This Row],[Country]],tbl_PlannedNewStores2026[Country],tbl_PlannedNewStores2026[PlannedOpening],0),0)=1,IFERROR(_xlfn.XLOOKUP(tbl_ChannelMix[[#This Row],[Country]],tbl_PlannedNewStores2026[Country],tbl_PlannedNewStores2026[ModeShiftAssumption],0),0),0))) -> 0.49094488 | AI31: =1-tbl_ChannelMix[[#This Row],[BoutiqueRetailShare_2026_Effective]] -> 0.50905512 | AJ31: 0.651972 | AK31: 0.65197216 | AL31: =1-tbl_ChannelMix[[#This Row],[WholesaleRetailShare_2026]] -> 0.34802784 | AN31: Argentina | AO31: 19 | AP31: LATAM | AR31: Argentina | AS31: 0.391
... B44: Vietnam | C44: 687 | D44: 800 | F44: SKU0032 | G44: Celeste Titanium 42mm Silver | H44: Celeste | I44: 18191.55 | J44: 19052.01 | K44: 19953.17 | L44: 4699.6 | M44: 746 | N44: 20600 | O44: 4800 | Q44: Belgium | R44: Terra | S44: 0.088582 | T44: 0.088582677 | Z44: Greece | AA44: Atelier | AB44: 0 | AC44: 0 | AD44: =MIN(1,MAX(0,tbl_ChannelMix[[#This Row],[BoutiqueShare_2026]]+IF(IFERROR(_xlfn.XLOOKUP(tbl_ChannelMix[[#This Row],[Country]],tbl_PlannedNewStores2026[Country],tbl_PlannedNewStores2026[PlannedOpening],0),0)=1,IFERROR(_xlfn.XLOOKUP(tbl_ChannelMix[[#This Row],[Country]],tbl_PlannedNewStores2026[Country],tbl_PlannedNewStores2026[ModeShiftAssumption],0),0),0))) -> 0 | AE44: =1-tbl_ChannelMix[[#This Row],[BoutiqueShare_2026_Effective]] -> 1 | AF44: 0.843 | AG44: 0.843 | AH44: =MIN(1,MAX(0,tbl_ChannelMix[[#This Row],[BoutiqueRetailShare_2026]]+IF(IFERROR(_xlfn.XLOOKUP(tbl_ChannelMix[[#This Row],[Country]],tbl_PlannedNewStores2026[Country],tbl_PlannedNewStores2026[PlannedOpening],0),0)=1,IFERROR(_xlfn.XLOOKUP(tbl_ChannelMix[[#This Row],[Country]],tbl_PlannedNewStores2026[Country],tbl_PlannedNewStores2026[ModeShiftAssumption],0),0),0))) -> 0.843 | AI44: =1-tbl_ChannelMix[[#This Row],[BoutiqueRetailShare_2026_Effective]] -> 0.157 | AJ44: 0.508771 | AK44: 0.50877193 | AL44: =1-tbl_ChannelMix[[#This Row],[WholesaleRetailShare_2026]] -> 0.49122807 | AN44: Vietnam | AO44: 32 | AP44: APAC | AR44: Vietnam | AS44: 0.363
F45: SKU0033 | G45: Celeste Steel 42mm Blue | H45: Celeste | I45: 17325.29 | J45: 18144.77 | K45: 19003.02 | L45: 4313.94 | M45: 672 | N45: 19600 | O45: 4400 | Q45: Belgium | R45: Heritage | S45: 0.122047 | T45: 0.12204724 | Z45: Brazil | AA45: Celeste | AB45: 0.074168 | AC45: 0.077877238 | AD45: =MIN(1,MAX(0,tbl_ChannelMix[[#This Row],[BoutiqueShare_2026]]+IF(IFERROR(_xlfn.XLOOKUP(tbl_ChannelMix[[#This Row],[Country]],tbl_PlannedNewStores2026[Country],tbl_PlannedNewStores2026[PlannedOpening],0),0)=1,IFERROR(_xlfn.XLOOKUP(tbl_ChannelMix[[#This Row],[Country]],tbl_PlannedNewStores2026[Country],tbl_PlannedNewStores2026[ModeShiftAssumption],0),0),0))) -> 0.15287724 | AE45: =1-tbl_ChannelMix[[#This Row],[BoutiqueShare_2026_Effective]] -> 0.84712276 | AF45: 1 | AG45: 1 | AH45: =MIN(1,MAX(0,tbl_ChannelMix[[#This Row],[BoutiqueRetailShare_2026]]+IF(IFERROR(_xlfn.XLOOKUP(tbl_ChannelMix[[#This Row],[Country]],tbl_PlannedNewStores2026[Country],tbl_PlannedNewStores2026[PlannedOpening],0),0)=1,IFERROR(_xlfn.XLOOKUP(tbl_ChannelMix[[#This Row],[Country]],tbl_PlannedNewStores2026[Country],tbl_PlannedNewStores2026[ModeShiftAssumption],0),0),0))) -> 1 | AI45: =1-tbl_ChannelMix[[#This Row],[BoutiqueRetailShare_2026_Effective]] -> 0 | AJ45: 0.68232 | AK45: 0.68232044 | AL45: =1-tbl_ChannelMix[[#This Row],[WholesaleRetailShare_2026]] -> 0.31767956
A46: 1 | F46: SKU0034 | G46: Aventus Steel 36mm Black | H46: Aventus | I46: 6333.98 | J46: 6651.31 | K46: 6984.54 | L46: 1977.13 | M46: 540 | N46: 7200 | O46: 2000 | Q46: Belgium | R46: Celeste | S46: 0.145669 | T46: 0.14566929 | Z46: Brazil | AA46: Grand Complication | AB46: 0.142335 | AC46: 0.14945255 | AD46: =MIN(1,MAX(0,tbl_ChannelMix[[#This Row],[BoutiqueShare_2026]]+IF(IFERROR(_xlfn.XLOOKUP(tbl_ChannelMix[[#This Row],[Country]],tbl_PlannedNewStores2026[Country],tbl_PlannedNewStores2026[PlannedOpening],0),0)=1,IFERROR(_xlfn.XLOOKUP(tbl_ChannelMix[[#This Row],[Country]],tbl_PlannedNewStores2026[Country],tbl_PlannedNewStores2026[ModeShiftAssumption],0),0),0))) -> 0.22445255 | AE46: =1-tbl_ChannelMix[[#This Row],[BoutiqueShare_2026_Effective]] -> 0.77554745 | AF46: 1 | AG46: 1 | AH46: =MIN(1,MAX(0,tbl_ChannelMix[[#This Row],[BoutiqueRetailShare_2026]]+IF(IFERROR(_xlfn.XLOOKUP(tbl_ChannelMix[[#This Row],[Country]],tbl_PlannedNewStores2026[Country],tbl_PlannedNewStores2026[PlannedOpening],0),0)=1,IFERROR(_xlfn.XLOOKUP(tbl_ChannelMix[[#This Row],[Country]],tbl_PlannedNewStores2026[Country],tbl_PlannedNewStores2026[ModeShiftAssumption],0),0),0))) -> 1 | AI46: =1-tbl_ChannelMix[[#This Row],[BoutiqueRetailShare_2026_Effective]] -> 0 | AJ46: 0.668085 | AK46: 0.66808511 | AL46: =1-tbl_ChannelMix[[#This Row],[WholesaleRetailShare_2026]] -> 0.33191489
F47: SKU0035 | G47: Aventus Titanium 44mm Green | H47: Aventus | I47: 6650.67 | J47: 6983.87 | K47: 7333.76 | L47: 2051.81 | M47: 556 | N47: 7600 | O47: 2100 | Q47: Belgium | R47: Lumina | S47: 0.084645 | T47: 0.084645669 | Z47: Hong Kong | AA47: Atelier | AB47: 0.221453 | AC47: 0.23252595 | AD47: =MIN(1,MAX(0,tbl_ChannelMix[[#This Row],[BoutiqueShare_2026]]+IF(IFERROR(_xlfn.XLOOKUP(tbl_ChannelMix[[#This Row],[Country]],tbl_PlannedNewStores2026[Country],tbl_PlannedNewStores2026[PlannedOpening],0),0)=1,IFERROR(_xlfn.XLOOKUP(tbl_ChannelMix[[#This Row],[Country]],tbl_PlannedNewStores2026[Country],tbl_PlannedNewStores2026[ModeShiftAssumption],0),0),0))) -> 0.23252595 | AE47: =1-tbl_ChannelMix[[#This Row],[BoutiqueShare_2026_Effective]] -> 0.76747405 | AF47: 1 | AG47: 1 | AH47: =MIN(1,MAX(0,tbl_ChannelMix[[#This Row],[BoutiqueRetailShare_2026]]+IF(IFERROR(_xlfn.XLOOKUP(tbl_ChannelMix[[#This Row],[Country]],tbl_PlannedNewStores2026[Country],tbl_PlannedNewStores2026[PlannedOpening],0),0)=1,IFERROR(_xlfn.XLOOKUP(tbl_ChannelMix[[#This Row],[Country]],tbl_PlannedNewStores2026[Country],tbl_PlannedNewStores2026[ModeShiftAssumption],0),0),0))) -> 1 | AI47: =1-tbl_ChannelMix[[#This Row],[BoutiqueRetailShare_2026_Effective]] -> 0 | AJ47: 0.751111 | AK47: 0.75111111 | AL47: =1-tbl_ChannelMix[[#This Row],[WholesaleRetailShare_2026]] -> 0.24888889
F48: SKU0036 | G48: Aventus White Gold 40mm Blue | H48: Aventus | I48: 10134.36 | J48: 10642.09 | K48: 11175.26 | L48: 3288.22 | M48: 515 | N48: 11500 | O48: 3400 | Q48: Belgium | R48: Sportivo | S48: 0.135826 | T48: 0.13582677 | Z48: Brazil | AA48: Heritage | AB48: 0.053003 | AC48: 0.05565371 | AD48: =MIN(1,MAX(0,tbl_ChannelMix[[#This Row],[BoutiqueShare_2026]]+IF(IFERROR(_xlfn.XLOOKUP(tbl_ChannelMix[[#This Row],[Country]],tbl_PlannedNewStores2026[Country],tbl_PlannedNewStores2026[PlannedOpening],0),0)=1,IFERROR(_xlfn.XLOOKUP(tbl_ChannelMix[[#This Row],[Country]],tbl_PlannedNewStores2026[Country],tbl_PlannedNewStores2026[ModeShiftAssumption],0),0),0))) -> 0.13065371 | AE48: =1-tbl_ChannelMix[[#This Row],[BoutiqueShare_2026_Effective]] -> 0.86934629 | AF48: 1 | AG48: 1 | AH48: =MIN(1,MAX(0,tbl_ChannelMix[[#This Row],[BoutiqueRetailShare_2026]]+IF(IFERROR(_xlfn.XLOOKUP(tbl_ChannelMix[[#This Row],[Country]],tbl_PlannedNewStores2026[Country],tbl_PlannedNewStores2026[PlannedOpening],0),0)=1,IFERROR(_xlfn.XLOOKUP(tbl_ChannelMix[[#This Row],[Country]],tbl_PlannedNewStores2026[Country],tbl_PlannedNewStores2026[ModeShiftAssumption],0),0),0))) -> 1 | AI48: =1-tbl_ChannelMix[[#This Row],[BoutiqueRetailShare_2026_Effective]] -> 0 | AJ48: 0.604477 | AK48: 0.60447761 | AL48: =1-tbl_ChannelMix[[#This Row],[WholesaleRetailShare_2026]] -> 0.39552239
F49: SKU0037 | G49: Aventus Titanium 36mm White | H49: Aventus | I49: 6650.67 | J49: 6983.87 | K49: 7333.76 | L49: 2164.36 | M49: 541 | N49: 7600 | O49: 2200 | Q49: Belgium | R49: Atelier | S49: 0.110236 | T49: 0.11023622 | Z49: Brazil | AA49: Lumina | AB49: 0.074626 | AC49: 0.078358209 | AD49: =MIN(1,MAX(0,tbl_ChannelMix[[#This Row],[BoutiqueShare_2026]]+IF(IFERROR(_xlfn.XLOOKUP(tbl_ChannelMix[[#This Row],[Country]],tbl_PlannedNewStores2026[Country],tbl_PlannedNewStores2026[PlannedOpening],0),0)=1,IFERROR(_xlfn.XLOOKUP(tbl_ChannelMix[[#This Row],[Country]],tbl_PlannedNewStores2026[Country],tbl_PlannedNewStores2026[ModeShiftAssumption],0),0),0))) -> 0.15335821 | AE49: =1-tbl_ChannelMix[[#This Row],[BoutiqueShare_2026_Effective]] -> 0.84664179 | AF49: 1 | AG49: 1 | AH49: =MIN(1,MAX(0,tbl_ChannelMix[[#This Row],[BoutiqueRetailShare_2026]]+IF(IFERROR(_xlfn.XLOOKUP(tbl_ChannelMix[[#This Row],[Country]],tbl_PlannedNewStores2026[Country],tbl_PlannedNewStores2026[PlannedOpening],0),0)=1,IFERROR(_xlfn.XLOOKUP(tbl_ChannelMix[[#This Row],[Country]],tbl_PlannedNewStores2026[Country],tbl_PlannedNewStores2026[ModeShiftAssumption],0),0),0))) -> 1 | AI49: =1-tbl_ChannelMix[[#This Row],[BoutiqueRetailShare_2026_Effective]] -> 0 | AJ49: 0.677419 | AK49: 0.67741935 | AL49: =1-tbl_ChannelMix[[#This Row],[WholesaleRetailShare_2026]] -> 0.32258065
F50: SKU0038 | G50: Aventus Rose Gold 42mm Blue | H50: Aventus | I50: 10134.36 | J50: 10642.09 | K50: 11175.26 | L50: 3258.56 | M50: 669 | N50: 11500 | O50: 3300 | Q50: Belgium | R50: Nautique | S50: 0.062992 | T50: 0.062992126 | Z50: Italy | AA50: Atelier | AB50: 0.27234 | AC50: 0.28595745 | AD50: =MIN(1,MAX(0,tbl_ChannelMix[[#This Row],[BoutiqueShare_2026]]+IF(IFERROR(_xlfn.XLOOKUP(tbl_ChannelMix[[#This Row],[Country]],tbl_PlannedNewStores2026[Country],tbl_PlannedNewStores2026[PlannedOpening],0),0)=1,IFERROR(_xlfn.XLOOKUP(tbl_ChannelMix[[#This Row],[Country]],tbl_PlannedNewStores2026[Country],tbl_PlannedNewStores2026[ModeShiftAssumption],0),0),0))) -> 0.28595745 | AE50: =1-tbl_ChannelMix[[#This Row],[BoutiqueShare_2026_Effective]] -> 0.71404255 | AF50: 1 | AG50: 1 | AH50: =MIN(1,MAX(0,tbl_ChannelMix[[#This Row],[BoutiqueRetailShare_2026]]+IF(IFERROR(_xlfn.XLOOKUP(tbl_ChannelMix[[#This Row],[Country]],tbl_PlannedNewStores2026[Country],tbl_PlannedNewStores2026[PlannedOpening],0),0)=1,IFERROR(_xlfn.XLOOKUP(tbl_ChannelMix[[#This Row],[Country]],tbl_PlannedNewStores2026[Country],tbl_PlannedNewStores2026[ModeShiftAssumption],0),0),0))) -> 1 | AI50: =1-tbl_ChannelMix[[#This Row],[BoutiqueRetailShare_2026_Effective]] -> 0 | AJ50: 0.818713 | AK50: 0.81871345 | AL50: =1-tbl_ChannelMix[[#This Row],[WholesaleRetailShare_2026]] -> 0.18128655
F51: SKU0039 | G51: Aventus Yellow Gold 36mm White | H51: Aventus | I51: 10134.36 | J51: 10642.09 | K51: 11175.26 | L51: 3181.36 | M51: 553 | N51: 11500 | O51: 3200 | Q51: Belgium | R51: Aventus | S51: 0.045275 | T51: 0.045275591 | Z51: Brazil | AA51: Meridian Classic | AB51: 0.079545 | AC51: 0.083522727 | AD51: =MIN(1,MAX(0,tbl_ChannelMix[[#This Row],[BoutiqueShare_2026]]+IF(IFERROR(_xlfn.XLOOKUP(tbl_ChannelMix[[#This Row],[Country]],tbl_PlannedNewStores2026[Country],tbl_PlannedNewStores2026[PlannedOpening],0),0)=1,IFERROR(_xlfn.XLOOKUP(tbl_ChannelMix[[#This Row],[Country]],tbl_PlannedNewStores2026[Country],tbl_PlannedNewStores2026[ModeShiftAssumption],0),0),0))) -> 0.15852273 | AE51: =1-tbl_ChannelMix[[#This Row],[BoutiqueShare_2026_Effective]] -> 0.84147727 | AF51: 1 | AG51: 1 | AH51: =MIN(1,MAX(0,tbl_ChannelMix[[#This Row],[BoutiqueRetailShare_2026]]+IF(IFERROR(_xlfn.XLOOKUP(tbl_ChannelMix[[#This Row],[Country]],tbl_PlannedNewStores2026[Country],tbl_PlannedNewStores2026[PlannedOpening],0),0)=1,IFERROR(_xlfn.XLOOKUP(tbl_ChannelMix[[#This Row],[Country]],tbl_PlannedNewStores2026[Country],tbl_PlannedNewStores2026[ModeShiftAssumption],0),0),0))) -> 1 | AI51: =1-tbl_ChannelMix[[#This Row],[BoutiqueRetailShare_2026_Effective]] -> 0 | AJ51: 0.685185 | AK51: 0.68518519 | AL51: =1-tbl_ChannelMix[[#This Row],[WholesaleRetailShare_2026]] -> 0.31481481
F52: SKU0040 | G52: Aventus Yellow Gold 42mm Salmon | H52: Aventus | I52: 10134.36 | J52: 10642.09 | K52: 11175.26 | L52: 3117.7 | M52: 663 | N52: 11500 | O52: 3200 | Q52: Belgium | R52: Grand Complication | S52: 0.106299 | T52: 0.10629921 | Z52: Brazil | AA52: Nautique | AB52: 0.083623 | AC52: 0.087804878 | AD52: =MIN(1,MAX(0,tbl_ChannelMix[[#This Row],[BoutiqueShare_2026]]+IF(IFERROR(_xlfn.XLOOKUP(tbl_ChannelMix[[#This Row],[Country]],tbl_PlannedNewStores2026[Country],tbl_PlannedNewStores2026[PlannedOpening],0),0)=1,IFERROR(_xlfn.XLOOKUP(tbl_ChannelMix[[#This Row],[Country]],tbl_PlannedNewStores2026[Country],tbl_PlannedNewStores2026[ModeShiftAssumption],0),0),0))) -> 0.16280488 | AE52: =1-tbl_ChannelMix[[#This Row],[BoutiqueShare_2026_Effective]] -> 0.83719512 | AF52: 1 | AG52: 1 | AH52: =MIN(1,MAX(0,tbl_ChannelMix[[#This Row],[BoutiqueRetailShare_2026]]+IF(IFERROR(_xlfn.XLOOKUP(tbl_ChannelMix[[#This Row],[Country]],tbl_PlannedNewStores2026[Country],tbl_PlannedNewStores2026[PlannedOpening],0),0)=1,IFERROR(_xlfn.XLOOKUP(tbl_ChannelMix[[#This Row],[Country]],tbl_PlannedNewStores2026[Country],tbl_PlannedNewStores2026[ModeShiftAssumption],0),0),0))) -> 1 | AI52: =1-tbl_ChannelMix[[#This Row],[BoutiqueRetailShare_2026_Effective]] -> 0 | AJ52: 0.703422 | AK52: 0.70342205 | AL52: =1-tbl_ChannelMix[[#This Row],[WholesaleRetailShare_2026]] -> 0.29657795
F53: SKU0041 | G53: Aventus Titanium 40mm Salmon | H53: Aventus | I53: 6650.67 | J53: 6983.87 | K53: 7333.76 | L53: 2065.75 | M53: 475 | N53: 7600 | O53: 2100 | Q53: Brazil | R53: Terra | S53: 0.088962 | T53: 0.088962717 | Z53: Japan | AA53: Atelier | AB53: 0.166139 | AC53: 0.1744462 | AD53: =MIN(1,MAX(0,tbl_ChannelMix[[#This Row],[BoutiqueShare_2026]]+IF(IFERROR(_xlfn.XLOOKUP(tbl_ChannelMix[[#This Row],[Country]],tbl_PlannedNewStores2026[Country],tbl_PlannedNewStores2026[PlannedOpening],0),0)=1,IFERROR(_xlfn.XLOOKUP(tbl_ChannelMix[[#This Row],[Country]],tbl_PlannedNewStores2026[Country],tbl_PlannedNewStores2026[ModeShiftAssumption],0),0),0))) -> 0.1744462 | AE53: =1-tbl_ChannelMix[[#This Row],[BoutiqueShare_2026_Effective]] -> 0.8255538 | AF53: 0.771428 | AG53: 0.77142857 | AH53: =MIN(1,MAX(0,tbl_ChannelMix[[#This Row],[BoutiqueRetailShare_2026]]+IF(IFERROR(_xlfn.XLOOKUP(tbl_ChannelMix[[#This Row],[Country]],tbl_PlannedNewStores2026[Country],tbl_PlannedNewStores2026[PlannedOpening],0),0)=1,IFERROR(_xlfn.XLOOKUP(tbl_ChannelMix[[#This Row],[Country]],tbl_PlannedNewStores2026[Country],tbl_PlannedNewStores2026[ModeShiftAssumption],0),0),0))) -> 0.77142857 | AI53: =1-tbl_ChannelMix[[#This Row],[BoutiqueRetailShare_2026_Effective]] -> 0.22857143 | AJ53: 0.741935 | AK53: 0.74193548 | AL53: =1-tbl_ChannelMix[[#This Row],[WholesaleRetailShare_2026]] -> 0.25806452
F54: SKU0042 | G54: Meridian Classic Two-Tone 44mm Black | H54: Meridian Classic | I54: 6741.76 | J54: 7070.08 | K54: 7414.4 | L54: 2095.76 | M54: 742 | N54: 7600 | O54: 2100 | Q54: Brazil | R54: Heritage | S54: 0.104466 | T54: 0.10446659 | Z54: Brazil | AA54: Sportivo | AB54: 0.092391 | AC54: 0.09701087 | AD54: =MIN(1,MAX(0,tbl_ChannelMix[[#This Row],[BoutiqueShare_2026]]+IF(IFERROR(_xlfn.XLOOKUP(tbl_ChannelMix[[#This Row],[Country]],tbl_PlannedNewStores2026[Country],tbl_PlannedNewStores2026[PlannedOpening],0),0)=1,IFERROR(_xlfn.XLOOKUP(tbl_ChannelMix[[#This Row],[Country]],tbl_PlannedNewStores2026[Country],tbl_PlannedNewStores2026[ModeShiftAssumption],0),0),0))) -> 0.17201087 | AE54: =1-tbl_ChannelMix[[#This Row],[BoutiqueShare_2026_Effective]] -> 0.82798913 | AF54: 1 | AG54: 1 | AH54: =MIN(1,MAX(0,tbl_ChannelMix[[#This Row],[BoutiqueRetailShare_2026]]+IF(IFERROR(_xlfn.XLOOKUP(tbl_ChannelMix[[#This Row],[Country]],tbl_PlannedNewStores2026[Country],tbl_PlannedNewStores2026[PlannedOpening],0),0)=1,IFERROR(_xlfn.XLOOKUP(tbl_ChannelMix[[#This Row],[Country]],tbl_PlannedNewStores2026[Country],tbl_PlannedNewStores2026[ModeShiftAssumption],0),0),0))) -> 1 | AI54: =1-tbl_ChannelMix[[#This Row],[BoutiqueRetailShare_2026_Effective]] -> 0 | AJ54: 0.667664 | AK54: 0.66766467 | AL54: =1-tbl_ChannelMix[[#This Row],[WholesaleRetailShare_2026]] -> 0.33233533
F55: SKU0043 | G55: Meridian Classic Yellow Gold 42mm Salmon | H55: Meridian Classic | I55: 9379.84 | J55: 9836.64 | K55: 10315.68 | L55: 3036.12 | M55: 743 | N55: 10600 | O55: 3100 | Q55: Brazil | R55: Aventus | S55: 0.059062 | T55: 0.059062385 | Z55: Brazil | AA55: Terra | AB55: 0.074688 | AC55: 0.078423237 | AD55: =MIN(1,MAX(0,tbl_ChannelMix[[#This Row],[BoutiqueShare_2026]]+IF(IFERROR(_xlfn.XLOOKUP(tbl_ChannelMix[[#This Row],[Country]],tbl_PlannedNewStores2026[Country],tbl_PlannedNewStores2026[PlannedOpening],0),0)=1,IFERROR(_xlfn.XLOOKUP(tbl_ChannelMix[[#This Row],[Country]],tbl_PlannedNewStores2026[Country],tbl_PlannedNewStores2026[ModeShiftAssumption],0),0),0))) -> 0.15342324 | AE55: =1-tbl_ChannelMix[[#This Row],[BoutiqueShare_2026_Effective]] -> 0.84657676 | AF55: 1 | AG55: 1 | AH55: =MIN(1,MAX(0,tbl_ChannelMix[[#This Row],[BoutiqueRetailShare_2026]]+IF(IFERROR(_xlfn.XLOOKUP(tbl_ChannelMix[[#This Row],[Country]],tbl_PlannedNewStores2026[Country],tbl_PlannedNewStores2026[PlannedOpening],0),0)=1,IFERROR(_xlfn.XLOOKUP(tbl_ChannelMix[[#This Row],[Country]],tbl_PlannedNewStores2026[Country],tbl_PlannedNewStores2026[ModeShiftAssumption],0),0),0))) -> 1 | AI55: =1-tbl_ChannelMix[[#This Row],[BoutiqueRetailShare_2026_Effective]] -> 0 | AJ55: 0.573991 | AK55: 0.57399103 | AL55: =1-tbl_ChannelMix[[#This Row],[WholesaleRetailShare_2026]] -> 0.42600897
F56: SKU0044 | G56: Meridian Classic Yellow Gold 40mm Green | H56: Meridian Classic | I56: 9379.84 | J56: 9836.64 | K56: 10315.68 | L56: 2956.19 | M56: 810 | N56: 10600 | O56: 3000 | Q56: Brazil | R56: Atelier | S56: 0.121077 | T56: 0.12107789 | Z56: Malaysia | AA56: Atelier | AB56: 0 | AC56: 0 | AD56: =MIN(1,MAX(0,tbl_ChannelMix[[#This Row],[BoutiqueShare_2026]]+IF(IFERROR(_xlfn.XLOOKUP(tbl_ChannelMix[[#This Row],[Country]],tbl_PlannedNewStores2026[Country],tbl_PlannedNewStores2026[PlannedOpening],0),0)=1,IFERROR(_xlfn.XLOOKUP(tbl_ChannelMix[[#This Row],[Country]],tbl_PlannedNewStores2026[Country],tbl_PlannedNewStores2026[ModeShiftAssumption],0),0),0))) -> 0 | AE56: =1-tbl_ChannelMix[[#This Row],[BoutiqueShare_2026_Effective]] -> 1 | AF56: 0.843 | AG56: 0.843 | AH56: =MIN(1,MAX(0,tbl_ChannelMix[[#This Row],[BoutiqueRetailShare_2026]]+IF(IFERROR(_xlfn.XLOOKUP(tbl_ChannelMix[[#This Row],[Country]],tbl_PlannedNewStores2026[Country],tbl_PlannedNewStores2026[PlannedOpening],0),0)=1,IFERROR(_xlfn.XLOOKUP(tbl_ChannelMix[[#This Row],[Country]],tbl_PlannedNewStores2026[Country],tbl_PlannedNewStores2026[ModeShiftAssumption],0),0),0))) -> 0.843 | AI56: =1-tbl_ChannelMix[[#This Row],[BoutiqueRetailShare_2026_Effective]] -> 0.157 | AJ56: 1 | AK56: 1 | AL56: =1-tbl_ChannelMix[[#This Row],[WholesaleRetailShare_2026]] -> 0
F57: SKU0045 | G57: Meridian Classic White Gold 40mm Black | H57: Meridian Classic | I57: 9379.84 | J57: 9836.64 | K57: 10315.68 | L57: 2895.81 | M57: 734 | N57: 10600 | O57: 3000 | Q57: Brazil | R57: Nautique | S57: 0.105943 | T57: 0.10594315 | Z57: Canada | AA57: Aventus | AB57: 0.121951 | AC57: 0.12804878 | AD57: =MIN(1,MAX(0,tbl_ChannelMix[[#This Row],[BoutiqueShare_2026]]+IF(IFERROR(_xlfn.XLOOKUP(tbl_ChannelMix[[#This Row],[Country]],tbl_PlannedNewStores2026[Country],tbl_PlannedNewStores2026[PlannedOpening],0),0)=1,IFERROR(_xlfn.XLOOKUP(tbl_ChannelMix[[#This Row],[Country]],tbl_PlannedNewStores2026[Country],tbl_PlannedNewStores2026[ModeShiftAssumption],0),0),0))) -> 0.12804878 | AE57: =1-tbl_ChannelMix[[#This Row],[BoutiqueShare_2026_Effective]] -> 0.87195122 | AF57: 1 | AG57: 1 | AH57: =MIN(1,MAX(0,tbl_ChannelMix[[#This Row],[BoutiqueRetailShare_2026]]+IF(IFERROR(_xlfn.XLOOKUP(tbl_ChannelMix[[#This Row],[Country]],tbl_PlannedNewStores2026[Country],tbl_PlannedNewStores2026[PlannedOpening],0),0)=1,IFERROR(_xlfn.XLOOKUP(tbl_ChannelMix[[#This Row],[Country]],tbl_PlannedNewStores2026[Country],tbl_PlannedNewStores2026[ModeShiftAssumption],0),0),0))) -> 1 | AI57: =1-tbl_ChannelMix[[#This Row],[BoutiqueRetailShare_2026_Effective]] -> 0 | AJ57: 0.574074 | AK57: 0.57407407 | AL57: =1-tbl_ChannelMix[[#This Row],[WholesaleRetailShare_2026]] -> 0.42592593
F58: SKU0046 | G58: Meridian Classic Steel 44mm Salmon | H58: Meridian Classic | I58: 5862.4 | J58: 6147.9 | K58: 6447.3 | L58: 1810.15 | M58: 693 | N58: 6600 | O58: 1800 | Q58: Brazil | R58: Lumina | S58: 0.074197 | T58: 0.074197121 | Z58: Mexico | AA58: Atelier | AB58: 0.117936 | AC58: 0.12383292 | AD58: =MIN(1,MAX(0,tbl_ChannelMix[[#This Row],[BoutiqueShare_2026]]+IF(IFERROR(_xlfn.XLOOKUP(tbl_ChannelMix[[#This Row],[Country]],tbl_PlannedNewStores2026[Country],tbl_PlannedNewStores2026[PlannedOpening],0),0)=1,IFERROR(_xlfn.XLOOKUP(tbl_ChannelMix[[#This Row],[Country]],tbl_PlannedNewStores2026[Country],tbl_PlannedNewStores2026[ModeShiftAssumption],0),0),0))) -> 0.12383292 | AE58: =1-tbl_ChannelMix[[#This Row],[BoutiqueShare_2026_Effective]] -> 0.87616708 | AF58: 0.395833 | AG58: 0.39583333 | AH58: =MIN(1,MAX(0,tbl_ChannelMix[[#This Row],[BoutiqueRetailShare_2026]]+IF(IFERROR(_xlfn.XLOOKUP(tbl_ChannelMix[[#This Row],[Country]],tbl_PlannedNewStores2026[Country],tbl_PlannedNewStores2026[PlannedOpening],0),0)=1,IFERROR(_xlfn.XLOOKUP(tbl_ChannelMix[[#This Row],[Country]],tbl_PlannedNewStores2026[Country],tbl_PlannedNewStores2026[ModeShiftAssumption],0),0),0))) -> 0.39583333 | AI58: =1-tbl_ChannelMix[[#This Row],[BoutiqueRetailShare_2026_Effective]] -> 0.60416667 | AJ58: 0.810584 | AK58: 0.81058496 | AL58: =1-tbl_ChannelMix[[#This Row],[WholesaleRetailShare_2026]] -> 0.18941504
... F113: SKU0101 | G113: Atelier Rose Gold 44mm Salmon | H113: Atelier | I113: 29237.39 | J113: 30637.86 | K113: 32105.41 | L113: 7614.94 | M113: 715 | N113: 33100 | O113: 7800 | Q113: France | R113: Meridian Classic | S113: 0.090946 | T113: 0.090946166 | Z113: France | AA113: Celeste | AB113: 0.128919 | AC113: 0.13536585 | AD113: =MIN(1,MAX(0,tbl_ChannelMix[[#This Row],[BoutiqueShare_2026]]+IF(IFERROR(_xlfn.XLOOKUP(tbl_ChannelMix[[#This Row],[Country]],tbl_PlannedNewStores2026[Country],tbl_PlannedNewStores2026[PlannedOpening],0),0)=1,IFERROR(_xlfn.XLOOKUP(tbl_ChannelMix[[#This Row],[Country]],tbl_PlannedNewStores2026[Country],tbl_PlannedNewStores2026[ModeShiftAssumption],0),0),0))) -> 0.13536585 | AE113: =1-tbl_ChannelMix[[#This Row],[BoutiqueShare_2026_Effective]] -> 0.86463415 | AF113: 0.77027 | AG113: 0.77027027 | AH113: =MIN(1,MAX(0,tbl_ChannelMix[[#This Row],[BoutiqueRetailShare_2026]]+IF(IFERROR(_xlfn.XLOOKUP(tbl_ChannelMix[[#This Row],[Country]],tbl_PlannedNewStores2026[Country],tbl_PlannedNewStores2026[PlannedOpening],0),0)=1,IFERROR(_xlfn.XLOOKUP(tbl_ChannelMix[[#This Row],[Country]],tbl_PlannedNewStores2026[Country],tbl_PlannedNewStores2026[ModeShiftAssumption],0),0),0))) -> 0.77027027 | AI113: =1-tbl_ChannelMix[[#This Row],[BoutiqueRetailShare_2026_Effective]] -> 0.22972973 | AJ113: 0.818 | AK113: 0.818 | AL113: =1-tbl_ChannelMix[[#This Row],[WholesaleRetailShare_2026]] -> 0.182
Q114: France | R114: Nautique | S114: 0.089518 | T114: 0.08951876 | Z114: Belgium | AA114: Lumina | AB114: 0 | AC114: 0 | AD114: =MIN(1,MAX(0,tbl_ChannelMix[[#This Row],[BoutiqueShare_2026]]+IF(IFERROR(_xlfn.XLOOKUP(tbl_ChannelMix[[#This Row],[Country]],tbl_PlannedNewStores2026[Country],tbl_PlannedNewStores2026[PlannedOpening],0),0)=1,IFERROR(_xlfn.XLOOKUP(tbl_ChannelMix[[#This Row],[Country]],tbl_PlannedNewStores2026[Country],tbl_PlannedNewStores2026[ModeShiftAssumption],0),0),0))) -> 0 | AE114: =1-tbl_ChannelMix[[#This Row],[BoutiqueShare_2026_Effective]] -> 1 | AF114: 0.843 | AG114: 0.843 | AH114: =MIN(1,MAX(0,tbl_ChannelMix[[#This Row],[BoutiqueRetailShare_2026]]+IF(IFERROR(_xlfn.XLOOKUP(tbl_ChannelMix[[#This Row],[Country]],tbl_PlannedNewStores2026[Country],tbl_PlannedNewStores2026[PlannedOpening],0),0)=1,IFERROR(_xlfn.XLOOKUP(tbl_ChannelMix[[#This Row],[Country]],tbl_PlannedNewStores2026[Country],tbl_PlannedNewStores2026[ModeShiftAssumption],0),0),0))) -> 0.843 | AI114: =1-tbl_ChannelMix[[#This Row],[BoutiqueRetailShare_2026_Effective]] -> 0.157 | AJ114: 1 | AK114: 1 | AL114: =1-tbl_ChannelMix[[#This Row],[WholesaleRetailShare_2026]] -> 0
Q115: France | R115: Heritage | S115: 0.099102 | T115: 0.099102773 | Z115: France | AA115: Grand Complication | AB115: 0.130357 | AC115: 0.136875 | AD115: =MIN(1,MAX(0,tbl_ChannelMix[[#This Row],[BoutiqueShare_2026]]+IF(IFERROR(_xlfn.XLOOKUP(tbl_ChannelMix[[#This Row],[Country]],tbl_PlannedNewStores2026[Country],tbl_PlannedNewStores2026[PlannedOpening],0),0)=1,IFERROR(_xlfn.XLOOKUP(tbl_ChannelMix[[#This Row],[Country]],tbl_PlannedNewStores2026[Country],tbl_PlannedNewStores2026[ModeShiftAssumption],0),0),0))) -> 0.136875 | AE115: =1-tbl_ChannelMix[[#This Row],[BoutiqueShare_2026_Effective]] -> 0.863125 | AF115: 0.712328 | AG115: 0.71232877 | AH115: =MIN(1,MAX(0,tbl_ChannelMix[[#This Row],[BoutiqueRetailShare_2026]]+IF(IFERROR(_xlfn.XLOOKUP(tbl_ChannelMix[[#This Row],[Country]],tbl_PlannedNewStores2026[Country],tbl_PlannedNewStores2026[PlannedOpening],0),0)=1,IFERROR(_xlfn.XLOOKUP(tbl_ChannelMix[[#This Row],[Country]],tbl_PlannedNewStores2026[Country],tbl_PlannedNewStores2026[ModeShiftAssumption],0),0),0))) -> 0.71232877 | AI115: =1-tbl_ChannelMix[[#This Row],[BoutiqueRetailShare_2026_Effective]] -> 0.28767123 | AJ115: 0.731006 | AK115: 0.73100616 | AL115: =1-tbl_ChannelMix[[#This Row],[WholesaleRetailShare_2026]] -> 0.26899384
Q116: France | R116: Lumina | S116: 0.083197 | T116: 0.08319739 | Z116: France | AA116: Heritage | AB116: 0.049382 | AC116: 0.051851852 | AD116: =MIN(1,MAX(0,tbl_ChannelMix[[#This Row],[BoutiqueShare_2026]]+IF(IFERROR(_xlfn.XLOOKUP(tbl_ChannelMix[[#This Row],[Country]],tbl_PlannedNewStores2026[Country],tbl_PlannedNewStores2026[PlannedOpening],0),0)=1,IFERROR(_xlfn.XLOOKUP(tbl_ChannelMix[[#This Row],[Country]],tbl_PlannedNewStores2026[Country],tbl_PlannedNewStores2026[ModeShiftAssumption],0),0),0))) -> 0.051851852 | AE116: =1-tbl_ChannelMix[[#This Row],[BoutiqueShare_2026_Effective]] -> 0.94814815 | AF116: 0.583333 | AG116: 0.58333333 | AH116: =MIN(1,MAX(0,tbl_ChannelMix[[#This Row],[BoutiqueRetailShare_2026]]+IF(IFERROR(_xlfn.XLOOKUP(tbl_ChannelMix[[#This Row],[Country]],tbl_PlannedNewStores2026[Country],tbl_PlannedNewStores2026[PlannedOpening],0),0)=1,IFERROR(_xlfn.XLOOKUP(tbl_ChannelMix[[#This Row],[Country]],tbl_PlannedNewStores2026[Country],tbl_PlannedNewStores2026[ModeShiftAssumption],0),0),0))) -> 0.58333333 | AI116: =1-tbl_ChannelMix[[#This Row],[BoutiqueRetailShare_2026_Effective]] -> 0.41666667 | AJ116: 0.733766 | AK116: 0.73376623 | AL116: =1-tbl_ChannelMix[[#This Row],[WholesaleRetailShare_2026]] -> 0.26623377
Q117: France | R117: Grand Complication | S117: 0.114192 | T117: 0.1141925 | Z117: Belgium | AA117: Meridian Classic | AB117: 0 | AC117: 0 | AD117: =MIN(1,MAX(0,tbl_ChannelMix[[#This Row],[BoutiqueShare_2026]]+IF(IFERROR(_xlfn.XLOOKUP(tbl_ChannelMix[[#This Row],[Country]],tbl_PlannedNewStores2026[Country],tbl_PlannedNewStores2026[PlannedOpening],0),0)=1,IFERROR(_xlfn.XLOOKUP(tbl_ChannelMix[[#This Row],[Country]],tbl_PlannedNewStores2026[Country],tbl_PlannedNewStores2026[ModeShiftAssumption],0),0),0))) -> 0 | AE117: =1-tbl_ChannelMix[[#This Row],[BoutiqueShare_2026_Effective]] -> 1 | AF117: 0.843 | AG117: 0.843 | AH117: =MIN(1,MAX(0,tbl_ChannelMix[[#This Row],[BoutiqueRetailShare_2026]]+IF(IFERROR(_xlfn.XLOOKUP(tbl_ChannelMix[[#This Row],[Country]],tbl_PlannedNewStores2026[Country],tbl_PlannedNewStores2026[PlannedOpening],0),0)=1,IFERROR(_xlfn.XLOOKUP(tbl_ChannelMix[[#This Row],[Country]],tbl_PlannedNewStores2026[Country],tbl_PlannedNewStores2026[ModeShiftAssumption],0),0),0))) -> 0.843 | AI117: =1-tbl_ChannelMix[[#This Row],[BoutiqueRetailShare_2026_Effective]] -> 0.157 | AJ117: 1 | AK117: 1 | AL117: =1-tbl_ChannelMix[[#This Row],[WholesaleRetailShare_2026]] -> 0
Q118: France | R118: Atelier | S118: 0.111949 | T118: 0.11194943 | Z118: France | AA118: Lumina | AB118: 0.125 | AC118: 0.13125 | AD118: =MIN(1,MAX(0,tbl_ChannelMix[[#This Row],[BoutiqueShare_2026]]+IF(IFERROR(_xlfn.XLOOKUP(tbl_ChannelMix[[#This Row],[Country]],tbl_PlannedNewStores2026[Country],tbl_PlannedNewStores2026[PlannedOpening],0),0)=1,IFERROR(_xlfn.XLOOKUP(tbl_ChannelMix[[#This Row],[Country]],tbl_PlannedNewStores2026[Country],tbl_PlannedNewStores2026[ModeShiftAssumption],0),0),0))) -> 0.13125 | AE118: =1-tbl_ChannelMix[[#This Row],[BoutiqueShare_2026_Effective]] -> 0.86875 | AF118: 0.686274 | AG118: 0.68627451 | AH118: =MIN(1,MAX(0,tbl_ChannelMix[[#This Row],[BoutiqueRetailShare_2026]]+IF(IFERROR(_xlfn.XLOOKUP(tbl_ChannelMix[[#This Row],[Country]],tbl_PlannedNewStores2026[Country],tbl_PlannedNewStores2026[PlannedOpening],0),0)=1,IFERROR(_xlfn.XLOOKUP(tbl_ChannelMix[[#This Row],[Country]],tbl_PlannedNewStores2026[Country],tbl_PlannedNewStores2026[ModeShiftAssumption],0),0),0))) -> 0.68627451 | AI118: =1-tbl_ChannelMix[[#This Row],[BoutiqueRetailShare_2026_Effective]] -> 0.31372549 | AJ118: 0.798319 | AK118: 0.79831933 | AL118: =1-tbl_ChannelMix[[#This Row],[WholesaleRetailShare_2026]] -> 0.20168067
Q119: France | R119: Terra | S119: 0.096451 | T119: 0.096451876 | Z119: France | AA119: Meridian Classic | AB119: 0.145739 | AC119: 0.15302691 | AD119: =MIN(1,MAX(0,tbl_ChannelMix[[#This Row],[BoutiqueShare_2026]]+IF(IFERROR(_xlfn.XLOOKUP(tbl_ChannelMix[[#This Row],[Country]],tbl_PlannedNewStores2026[Country],tbl_PlannedNewStores2026[PlannedOpening],0),0)=1,IFERROR(_xlfn.XLOOKUP(tbl_ChannelMix[[#This Row],[Country]],tbl_PlannedNewStores2026[Country],tbl_PlannedNewStores2026[ModeShiftAssumption],0),0),0))) -> 0.15302691 | AE119: =1-tbl_ChannelMix[[#This Row],[BoutiqueShare_2026_Effective]] -> 0.84697309 | AF119: 0.584615 | AG119: 0.58461538 | AH119: =MIN(1,MAX(0,tbl_ChannelMix[[#This Row],[BoutiqueRetailShare_2026]]+IF(IFERROR(_xlfn.XLOOKUP(tbl_ChannelMix[[#This Row],[Country]],tbl_PlannedNewStores2026[Country],tbl_PlannedNewStores2026[PlannedOpening],0),0)=1,IFERROR(_xlfn.XLOOKUP(tbl_ChannelMix[[#This Row],[Country]],tbl_PlannedNewStores2026[Country],tbl_PlannedNewStores2026[ModeShiftAssumption],0),0),0))) -> 0.58461538 | AI119: =1-tbl_ChannelMix[[#This Row],[BoutiqueRetailShare_2026_Effective]] -> 0.41538462 | AJ119: 0.71391 | AK119: 0.71391076 | AL119: =1-tbl_ChannelMix[[#This Row],[WholesaleRetailShare_2026]] -> 0.28608924
Q120: France | R120: Aventus | S120: 0.061786 | T120: 0.061786297 | Z120: Belgium | AA120: Nautique | AB120: 0 | AC120: 0 | AD120: =MIN(1,MAX(0,tbl_ChannelMix[[#This Row],[BoutiqueShare_2026]]+IF(IFERROR(_xlfn.XLOOKUP(tbl_ChannelMix[[#This Row],[Country]],tbl_PlannedNewStores2026[Country],tbl_PlannedNewStores2026[PlannedOpening],0),0)=1,IFERROR(_xlfn.XLOOKUP(tbl_ChannelMix[[#This Row],[Country]],tbl_PlannedNewStores2026[Country],tbl_PlannedNewStores2026[ModeShiftAssumption],0),0),0))) -> 0 | AE120: =1-tbl_ChannelMix[[#This Row],[BoutiqueShare_2026_Effective]] -> 1 | AF120: 0.843 | AG120: 0.843 | AH120: =MIN(1,MAX(0,tbl_ChannelMix[[#This Row],[BoutiqueRetailShare_2026]]+IF(IFERROR(_xlfn.XLOOKUP(tbl_ChannelMix[[#This Row],[Country]],tbl_PlannedNewStores2026[Country],tbl_PlannedNewStores2026[PlannedOpening],0),0)=1,IFERROR(_xlfn.XLOOKUP(tbl_ChannelMix[[#This Row],[Country]],tbl_PlannedNewStores2026[Country],tbl_PlannedNewStores2026[ModeShiftAssumption],0),0),0))) -> 0.843 | AI120: =1-tbl_ChannelMix[[#This Row],[BoutiqueRetailShare_2026_Effective]] -> 0.157 | AJ120: 1 | AK120: 1 | AL120: =1-tbl_ChannelMix[[#This Row],[WholesaleRetailShare_2026]] -> 0
Q121: France | R121: Sportivo | S121: 0.135807 | T121: 0.1358075 | Z121: France | AA121: Nautique | AB121: 0.120728 | AC121: 0.12676538 | AD121: =MIN(1,MAX(0,tbl_ChannelMix[[#This Row],[BoutiqueShare_2026]]+IF(IFERROR(_xlfn.XLOOKUP(tbl_ChannelMix[[#This Row],[Country]],tbl_PlannedNewStores2026[Country],tbl_PlannedNewStores2026[PlannedOpening],0),0)=1,IFERROR(_xlfn.XLOOKUP(tbl_ChannelMix[[#This Row],[Country]],tbl_PlannedNewStores2026[Country],tbl_PlannedNewStores2026[ModeShiftAssumption],0),0),0))) -> 0.12676538 | AE121: =1-tbl_ChannelMix[[#This Row],[BoutiqueShare_2026_Effective]] -> 0.87323462 | AF121: 0.81132 | AG121: 0.81132075 | AH121: =MIN(1,MAX(0,tbl_ChannelMix[[#This Row],[BoutiqueRetailShare_2026]]+IF(IFERROR(_xlfn.XLOOKUP(tbl_ChannelMix[[#This Row],[Country]],tbl_PlannedNewStores2026[Country],tbl_PlannedNewStores2026[PlannedOpening],0),0)=1,IFERROR(_xlfn.XLOOKUP(tbl_ChannelMix[[#This Row],[Country]],tbl_PlannedNewStores2026[Country],tbl_PlannedNewStores2026[ModeShiftAssumption],0),0),0))) -> 0.81132075 | AI121: =1-tbl_ChannelMix[[#This Row],[BoutiqueRetailShare_2026_Effective]] -> 0.18867925 | AJ121: 0.852331 | AK121: 0.85233161 | AL121: =1-tbl_ChannelMix[[#This Row],[WholesaleRetailShare_2026]] -> 0.14766839
Q122: France | R122: Celeste | S122: 0.117047 | T122: 0.11704731 | Z122: France | AA122: Sportivo | AB122: 0.118618 | AC122: 0.12454955 | AD122: =MIN(1,MAX(0,tbl_ChannelMix[[#This Row],[BoutiqueShare_2026]]+IF(IFERROR(_xlfn.XLOOKUP(tbl_ChannelMix[[#This Row],[Country]],tbl_PlannedNewStores2026[Country],tbl_PlannedNewStores2026[PlannedOpening],0),0)=1,IFERROR(_xlfn.XLOOKUP(tbl_ChannelMix[[#This Row],[Country]],tbl_PlannedNewStores2026[Country],tbl_PlannedNewStores2026[ModeShiftAssumption],0),0),0))) -> 0.12454955 | AE122: =1-tbl_ChannelMix[[#This Row],[BoutiqueShare_2026_Effective]] -> 0.87545045 | AF122: 0.772151 | AG122: 0.7721519 | AH122: =MIN(1,MAX(0,tbl_ChannelMix[[#This Row],[BoutiqueRetailShare_2026]]+IF(IFERROR(_xlfn.XLOOKUP(tbl_ChannelMix[[#This Row],[Country]],tbl_PlannedNewStores2026[Country],tbl_PlannedNewStores2026[PlannedOpening],0),0)=1,IFERROR(_xlfn.XLOOKUP(tbl_ChannelMix[[#This Row],[Country]],tbl_PlannedNewStores2026[Country],tbl_PlannedNewStores2026[ModeShiftAssumption],0),0),0))) -> 0.7721519 | AI122: =1-tbl_ChannelMix[[#This Row],[BoutiqueRetailShare_2026_Effective]] -> 0.2278481 | AJ122: 0.689948 | AK122: 0.68994889 | AL122: =1-tbl_ChannelMix[[#This Row],[WholesaleRetailShare_2026]] -> 0.31005111
Q123: Germany | R123: Sportivo | S123: 0.121194 | T123: 0.12119438 | Z123: Belgium | AA123: Sportivo | AB123: 0 | AC123: 0 | AD123: =MIN(1,MAX(0,tbl_ChannelMix[[#This Row],[BoutiqueShare_2026]]+IF(IFERROR(_xlfn.XLOOKUP(tbl_ChannelMix[[#This Row],[Country]],tbl_PlannedNewStores2026[Country],tbl_PlannedNewStores2026[PlannedOpening],0),0)=1,IFERROR(_xlfn.XLOOKUP(tbl_ChannelMix[[#This Row],[Country]],tbl_PlannedNewStores2026[Country],tbl_PlannedNewStores2026[ModeShiftAssumption],0),0),0))) -> 0 | AE123: =1-tbl_ChannelMix[[#This Row],[BoutiqueShare_2026_Effective]] -> 1 | AF123: 0.843 | AG123: 0.843 | AH123: =MIN(1,MAX(0,tbl_ChannelMix[[#This Row],[BoutiqueRetailShare_2026]]+IF(IFERROR(_xlfn.XLOOKUP(tbl_ChannelMix[[#This Row],[Country]],tbl_PlannedNewStores2026[Country],tbl_PlannedNewStores2026[PlannedOpening],0),0)=1,IFERROR(_xlfn.XLOOKUP(tbl_ChannelMix[[#This Row],[Country]],tbl_PlannedNewStores2026[Country],tbl_PlannedNewStores2026[ModeShiftAssumption],0),0),0))) -> 0.843 | AI123: =1-tbl_ChannelMix[[#This Row],[BoutiqueRetailShare_2026_Effective]] -> 0.157 | AJ123: 1 | AK123: 1 | AL123: =1-tbl_ChannelMix[[#This Row],[WholesaleRetailShare_2026]] -> 0
Q124: Germany | R124: Meridian Classic | S124: 0.093871 | T124: 0.093871975 | Z124: France | AA124: Terra | AB124: 0.152219 | AC124: 0.15983087 | AD124: =MIN(1,MAX(0,tbl_ChannelMix[[#This Row],[BoutiqueShare_2026]]+IF(IFERROR(_xlfn.XLOOKUP(tbl_ChannelMix[[#This Row],[Country]],tbl_PlannedNewStores2026[Country],tbl_PlannedNewStores2026[PlannedOpening],0),0)=1,IFERROR(_xlfn.XLOOKUP(tbl_ChannelMix[[#This Row],[Country]],tbl_PlannedNewStores2026[Country],tbl_PlannedNewStores2026[ModeShiftAssumption],0),0),0))) -> 0.15983087 | AE124: =1-tbl_ChannelMix[[#This Row],[BoutiqueShare_2026_Effective]] -> 0.84016913 | AF124: 0.75 | AG124: 0.75 | AH124: =MIN(1,MAX(0,tbl_ChannelMix[[#This Row],[BoutiqueRetailShare_2026]]+IF(IFERROR(_xlfn.XLOOKUP(tbl_ChannelMix[[#This Row],[Country]],tbl_PlannedNewStores2026[Country],tbl_PlannedNewStores2026[PlannedOpening],0),0)=1,IFERROR(_xlfn.XLOOKUP(tbl_ChannelMix[[#This Row],[Country]],tbl_PlannedNewStores2026[Country],tbl_PlannedNewStores2026[ModeShiftAssumption],0),0),0))) -> 0.75 | AI124: =1-tbl_ChannelMix[[#This Row],[BoutiqueRetailShare_2026_Effective]] -> 0.25 | AJ124: 0.852867 | AK124: 0.85286783 | AL124: =1-tbl_ChannelMix[[#This Row],[WholesaleRetailShare_2026]] -> 0.14713217
Q125: Germany | R125: Atelier | S125: 0.120999 | T125: 0.12099922 | Z125: Belgium | AA125: Terra | AB125: 0 | AC125: 0 | AD125: =MIN(1,MAX(0,tbl_ChannelMix[[#This Row],[BoutiqueShare_2026]]+IF(IFERROR(_xlfn.XLOOKUP(tbl_ChannelMix[[#This Row],[Country]],tbl_PlannedNewStores2026[Country],tbl_PlannedNewStores2026[PlannedOpening],0),0)=1,IFERROR(_xlfn.XLOOKUP(tbl_ChannelMix[[#This Row],[Country]],tbl_PlannedNewStores2026[Country],tbl_PlannedNewStores2026[ModeShiftAssumption],0),0),0))) -> 0 | AE125: =1-tbl_ChannelMix[[#This Row],[BoutiqueShare_2026_Effective]] -> 1 | AF125: 0.843 | AG125: 0.843 | AH125: =MIN(1,MAX(0,tbl_ChannelMix[[#This Row],[BoutiqueRetailShare_2026]]+IF(IFERROR(_xlfn.XLOOKUP(tbl_ChannelMix[[#This Row],[Country]],tbl_PlannedNewStores2026[Country],tbl_PlannedNewStores2026[PlannedOpening],0),0)=1,IFERROR(_xlfn.XLOOKUP(tbl_ChannelMix[[#This Row],[Country]],tbl_PlannedNewStores2026[Country],tbl_PlannedNewStores2026[ModeShiftAssumption],0),0),0))) -> 0.843 | AI125: =1-tbl_ChannelMix[[#This Row],[BoutiqueRetailShare_2026_Effective]] -> 0.157 | AJ125: 1 | AK125: 1 | AL125: =1-tbl_ChannelMix[[#This Row],[WholesaleRetailShare_2026]] -> 0
... Q149: Hong Kong | R149: Sportivo | S149: 0.12323 | T149: 0.12323 | Z149: Hong Kong | AA149: Sportivo | AB149: 0.167701 | AC149: 0.17608696 | AD149: =MIN(1,MAX(0,tbl_ChannelMix[[#This Row],[BoutiqueShare_2026]]+IF(IFERROR(_xlfn.XLOOKUP(tbl_ChannelMix[[#This Row],[Country]],tbl_PlannedNewStores2026[Country],tbl_PlannedNewStores2026[PlannedOpening],0),0)=1,IFERROR(_xlfn.XLOOKUP(tbl_ChannelMix[[#This Row],[Country]],tbl_PlannedNewStores2026[Country],tbl_PlannedNewStores2026[ModeShiftAssumption],0),0),0))) -> 0.17608696 | AE149: =1-tbl_ChannelMix[[#This Row],[BoutiqueShare_2026_Effective]] -> 0.82391304 | AF149: 1 | AG149: 1 | AH149: =MIN(1,MAX(0,tbl_ChannelMix[[#This Row],[BoutiqueRetailShare_2026]]+IF(IFERROR(_xlfn.XLOOKUP(tbl_ChannelMix[[#This Row],[Country]],tbl_PlannedNewStores2026[Country],tbl_PlannedNewStores2026[PlannedOpening],0),0)=1,IFERROR(_xlfn.XLOOKUP(tbl_ChannelMix[[#This Row],[Country]],tbl_PlannedNewStores2026[Country],tbl_PlannedNewStores2026[ModeShiftAssumption],0),0),0))) -> 1 | AI149: =1-tbl_ChannelMix[[#This Row],[BoutiqueRetailShare_2026_Effective]] -> 0 | AJ149: 0.664179 | AK149: 0.6641791 | AL149: =1-tbl_ChannelMix[[#This Row],[WholesaleRetailShare_2026]] -> 0.3358209
A150: 1 | Q150: Hong Kong | R150: Nautique | S150: 0.070417 | T150: 0.070417145 | Z150: Hong Kong | AA150: Terra | AB150: 0.141791 | AC150: 0.1488806 | AD150: =MIN(1,MAX(0,tbl_ChannelMix[[#This Row],[BoutiqueShare_2026]]+IF(IFERROR(_xlfn.XLOOKUP(tbl_ChannelMix[[#This Row],[Country]],tbl_PlannedNewStores2026[Country],tbl_PlannedNewStores2026[PlannedOpening],0),0)=1,IFERROR(_xlfn.XLOOKUP(tbl_ChannelMix[[#This Row],[Country]],tbl_PlannedNewStores2026[Country],tbl_PlannedNewStores2026[ModeShiftAssumption],0),0),0))) -> 0.1488806 | AE150: =1-tbl_ChannelMix[[#This Row],[BoutiqueShare_2026_Effective]] -> 0.8511194 | AF150: 1 | AG150: 1 | AH150: =MIN(1,MAX(0,tbl_ChannelMix[[#This Row],[BoutiqueRetailShare_2026]]+IF(IFERROR(_xlfn.XLOOKUP(tbl_ChannelMix[[#This Row],[Country]],tbl_PlannedNewStores2026[Country],tbl_PlannedNewStores2026[PlannedOpening],0),0)=1,IFERROR(_xlfn.XLOOKUP(tbl_ChannelMix[[#This Row],[Country]],tbl_PlannedNewStores2026[Country],tbl_PlannedNewStores2026[ModeShiftAssumption],0),0),0))) -> 1 | AI150: =1-tbl_ChannelMix[[#This Row],[BoutiqueRetailShare_2026_Effective]] -> 0 | AJ150: 0.652173 | AK150: 0.65217391 | AL150: =1-tbl_ChannelMix[[#This Row],[WholesaleRetailShare_2026]] -> 0.34782609
Q151: Hong Kong | R151: Grand Complication | S151: 0.12476 | T151: 0.12476081 | Z151: Netherlands | AA151: Aventus | AB151: 0.092485 | AC151: 0.097109827 | AD151: =MIN(1,MAX(0,tbl_ChannelMix[[#This Row],[BoutiqueShare_2026]]+IF(IFERROR(_xlfn.XLOOKUP(tbl_ChannelMix[[#This Row],[Country]],tbl_PlannedNewStores2026[Country],tbl_PlannedNewStores2026[PlannedOpening],0),0)=1,IFERROR(_xlfn.XLOOKUP(tbl_ChannelMix[[#This Row],[Country]],tbl_PlannedNewStores2026[Country],tbl_PlannedNewStores2026[ModeShiftAssumption],0),0),0))) -> 0.097109827 | AE151: =1-tbl_ChannelMix[[#This Row],[BoutiqueShare_2026_Effective]] -> 0.90289017 | AF151: 1 | AG151: 1 | AH151: =MIN(1,MAX(0,tbl_ChannelMix[[#This Row],[BoutiqueRetailShare_2026]]+IF(IFERROR(_xlfn.XLOOKUP(tbl_ChannelMix[[#This Row],[Country]],tbl_PlannedNewStores2026[Country],tbl_PlannedNewStores2026[PlannedOpening],0),0)=1,IFERROR(_xlfn.XLOOKUP(tbl_ChannelMix[[#This Row],[Country]],tbl_PlannedNewStores2026[Country],tbl_PlannedNewStores2026[ModeShiftAssumption],0),0),0))) -> 1 | AI151: =1-tbl_ChannelMix[[#This Row],[BoutiqueRetailShare_2026_Effective]] -> 0 | AJ151: 0.318471 | AK151: 0.31847134 | AL151: =1-tbl_ChannelMix[[#This Row],[WholesaleRetailShare_2026]] -> 0.68152866
Q152: Hong Kong | R152: Heritage | S152: 0.119785 | T152: 0.11978569 | Z152: Peru | AA152: Aventus | AB152: 0.328571 | AC152: 0.345 | AD152: =MIN(1,MAX(0,tbl_ChannelMix[[#This Row],[BoutiqueShare_2026]]+IF(IFERROR(_xlfn.XLOOKUP(tbl_ChannelMix[[#This Row],[Country]],tbl_PlannedNewStores2026[Country],tbl_PlannedNewStores2026[PlannedOpening],0),0)=1,IFERROR(_xlfn.XLOOKUP(tbl_ChannelMix[[#This Row],[Country]],tbl_PlannedNewStores2026[Country],tbl_PlannedNewStores2026[ModeShiftAssumption],0),0),0))) -> 0.345 | AE152: =1-tbl_ChannelMix[[#This Row],[BoutiqueShare_2026_Effective]] -> 0.655 | AF152: 1 | AG152: 1 | AH152: =MIN(1,MAX(0,tbl_ChannelMix[[#This Row],[BoutiqueRetailShare_2026]]+IF(IFERROR(_xlfn.XLOOKUP(tbl_ChannelMix[[#This Row],[Country]],tbl_PlannedNewStores2026[Country],tbl_PlannedNewStores2026[PlannedOpening],0),0)=1,IFERROR(_xlfn.XLOOKUP(tbl_ChannelMix[[#This Row],[Country]],tbl_PlannedNewStores2026[Country],tbl_PlannedNewStores2026[ModeShiftAssumption],0),0),0))) -> 1 | AI152: =1-tbl_ChannelMix[[#This Row],[BoutiqueRetailShare_2026_Effective]] -> 0 | AJ152: 0.468085 | AK152: 0.46808511 | AL152: =1-tbl_ChannelMix[[#This Row],[WholesaleRetailShare_2026]] -> 0.53191489
Q153: Italy | R153: Aventus | S153: 0.048516 | T153: 0.048516251 | Z153: Portugal | AA153: Aventus | AB153: 0 | AC153: 0 | AD153: =MIN(1,MAX(0,tbl_ChannelMix[[#This Row],[BoutiqueShare_2026]]+IF(IFERROR(_xlfn.XLOOKUP(tbl_ChannelMix[[#This Row],[Country]],tbl_PlannedNewStores2026[Country],tbl_PlannedNewStores2026[PlannedOpening],0),0)=1,IFERROR(_xlfn.XLOOKUP(tbl_ChannelMix[[#This Row],[Country]],tbl_PlannedNewStores2026[Country],tbl_PlannedNewStores2026[ModeShiftAssumption],0),0),0))) -> 0 | AE153: =1-tbl_ChannelMix[[#This Row],[BoutiqueShare_2026_Effective]] -> 1 | AF153: 0.843 | AG153: 0.843 | AH153: =MIN(1,MAX(0,tbl_ChannelMix[[#This Row],[BoutiqueRetailShare_2026]]+IF(IFERROR(_xlfn.XLOOKUP(tbl_ChannelMix[[#This Row],[Country]],tbl_PlannedNewStores2026[Country],tbl_PlannedNewStores2026[PlannedOpening],0),0)=1,IFERROR(_xlfn.XLOOKUP(tbl_ChannelMix[[#This Row],[Country]],tbl_PlannedNewStores2026[Country],tbl_PlannedNewStores2026[ModeShiftAssumption],0),0),0))) -> 0.843 | AI153: =1-tbl_ChannelMix[[#This Row],[BoutiqueRetailShare_2026_Effective]] -> 0.157 | AJ153: 0.710526 | AK153: 0.71052632 | AL153: =1-tbl_ChannelMix[[#This Row],[WholesaleRetailShare_2026]] -> 0.28947368
Q154: Italy | R154: Lumina | S154: 0.103155 | T154: 0.10315591 | Z154: Italy | AA154: Celeste | AB154: 0.155844 | AC154: 0.16363636 | AD154: =MIN(1,MAX(0,tbl_ChannelMix[[#This Row],[BoutiqueShare_2026]]+IF(IFERROR(_xlfn.XLOOKUP(tbl_ChannelMix[[#This Row],[Country]],tbl_PlannedNewStores2026[Country],tbl_PlannedNewStores2026[PlannedOpening],0),0)=1,IFERROR(_xlfn.XLOOKUP(tbl_ChannelMix[[#This Row],[Country]],tbl_PlannedNewStores2026[Country],tbl_PlannedNewStores2026[ModeShiftAssumption],0),0),0))) -> 0.16363636 | AE154: =1-tbl_ChannelMix[[#This Row],[BoutiqueShare_2026_Effective]] -> 0.83636364 | AF154: 1 | AG154: 1 | AH154: =MIN(1,MAX(0,tbl_ChannelMix[[#This Row],[BoutiqueRetailShare_2026]]+IF(IFERROR(_xlfn.XLOOKUP(tbl_ChannelMix[[#This Row],[Country]],tbl_PlannedNewStores2026[Country],tbl_PlannedNewStores2026[PlannedOpening],0),0)=1,IFERROR(_xlfn.XLOOKUP(tbl_ChannelMix[[#This Row],[Country]],tbl_PlannedNewStores2026[Country],tbl_PlannedNewStores2026[ModeShiftAssumption],0),0),0))) -> 1 | AI154: =1-tbl_ChannelMix[[#This Row],[BoutiqueRetailShare_2026_Effective]] -> 0 | AJ154: 0.866666 | AK154: 0.86666667 | AL154: =1-tbl_ChannelMix[[#This Row],[WholesaleRetailShare_2026]] -> 0.13333333
Q155: Italy | R155: Sportivo | S155: 0.150259 | T155: 0.15025907 | Z155: Italy | AA155: Grand Complication | AB155: 0.276018 | AC155: 0.289819 | AD155: =MIN(1,MAX(0,tbl_ChannelMix[[#This Row],[BoutiqueShare_2026]]+IF(IFERROR(_xlfn.XLOOKUP(tbl_ChannelMix[[#This Row],[Country]],tbl_PlannedNewStores2026[Country],tbl_PlannedNewStores2026[PlannedOpening],0),0)=1,IFERROR(_xlfn.XLOOKUP(tbl_ChannelMix[[#This Row],[Country]],tbl_PlannedNewStores2026[Country],tbl_PlannedNewStores2026[ModeShiftAssumption],0),0),0))) -> 0.289819 | AE155: =1-tbl_ChannelMix[[#This Row],[BoutiqueShare_2026_Effective]] -> 0.710181 | AF155: 1 | AG155: 1 | AH155: =MIN(1,MAX(0,tbl_ChannelMix[[#This Row],[BoutiqueRetailShare_2026]]+IF(IFERROR(_xlfn.XLOOKUP(tbl_ChannelMix[[#This Row],[Country]],tbl_PlannedNewStores2026[Country],tbl_PlannedNewStores2026[PlannedOpening],0),0)=1,IFERROR(_xlfn.XLOOKUP(tbl_ChannelMix[[#This Row],[Country]],tbl_PlannedNewStores2026[Country],tbl_PlannedNewStores2026[ModeShiftAssumption],0),0),0))) -> 1 | AI155: =1-tbl_ChannelMix[[#This Row],[BoutiqueRetailShare_2026_Effective]] -> 0 | AJ155: 0.8375 | AK155: 0.8375 | AL155: =1-tbl_ChannelMix[[#This Row],[WholesaleRetailShare_2026]] -> 0.1625
Q156: Italy | R156: Grand Complication | S156: 0.104097 | T156: 0.10409797 | Z156: Saudi Arabia | AA156: Aventus | AB156: 0.102941 | AC156: 0.10808824 | AD156: =MIN(1,MAX(0,tbl_ChannelMix[[#This Row],[BoutiqueShare_2026]]+IF(IFERROR(_xlfn.XLOOKUP(tbl_ChannelMix[[#This Row],[Country]],tbl_PlannedNewStores2026[Country],tbl_PlannedNewStores2026[PlannedOpening],0),0)=1,IFERROR(_xlfn.XLOOKUP(tbl_ChannelMix[[#This Row],[Country]],tbl_PlannedNewStores2026[Country],tbl_PlannedNewStores2026[ModeShiftAssumption],0),0),0))) -> 0.10808824 | AE156: =1-tbl_ChannelMix[[#This Row],[BoutiqueShare_2026_Effective]] -> 0.89191176 | AF156: 1 | AG156: 1 | AH156: =MIN(1,MAX(0,tbl_ChannelMix[[#This Row],[BoutiqueRetailShare_2026]]+IF(IFERROR(_xlfn.XLOOKUP(tbl_ChannelMix[[#This Row],[Country]],tbl_PlannedNewStores2026[Country],tbl_PlannedNewStores2026[PlannedOpening],0),0)=1,IFERROR(_xlfn.XLOOKUP(tbl_ChannelMix[[#This Row],[Country]],tbl_PlannedNewStores2026[Country],tbl_PlannedNewStores2026[ModeShiftAssumption],0),0),0))) -> 1 | AI156: =1-tbl_ChannelMix[[#This Row],[BoutiqueRetailShare_2026_Effective]] -> 0 | AJ156: 0.745901 | AK156: 0.74590164 | AL156: =1-tbl_ChannelMix[[#This Row],[WholesaleRetailShare_2026]] -> 0.25409836
Q157: Italy | R157: Celeste | S157: 0.108808 | T157: 0.10880829 | Z157: Italy | AA157: Heritage | AB157: 0.136563 | AC157: 0.14339207 | AD157: =MIN(1,MAX(0,tbl_ChannelMix[[#This Row],[BoutiqueShare_2026]]+IF(IFERROR(_xlfn.XLOOKUP(tbl_ChannelMix[[#This Row],[Country]],tbl_PlannedNewStores2026[Country],tbl_PlannedNewStores2026[PlannedOpening],0),0)=1,IFERROR(_xlfn.XLOOKUP(tbl_ChannelMix[[#This Row],[Country]],tbl_PlannedNewStores2026[Country],tbl_PlannedNewStores2026[ModeShiftAssumption],0),0),0))) -> 0.14339207 | AE157: =1-tbl_ChannelMix[[#This Row],[BoutiqueShare_2026_Effective]] -> 0.85660793 | AF157: 1 | AG157: 1 | AH157: =MIN(1,MAX(0,tbl_ChannelMix[[#This Row],[BoutiqueRetailShare_2026]]+IF(IFERROR(_xlfn.XLOOKUP(tbl_ChannelMix[[#This Row],[Country]],tbl_PlannedNewStores2026[Country],tbl_PlannedNewStores2026[PlannedOpening],0),0)=1,IFERROR(_xlfn.XLOOKUP(tbl_ChannelMix[[#This Row],[Country]],tbl_PlannedNewStores2026[Country],tbl_PlannedNewStores2026[ModeShiftAssumption],0),0),0))) -> 1 | AI157: =1-tbl_ChannelMix[[#This Row],[BoutiqueRetailShare_2026_Effective]] -> 0 | AJ157: 0.739795 | AK157: 0.73979592 | AL157: =1-tbl_ChannelMix[[#This Row],[WholesaleRetailShare_2026]] -> 0.26020408
Q158: Italy | R158: Terra | S158: 0.093264 | T158: 0.093264249 | Z158: Italy | AA158: Lumina | AB158: 0.19178 | AC158: 0.20136986 | AD158: =MIN(1,MAX(0,tbl_ChannelMix[[#This Row],[BoutiqueShare_2026]]+IF(IFERROR(_xlfn.XLOOKUP(tbl_ChannelMix[[#This Row],[Country]],tbl_PlannedNewStores2026[Country],tbl_PlannedNewStores2026[PlannedOpening],0),0)=1,IFERROR(_xlfn.XLOOKUP(tbl_ChannelMix[[#This Row],[Country]],tbl_PlannedNewStores2026[Country],tbl_PlannedNewStores2026[ModeShiftAssumption],0),0),0))) -> 0.20136986 | AE158: =1-tbl_ChannelMix[[#This Row],[BoutiqueShare_2026_Effective]] -> 0.79863014 | AF158: 1 | AG158: 1 | AH158: =MIN(1,MAX(0,tbl_ChannelMix[[#This Row],[BoutiqueRetailShare_2026]]+IF(IFERROR(_xlfn.XLOOKUP(tbl_ChannelMix[[#This Row],[Country]],tbl_PlannedNewStores2026[Country],tbl_PlannedNewStores2026[PlannedOpening],0),0)=1,IFERROR(_xlfn.XLOOKUP(tbl_ChannelMix[[#This Row],[Country]],tbl_PlannedNewStores2026[Country],tbl_PlannedNewStores2026[ModeShiftAssumption],0),0),0))) -> 1 | AI158: =1-tbl_ChannelMix[[#This Row],[BoutiqueRetailShare_2026_Effective]] -> 0 | AJ158: 0.632768 | AK158: 0.63276836 | AL158: =1-tbl_ChannelMix[[#This Row],[WholesaleRetailShare_2026]] -> 0.36723164
Q159: Italy | R159: Atelier | S159: 0.110692 | T159: 0.11069242 | Z159: Singapore | AA159: Aventus | AB159: 0.112781 | AC159: 0.11842105 | AD159: =MIN(1,MAX(0,tbl_ChannelMix[[#This Row],[BoutiqueShare_2026]]+IF(IFERROR(_xlfn.XLOOKUP(tbl_ChannelMix[[#This Row],[Country]],tbl_PlannedNewStores2026[Country],tbl_PlannedNewStores2026[PlannedOpening],0),0)=1,IFERROR(_xlfn.XLOOKUP(tbl_ChannelMix[[#This Row],[Country]],tbl_PlannedNewStores2026[Country],tbl_PlannedNewStores2026[ModeShiftAssumption],0),0),0))) -> 0.11842105 | AE159: =1-tbl_ChannelMix[[#This Row],[BoutiqueShare_2026_Effective]] -> 0.88157895 | AF159: 1 | AG159: 1 | AH159: =MIN(1,MAX(0,tbl_ChannelMix[[#This Row],[BoutiqueRetailShare_2026]]+IF(IFERROR(_xlfn.XLOOKUP(tbl_ChannelMix[[#This Row],[Country]],tbl_PlannedNewStores2026[Country],tbl_PlannedNewStores2026[PlannedOpening],0),0)=1,IFERROR(_xlfn.XLOOKUP(tbl_ChannelMix[[#This Row],[Country]],tbl_PlannedNewStores2026[Country],tbl_PlannedNewStores2026[ModeShiftAssumption],0),0),0))) -> 1 | AI159: =1-tbl_ChannelMix[[#This Row],[BoutiqueRetailShare_2026_Effective]] -> 0 | AJ159: 0.533898 | AK159: 0.53389831 | AL159: =1-tbl_ChannelMix[[#This Row],[WholesaleRetailShare_2026]] -> 0.46610169
Q160: Italy | R160: Meridian Classic | S160: 0.093264 | T160: 0.093264249 | Z160: Italy | AA160: Meridian Classic | AB160: 0.196969 | AC160: 0.20681818 | AD160: =MIN(1,MAX(0,tbl_ChannelMix[[#This Row],[BoutiqueShare_2026]]+IF(IFERROR(_xlfn.XLOOKUP(tbl_ChannelMix[[#This Row],[Country]],tbl_PlannedNewStores2026[Country],tbl_PlannedNewStores2026[PlannedOpening],0),0)=1,IFERROR(_xlfn.XLOOKUP(tbl_ChannelMix[[#This Row],[Country]],tbl_PlannedNewStores2026[Country],tbl_PlannedNewStores2026[ModeShiftAssumption],0),0),0))) -> 0.20681818 | AE160: =1-tbl_ChannelMix[[#This Row],[BoutiqueShare_2026_Effective]] -> 0.79318182 | AF160: 1 | AG160: 1 | AH160: =MIN(1,MAX(0,tbl_ChannelMix[[#This Row],[BoutiqueRetailShare_2026]]+IF(IFERROR(_xlfn.XLOOKUP(tbl_ChannelMix[[#This Row],[Country]],tbl_PlannedNewStores2026[Country],tbl_PlannedNewStores2026[PlannedOpening],0),0)=1,IFERROR(_xlfn.XLOOKUP(tbl_ChannelMix[[#This Row],[Country]],tbl_PlannedNewStores2026[Country],tbl_PlannedNewStores2026[ModeShiftAssumption],0),0),0))) -> 1 | AI160: =1-tbl_ChannelMix[[#This Row],[BoutiqueRetailShare_2026_Effective]] -> 0 | AJ160: 0.893081 | AK160: 0.89308176 | AL160: =1-tbl_ChannelMix[[#This Row],[WholesaleRetailShare_2026]] -> 0.10691824
Q161: Italy | R161: Heritage | S161: 0.106924 | T161: 0.10692416 | Z161: Italy | AA161: Nautique | AB161: 0.238372 | AC161: 0.2502907 | AD161: =MIN(1,MAX(0,tbl_ChannelMix[[#This Row],[BoutiqueShare_2026]]+IF(IFERROR(_xlfn.XLOOKUP(tbl_ChannelMix[[#This Row],[Country]],tbl_PlannedNewStores2026[Country],tbl_PlannedNewStores2026[PlannedOpening],0),0)=1,IFERROR(_xlfn.XLOOKUP(tbl_ChannelMix[[#This Row],[Country]],tbl_PlannedNewStores2026[Country],tbl_PlannedNewStores2026[ModeShiftAssumption],0),0),0))) -> 0.2502907 | AE161: =1-tbl_ChannelMix[[#This Row],[BoutiqueShare_2026_Effective]] -> 0.7497093 | AF161: 1 | AG161: 1 | AH161: =MIN(1,MAX(0,tbl_ChannelMix[[#This Row],[BoutiqueRetailShare_2026]]+IF(IFERROR(_xlfn.XLOOKUP(tbl_ChannelMix[[#This Row],[Country]],tbl_PlannedNewStores2026[Country],tbl_PlannedNewStores2026[PlannedOpening],0),0)=1,IFERROR(_xlfn.XLOOKUP(tbl_ChannelMix[[#This Row],[Country]],tbl_PlannedNewStores2026[Country],tbl_PlannedNewStores2026[ModeShiftAssumption],0),0),0))) -> 1 | AI161: =1-tbl_ChannelMix[[#This Row],[BoutiqueRetailShare_2026_Effective]] -> 0 | AJ161: 0.893129 | AK161: 0.89312977 | AL161: =1-tbl_ChannelMix[[#This Row],[WholesaleRetailShare_2026]] -> 0.10687023
Q162: Italy | R162: Nautique | S162: 0.081017 | T162: 0.081017428 | Z162: South Korea | AA162: Aventus | AB162: 0.171875 | AC162: 0.18046875 | AD162: =MIN(1,MAX(0,tbl_ChannelMix[[#This Row],[BoutiqueShare_2026]]+IF(IFERROR(_xlfn.XLOOKUP(tbl_ChannelMix[[#This Row],[Country]],tbl_PlannedNewStores2026[Country],tbl_PlannedNewStores2026[PlannedOpening],0),0)=1,IFERROR(_xlfn.XLOOKUP(tbl_ChannelMix[[#This Row],[Country]],tbl_PlannedNewStores2026[Country],tbl_PlannedNewStores2026[ModeShiftAssumption],0),0),0))) -> 0.18046875 | AE162: =1-tbl_ChannelMix[[#This Row],[BoutiqueShare_2026_Effective]] -> 0.81953125 | AF162: 1 | AG162: 1 | AH162: =MIN(1,MAX(0,tbl_ChannelMix[[#This Row],[BoutiqueRetailShare_2026]]+IF(IFERROR(_xlfn.XLOOKUP(tbl_ChannelMix[[#This Row],[Country]],tbl_PlannedNewStores2026[Country],tbl_PlannedNewStores2026[PlannedOpening],0),0)=1,IFERROR(_xlfn.XLOOKUP(tbl_ChannelMix[[#This Row],[Country]],tbl_PlannedNewStores2026[Country],tbl_PlannedNewStores2026[ModeShiftAssumption],0),0),0))) -> 1 | AI162: =1-tbl_ChannelMix[[#This Row],[BoutiqueRetailShare_2026_Effective]] -> 0 | AJ162: 0.949685 | AK162: 0.94968553 | AL162: =1-tbl_ChannelMix[[#This Row],[WholesaleRetailShare_2026]] -> 0.050314465
... Q332: Vietnam | R332: Terra | S332: 0.093158 | T332: 0.093158661 | Z332: Vietnam | AA332: Terra | AB332: 0.390625 | AC332: 0.41015625 | AD332: =MIN(1,MAX(0,tbl_ChannelMix[[#This Row],[BoutiqueShare_2026]]+IF(IFERROR(_xlfn.XLOOKUP(tbl_ChannelMix[[#This Row],[Country]],tbl_PlannedNewStores2026[Country],tbl_PlannedNewStores2026[PlannedOpening],0),0)=1,IFERROR(_xlfn.XLOOKUP(tbl_ChannelMix[[#This Row],[Country]],tbl_PlannedNewStores2026[Country],tbl_PlannedNewStores2026[ModeShiftAssumption],0),0),0))) -> 0.56015625 | AE332: =1-tbl_ChannelMix[[#This Row],[BoutiqueShare_2026_Effective]] -> 0.43984375 | AF332: 1 | AG332: 1 | AH332: =MIN(1,MAX(0,tbl_ChannelMix[[#This Row],[BoutiqueRetailShare_2026]]+IF(IFERROR(_xlfn.XLOOKUP(tbl_ChannelMix[[#This Row],[Country]],tbl_PlannedNewStores2026[Country],tbl_PlannedNewStores2026[PlannedOpening],0),0)=1,IFERROR(_xlfn.XLOOKUP(tbl_ChannelMix[[#This Row],[Country]],tbl_PlannedNewStores2026[Country],tbl_PlannedNewStores2026[ModeShiftAssumption],0),0),0))) -> 1 | AI332: =1-tbl_ChannelMix[[#This Row],[BoutiqueRetailShare_2026_Effective]] -> 0 | AJ332: 1 | AK332: 1 | AL332: =1-tbl_ChannelMix[[#This Row],[WholesaleRetailShare_2026]] -> 0
A473: 1
A482: 1

Sheet Model
B2: MODEL
A3: 1 | B3: Channel Type x Collection x Country x Month
E4: =_xlfn.CONCAT("Actual ",tbl_Model[[#Headers],[Units2025]]) -> Actual Units2025 | F4: =_xlfn.CONCAT("Actual ",tbl_Model[[#Headers],[Revenue2025]]) -> Actual Revenue2025 | G4: =_xlfn.CONCAT("Actual ",tbl_Model[[#Headers],[COGS2025]]) -> Actual COGS2025 | H4: Monthly Units from 2023 onwards | AR4: Forecasted Monthly Units based on previous period | BD4: Monthly shared based on forecasted units | BP4: Budgeted Units from Input tab | BQ4: Budgeted price from inputs tab | BR4: Budgeted cost from inputs tab | BS4: Net Price (net of WHLS margin if channel is whls) | BT4: Budgeted Monthly Units based on monthly forecast allocation | CF4: Budgeted Monthly Revenue based on monthly forecast allocation | CR4: Budgeted Monthly Cost based on monthly forecast allocation | DD4: Budgeted Annual Revenue | DE4: Budgeted Annual Cost | DF4: Operating margin
H5: 1 | I5: 2 | J5: 3 | K5: 4 | L5: 5 | M5: 6 | N5: 7 | O5: 8 | P5: 9 | Q5: 10 | R5: 11 | S5: 12 | T5: 13 | U5: 14 | V5: 15 | W5: 16 | X5: 17 | Y5: 18 | Z5: 19 | AA5: 20 | AB5: 21 | AC5: 22 | AD5: 23 | AE5: 24 | AF5: 25 | AG5: 26 | AH5: 27 | AI5: 28 | AJ5: 29 | AK5: 30 | AL5: 31 | AM5: 32 | AN5: 33 | AO5: 34 | AP5: 35 | AQ5: 36 | AR5: =AQ5+1 -> 37 | AS5: =AR5+1 -> 38 | AT5: =AS5+1 -> 39 | AU5: =AT5+1 -> 40 | AV5: =AU5+1 -> 41 | AW5: =AV5+1 -> 42 | AX5: =AW5+1 -> 43 | AY5: =AX5+1 -> 44 | ... BC5: =BB5+1 -> 48 | BP5: =SUM(tbl_Model[AnnualUnits]) -> 74712.5 | DD5: =SUM(tbl_Model[Budgeted Revenue]) -> 1.0443122e+09
B6: Type | C6: collection | D6: country | E6: Units2025 | F6: Revenue2025 | G6: COGS2025 | H6: H_2023_01 | I6: H_2023_02 | J6: H_2023_03 | K6: H_2023_04 | L6: H_2023_05 | M6: H_2023_06 | N6: H_2023_07 | O6: H_2023_08 | P6: H_2023_09 | Q6: H_2023_10 | R6: H_2023_11 | S6: H_2023_12 | T6: H_2024_01 | U6: H_2024_02 | V6: H_2024_03 | W6: H_2024_04 | X6: H_2024_05 | Y6: H_2024_06 | Z6: H_2024_07 | AA6: H_2024_08 | AB6: H_2024_09 | AC6: H_2024_10 | AD6: H_2024_11 | AE6: H_2024_12 | AF6: H_2025_01 | AG6: H_2025_02 | AH6: H_2025_03 | AI6: H_2025_04 | AJ6: H_2025_05 | AK6: H_2025_06 | AL6: H_2025_07 | AM6: H_2025_08 | AN6: H_2025_09 | AO6: H_2025_10 | AP6: H_2025_11 | AQ6: H_2025_12 | AR6: RawShape_01 | AS6: RawShape_02 | AT6: RawShape_03 | AU6: RawShape_04 | AV6: RawShape_05 | AW6: RawShape_06 | AX6: RawShape_07 | AY6: RawShape_08 | AZ6: RawShape_09 | BA6: RawShape_10 | BB6: RawShape_11 | BC6: RawShape_12 | BD6: MonthlyShare_01 | BE6: MonthlyShare_02 | BF6: MonthlyShare_03 | BG6: MonthlyShare_04 | BH6: MonthlyShare_05 | BI6: MonthlyShare_06 | BJ6: MonthlyShare_07 | BK6: MonthlyShare_08 | BL6: MonthlyShare_09 | BM6: MonthlyShare_10 | BN6: MonthlyShare_11 | BO6: MonthlyShare_12 | BP6: AnnualUnits | BQ6: UnitListPrice | BR6: UnitCost | BS6: RealizedUnitPrice | BT6: BudgetedUnits_01 | BU6: BudgetedUnits_02 | BV6: BudgetedUnits_03 | BW6: BudgetedUnits_04 | BX6: BudgetedUnits_05 | BY6: BudgetedUnits_06 | BZ6: BudgetedUnits_07 | CA6: BudgetedUnits_08 | CB6: BudgetedUnits_09 | CC6: BudgetedUnits_10 | CD6: BudgetedUnits_11 | CE6: BudgetedUnits_12 | CF6: BudgetedRevenue_01 | CG6: BudgetedRevenue_02 | CH6: BudgetedRevenue_03 | CI6: BudgetedRevenue_04 | CJ6: BudgetedRevenue_05 | CK6: BudgetedRevenue_06 | CL6: BudgetedRevenue_07 | CM6: BudgetedRevenue_08 | CN6: BudgetedRevenue_09 | CO6: BudgetedRevenue_10 | CP6: BudgetedRevenue_11 | CQ6: BudgetedRevenue_12 | CR6: BudgetedCost_01 | CS6: BudgetedCost_02 | CT6: BudgetedCost_03 | CU6: BudgetedCost_04 | CV6: BudgetedCost_05 | CW6: BudgetedCost_06 | CX6: BudgetedCost_07 | CY6: BudgetedCost_08 | CZ6: BudgetedCost_09 | DA6: BudgetedCost_10 | DB6: BudgetedCost_11 | DC6: BudgetedCost_12 | DD6: Budgeted Revenue | DE6: Budgeted COGS | DF6: MarginPct
B7: Boutique | C7: Atelier | D7: Argentina | E7: 26 | F7: 747454.13 | G7: 174523 | H7: 0 | I7: 0 | J7: 0 | K7: 0 | L7: 0 | M7: 0 | N7: 0 | O7: 0 | P7: 0 | Q7: 0 | R7: 0 | S7: 0 | T7: 0 | U7: 0 | V7: 0 | W7: 0 | X7: 0 | Y7: 0 | Z7: 0 | AA7: 0 | AB7: 0 | AC7: 0 | AD7: 0 | AE7: 0 | AF7: 3 | AG7: 1 | AH7: 2 | AI7: 3 | AJ7: 3 | AK7: 1 | AL7: 1 | AM7: 3 | AN7: 3 | AO7: 4 | AP7: 1 | AQ7: 1 | AR7: =MAX(IFERROR(IFERROR(_xlfn.FORECAST.ETS(AR$5,tbl_Model[[#This Row],[H_2023_01]:[H_2025_12]],$H$5:$AQ$5),_xlfn.FORECAST.LINEAR(AR$5,tbl_Model[[#This Row],[H_2023_01]:[H_2025_12]],$H$5:$AQ$5)),0),0) -> 1.7317961 | AS7: =MAX(IFERROR(IFERROR(_xlfn.FORECAST.ETS(AS$5,tbl_Model[[#This Row],[H_2023_01]:[H_2025_12]],$H$5:$AQ$5),_xlfn.FORECAST.LINEAR(AS$5,tbl_Model[[#This Row],[H_2023_01]:[H_2025_12]],$H$5:$AQ$5)),0),0) -> 1.8089192 | AT7: =MAX(IFERROR(IFERROR(_xlfn.FORECAST.ETS(AT$5,tbl_Model[[#This Row],[H_2023_01]:[H_2025_12]],$H$5:$AQ$5),_xlfn.FORECAST.LINEAR(AT$5,tbl_Model[[#This Row],[H_2023_01]:[H_2025_12]],$H$5:$AQ$5)),0),0) -> 1.8860423 | AU7: =MAX(IFERROR(IFERROR(_xlfn.FORECAST.ETS(AU$5,tbl_Model[[#This Row],[H_2023_01]:[H_2025_12]],$H$5:$AQ$5),_xlfn.FORECAST.LINEAR(AU$5,tbl_Model[[#This Row],[H_2023_01]:[H_2025_12]],$H$5:$AQ$5)),0),0) -> 1.9631654 | AV7: =MAX(IFERROR(IFERROR(_xlfn.FORECAST.ETS(AV$5,tbl_Model[[#This Row],[H_2023_01]:[H_2025_12]],$H$5:$AQ$5),_xlfn.FORECAST.LINEAR(AV$5,tbl_Model[[#This Row],[H_2023_01]:[H_2025_12]],$H$5:$AQ$5)),0),0) -> 2.0402885 | AW7: =MAX(IFERROR(IFERROR(_xlfn.FORECAST.ETS(AW$5,tbl_Model[[#This Row],[H_2023_01]:[H_2025_12]],$H$5:$AQ$5),_xlfn.FORECAST.LINEAR(AW$5,tbl_Model[[#This Row],[H_2023_01]:[H_2025_12]],$H$5:$AQ$5)),0),0) -> 2.1174116 | AX7: =MAX(IFERROR(IFERROR(_xlfn.FORECAST.ETS(AX$5,tbl_Model[[#This Row],[H_2023_01]:[H_2025_12]],$H$5:$AQ$5),_xlfn.FORECAST.LINEAR(AX$5,tbl_Model[[#This Row],[H_2023_01]:[H_2025_12]],$H$5:$AQ$5)),0),0) -> 2.1945348 | AY7: =MAX(IFERROR(IFERROR(_xlfn.FORECAST.ETS(AY$5,tbl_Model[[#This Row],[H_2023_01]:[H_2025_12]],$H$5:$AQ$5),_xlfn.FORECAST.LINEAR(AY$5,tbl_Model[[#This Row],[H_2023_01]:[H_2025_12]],$H$5:$AQ$5)),0),0) -> 2.2716579 | ... BC7: =MAX(IFERROR(IFERROR(_xlfn.FORECAST.ETS(BC$5,tbl_Model[[#This Row],[H_2023_01]:[H_2025_12]],$H$5:$AQ$5),_xlfn.FORECAST.LINEAR(BC$5,tbl_Model[[#This Row],[H_2023_01]:[H_2025_12]],$H$5:$AQ$5)),0),0) -> 2.5801503 | BD7: =IFERROR(AR7/SUM(Model!$AR7:$BC7),1/12) -> 0.06693791 | BE7: =IFERROR(AS7/SUM(Model!$AR7:$BC7),1/12) -> 0.069918896 | BF7: =IFERROR(AT7/SUM(Model!$AR7:$BC7),1/12) -> 0.072899882 | BG7: =IFERROR(AU7/SUM(Model!$AR7:$BC7),1/12) -> 0.075880868 | BH7: =IFERROR(AV7/SUM(Model!$AR7:$BC7),1/12) -> 0.078861854 | BI7: =IFERROR(AW7/SUM(Model!$AR7:$BC7),1/12) -> 0.08184284 | BJ7: =IFERROR(AX7/SUM(Model!$AR7:$BC7),1/12) -> 0.084823826 | BK7: =IFERROR(AY7/SUM(Model!$AR7:$BC7),1/12) -> 0.087804812 | ... BO7: =IFERROR(BC7/SUM(Model!$AR7:$BC7),1/12) -> 0.099728756 | BP7: =_xlfn.XLOOKUP(tbl_Model[[#This Row],[country]],tbl_UnitsPerCountry[Country],tbl_UnitsPerCountry[Units2026],0) *SUMIFS(tbl_CollectionMix[Mix2026],tbl_CollectionMix[country],tbl_Model[[#This Row],[country]],tbl_CollectionMix[collection],tbl_Model[[#This Row],[collection]]) *IF(tbl_Model[[#This Row],[Type]]="Boutique", SUMIFS(tbl_ChannelMix[BoutiqueShare_2026_Effective],tbl_ChannelMix[Country],tbl_Model[[#This Row],[country]],tbl_ChannelMix[Collection],tbl_Model[[#This Row],[collection]]), 1-SUMIFS(tbl_ChannelMix[BoutiqueShare_2026_Effective],tbl_ChannelMix[Country],tbl_Model[[#This Row],[country]],tbl_ChannelMix[Collection],tbl_Model[[#This Row],[collection]])) -> 28.583333 | BQ7: {=IF(SUMIFS(tbl_SkuPrices[Units2025Actual],tbl_SkuPrices[Collection],tbl_Model[[#This Row],[collection]])=0, 0, SUMPRODUCT((tbl_SkuPrices[Collection]=tbl_Model[[#This Row],[collection]])*tbl_SkuPrices[BudgetedPrice2026]*tbl_SkuPrices[Units2025Actual]) /SUMIFS(tbl_SkuPrices[Units2025Actual],tbl_SkuPrices[Collection],tbl_Model[[#This Row],[collection]]))} -> 29113.63 | BR7: {=IF(SUMIFS(tbl_SkuPrices[Units2025Actual],tbl_SkuPrices[Collection],tbl_Model[[#This Row],[collection]])=0,0,SUMPRODUCT((tbl_SkuPrices[Collection]=tbl_Model[[#This Row],[collection]])*tbl_SkuPrices[BudgetedCost2026]*tbl_SkuPrices[Units2025Actual]) /SUMIFS(tbl_SkuPrices[Units2025Actual],tbl_SkuPrices[Collection],tbl_Model[[#This Row],[collection]]))} -> 6636.0593 | BS7: =IF(tbl_Model[[#This Row],[Type]]="Boutique", tbl_Model[[#This Row],[UnitListPrice]], tbl_Model[[#This Row],[UnitListPrice]]*(1-SUMIFS(tbl_MarketTerms[WholesaleMarginPct],tbl_MarketTerms[Country],tbl_Model[[#This Row],[country]]))) -> 29113.63 | BT7: =Model!$BP7*BD7 -> 1.9133086 | BU7: =Model!$BP7*BE7 -> 1.9985151 | BV7: =Model!$BP7*BF7 -> 2.0837216 | BW7: =Model!$BP7*BG7 -> 2.1689282 | BX7: =Model!$BP7*BH7 -> 2.2541347 | BY7: =Model!$BP7*BI7 -> 2.3393412 | BZ7: =Model!$BP7*BJ7 -> 2.4245477 | CA7: =Model!$BP7*BK7 -> 2.5097542 | ... CE7: =Model!$BP7*BO7 -> 2.8505803 | CF7: =Model!$BS7*BT7 -> 55703.359 | CG7: =Model!$BS7*BU7 -> 58184.029 | CH7: =Model!$BS7*BV7 -> 60664.7 | CI7: =Model!$BS7*BW7 -> 63145.371 | CJ7: =Model!$BS7*BX7 -> 65626.042 | CK7: =Model!$BS7*BY7 -> 68106.713 | CL7: =Model!$BS7*BZ7 -> 70587.384 | CM7: =Model!$BS7*CA7 -> 73068.055 | ... CQ7: =Model!$BS7*CE7 -> 82990.739 | CR7: =Model!$BR7*BT7 -> 12696.829 | CS7: =Model!$BR7*BU7 -> 13262.265 | CT7: =Model!$BR7*BV7 -> 13827.7 | CU7: =Model!$BR7*BW7 -> 14393.136 | CV7: =Model!$BR7*BX7 -> 14958.571 | CW7: =Model!$BR7*BY7 -> 15524.007 | CX7: =Model!$BR7*BZ7 -> 16089.442 | CY7: =Model!$BR7*CA7 -> 16654.878 | ... DC7: =Model!$BR7*CE7 -> 18916.62 | DD7: =SUM(Model!$CF7:$CQ7) -> 832164.59 | DE7: =SUM(Model!$CR7:$DC7) -> 189680.7 | DF7: =IFERROR((Model!$DD7-Model!$DE7)/Model!$DD7,0) -> 0.77206349
B8: Boutique | C8: Aventus | D8: Australia | E8: 32 | F8: 306621.16 | G8: 88592.95 | H8: 2 | I8: 0 | J8: 2 | K8: 1 | L8: 0 | M8: 1 | N8: 1 | O8: 0 | P8: 2 | Q8: 0 | R8: 2 | S8: 0 | T8: 4 | U8: 1 | V8: 0 | W8: 1 | X8: 3 | Y8: 4 | Z8: 2 | AA8: 3 | AB8: 0 | AC8: 2 | AD8: 5 | AE8: 2 | AF8: 0 | AG8: 0 | AH8: 5 | AI8: 5 | AJ8: 2 | AK8: 2 | AL8: 1 | AM8: 2 | AN8: 2 | AO8: 5 | AP8: 4 | AQ8: 4 | AR8: =MAX(IFERROR(IFERROR(_xlfn.FORECAST.ETS(AR$5,tbl_Model[[#This Row],[H_2023_01]:[H_2025_12]],$H$5:$AQ$5),_xlfn.FORECAST.LINEAR(AR$5,tbl_Model[[#This Row],[H_2023_01]:[H_2025_12]],$H$5:$AQ$5)),0),0) -> 2.863955 | AS8: =MAX(IFERROR(IFERROR(_xlfn.FORECAST.ETS(AS$5,tbl_Model[[#This Row],[H_2023_01]:[H_2025_12]],$H$5:$AQ$5),_xlfn.FORECAST.LINEAR(AS$5,tbl_Model[[#This Row],[H_2023_01]:[H_2025_12]],$H$5:$AQ$5)),0),0) -> 4.6623545 | AT8: =MAX(IFERROR(IFERROR(_xlfn.FORECAST.ETS(AT$5,tbl_Model[[#This Row],[H_2023_01]:[H_2025_12]],$H$5:$AQ$5),_xlfn.FORECAST.LINEAR(AT$5,tbl_Model[[#This Row],[H_2023_01]:[H_2025_12]],$H$5:$AQ$5)),0),0) -> 3.9296545 | AU8: =MAX(IFERROR(IFERROR(_xlfn.FORECAST.ETS(AU$5,tbl_Model[[#This Row],[H_2023_01]:[H_2025_12]],$H$5:$AQ$5),_xlfn.FORECAST.LINEAR(AU$5,tbl_Model[[#This Row],[H_2023_01]:[H_2025_12]],$H$5:$AQ$5)),0),0) -> 2.4368551 | AV8: =MAX(IFERROR(IFERROR(_xlfn.FORECAST.ETS(AV$5,tbl_Model[[#This Row],[H_2023_01]:[H_2025_12]],$H$5:$AQ$5),_xlfn.FORECAST.LINEAR(AV$5,tbl_Model[[#This Row],[H_2023_01]:[H_2025_12]],$H$5:$AQ$5)),0),0) -> 3.7960737 | AW8: =MAX(IFERROR(IFERROR(_xlfn.FORECAST.ETS(AW$5,tbl_Model[[#This Row],[H_2023_01]:[H_2025_12]],$H$5:$AQ$5),_xlfn.FORECAST.LINEAR(AW$5,tbl_Model[[#This Row],[H_2023_01]:[H_2025_12]],$H$5:$AQ$5)),0),0) -> 3.2090504 | AX8: =MAX(IFERROR(IFERROR(_xlfn.FORECAST.ETS(AX$5,tbl_Model[[#This Row],[H_2023_01]:[H_2025_12]],$H$5:$AQ$5),_xlfn.FORECAST.LINEAR(AX$5,tbl_Model[[#This Row],[H_2023_01]:[H_2025_12]],$H$5:$AQ$5)),0),0) -> 5.00745 | AY8: =MAX(IFERROR(IFERROR(_xlfn.FORECAST.ETS(AY$5,tbl_Model[[#This Row],[H_2023_01]:[H_2025_12]],$H$5:$AQ$5),_xlfn.FORECAST.LINEAR(AY$5,tbl_Model[[#This Row],[H_2023_01]:[H_2025_12]],$H$5:$AQ$5)),0),0) -> 4.2747499 | ... BC8: =MAX(IFERROR(IFERROR(_xlfn.FORECAST.ETS(BC$5,tbl_Model[[#This Row],[H_2023_01]:[H_2025_12]],$H$5:$AQ$5),_xlfn.FORECAST.LINEAR(BC$5,tbl_Model[[#This Row],[H_2023_01]:[H_2025_12]],$H$5:$AQ$5)),0),0) -> 5.3525454 | BD8: =IFERROR(AR8/SUM(Model!$AR8:$BC8),1/12) -> 0.062246422 | BE8: =IFERROR(AS8/SUM(Model!$AR8:$BC8),1/12) -> 0.10133361 | BF8: =IFERROR(AT8/SUM(Model!$AR8:$BC8),1/12) -> 0.08540879 | BG8: =IFERROR(AU8/SUM(Model!$AR8:$BC8),1/12) -> 0.052963651 | BH8: =IFERROR(AV8/SUM(Model!$AR8:$BC8),1/12) -> 0.082505488 | BI8: =IFERROR(AW8/SUM(Model!$AR8:$BC8),1/12) -> 0.069746873 | BJ8: =IFERROR(AX8/SUM(Model!$AR8:$BC8),1/12) -> 0.10883406 | BK8: =IFERROR(AY8/SUM(Model!$AR8:$BC8),1/12) -> 0.092909241 | ... BO8: =IFERROR(BC8/SUM(Model!$AR8:$BC8),1/12) -> 0.11633451 | BP8: =_xlfn.XLOOKUP(tbl_Model[[#This Row],[country]],tbl_UnitsPerCountry[Country],tbl_UnitsPerCountry[Units2026],0) *SUMIFS(tbl_CollectionMix[Mix2026],tbl_CollectionMix[country],tbl_Model[[#This Row],[country]],tbl_CollectionMix[collection],tbl_Model[[#This Row],[collection]]) *IF(tbl_Model[[#This Row],[Type]]="Boutique", SUMIFS(tbl_ChannelMix[BoutiqueShare_2026_Effective],tbl_ChannelMix[Country],tbl_Model[[#This Row],[country]],tbl_ChannelMix[Collection],tbl_Model[[#This Row],[collection]]), 1-SUMIFS(tbl_ChannelMix[BoutiqueShare_2026_Effective],tbl_ChannelMix[Country],tbl_Model[[#This Row],[country]],tbl_ChannelMix[Collection],tbl_Model[[#This Row],[collection]])) -> 35.316788 | BQ8: {=IF(SUMIFS(tbl_SkuPrices[Units2025Actual],tbl_SkuPrices[Collection],tbl_Model[[#This Row],[collection]])=0, 0, SUMPRODUCT((tbl_SkuPrices[Collection]=tbl_Model[[#This Row],[collection]])*tbl_SkuPrices[BudgetedPrice2026]*tbl_SkuPrices[Units2025Actual]) /SUMIFS(tbl_SkuPrices[Units2025Actual],tbl_SkuPrices[Collection],tbl_Model[[#This Row],[collection]]))} -> 9626.5957 | BR8: {=IF(SUMIFS(tbl_SkuPrices[Units2025Actual],tbl_SkuPrices[Collection],tbl_Model[[#This Row],[collection]])=0,0,SUMPRODUCT((tbl_SkuPrices[Collection]=tbl_Model[[#This Row],[collection]])*tbl_SkuPrices[BudgetedCost2026]*tbl_SkuPrices[Units2025Actual]) /SUMIFS(tbl_SkuPrices[Units2025Actual],tbl_SkuPrices[Collection],tbl_Model[[#This Row],[collection]]))} -> 2722.7837 | BS8: =IF(tbl_Model[[#This Row],[Type]]="Boutique", tbl_Model[[#This Row],[UnitListPrice]], tbl_Model[[#This Row],[UnitListPrice]]*(1-SUMIFS(tbl_MarketTerms[WholesaleMarginPct],tbl_MarketTerms[Country],tbl_Model[[#This Row],[country]]))) -> 9626.5957 | BT8: =Model!$BP8*BD8 -> 2.1983437 | BU8: =Model!$BP8*BE8 -> 3.5787775 | BV8: =Model!$BP8*BF8 -> 3.0163642 | BW8: =Model!$BP8*BG8 -> 1.870506 | BX8: =Model!$BP8*BH8 -> 2.9138289 | BY8: =Model!$BP8*BI8 -> 2.4632355 | BZ8: =Model!$BP8*BJ8 -> 3.8436693 | CA8: =Model!$BP8*BK8 -> 3.281256 | ... CE8: =Model!$BP8*BO8 -> 4.1085612 | CF8: =Model!$BS8*BT8 -> 21162.566 | CG8: =Model!$BS8*BU8 -> 34451.444 | CH8: =Model!$BS8*BV8 -> 29037.318 | CI8: =Model!$BS8*BW8 -> 18006.605 | CJ8: =Model!$BS8*BX8 -> 28050.253 | CK8: =Model!$BS8*BY8 -> 23712.573 | CL8: =Model!$BS8*BZ8 -> 37001.451 | CM8: =Model!$BS8*CA8 -> 31587.325 | ... CQ8: =Model!$BS8*CE8 -> 39551.458 | CR8: =Model!$BR8*BT8 -> 5985.6144 | CS8: =Model!$BR8*BU8 -> 9744.237 | CT8: =Model!$BR8*BV8 -> 8212.9071 | CU8: =Model!$BR8*BW8 -> 5092.9833 | CV8: =Model!$BR8*BX8 -> 7933.7257 | CW8: =Model!$BR8*BY8 -> 6706.8576 | CX8: =Model!$BR8*BZ8 -> 10465.48 | CY8: =Model!$BR8*CA8 -> 8934.1503 | ... DC8: =Model!$BR8*CE8 -> 11186.723 | DD8: =SUM(Model!$CF8:$CQ8) -> 339980.44 | DE8: =SUM(Model!$CR8:$DC8) -> 96159.975 | DF8: =IFERROR((Model!$DD8-Model!$DE8)/Model!$DD8,0) -> 0.71716028
B9: Boutique | C9: Atelier | D9: Australia | E9: 71 | F9: 2065782.6 | G9: 477234.27 | H9: 1 | I9: 2 | J9: 2 | K9: 1 | L9: 1 | M9: 1 | N9: 0 | O9: 0 | P9: 2 | Q9: 1 | R9: 2 | S9: 2 | T9: 8 | U9: 3 | V9: 2 | W9: 6 | X9: 7 | Y9: 5 | Z9: 2 | AA9: 7 | AB9: 3 | AC9: 3 | AD9: 4 | AE9: 11 | AF9: 3 | AG9: 2 | AH9: 4 | AI9: 5 | AJ9: 5 | AK9: 4 | AL9: 3 | AM9: 4 | AN9: 8 | AO9: 8 | AP9: 9 | AQ9: 16 | AR9: =MAX(IFERROR(IFERROR(_xlfn.FORECAST.ETS(AR$5,tbl_Model[[#This Row],[H_2023_01]:[H_2025_12]],$H$5:$AQ$5),_xlfn.FORECAST.LINEAR(AR$5,tbl_Model[[#This Row],[H_2023_01]:[H_2025_12]],$H$5:$AQ$5)),0),0) -> 8.1495783 | AS9: =MAX(IFERROR(IFERROR(_xlfn.FORECAST.ETS(AS$5,tbl_Model[[#This Row],[H_2023_01]:[H_2025_12]],$H$5:$AQ$5),_xlfn.FORECAST.LINEAR(AS$5,tbl_Model[[#This Row],[H_2023_01]:[H_2025_12]],$H$5:$AQ$5)),0),0) -> 8.3420689 | AT9: =MAX(IFERROR(IFERROR(_xlfn.FORECAST.ETS(AT$5,tbl_Model[[#This Row],[H_2023_01]:[H_2025_12]],$H$5:$AQ$5),_xlfn.FORECAST.LINEAR(AT$5,tbl_Model[[#This Row],[H_2023_01]:[H_2025_12]],$H$5:$AQ$5)),0),0) -> 8.5345596 | AU9: =MAX(IFERROR(IFERROR(_xlfn.FORECAST.ETS(AU$5,tbl_Model[[#This Row],[H_2023_01]:[H_2025_12]],$H$5:$AQ$5),_xlfn.FORECAST.LINEAR(AU$5,tbl_Model[[#This Row],[H_2023_01]:[H_2025_12]],$H$5:$AQ$5)),0),0) -> 8.7270503 | AV9: =MAX(IFERROR(IFERROR(_xlfn.FORECAST.ETS(AV$5,tbl_Model[[#This Row],[H_2023_01]:[H_2025_12]],$H$5:$AQ$5),_xlfn.FORECAST.LINEAR(AV$5,tbl_Model[[#This Row],[H_2023_01]:[H_2025_12]],$H$5:$AQ$5)),0),0) -> 8.919541 | AW9: =MAX(IFERROR(IFERROR(_xlfn.FORECAST.ETS(AW$5,tbl_Model[[#This Row],[H_2023_01]:[H_2025_12]],$H$5:$AQ$5),_xlfn.FORECAST.LINEAR(AW$5,tbl_Model[[#This Row],[H_2023_01]:[H_2025_12]],$H$5:$AQ$5)),0),0) -> 9.1120317 | AX9: =MAX(IFERROR(IFERROR(_xlfn.FORECAST.ETS(AX$5,tbl_Model[[#This Row],[H_2023_01]:[H_2025_12]],$H$5:$AQ$5),_xlfn.FORECAST.LINEAR(AX$5,tbl_Model[[#This Row],[H_2023_01]:[H_2025_12]],$H$5:$AQ$5)),0),0) -> 9.3045224 | AY9: =MAX(IFERROR(IFERROR(_xlfn.FORECAST.ETS(AY$5,tbl_Model[[#This Row],[H_2023_01]:[H_2025_12]],$H$5:$AQ$5),_xlfn.FORECAST.LINEAR(AY$5,tbl_Model[[#This Row],[H_2023_01]:[H_2025_12]],$H$5:$AQ$5)),0),0) -> 9.4970131 | ... BC9: =MAX(IFERROR(IFERROR(_xlfn.FORECAST.ETS(BC$5,tbl_Model[[#This Row],[H_2023_01]:[H_2025_12]],$H$5:$AQ$5),_xlfn.FORECAST.LINEAR(BC$5,tbl_Model[[#This Row],[H_2023_01]:[H_2025_12]],$H$5:$AQ$5)),0),0) -> 10.266976 | BD9: =IFERROR(AR9/SUM(Model!$AR9:$BC9),1/12) -> 0.07375229 | BE9: =IFERROR(AS9/SUM(Model!$AR9:$BC9),1/12) -> 0.075494298 | BF9: =IFERROR(AT9/SUM(Model!$AR9:$BC9),1/12) -> 0.077236306 | BG9: =IFERROR(AU9/SUM(Model!$AR9:$BC9),1/12) -> 0.078978314 | BH9: =IFERROR(AV9/SUM(Model!$AR9:$BC9),1/12) -> 0.080720322 | BI9: =IFERROR(AW9/SUM(Model!$AR9:$BC9),1/12) -> 0.082462329 | BJ9: =IFERROR(AX9/SUM(Model!$AR9:$BC9),1/12) -> 0.084204337 | BK9: =IFERROR(AY9/SUM(Model!$AR9:$BC9),1/12) -> 0.085946345 | ... BO9: =IFERROR(BC9/SUM(Model!$AR9:$BC9),1/12) -> 0.092914376 | BP9: =_xlfn.XLOOKUP(tbl_Model[[#This Row],[country]],tbl_UnitsPerCountry[Country],tbl_UnitsPerCountry[Units2026],0) *SUMIFS(tbl_CollectionMix[Mix2026],tbl_CollectionMix[country],tbl_Model[[#This Row],[country]],tbl_CollectionMix[collection],tbl_Model[[#This Row],[collection]]) *IF(tbl_Model[[#This Row],[Type]]="Boutique", SUMIFS(tbl_ChannelMix[BoutiqueShare_2026_Effective],tbl_ChannelMix[Country],tbl_Model[[#This Row],[country]],tbl_ChannelMix[Collection],tbl_Model[[#This Row],[collection]]), 1-SUMIFS(tbl_ChannelMix[BoutiqueShare_2026_Effective],tbl_ChannelMix[Country],tbl_Model[[#This Row],[country]],tbl_ChannelMix[Collection],tbl_Model[[#This Row],[collection]])) -> 78.359124 | BQ9: {=IF(SUMIFS(tbl_SkuPrices[Units2025Actual],tbl_SkuPrices[Collection],tbl_Model[[#This Row],[collection]])=0, 0, SUMPRODUCT((tbl_SkuPrices[Collection]=tbl_Model[[#This Row],[collection]])*tbl_SkuPrices[BudgetedPrice2026]*tbl_SkuPrices[Units2025Actual]) /SUMIFS(tbl_SkuPrices[Units2025Actual],tbl_SkuPrices[Collection],tbl_Model[[#This Row],[collection]]))} -> 29113.63 | BR9: {=IF(SUMIFS(tbl_SkuPrices[Units2025Actual],tbl_SkuPrices[Collection],tbl_Model[[#This Row],[collection]])=0,0,SUMPRODUCT((tbl_SkuPrices[Collection]=tbl_Model[[#This Row],[collection]])*tbl_SkuPrices[BudgetedCost2026]*tbl_SkuPrices[Units2025Actual]) /SUMIFS(tbl_SkuPrices[Units2025Actual],tbl_SkuPrices[Collection],tbl_Model[[#This Row],[collection]]))} -> 6636.0593 | BS9: =IF(tbl_Model[[#This Row],[Type]]="Boutique", tbl_Model[[#This Row],[UnitListPrice]], tbl_Model[[#This Row],[UnitListPrice]]*(1-SUMIFS(tbl_MarketTerms[WholesaleMarginPct],tbl_MarketTerms[Country],tbl_Model[[#This Row],[country]]))) -> 29113.63 | BT9: =Model!$BP9*BD9 -> 5.7791649 | BU9: =Model!$BP9*BE9 -> 5.9156671 | BV9: =Model!$BP9*BF9 -> 6.0521693 | BW9: =Model!$BP9*BG9 -> 6.1886715 | BX9: =Model!$BP9*BH9 -> 6.3251737 | BY9: =Model!$BP9*BI9 -> 6.4616759 | BZ9: =Model!$BP9*BJ9 -> 6.5981781 | CA9: =Model!$BP9*BK9 -> 6.7346803 | ... CE9: =Model!$BP9*BO9 -> 7.2806891 | CF9: =Model!$BS9*BT9 -> 168252.47 | CG9: =Model!$BS9*BU9 -> 172226.54 | CH9: =Model!$BS9*BV9 -> 176200.62 | CI9: =Model!$BS9*BW9 -> 180174.69 | CJ9: =Model!$BS9*BX9 -> 184148.77 | CK9: =Model!$BS9*BY9 -> 188122.84 | CL9: =Model!$BS9*BZ9 -> 192096.92 | CM9: =Model!$BS9*CA9 -> 196070.99 | ... CQ9: =Model!$BS9*CE9 -> 211967.29 | CR9: =Model!$BR9*BT9 -> 38350.881 | CS9: =Model!$BR9*BU9 -> 39256.718 | CT9: =Model!$BR9*BV9 -> 40162.554 | CU9: =Model!$BR9*BW9 -> 41068.391 | CV9: =Model!$BR9*BX9 -> 41974.228 | CW9: =Model!$BR9*BY9 -> 42880.064 | CX9: =Model!$BR9*BZ9 -> 43785.901 | CY9: =Model!$BR9*CA9 -> 44691.738 | ... DC9: =Model!$BR9*CE9 -> 48315.085 | DD9: =SUM(Model!$CF9:$CQ9) -> 2281318.5 | DE9: =SUM(Model!$CR9:$DC9) -> 519995.79 | DF9: =IFERROR((Model!$DD9-Model!$DE9)/Model!$DD9,0) -> 0.77206349
B10: Boutique | C10: Celeste | D10: Germany | E10: 123 | F10: 2754487.5 | G10: 643607.26 | H10: 5 | I10: 3 | J10: 4 | K10: 7 | L10: 3 | M10: 5 | N10: 6 | O10: 3 | P10: 3 | Q10: 6 | R10: 8 | S10: 9 | T10: 10 | U10: 11 | V10: 5 | W10: 6 | X10: 8 | Y10: 6 | Z10: 4 | AA10: 9 | AB10: 9 | AC10: 5 | AD10: 15 | AE10: 15 | AF10: 6 | AG10: 9 | AH10: 13 | AI10: 11 | AJ10: 9 | AK10: 7 | AL10: 5 | AM10: 16 | AN10: 5 | AO10: 10 | AP10: 14 | AQ10: 18 | AR10: =MAX(IFERROR(IFERROR(_xlfn.FORECAST.ETS(AR$5,tbl_Model[[#This Row],[H_2023_01]:[H_2025_12]],$H$5:$AQ$5),_xlfn.FORECAST.LINEAR(AR$5,tbl_Model[[#This Row],[H_2023_01]:[H_2025_12]],$H$5:$AQ$5)),0),0) -> 12.059864 | AS10: =MAX(IFERROR(IFERROR(_xlfn.FORECAST.ETS(AS$5,tbl_Model[[#This Row],[H_2023_01]:[H_2025_12]],$H$5:$AQ$5),_xlfn.FORECAST.LINEAR(AS$5,tbl_Model[[#This Row],[H_2023_01]:[H_2025_12]],$H$5:$AQ$5)),0),0) -> 13.659017 | AT10: =MAX(IFERROR(IFERROR(_xlfn.FORECAST.ETS(AT$5,tbl_Model[[#This Row],[H_2023_01]:[H_2025_12]],$H$5:$AQ$5),_xlfn.FORECAST.LINEAR(AT$5,tbl_Model[[#This Row],[H_2023_01]:[H_2025_12]],$H$5:$AQ$5)),0),0) -> 13.563471 | AU10: =MAX(IFERROR(IFERROR(_xlfn.FORECAST.ETS(AU$5,tbl_Model[[#This Row],[H_2023_01]:[H_2025_12]],$H$5:$AQ$5),_xlfn.FORECAST.LINEAR(AU$5,tbl_Model[[#This Row],[H_2023_01]:[H_2025_12]],$H$5:$AQ$5)),0),0) -> 13.321308 | AV10: =MAX(IFERROR(IFERROR(_xlfn.FORECAST.ETS(AV$5,tbl_Model[[#This Row],[H_2023_01]:[H_2025_12]],$H$5:$AQ$5),_xlfn.FORECAST.LINEAR(AV$5,tbl_Model[[#This Row],[H_2023_01]:[H_2025_12]],$H$5:$AQ$5)),0),0) -> 12.571026 | AW10: =MAX(IFERROR(IFERROR(_xlfn.FORECAST.ETS(AW$5,tbl_Model[[#This Row],[H_2023_01]:[H_2025_12]],$H$5:$AQ$5),_xlfn.FORECAST.LINEAR(AW$5,tbl_Model[[#This Row],[H_2023_01]:[H_2025_12]],$H$5:$AQ$5)),0),0) -> 11.153958 | AX10: =MAX(IFERROR(IFERROR(_xlfn.FORECAST.ETS(AX$5,tbl_Model[[#This Row],[H_2023_01]:[H_2025_12]],$H$5:$AQ$5),_xlfn.FORECAST.LINEAR(AX$5,tbl_Model[[#This Row],[H_2023_01]:[H_2025_12]],$H$5:$AQ$5)),0),0) -> 9.7426845 | AY10: =MAX(IFERROR(IFERROR(_xlfn.FORECAST.ETS(AY$5,tbl_Model[[#This Row],[H_2023_01]:[H_2025_12]],$H$5:$AQ$5),_xlfn.FORECAST.LINEAR(AY$5,tbl_Model[[#This Row],[H_2023_01]:[H_2025_12]],$H$5:$AQ$5)),0),0) -> 16.267437 | ... BC10: =MAX(IFERROR(IFERROR(_xlfn.FORECAST.ETS(BC$5,tbl_Model[[#This Row],[H_2023_01]:[H_2025_12]],$H$5:$AQ$5),_xlfn.FORECAST.LINEAR(BC$5,tbl_Model[[#This Row],[H_2023_01]:[H_2025_12]],$H$5:$AQ$5)),0),0) -> 20.05741 | BD10: =IFERROR(AR10/SUM(Model!$AR10:$BC10),1/12) -> 0.07362789 | BE10: =IFERROR(AS10/SUM(Model!$AR10:$BC10),1/12) -> 0.083391035 | BF10: =IFERROR(AT10/SUM(Model!$AR10:$BC10),1/12) -> 0.08280771 | BG10: =IFERROR(AU10/SUM(Model!$AR10:$BC10),1/12) -> 0.081329258 | BH10: =IFERROR(AV10/SUM(Model!$AR10:$BC10),1/12) -> 0.076748636 | BI10: =IFERROR(AW10/SUM(Model!$AR10:$BC10),1/12) -> 0.068097149 | BJ10: =IFERROR(AX10/SUM(Model!$AR10:$BC10),1/12) -> 0.059481042 | BK10: =IFERROR(AY10/SUM(Model!$AR10:$BC10),1/12) -> 0.099315965 | ... BO10: =IFERROR(BC10/SUM(Model!$AR10:$BC10),1/12) -> 0.12245451 | BP10: =_xlfn.XLOOKUP(tbl_Model[[#This Row],[country]],tbl_UnitsPerCountry[Country],tbl_UnitsPerCountry[Units2026],0) *SUMIFS(tbl_CollectionMix[Mix2026],tbl_CollectionMix[country],tbl_Model[[#This Row],[country]],tbl_CollectionMix[collection],tbl_Model[[#This Row],[collection]]) *IF(tbl_Model[[#This Row],[Type]]="Boutique", SUMIFS(tbl_ChannelMix[BoutiqueShare_2026_Effective],tbl_ChannelMix[Country],tbl_Model[[#This Row],[country]],tbl_ChannelMix[Collection],tbl_Model[[#This Row],[collection]]), 1-SUMIFS(tbl_ChannelMix[BoutiqueShare_2026_Effective],tbl_ChannelMix[Country],tbl_Model[[#This Row],[country]],tbl_ChannelMix[Collection],tbl_Model[[#This Row],[collection]])) -> 135.60246 | BQ10: {=IF(SUMIFS(tbl_SkuPrices[Units2025Actual],tbl_SkuPrices[Collection],tbl_Model[[#This Row],[collection]])=0, 0, SUMPRODUCT((tbl_SkuPrices[Collection]=tbl_Model[[#This Row],[collection]])*tbl_SkuPrices[BudgetedPrice2026]*tbl_SkuPrices[Units2025Actual]) /SUMIFS(tbl_SkuPrices[Units2025Actual],tbl_SkuPrices[Collection],tbl_Model[[#This Row],[collection]]))} -> 23436.225 | BR10: {=IF(SUMIFS(tbl_SkuPrices[Units2025Actual],tbl_SkuPrices[Collection],tbl_Model[[#This Row],[collection]])=0,0,SUMPRODUCT((tbl_SkuPrices[Collection]=tbl_Model[[#This Row],[collection]])*tbl_SkuPrices[BudgetedCost2026]*tbl_SkuPrices[Units2025Actual]) /SUMIFS(tbl_SkuPrices[Units2025Actual],tbl_SkuPrices[Collection],tbl_Model[[#This Row],[collection]]))} -> 5419.716 | BS10: =IF(tbl_Model[[#This Row],[Type]]="Boutique", tbl_Model[[#This Row],[UnitListPrice]], tbl_Model[[#This Row],[UnitListPrice]]*(1-SUMIFS(tbl_MarketTerms[WholesaleMarginPct],tbl_MarketTerms[Country],tbl_Model[[#This Row],[country]]))) -> 23436.225 | BT10: =Model!$BP10*BD10 -> 9.9841229 | BU10: =Model!$BP10*BE10 -> 11.308029 | BV10: =Model!$BP10*BF10 -> 11.228929 | BW10: =Model!$BP10*BG10 -> 11.028447 | BX10: =Model!$BP10*BH10 -> 10.407304 | BY10: =Model!$BP10*BI10 -> 9.2341409 | BZ10: =Model!$BP10*BJ10 -> 8.0657756 | CA10: =Model!$BP10*BK10 -> 13.467489 | ... CE10: =Model!$BP10*BO10 -> 16.605133 | CF10: =Model!$BS10*BT10 -> 233990.15 | CG10: =Model!$BS10*BU10 -> 265017.52 | CH10: =Model!$BS10*BV10 -> 263163.71 | CI10: =Model!$BS10*BW10 -> 258465.17 | CJ10: =Model!$BS10*BX10 -> 243907.91 | CK10: =Model!$BS10*BY10 -> 216413.4 | CL10: =Model!$BS10*BZ10 -> 189031.33 | CM10: =Model!$BS10*CA10 -> 315627.1 | ... CQ10: =Model!$BS10*CE10 -> 389161.63 | CR10: =Model!$BR10*BT10 -> 54111.11 | CS10: =Model!$BR10*BU10 -> 61286.308 | CT10: =Model!$BR10*BV10 -> 60857.606 | CU10: =Model!$BR10*BW10 -> 59771.053 | CV10: =Model!$BR10*BX10 -> 56404.63 | CW10: =Model!$BR10*BY10 -> 50046.421 | CX10: =Model!$BR10*BZ10 -> 43714.213 | CY10: =Model!$BR10*CA10 -> 72989.966 | ... DC10: =Model!$BR10*CE10 -> 89995.104 | DD10: =SUM(Model!$CF10:$CQ10) -> 3178009.7 | DE10: =SUM(Model!$CR10:$DC10) -> 734926.81 | DF10: =IFERROR((Model!$DD10-Model!$DE10)/Model!$DD10,0) -> 0.7687462
B11: Boutique | C11: Atelier | D11: Brazil | E11: 31 | F11: 914000.95 | G11: 210113.11 | H11: 0 | I11: 2 | J11: 2 | K11: 2 | L11: 6 | M11: 0 | N11: 1 | O11: 2 | P11: 4 | Q11: 3 | R11: 2 | S11: 0 | T11: 0 | U11: 0 | V11: 2 | W11: 4 | X11: 1 | Y11: 2 | Z11: 0 | AA11: 2 | AB11: 7 | AC11: 1 | AD11: 3 | AE11: 3 | AF11: 4 | AG11: 5 | AH11: 2 | AI11: 2 | AJ11: 3 | AK11: 1 | AL11: 1 | AM11: 1 | AN11: 2 | AO11: 3 | AP11: 3 | AQ11: 4 | AR11: =MAX(IFERROR(IFERROR(_xlfn.FORECAST.ETS(AR$5,tbl_Model[[#This Row],[H_2023_01]:[H_2025_12]],$H$5:$AQ$5),_xlfn.FORECAST.LINEAR(AR$5,tbl_Model[[#This Row],[H_2023_01]:[H_2025_12]],$H$5:$AQ$5)),0),0) -> 2.8543133 | AS11: =MAX(IFERROR(IFERROR(_xlfn.FORECAST.ETS(AS$5,tbl_Model[[#This Row],[H_2023_01]:[H_2025_12]],$H$5:$AQ$5),_xlfn.FORECAST.LINEAR(AS$5,tbl_Model[[#This Row],[H_2023_01]:[H_2025_12]],$H$5:$AQ$5)),0),0) -> 2.8971878 | AT11: =MAX(IFERROR(IFERROR(_xlfn.FORECAST.ETS(AT$5,tbl_Model[[#This Row],[H_2023_01]:[H_2025_12]],$H$5:$AQ$5),_xlfn.FORECAST.LINEAR(AT$5,tbl_Model[[#This Row],[H_2023_01]:[H_2025_12]],$H$5:$AQ$5)),0),0) -> 2.9400622 | AU11: =MAX(IFERROR(IFERROR(_xlfn.FORECAST.ETS(AU$5,tbl_Model[[#This Row],[H_2023_01]:[H_2025_12]],$H$5:$AQ$5),_xlfn.FORECAST.LINEAR(AU$5,tbl_Model[[#This Row],[H_2023_01]:[H_2025_12]],$H$5:$AQ$5)),0),0) -> 2.9829367 | AV11: =MAX(IFERROR(IFERROR(_xlfn.FORECAST.ETS(AV$5,tbl_Model[[#This Row],[H_2023_01]:[H_2025_12]],$H$5:$AQ$5),_xlfn.FORECAST.LINEAR(AV$5,tbl_Model[[#This Row],[H_2023_01]:[H_2025_12]],$H$5:$AQ$5)),0),0) -> 3.0258111 | AW11: =MAX(IFERROR(IFERROR(_xlfn.FORECAST.ETS(AW$5,tbl_Model[[#This Row],[H_2023_01]:[H_2025_12]],$H$5:$AQ$5),_xlfn.FORECAST.LINEAR(AW$5,tbl_Model[[#This Row],[H_2023_01]:[H_2025_12]],$H$5:$AQ$5)),0),0) -> 3.0686856 | AX11: =MAX(IFERROR(IFERROR(_xlfn.FORECAST.ETS(AX$5,tbl_Model[[#This Row],[H_2023_01]:[H_2025_12]],$H$5:$AQ$5),_xlfn.FORECAST.LINEAR(AX$5,tbl_Model[[#This Row],[H_2023_01]:[H_2025_12]],$H$5:$AQ$5)),0),0) -> 3.1115601 | AY11: =MAX(IFERROR(IFERROR(_xlfn.FORECAST.ETS(AY$5,tbl_Model[[#This Row],[H_2023_01]:[H_2025_12]],$H$5:$AQ$5),_xlfn.FORECAST.LINEAR(AY$5,tbl_Model[[#This Row],[H_2023_01]:[H_2025_12]],$H$5:$AQ$5)),0),0) -> 3.1544345 | ... BC11: =MAX(IFERROR(IFERROR(_xlfn.FORECAST.ETS(BC$5,tbl_Model[[#This Row],[H_2023_01]:[H_2025_12]],$H$5:$AQ$5),_xlfn.FORECAST.LINEAR(BC$5,tbl_Model[[#This Row],[H_2023_01]:[H_2025_12]],$H$5:$AQ$5)),0),0) -> 3.3259323 | BD11: =IFERROR(AR11/SUM(Model!$AR11:$BC11),1/12) -> 0.076974107 | BE11: =IFERROR(AS11/SUM(Model!$AR11:$BC11),1/12) -> 0.07813033 | BF11: =IFERROR(AT11/SUM(Model!$AR11:$BC11),1/12) -> 0.079286553 | BG11: =IFERROR(AU11/SUM(Model!$AR11:$BC11),1/12) -> 0.080442776 | BH11: =IFERROR(AV11/SUM(Model!$AR11:$BC11),1/12) -> 0.081598999 | BI11: =IFERROR(AW11/SUM(Model!$AR11:$BC11),1/12) -> 0.082755222 | BJ11: =IFERROR(AX11/SUM(Model!$AR11:$BC11),1/12) -> 0.083911445 | BK11: =IFERROR(AY11/SUM(Model!$AR11:$BC11),1/12) -> 0.085067668 | ... BO11: =IFERROR(BC11/SUM(Model!$AR11:$BC11),1/12) -> 0.08969256 | BP11: =_xlfn.XLOOKUP(tbl_Model[[#This Row],[country]],tbl_UnitsPerCountry[Country],tbl_UnitsPerCountry[Units2026],0) *SUMIFS(tbl_CollectionMix[Mix2026],tbl_CollectionMix[country],tbl_Model[[#This Row],[country]],tbl_CollectionMix[collection],tbl_Model[[#This Row],[collection]]) *IF(tbl_Model[[#This Row],[Type]]="Boutique", SUMIFS(tbl_ChannelMix[BoutiqueShare_2026_Effective],tbl_ChannelMix[Country],tbl_Model[[#This Row],[country]],tbl_ChannelMix[Collection],tbl_Model[[#This Row],[collection]]), 1-SUMIFS(tbl_ChannelMix[BoutiqueShare_2026_Effective],tbl_ChannelMix[Country],tbl_Model[[#This Row],[country]],tbl_ChannelMix[Collection],tbl_Model[[#This Row],[collection]])) -> 63.289037 | BQ11: {=IF(SUMIFS(tbl_SkuPrices[Units2025Actual],tbl_SkuPrices[Collection],tbl_Model[[#This Row],[collection]])=0, 0, SUMPRODUCT((tbl_SkuPrices[Collection]=tbl_Model[[#This Row],[collection]])*tbl_SkuPrices[BudgetedPrice2026]*tbl_SkuPrices[Units2025Actual]) /SUMIFS(tbl_SkuPrices[Units2025Actual],tbl_SkuPrices[Collection],tbl_Model[[#This Row],[collection]]))} -> 29113.63 | BR11: {=IF(SUMIFS(tbl_SkuPrices[Units2025Actual],tbl_SkuPrices[Collection],tbl_Model[[#This Row],[collection]])=0,0,SUMPRODUCT((tbl_SkuPrices[Collection]=tbl_Model[[#This Row],[collection]])*tbl_SkuPrices[BudgetedCost2026]*tbl_SkuPrices[Units2025Actual]) /SUMIFS(tbl_SkuPrices[Units2025Actual],tbl_SkuPrices[Collection],tbl_Model[[#This Row],[collection]]))} -> 6636.0593 | BS11: =IF(tbl_Model[[#This Row],[Type]]="Boutique", tbl_Model[[#This Row],[UnitListPrice]], tbl_Model[[#This Row],[UnitListPrice]]*(1-SUMIFS(tbl_MarketTerms[WholesaleMarginPct],tbl_MarketTerms[Country],tbl_Model[[#This Row],[country]]))) -> 29113.63 | BT11: =Model!$BP11*BD11 -> 4.871617 | BU11: =Model!$BP11*BE11 -> 4.9447933 | BV11: =Model!$BP11*BF11 -> 5.0179695 | BW11: =Model!$BP11*BG11 -> 5.0911458 | BX11: =Model!$BP11*BH11 -> 5.164322 | BY11: =Model!$BP11*BI11 -> 5.2374983 | BZ11: =Model!$BP11*BJ11 -> 5.3106745 | CA11: =Model!$BP11*BK11 -> 5.3838507 | ... CE11: =Model!$BP11*BO11 -> 5.6765557 | CF11: =Model!$BS11*BT11 -> 141830.46 | CG11: =Model!$BS11*BU11 -> 143960.88 | CH11: =Model!$BS11*BV11 -> 146091.31 | CI11: =Model!$BS11*BW11 -> 148221.73 | CJ11: =Model!$BS11*BX11 -> 150352.16 | CK11: =Model!$BS11*BY11 -> 152482.59 | CL11: =Model!$BS11*BZ11 -> 154613.01 | CM11: =Model!$BS11*CA11 -> 156743.44 | ... CQ11: =Model!$BS11*CE11 -> 165265.14 | CR11: =Model!$BR11*BT11 -> 32328.34 | CS11: =Model!$BR11*BU11 -> 32813.941 | CT11: =Model!$BR11*BV11 -> 33299.543 | CU11: =Model!$BR11*BW11 -> 33785.145 | CV11: =Model!$BR11*BX11 -> 34270.747 | CW11: =Model!$BR11*BY11 -> 34756.349 | CX11: =Model!$BR11*BZ11 -> 35241.951 | CY11: =Model!$BR11*CA11 -> 35727.553 | ... DC11: =Model!$BR11*CE11 -> 37669.96 | DD11: =SUM(Model!$CF11:$CQ11) -> 1842573.6 | DE11: =SUM(Model!$CR11:$DC11) -> 419989.8 | DF11: =IFERROR((Model!$DD11-Model!$DE11)/Model!$DD11,0) -> 0.77206349
B12: Boutique | C12: Atelier | D12: France | E12: 77 | F12: 2186178 | G12: 505271.07 | H12: 7 | I12: 2 | J12: 5 | K12: 3 | L12: 3 | M12: 3 | N12: 1 | O12: 6 | P12: 1 | Q12: 6 | R12: 5 | S12: 6 | T12: 3 | U12: 9 | V12: 5 | W12: 8 | X12: 5 | Y12: 6 | Z12: 4 | AA12: 7 | AB12: 8 | AC12: 7 | AD12: 8 | AE12: 10 | AF12: 2 | AG12: 7 | AH12: 11 | AI12: 5 | AJ12: 5 | AK12: 1 | AL12: 6 | AM12: 5 | AN12: 8 | AO12: 12 | AP12: 7 | AQ12: 8 | AR12: =MAX(IFERROR(IFERROR(_xlfn.FORECAST.ETS(AR$5,tbl_Model[[#This Row],[H_2023_01]:[H_2025_12]],$H$5:$AQ$5),_xlfn.FORECAST.LINEAR(AR$5,tbl_Model[[#This Row],[H_2023_01]:[H_2025_12]],$H$5:$AQ$5)),0),0) -> 7.90908 | AS12: =MAX(IFERROR(IFERROR(_xlfn.FORECAST.ETS(AS$5,tbl_Model[[#This Row],[H_2023_01]:[H_2025_12]],$H$5:$AQ$5),_xlfn.FORECAST.LINEAR(AS$5,tbl_Model[[#This Row],[H_2023_01]:[H_2025_12]],$H$5:$AQ$5)),0),0) -> 8.012984 | AT12: =MAX(IFERROR(IFERROR(_xlfn.FORECAST.ETS(AT$5,tbl_Model[[#This Row],[H_2023_01]:[H_2025_12]],$H$5:$AQ$5),_xlfn.FORECAST.LINEAR(AT$5,tbl_Model[[#This Row],[H_2023_01]:[H_2025_12]],$H$5:$AQ$5)),0),0) -> 8.1168881 | AU12: =MAX(IFERROR(IFERROR(_xlfn.FORECAST.ETS(AU$5,tbl_Model[[#This Row],[H_2023_01]:[H_2025_12]],$H$5:$AQ$5),_xlfn.FORECAST.LINEAR(AU$5,tbl_Model[[#This Row],[H_2023_01]:[H_2025_12]],$H$5:$AQ$5)),0),0) -> 8.2207922 | AV12: =MAX(IFERROR(IFERROR(_xlfn.FORECAST.ETS(AV$5,tbl_Model[[#This Row],[H_2023_01]:[H_2025_12]],$H$5:$AQ$5),_xlfn.FORECAST.LINEAR(AV$5,tbl_Model[[#This Row],[H_2023_01]:[H_2025_12]],$H$5:$AQ$5)),0),0) -> 8.3246962 | AW12: =MAX(IFERROR(IFERROR(_xlfn.FORECAST.ETS(AW$5,tbl_Model[[#This Row],[H_2023_01]:[H_2025_12]],$H$5:$AQ$5),_xlfn.FORECAST.LINEAR(AW$5,tbl_Model[[#This Row],[H_2023_01]:[H_2025_12]],$H$5:$AQ$5)),0),0) -> 8.4286003 | AX12: =MAX(IFERROR(IFERROR(_xlfn.FORECAST.ETS(AX$5,tbl_Model[[#This Row],[H_2023_01]:[H_2025_12]],$H$5:$AQ$5),_xlfn.FORECAST.LINEAR(AX$5,tbl_Model[[#This Row],[H_2023_01]:[H_2025_12]],$H$5:$AQ$5)),0),0) -> 8.5325044 | AY12: =MAX(IFERROR(IFERROR(_xlfn.FORECAST.ETS(AY$5,tbl_Model[[#This Row],[H_2023_01]:[H_2025_12]],$H$5:$AQ$5),_xlfn.FORECAST.LINEAR(AY$5,tbl_Model[[#This Row],[H_2023_01]:[H_2025_12]],$H$5:$AQ$5)),0),0) -> 8.6364084 | ... BC12: =MAX(IFERROR(IFERROR(_xlfn.FORECAST.ETS(BC$5,tbl_Model[[#This Row],[H_2023_01]:[H_2025_12]],$H$5:$AQ$5),_xlfn.FORECAST.LINEAR(BC$5,tbl_Model[[#This Row],[H_2023_01]:[H_2025_12]],$H$5:$AQ$5)),0),0) -> 9.0520247 | BD12: =IFERROR(AR12/SUM(Model!$AR12:$BC12),1/12) -> 0.077717815 | BE12: =IFERROR(AS12/SUM(Model!$AR12:$BC12),1/12) -> 0.078738818 | BF12: =IFERROR(AT12/SUM(Model!$AR12:$BC12),1/12) -> 0.079759822 | BG12: =IFERROR(AU12/SUM(Model!$AR12:$BC12),1/12) -> 0.080780825 | BH12: =IFERROR(AV12/SUM(Model!$AR12:$BC12),1/12) -> 0.081801828 | BI12: =IFERROR(AW12/SUM(Model!$AR12:$BC12),1/12) -> 0.082822832 | BJ12: =IFERROR(AX12/SUM(Model!$AR12:$BC12),1/12) -> 0.083843835 | BK12: =IFERROR(AY12/SUM(Model!$AR12:$BC12),1/12) -> 0.084864838 | ... BO12: =IFERROR(BC12/SUM(Model!$AR12:$BC12),1/12) -> 0.088948852 | BP12: =_xlfn.XLOOKUP(tbl_Model[[#This Row],[country]],tbl_UnitsPerCountry[Country],tbl_UnitsPerCountry[Units2026],0) *SUMIFS(tbl_CollectionMix[Mix2026],tbl_CollectionMix[country],tbl_Model[[#This Row],[country]],tbl_CollectionMix[collection],tbl_Model[[#This Row],[collection]]) *IF(tbl_Model[[#This Row],[Type]]="Boutique", SUMIFS(tbl_ChannelMix[BoutiqueShare_2026_Effective],tbl_ChannelMix[Country],tbl_Model[[#This Row],[country]],tbl_ChannelMix[Collection],tbl_Model[[#This Row],[collection]]), 1-SUMIFS(tbl_ChannelMix[BoutiqueShare_2026_Effective],tbl_ChannelMix[Country],tbl_Model[[#This Row],[country]],tbl_ChannelMix[Collection],tbl_Model[[#This Row],[collection]])) -> 84.905689 | BQ12: {=IF(SUMIFS(tbl_SkuPrices[Units2025Actual],tbl_SkuPrices[Collection],tbl_Model[[#This Row],[collection]])=0, 0, SUMPRODUCT((tbl_SkuPrices[Collection]=tbl_Model[[#This Row],[collection]])*tbl_SkuPrices[BudgetedPrice2026]*tbl_SkuPrices[Units2025Actual]) /SUMIFS(tbl_SkuPrices[Units2025Actual],tbl_SkuPrices[Collection],tbl_Model[[#This Row],[collection]]))} -> 29113.63 | BR12: {=IF(SUMIFS(tbl_SkuPrices[Units2025Actual],tbl_SkuPrices[Collection],tbl_Model[[#This Row],[collection]])=0,0,SUMPRODUCT((tbl_SkuPrices[Collection]=tbl_Model[[#This Row],[collection]])*tbl_SkuPrices[BudgetedCost2026]*tbl_SkuPrices[Units2025Actual]) /SUMIFS(tbl_SkuPrices[Units2025Actual],tbl_SkuPrices[Collection],tbl_Model[[#This Row],[collection]]))} -> 6636.0593 | BS12: =IF(tbl_Model[[#This Row],[Type]]="Boutique", tbl_Model[[#This Row],[UnitListPrice]], tbl_Model[[#This Row],[UnitListPrice]]*(1-SUMIFS(tbl_MarketTerms[WholesaleMarginPct],tbl_MarketTerms[Country],tbl_Model[[#This Row],[country]]))) -> 29113.63 | BT12: =Model!$BP12*BD12 -> 6.5986847 | BU12: =Model!$BP12*BE12 -> 6.6853736 | BV12: =Model!$BP12*BF12 -> 6.7720626 | BW12: =Model!$BP12*BG12 -> 6.8587516 | BX12: =Model!$BP12*BH12 -> 6.9454406 | BY12: =Model!$BP12*BI12 -> 7.0321296 | BZ12: =Model!$BP12*BJ12 -> 7.1188186 | CA12: =Model!$BP12*BK12 -> 7.2055076 | ... CE12: =Model!$BP12*BO12 -> 7.5522635 | CF12: =Model!$BS12*BT12 -> 192111.66 | CG12: =Model!$BS12*BU12 -> 194635.49 | CH12: =Model!$BS12*BV12 -> 197159.32 | CI12: =Model!$BS12*BW12 -> 199683.16 | CJ12: =Model!$BS12*BX12 -> 202206.99 | CK12: =Model!$BS12*BY12 -> 204730.82 | CL12: =Model!$BS12*BZ12 -> 207254.65 | CM12: =Model!$BS12*CA12 -> 209778.48 | ... CQ12: =Model!$BS12*CE12 -> 219873.81 | CR12: =Model!$BR12*BT12 -> 43789.263 | CS12: =Model!$BR12*BU12 -> 44364.536 | CT12: =Model!$BR12*BV12 -> 44939.809 | CU12: =Model!$BR12*BW12 -> 45515.083 | CV12: =Model!$BR12*BX12 -> 46090.356 | CW12: =Model!$BR12*BY12 -> 46665.629 | CX12: =Model!$BR12*BZ12 -> 47240.902 | CY12: =Model!$BR12*CA12 -> 47816.176 | ... DC12: =Model!$BR12*CE12 -> 50117.269 | DD12: =SUM(Model!$CF12:$CQ12) -> 2471912.8 | DE12: =SUM(Model!$CR12:$DC12) -> 563439.19 | DF12: =IFERROR((Model!$DD12-Model!$DE12)/Model!$DD12,0) -> 0.77206349
B13: Boutique | C13: Atelier | D13: Canada | E13: 23 | F13: 666187.31 | G13: 154532.1 | H13: 2 | I13: 0 | J13: 4 | K13: 2 | L13: 4 | M13: 2 | N13: 2 | O13: 2 | P13: 5 | Q13: 1 | R13: 6 | S13: 0 | T13: 3 | U13: 5 | V13: 2 | W13: 7 | X13: 0 | Y13: 0 | Z13: 2 | AA13: 2 | AB13: 0 | AC13: 1 | AD13: 2 | AE13: 6 | AF13: 0 | AG13: 0 | AH13: 3 | AI13: 1 | AJ13: 5 | AK13: 2 | AL13: 1 | AM13: 3 | AN13: 2 | AO13: 3 | AP13: 0 | AQ13: 3 | AR13: =MAX(IFERROR(IFERROR(_xlfn.FORECAST.ETS(AR$5,tbl_Model[[#This Row],[H_2023_01]:[H_2025_12]],$H$5:$AQ$5),_xlfn.FORECAST.LINEAR(AR$5,tbl_Model[[#This Row],[H_2023_01]:[H_2025_12]],$H$5:$AQ$5)),0),0) -> 1.6018444 | AS13: =MAX(IFERROR(IFERROR(_xlfn.FORECAST.ETS(AS$5,tbl_Model[[#This Row],[H_2023_01]:[H_2025_12]],$H$5:$AQ$5),_xlfn.FORECAST.LINEAR(AS$5,tbl_Model[[#This Row],[H_2023_01]:[H_2025_12]],$H$5:$AQ$5)),0),0) -> 1.8269413 | AT13: =MAX(IFERROR(IFERROR(_xlfn.FORECAST.ETS(AT$5,tbl_Model[[#This Row],[H_2023_01]:[H_2025_12]],$H$5:$AQ$5),_xlfn.FORECAST.LINEAR(AT$5,tbl_Model[[#This Row],[H_2023_01]:[H_2025_12]],$H$5:$AQ$5)),0),0) -> 2.2326018 | AU13: =MAX(IFERROR(IFERROR(_xlfn.FORECAST.ETS(AU$5,tbl_Model[[#This Row],[H_2023_01]:[H_2025_12]],$H$5:$AQ$5),_xlfn.FORECAST.LINEAR(AU$5,tbl_Model[[#This Row],[H_2023_01]:[H_2025_12]],$H$5:$AQ$5)),0),0) -> 1.5466748 | AV13: =MAX(IFERROR(IFERROR(_xlfn.FORECAST.ETS(AV$5,tbl_Model[[#This Row],[H_2023_01]:[H_2025_12]],$H$5:$AQ$5),_xlfn.FORECAST.LINEAR(AV$5,tbl_Model[[#This Row],[H_2023_01]:[H_2025_12]],$H$5:$AQ$5)),0),0) -> 1.7717717 | AW13: =MAX(IFERROR(IFERROR(_xlfn.FORECAST.ETS(AW$5,tbl_Model[[#This Row],[H_2023_01]:[H_2025_12]],$H$5:$AQ$5),_xlfn.FORECAST.LINEAR(AW$5,tbl_Model[[#This Row],[H_2023_01]:[H_2025_12]],$H$5:$AQ$5)),0),0) -> 2.1774323 | AX13: =MAX(IFERROR(IFERROR(_xlfn.FORECAST.ETS(AX$5,tbl_Model[[#This Row],[H_2023_01]:[H_2025_12]],$H$5:$AQ$5),_xlfn.FORECAST.LINEAR(AX$5,tbl_Model[[#This Row],[H_2023_01]:[H_2025_12]],$H$5:$AQ$5)),0),0) -> 1.4915053 | AY13: =MAX(IFERROR(IFERROR(_xlfn.FORECAST.ETS(AY$5,tbl_Model[[#This Row],[H_2023_01]:[H_2025_12]],$H$5:$AQ$5),_xlfn.FORECAST.LINEAR(AY$5,tbl_Model[[#This Row],[H_2023_01]:[H_2025_12]],$H$5:$AQ$5)),0),0) -> 1.7166022 | ... BC13: =MAX(IFERROR(IFERROR(_xlfn.FORECAST.ETS(BC$5,tbl_Model[[#This Row],[H_2023_01]:[H_2025_12]],$H$5:$AQ$5),_xlfn.FORECAST.LINEAR(BC$5,tbl_Model[[#This Row],[H_2023_01]:[H_2025_12]],$H$5:$AQ$5)),0),0) -> 2.0670932 | BD13: =IFERROR(AR13/SUM(Model!$AR13:$BC13),1/12) -> 0.073979656 | BE13: =IFERROR(AS13/SUM(Model!$AR13:$BC13),1/12) -> 0.084375542 | BF13: =IFERROR(AT13/SUM(Model!$AR13:$BC13),1/12) -> 0.10311059 | BG13: =IFERROR(AU13/SUM(Model!$AR13:$BC13),1/12) -> 0.071431703 | BH13: =IFERROR(AV13/SUM(Model!$AR13:$BC13),1/12) -> 0.081827589 | BI13: =IFERROR(AW13/SUM(Model!$AR13:$BC13),1/12) -> 0.10056264 | BJ13: =IFERROR(AX13/SUM(Model!$AR13:$BC13),1/12) -> 0.068883751 | BK13: =IFERROR(AY13/SUM(Model!$AR13:$BC13),1/12) -> 0.079279637 | ... BO13: =IFERROR(BC13/SUM(Model!$AR13:$BC13),1/12) -> 0.095466731 | BP13: =_xlfn.XLOOKUP(tbl_Model[[#This Row],[country]],tbl_UnitsPerCountry[Country],tbl_UnitsPerCountry[Units2026],0) *SUMIFS(tbl_CollectionMix[Mix2026],tbl_CollectionMix[country],tbl_Model[[#This Row],[country]],tbl_CollectionMix[collection],tbl_Model[[#This Row],[collection]]) *IF(tbl_Model[[#This Row],[Type]]="Boutique", SUMIFS(tbl_ChannelMix[BoutiqueShare_2026_Effective],tbl_ChannelMix[Country],tbl_Model[[#This Row],[country]],tbl_ChannelMix[Collection],tbl_Model[[#This Row],[collection]]), 1-SUMIFS(tbl_ChannelMix[BoutiqueShare_2026_Effective],tbl_ChannelMix[Country],tbl_Model[[#This Row],[country]],tbl_ChannelMix[Collection],tbl_Model[[#This Row],[collection]])) -> 25.389085 | BQ13: {=IF(SUMIFS(tbl_SkuPrices[Units2025Actual],tbl_SkuPrices[Collection],tbl_Model[[#This Row],[collection]])=0, 0, SUMPRODUCT((tbl_SkuPrices[Collection]=tbl_Model[[#This Row],[collection]])*tbl_SkuPrices[BudgetedPrice2026]*tbl_SkuPrices[Units2025Actual]) /SUMIFS(tbl_SkuPrices[Units2025Actual],tbl_SkuPrices[Collection],tbl_Model[[#This Row],[collection]]))} -> 29113.63 | BR13: {=IF(SUMIFS(tbl_SkuPrices[Units2025Actual],tbl_SkuPrices[Collection],tbl_Model[[#This Row],[collection]])=0,0,SUMPRODUCT((tbl_SkuPrices[Collection]=tbl_Model[[#This Row],[collection]])*tbl_SkuPrices[BudgetedCost2026]*tbl_SkuPrices[Units2025Actual]) /SUMIFS(tbl_SkuPrices[Units2025Actual],tbl_SkuPrices[Collection],tbl_Model[[#This Row],[collection]]))} -> 6636.0593 | BS13: =IF(tbl_Model[[#This Row],[Type]]="Boutique", tbl_Model[[#This Row],[UnitListPrice]], tbl_Model[[#This Row],[UnitListPrice]]*(1-SUMIFS(tbl_MarketTerms[WholesaleMarginPct],tbl_MarketTerms[Country],tbl_Model[[#This Row],[country]]))) -> 29113.63 | BT13: =Model!$BP13*BD13 -> 1.8782757 | BU13: =Model!$BP13*BE13 -> 2.1422178 | BV13: =Model!$BP13*BF13 -> 2.6178835 | BW13: =Model!$BP13*BG13 -> 1.8135856 | BX13: =Model!$BP13*BH13 -> 2.0775276 | BY13: =Model!$BP13*BI13 -> 2.5531933 | BZ13: =Model!$BP13*BJ13 -> 1.7488954 | CA13: =Model!$BP13*BK13 -> 2.0128374 | ... CE13: =Model!$BP13*BO13 -> 2.4238129 | CF13: =Model!$BS13*BT13 -> 54683.425 | CG13: =Model!$BS13*BU13 -> 62367.735 | CH13: =Model!$BS13*BV13 -> 76216.09 | CI13: =Model!$BS13*BW13 -> 52800.058 | CJ13: =Model!$BS13*BX13 -> 60484.369 | CK13: =Model!$BS13*BY13 -> 74332.724 | CL13: =Model!$BS13*BZ13 -> 50916.692 | CM13: =Model!$BS13*CA13 -> 58601.003 | ... CQ13: =Model!$BS13*CE13 -> 70565.992 | CR13: =Model!$BR13*BT13 -> 12464.349 | CS13: =Model!$BR13*BU13 -> 14215.884 | CT13: =Model!$BR13*BV13 -> 17372.43 | CU13: =Model!$BR13*BW13 -> 12035.061 | CV13: =Model!$BR13*BX13 -> 13786.596 | CW13: =Model!$BR13*BY13 -> 16943.142 | CX13: =Model!$BR13*BZ13 -> 11605.773 | CY13: =Model!$BR13*CA13 -> 13357.308 | ... DC13: =Model!$BR13*CE13 -> 16084.566 | DD13: =SUM(Model!$CF13:$CQ13) -> 739168.41 | DE13: =SUM(Model!$CR13:$DC13) -> 168483.47 | DF13: =IFERROR((Model!$DD13-Model!$DE13)/Model!$DD13,0) -> 0.77206349
B14: Boutique | C14: Celeste | D14: Argentina | E14: 27 | F14: 619498.41 | G14: 143045.16 | H14: 0 | I14: 0 | J14: 0 | K14: 0 | L14: 0 | M14: 0 | N14: 0 | O14: 0 | P14: 0 | Q14: 0 | R14: 0 | S14: 0 | T14: 0 | U14: 0 | V14: 0 | W14: 0 | X14: 0 | Y14: 0 | Z14: 0 | AA14: 0 | AB14: 0 | AC14: 0 | AD14: 0 | AE14: 0 | AF14: 1 | AG14: 2 | AH14: 2 | AI14: 4 | AJ14: 8 | AK14: 1 | AL14: 1 | AM14: 1 | AN14: 1 | AO14: 1 | AP14: 3 | AQ14: 2 | AR14: =MAX(IFERROR(IFERROR(_xlfn.FORECAST.ETS(AR$5,tbl_Model[[#This Row],[H_2023_01]:[H_2025_12]],$H$5:$AQ$5),_xlfn.FORECAST.LINEAR(AR$5,tbl_Model[[#This Row],[H_2023_01]:[H_2025_12]],$H$5:$AQ$5)),0),0) -> 2.1685874 | AS14: =MAX(IFERROR(IFERROR(_xlfn.FORECAST.ETS(AS$5,tbl_Model[[#This Row],[H_2023_01]:[H_2025_12]],$H$5:$AQ$5),_xlfn.FORECAST.LINEAR(AS$5,tbl_Model[[#This Row],[H_2023_01]:[H_2025_12]],$H$5:$AQ$5)),0),0) -> 2.2482456 | AT14: =MAX(IFERROR(IFERROR(_xlfn.FORECAST.ETS(AT$5,tbl_Model[[#This Row],[H_2023_01]:[H_2025_12]],$H$5:$AQ$5),_xlfn.FORECAST.LINEAR(AT$5,tbl_Model[[#This Row],[H_2023_01]:[H_2025_12]],$H$5:$AQ$5)),0),0) -> 2.3279038 | AU14: =MAX(IFERROR(IFERROR(_xlfn.FORECAST.ETS(AU$5,tbl_Model[[#This Row],[H_2023_01]:[H_2025_12]],$H$5:$AQ$5),_xlfn.FORECAST.LINEAR(AU$5,tbl_Model[[#This Row],[H_2023_01]:[H_2025_12]],$H$5:$AQ$5)),0),0) -> 2.407562 | AV14: =MAX(IFERROR(IFERROR(_xlfn.FORECAST.ETS(AV$5,tbl_Model[[#This Row],[H_2023_01]:[H_2025_12]],$H$5:$AQ$5),_xlfn.FORECAST.LINEAR(AV$5,tbl_Model[[#This Row],[H_2023_01]:[H_2025_12]],$H$5:$AQ$5)),0),0) -> 2.4872202 | AW14: =MAX(IFERROR(IFERROR(_xlfn.FORECAST.ETS(AW$5,tbl_Model[[#This Row],[H_2023_01]:[H_2025_12]],$H$5:$AQ$5),_xlfn.FORECAST.LINEAR(AW$5,tbl_Model[[#This Row],[H_2023_01]:[H_2025_12]],$H$5:$AQ$5)),0),0) -> 2.5668784 | AX14: =MAX(IFERROR(IFERROR(_xlfn.FORECAST.ETS(AX$5,tbl_Model[[#This Row],[H_2023_01]:[H_2025_12]],$H$5:$AQ$5),_xlfn.FORECAST.LINEAR(AX$5,tbl_Model[[#This Row],[H_2023_01]:[H_2025_12]],$H$5:$AQ$5)),0),0) -> 2.6465366 | AY14: =MAX(IFERROR(IFERROR(_xlfn.FORECAST.ETS(AY$5,tbl_Model[[#This Row],[H_2023_01]:[H_2025_12]],$H$5:$AQ$5),_xlfn.FORECAST.LINEAR(AY$5,tbl_Model[[#This Row],[H_2023_01]:[H_2025_12]],$H$5:$AQ$5)),0),0) -> 2.7261948 | ... BC14: =MAX(IFERROR(IFERROR(_xlfn.FORECAST.ETS(BC$5,tbl_Model[[#This Row],[H_2023_01]:[H_2025_12]],$H$5:$AQ$5),_xlfn.FORECAST.LINEAR(BC$5,tbl_Model[[#This Row],[H_2023_01]:[H_2025_12]],$H$5:$AQ$5)),0),0) -> 3.0448276 | BD14: =IFERROR(AR14/SUM(Model!$AR14:$BC14),1/12) -> 0.069327157 | BE14: =IFERROR(AS14/SUM(Model!$AR14:$BC14),1/12) -> 0.071873734 | BF14: =IFERROR(AT14/SUM(Model!$AR14:$BC14),1/12) -> 0.074420312 | BG14: =IFERROR(AU14/SUM(Model!$AR14:$BC14),1/12) -> 0.076966889 | BH14: =IFERROR(AV14/SUM(Model!$AR14:$BC14),1/12) -> 0.079513467 | BI14: =IFERROR(AW14/SUM(Model!$AR14:$BC14),1/12) -> 0.082060045 | BJ14: =IFERROR(AX14/SUM(Model!$AR14:$BC14),1/12) -> 0.084606622 | BK14: =IFERROR(AY14/SUM(Model!$AR14:$BC14),1/12) -> 0.0871532 | ... BO14: =IFERROR(BC14/SUM(Model!$AR14:$BC14),1/12) -> 0.09733951 | BP14: =_xlfn.XLOOKUP(tbl_Model[[#This Row],[country]],tbl_UnitsPerCountry[Country],tbl_UnitsPerCountry[Units2026],0) *SUMIFS(tbl_CollectionMix[Mix2026],tbl_CollectionMix[country],tbl_Model[[#This Row],[country]],tbl_CollectionMix[collection],tbl_Model[[#This Row],[collection]]) *IF(tbl_Model[[#This Row],[Type]]="Boutique", SUMIFS(tbl_ChannelMix[BoutiqueShare_2026_Effective],tbl_ChannelMix[Country],tbl_Model[[#This Row],[country]],tbl_ChannelMix[Collection],tbl_Model[[#This Row],[collection]]), 1-SUMIFS(tbl_ChannelMix[BoutiqueShare_2026_Effective],tbl_ChannelMix[Country],tbl_Model[[#This Row],[country]],tbl_ChannelMix[Collection],tbl_Model[[#This Row],[collection]])) -> 29.682692 | BQ14: {=IF(SUMIFS(tbl_SkuPrices[Units2025Actual],tbl_SkuPrices[Collection],tbl_Model[[#This Row],[collection]])=0, 0, SUMPRODUCT((tbl_SkuPrices[Collection]=tbl_Model[[#This Row],[collection]])*tbl_SkuPrices[BudgetedPrice2026]*tbl_SkuPrices[Units2025Actual]) /SUMIFS(tbl_SkuPrices[Units2025Actual],tbl_SkuPrices[Collection],tbl_Model[[#This Row],[collection]]))} -> 23436.225 | BR14: {=IF(SUMIFS(tbl_SkuPrices[Units2025Actual],tbl_SkuPrices[Collection],tbl_Model[[#This Row],[collection]])=0,0,SUMPRODUCT((tbl_SkuPrices[Collection]=tbl_Model[[#This Row],[collection]])*tbl_SkuPrices[BudgetedCost2026]*tbl_SkuPrices[Units2025Actual]) /SUMIFS(tbl_SkuPrices[Units2025Actual],tbl_SkuPrices[Collection],tbl_Model[[#This Row],[collection]]))} -> 5419.716 | BS14: =IF(tbl_Model[[#This Row],[Type]]="Boutique", tbl_Model[[#This Row],[UnitListPrice]], tbl_Model[[#This Row],[UnitListPrice]]*(1-SUMIFS(tbl_MarketTerms[WholesaleMarginPct],tbl_MarketTerms[Country],tbl_Model[[#This Row],[country]]))) -> 23436.225 | BT14: =Model!$BP14*BD14 -> 2.0578167 | BU14: =Model!$BP14*BE14 -> 2.1334059 | BV14: =Model!$BP14*BF14 -> 2.2089952 | BW14: =Model!$BP14*BG14 -> 2.2845845 | BX14: =Model!$BP14*BH14 -> 2.3601738 | BY14: =Model!$BP14*BI14 -> 2.4357631 | BZ14: =Model!$BP14*BJ14 -> 2.5113523 | CA14: =Model!$BP14*BK14 -> 2.5869416 | ... CE14: =Model!$BP14*BO14 -> 2.8892987 | CF14: =Model!$BS14*BT14 -> 48227.454 | CG14: =Model!$BS14*BU14 -> 49998.981 | CH14: =Model!$BS14*BV14 -> 51770.509 | CI14: =Model!$BS14*BW14 -> 53542.036 | CJ14: =Model!$BS14*BX14 -> 55313.563 | CK14: =Model!$BS14*BY14 -> 57085.091 | CL14: =Model!$BS14*BZ14 -> 58856.618 | CM14: =Model!$BS14*CA14 -> 60628.145 | ... CQ14: =Model!$BS14*CE14 -> 67714.254 | CR14: =Model!$BR14*BT14 -> 11152.782 | CS14: =Model!$BR14*BU14 -> 11562.454 | CT14: =Model!$BR14*BV14 -> 11972.127 | CU14: =Model!$BR14*BW14 -> 12381.799 | CV14: =Model!$BR14*BX14 -> 12791.472 | CW14: =Model!$BR14*BY14 -> 13201.144 | CX14: =Model!$BR14*BZ14 -> 13610.816 | CY14: =Model!$BR14*CA14 -> 14020.489 | ... DC14: =Model!$BR14*CE14 -> 15659.178 | DD14: =SUM(Model!$CF14:$CQ14) -> 695650.25 | DE14: =SUM(Model!$CR14:$DC14) -> 160871.76 | DF14: =IFERROR((Model!$DD14-Model!$DE14)/Model!$DD14,0) -> 0.7687462
B15: Boutique | C15: Atelier | D15: Chile | E15: 38 | F15: 1073524.8 | G15: 248593.95 | H15: 0 | I15: 0 | J15: 0 | K15: 0 | L15: 0 | M15: 0 | N15: 0 | O15: 0 | P15: 0 | Q15: 0 | R15: 0 | S15: 0 | T15: 0 | U15: 0 | V15: 0 | W15: 0 | X15: 0 | Y15: 0 | Z15: 0 | AA15: 0 | AB15: 0 | AC15: 0 | AD15: 0 | AE15: 0 | AF15: 0 | AG15: 2 | AH15: 4 | AI15: 2 | AJ15: 8 | AK15: 4 | AL15: 2 | AM15: 1 | AN15: 1 | AO15: 0 | AP15: 9 | AQ15: 5 | AR15: =MAX(IFERROR(IFERROR(_xlfn.FORECAST.ETS(AR$5,tbl_Model[[#This Row],[H_2023_01]:[H_2025_12]],$H$5:$AQ$5),_xlfn.FORECAST.LINEAR(AR$5,tbl_Model[[#This Row],[H_2023_01]:[H_2025_12]],$H$5:$AQ$5)),0),0) -> 5.1253539 | AS15: =MAX(IFERROR(IFERROR(_xlfn.FORECAST.ETS(AS$5,tbl_Model[[#This Row],[H_2023_01]:[H_2025_12]],$H$5:$AQ$5),_xlfn.FORECAST.LINEAR(AS$5,tbl_Model[[#This Row],[H_2023_01]:[H_2025_12]],$H$5:$AQ$5)),0),0) -> 5.2507079 | AT15: =MAX(IFERROR(IFERROR(_xlfn.FORECAST.ETS(AT$5,tbl_Model[[#This Row],[H_2023_01]:[H_2025_12]],$H$5:$AQ$5),_xlfn.FORECAST.LINEAR(AT$5,tbl_Model[[#This Row],[H_2023_01]:[H_2025_12]],$H$5:$AQ$5)),0),0) -> 5.3760618 | AU15: =MAX(IFERROR(IFERROR(_xlfn.FORECAST.ETS(AU$5,tbl_Model[[#This Row],[H_2023_01]:[H_2025_12]],$H$5:$AQ$5),_xlfn.FORECAST.LINEAR(AU$5,tbl_Model[[#This Row],[H_2023_01]:[H_2025_12]],$H$5:$AQ$5)),0),0) -> 5.5014157 | AV15: =MAX(IFERROR(IFERROR(_xlfn.FORECAST.ETS(AV$5,tbl_Model[[#This Row],[H_2023_01]:[H_2025_12]],$H$5:$AQ$5),_xlfn.FORECAST.LINEAR(AV$5,tbl_Model[[#This Row],[H_2023_01]:[H_2025_12]],$H$5:$AQ$5)),0),0) -> 5.6267696 | AW15: =MAX(IFERROR(IFERROR(_xlfn.FORECAST.ETS(AW$5,tbl_Model[[#This Row],[H_2023_01]:[H_2025_12]],$H$5:$AQ$5),_xlfn.FORECAST.LINEAR(AW$5,tbl_Model[[#This Row],[H_2023_01]:[H_2025_12]],$H$5:$AQ$5)),0),0) -> 5.7521236 | AX15: =MAX(IFERROR(IFERROR(_xlfn.FORECAST.ETS(AX$5,tbl_Model[[#This Row],[H_2023_01]:[H_2025_12]],$H$5:$AQ$5),_xlfn.FORECAST.LINEAR(AX$5,tbl_Model[[#This Row],[H_2023_01]:[H_2025_12]],$H$5:$AQ$5)),0),0) -> 5.8774775 | AY15: =MAX(IFERROR(IFERROR(_xlfn.FORECAST.ETS(AY$5,tbl_Model[[#This Row],[H_2023_01]:[H_2025_12]],$H$5:$AQ$5),_xlfn.FORECAST.LINEAR(AY$5,tbl_Model[[#This Row],[H_2023_01]:[H_2025_12]],$H$5:$AQ$5)),0),0) -> 6.0028314 | ... BC15: =MAX(IFERROR(IFERROR(_xlfn.FORECAST.ETS(BC$5,tbl_Model[[#This Row],[H_2023_01]:[H_2025_12]],$H$5:$AQ$5),_xlfn.FORECAST.LINEAR(BC$5,tbl_Model[[#This Row],[H_2023_01]:[H_2025_12]],$H$5:$AQ$5)),0),0) -> 6.5042471 | BD15: =IFERROR(AR15/SUM(Model!$AR15:$BC15),1/12) -> 0.073452705 | BE15: =IFERROR(AS15/SUM(Model!$AR15:$BC15),1/12) -> 0.075249183 | BF15: =IFERROR(AT15/SUM(Model!$AR15:$BC15),1/12) -> 0.077045661 | BG15: =IFERROR(AU15/SUM(Model!$AR15:$BC15),1/12) -> 0.078842139 | BH15: =IFERROR(AV15/SUM(Model!$AR15:$BC15),1/12) -> 0.080638617 | BI15: =IFERROR(AW15/SUM(Model!$AR15:$BC15),1/12) -> 0.082435094 | BJ15: =IFERROR(AX15/SUM(Model!$AR15:$BC15),1/12) -> 0.084231572 | BK15: =IFERROR(AY15/SUM(Model!$AR15:$BC15),1/12) -> 0.08602805 | ... BO15: =IFERROR(BC15/SUM(Model!$AR15:$BC15),1/12) -> 0.093213962 | BP15: =_xlfn.XLOOKUP(tbl_Model[[#This Row],[country]],tbl_UnitsPerCountry[Country],tbl_UnitsPerCountry[Units2026],0) *SUMIFS(tbl_CollectionMix[Mix2026],tbl_CollectionMix[country],tbl_Model[[#This Row],[country]],tbl_CollectionMix[collection],tbl_Model[[#This Row],[collection]]) *IF(tbl_Model[[#This Row],[Type]]="Boutique", SUMIFS(tbl_ChannelMix[BoutiqueShare_2026_Effective],tbl_ChannelMix[Country],tbl_Model[[#This Row],[country]],tbl_ChannelMix[Collection],tbl_Model[[#This Row],[collection]]), 1-SUMIFS(tbl_ChannelMix[BoutiqueShare_2026_Effective],tbl_ChannelMix[Country],tbl_Model[[#This Row],[country]],tbl_ChannelMix[Collection],tbl_Model[[#This Row],[collection]])) -> 42.116667 | BQ15: {=IF(SUMIFS(tbl_SkuPrices[Units2025Actual],tbl_SkuPrices[Collection],tbl_Model[[#This Row],[collection]])=0, 0, SUMPRODUCT((tbl_SkuPrices[Collection]=tbl_Model[[#This Row],[collection]])*tbl_SkuPrices[BudgetedPrice2026]*tbl_SkuPrices[Units2025Actual]) /SUMIFS(tbl_SkuPrices[Units2025Actual],tbl_SkuPrices[Collection],tbl_Model[[#This Row],[collection]]))} -> 29113.63 | BR15: {=IF(SUMIFS(tbl_SkuPrices[Units2025Actual],tbl_SkuPrices[Collection],tbl_Model[[#This Row],[collection]])=0,0,SUMPRODUCT((tbl_SkuPrices[Collection]=tbl_Model[[#This Row],[collection]])*tbl_SkuPrices[BudgetedCost2026]*tbl_SkuPrices[Units2025Actual]) /SUMIFS(tbl_SkuPrices[Units2025Actual],tbl_SkuPrices[Collection],tbl_Model[[#This Row],[collection]]))} -> 6636.0593 | BS15: =IF(tbl_Model[[#This Row],[Type]]="Boutique", tbl_Model[[#This Row],[UnitListPrice]], tbl_Model[[#This Row],[UnitListPrice]]*(1-SUMIFS(tbl_MarketTerms[WholesaleMarginPct],tbl_MarketTerms[Country],tbl_Model[[#This Row],[country]]))) -> 29113.63 | BT15: =Model!$BP15*BD15 -> 3.0935831 | BU15: =Model!$BP15*BE15 -> 3.1692448 | BV15: =Model!$BP15*BF15 -> 3.2449064 | BW15: =Model!$BP15*BG15 -> 3.3205681 | BX15: =Model!$BP15*BH15 -> 3.3962297 | BY15: =Model!$BP15*BI15 -> 3.4718914 | BZ15: =Model!$BP15*BJ15 -> 3.5475531 | CA15: =Model!$BP15*BK15 -> 3.6232147 | ... CE15: =Model!$BP15*BO15 -> 3.9258614 | CF15: =Model!$BS15*BT15 -> 90065.433 | CG15: =Model!$BS15*BU15 -> 92268.219 | CH15: =Model!$BS15*BV15 -> 94471.004 | CI15: =Model!$BS15*BW15 -> 96673.79 | CJ15: =Model!$BS15*BX15 -> 98876.575 | CK15: =Model!$BS15*BY15 -> 101079.36 | CL15: =Model!$BS15*BZ15 -> 103282.15 | CM15: =Model!$BS15*CA15 -> 105484.93 | ... CQ15: =Model!$BS15*CE15 -> 114296.07 | CR15: =Model!$BR15*BT15 -> 20529.201 | CS15: =Model!$BR15*BU15 -> 21031.296 | CT15: =Model!$BR15*BV15 -> 21533.391 | CU15: =Model!$BR15*BW15 -> 22035.487 | CV15: =Model!$BR15*BX15 -> 22537.582 | CW15: =Model!$BR15*BY15 -> 23039.677 | CX15: =Model!$BR15*BZ15 -> 23541.772 | CY15: =Model!$BR15*CA15 -> 24043.868 | ... DC15: =Model!$BR15*CE15 -> 26052.249 | DD15: =SUM(Model!$CF15:$CQ15) -> 1226169 | DE15: =SUM(Model!$CR15:$DC15) -> 279488.7 | DF15: =IFERROR((Model!$DD15-Model!$DE15)/Model!$DD15,0) -> 0.77206349
B16: Boutique | C16: Heritage | D16: Peru | E16: 14 | F16: 311894.8 | G16: 67992.28 | H16: 1 | I16: 2 | J16: 1 | K16: 0 | L16: 1 | M16: 1 | N16: 1 | O16: 0 | P16: 1 | Q16: 0 | R16: 2 | S16: 4 | T16: 0 | U16: 1 | V16: 0 | W16: 3 | X16: 3 | Y16: 2 | Z16: 4 | AA16: 0 | AB16: 1 | AC16: 1 | AD16: 2 | AE16: 0 | AF16: 3 | AG16: 1 | AH16: 1 | AI16: 0 | AJ16: 0 | AK16: 1 | AL16: 2 | AM16: 0 | AN16: 0 | AO16: 0 | AP16: 5 | AQ16: 1 | AR16: =MAX(IFERROR(IFERROR(_xlfn.FORECAST.ETS(AR$5,tbl_Model[[#This Row],[H_2023_01]:[H_2025_12]],$H$5:$AQ$5),_xlfn.FORECAST.LINEAR(AR$5,tbl_Model[[#This Row],[H_2023_01]:[H_2025_12]],$H$5:$AQ$5)),0),0) -> 1.486372 | AS16: =MAX(IFERROR(IFERROR(_xlfn.FORECAST.ETS(AS$5,tbl_Model[[#This Row],[H_2023_01]:[H_2025_12]],$H$5:$AQ$5),_xlfn.FORECAST.LINEAR(AS$5,tbl_Model[[#This Row],[H_2023_01]:[H_2025_12]],$H$5:$AQ$5)),0),0) -> 0.18252149 | AT16: =MAX(IFERROR(IFERROR(_xlfn.FORECAST.ETS(AT$5,tbl_Model[[#This Row],[H_2023_01]:[H_2025_12]],$H$5:$AQ$5),_xlfn.FORECAST.LINEAR(AT$5,tbl_Model[[#This Row],[H_2023_01]:[H_2025_12]],$H$5:$AQ$5)),0),0) -> 0.62513543 | AU16: =MAX(IFERROR(IFERROR(_xlfn.FORECAST.ETS(AU$5,tbl_Model[[#This Row],[H_2023_01]:[H_2025_12]],$H$5:$AQ$5),_xlfn.FORECAST.LINEAR(AU$5,tbl_Model[[#This Row],[H_2023_01]:[H_2025_12]],$H$5:$AQ$5)),0),0) -> 0.81963243 | AV16: =MAX(IFERROR(IFERROR(_xlfn.FORECAST.ETS(AV$5,tbl_Model[[#This Row],[H_2023_01]:[H_2025_12]],$H$5:$AQ$5),_xlfn.FORECAST.LINEAR(AV$5,tbl_Model[[#This Row],[H_2023_01]:[H_2025_12]],$H$5:$AQ$5)),0),0) -> 1.8516118 | AW16: =MAX(IFERROR(IFERROR(_xlfn.FORECAST.ETS(AW$5,tbl_Model[[#This Row],[H_2023_01]:[H_2025_12]],$H$5:$AQ$5),_xlfn.FORECAST.LINEAR(AW$5,tbl_Model[[#This Row],[H_2023_01]:[H_2025_12]],$H$5:$AQ$5)),0),0) -> 2.1799432 | AX16: =MAX(IFERROR(IFERROR(_xlfn.FORECAST.ETS(AX$5,tbl_Model[[#This Row],[H_2023_01]:[H_2025_12]],$H$5:$AQ$5),_xlfn.FORECAST.LINEAR(AX$5,tbl_Model[[#This Row],[H_2023_01]:[H_2025_12]],$H$5:$AQ$5)),0),0) -> 1.4939324 | AY16: =MAX(IFERROR(IFERROR(_xlfn.FORECAST.ETS(AY$5,tbl_Model[[#This Row],[H_2023_01]:[H_2025_12]],$H$5:$AQ$5),_xlfn.FORECAST.LINEAR(AY$5,tbl_Model[[#This Row],[H_2023_01]:[H_2025_12]],$H$5:$AQ$5)),0),0) -> 0.1900819 | ... BC16: =MAX(IFERROR(IFERROR(_xlfn.FORECAST.ETS(BC$5,tbl_Model[[#This Row],[H_2023_01]:[H_2025_12]],$H$5:$AQ$5),_xlfn.FORECAST.LINEAR(BC$5,tbl_Model[[#This Row],[H_2023_01]:[H_2025_12]],$H$5:$AQ$5)),0),0) -> 2.1875037 | BD16: =IFERROR(AR16/SUM(Model!$AR16:$BC16),1/12) -> 0.10368256 | BE16: =IFERROR(AS16/SUM(Model!$AR16:$BC16),1/12) -> 0.012731871 | BF16: =IFERROR(AT16/SUM(Model!$AR16:$BC16),1/12) -> 0.04360661 | BG16: =IFERROR(AU16/SUM(Model!$AR16:$BC16),1/12) -> 0.057173838 | BH16: =IFERROR(AV16/SUM(Model!$AR16:$BC16),1/12) -> 0.12916003 | BI16: =IFERROR(AW16/SUM(Model!$AR16:$BC16),1/12) -> 0.15206294 | BJ16: =IFERROR(AX16/SUM(Model!$AR16:$BC16),1/12) -> 0.10420994 | BK16: =IFERROR(AY16/SUM(Model!$AR16:$BC16),1/12) -> 0.013259251 | ... BO16: =IFERROR(BC16/SUM(Model!$AR16:$BC16),1/12) -> 0.15259032 | BP16: =_xlfn.XLOOKUP(tbl_Model[[#This Row],[country]],tbl_UnitsPerCountry[Country],tbl_UnitsPerCountry[Units2026],0) *SUMIFS(tbl_CollectionMix[Mix2026],tbl_CollectionMix[country],tbl_Model[[#This Row],[country]],tbl_CollectionMix[collection],tbl_Model[[#This Row],[collection]]) *IF(tbl_Model[[#This Row],[Type]]="Boutique", SUMIFS(tbl_ChannelMix[BoutiqueShare_2026_Effective],tbl_ChannelMix[Country],tbl_Model[[#This Row],[country]],tbl_ChannelMix[Collection],tbl_Model[[#This Row],[collection]]), 1-SUMIFS(tbl_ChannelMix[BoutiqueShare_2026_Effective],tbl_ChannelMix[Country],tbl_Model[[#This Row],[country]],tbl_ChannelMix[Collection],tbl_Model[[#This Row],[collection]])) -> 15.435 | BQ16: {=IF(SUMIFS(tbl_SkuPrices[Units2025Actual],tbl_SkuPrices[Collection],tbl_Model[[#This Row],[collection]])=0, 0, SUMPRODUCT((tbl_SkuPrices[Collection]=tbl_Model[[#This Row],[collection]])*tbl_SkuPrices[BudgetedPrice2026]*tbl_SkuPrices[Units2025Actual]) /SUMIFS(tbl_SkuPrices[Units2025Actual],tbl_SkuPrices[Collection],tbl_Model[[#This Row],[collection]]))} -> 24503.914 | BR16: {=IF(SUMIFS(tbl_SkuPrices[Units2025Actual],tbl_SkuPrices[Collection],tbl_Model[[#This Row],[collection]])=0,0,SUMPRODUCT((tbl_SkuPrices[Collection]=tbl_Model[[#This Row],[collection]])*tbl_SkuPrices[BudgetedCost2026]*tbl_SkuPrices[Units2025Actual]) /SUMIFS(tbl_SkuPrices[Units2025Actual],tbl_SkuPrices[Collection],tbl_Model[[#This Row],[collection]]))} -> 5272.126 | BS16: =IF(tbl_Model[[#This Row],[Type]]="Boutique", tbl_Model[[#This Row],[UnitListPrice]], tbl_Model[[#This Row],[UnitListPrice]]*(1-SUMIFS(tbl_MarketTerms[WholesaleMarginPct],tbl_MarketTerms[Country],tbl_Model[[#This Row],[country]]))) -> 24503.914 | BT16: =Model!$BP16*BD16 -> 1.6003404 | BU16: =Model!$BP16*BE16 -> 0.19651643 | BV16: =Model!$BP16*BF16 -> 0.67306802 | BW16: =Model!$BP16*BG16 -> 0.88247819 | BX16: =Model!$BP16*BH16 -> 1.9935851 | BY16: =Model!$BP16*BI16 -> 2.3470916 | BZ16: =Model!$BP16*BJ16 -> 1.6084805 | CA16: =Model!$BP16*BK16 -> 0.20465653 | ... CE16: =Model!$BP16*BO16 -> 2.3552317 | CF16: =Model!$BS16*BT16 -> 39214.603 | CG16: =Model!$BS16*BU16 -> 4815.4216 | CH16: =Model!$BS16*BV16 -> 16492.801 | CI16: =Model!$BS16*BW16 -> 21624.169 | CJ16: =Model!$BS16*BX16 -> 48850.638 | CK16: =Model!$BS16*BY16 -> 57512.929 | CL16: =Model!$BS16*BZ16 -> 39414.067 | CM16: =Model!$BS16*CA16 -> 5014.886 | ... CQ16: =Model!$BS16*CE16 -> 57712.394 | CR16: =Model!$BR16*BT16 -> 8437.1961 | CS16: =Model!$BR16*BU16 -> 1036.0594 | CT16: =Model!$BR16*BV16 -> 3548.4994 | CU16: =Model!$BR16*BW16 -> 4652.5362 | CV16: =Model!$BR16*BX16 -> 10510.432 | CW16: =Model!$BR16*BY16 -> 12374.162 | CX16: =Model!$BR16*BZ16 -> 8480.1118 | CY16: =Model!$BR16*CA16 -> 1078.975 | ... DC16: =Model!$BR16*CE16 -> 12417.078 | DD16: =SUM(Model!$CF16:$CQ16) -> 378217.91 | DE16: =SUM(Model!$CR16:$DC16) -> 81375.265 | DF16: =IFERROR((Model!$DD16-Model!$DE16)/Model!$DD16,0) -> 0.78484555
B17: Boutique | C17: Atelier | D17: China | E17: 127 | F17: 3512532.9 | G17: 812382.11 | H17: 5 | I17: 6 | J17: 5 | K17: 7 | L17: 6 | M17: 6 | N17: 10 | O17: 5 | P17: 9 | Q17: 5 | R17: 7 | S17: 7 | T17: 6 | U17: 11 | V17: 12 | W17: 7 | X17: 6 | Y17: 11 | Z17: 10 | AA17: 8 | AB17: 5 | AC17: 12 | AD17: 11 | AE17: 9 | AF17: 8 | AG17: 9 | AH17: 5 | AI17: 6 | AJ17: 11 | AK17: 11 | AL17: 4 | AM17: 16 | AN17: 16 | AO17: 7 | AP17: 19 | AQ17: 15 | AR17: =MAX(IFERROR(IFERROR(_xlfn.FORECAST.ETS(AR$5,tbl_Model[[#This Row],[H_2023_01]:[H_2025_12]],$H$5:$AQ$5),_xlfn.FORECAST.LINEAR(AR$5,tbl_Model[[#This Row],[H_2023_01]:[H_2025_12]],$H$5:$AQ$5)),0),0) -> 12.088302 | AS17: =MAX(IFERROR(IFERROR(_xlfn.FORECAST.ETS(AS$5,tbl_Model[[#This Row],[H_2023_01]:[H_2025_12]],$H$5:$AQ$5),_xlfn.FORECAST.LINEAR(AS$5,tbl_Model[[#This Row],[H_2023_01]:[H_2025_12]],$H$5:$AQ$5)),0),0) -> 12.288305 | AT17: =MAX(IFERROR(IFERROR(_xlfn.FORECAST.ETS(AT$5,tbl_Model[[#This Row],[H_2023_01]:[H_2025_12]],$H$5:$AQ$5),_xlfn.FORECAST.LINEAR(AT$5,tbl_Model[[#This Row],[H_2023_01]:[H_2025_12]],$H$5:$AQ$5)),0),0) -> 12.488309 | AU17: =MAX(IFERROR(IFERROR(_xlfn.FORECAST.ETS(AU$5,tbl_Model[[#This Row],[H_2023_01]:[H_2025_12]],$H$5:$AQ$5),_xlfn.FORECAST.LINEAR(AU$5,tbl_Model[[#This Row],[H_2023_01]:[H_2025_12]],$H$5:$AQ$5)),0),0) -> 12.688313 | AV17: =MAX(IFERROR(IFERROR(_xlfn.FORECAST.ETS(AV$5,tbl_Model[[#This Row],[H_2023_01]:[H_2025_12]],$H$5:$AQ$5),_xlfn.FORECAST.LINEAR(AV$5,tbl_Model[[#This Row],[H_2023_01]:[H_2025_12]],$H$5:$AQ$5)),0),0) -> 12.888316 | AW17: =MAX(IFERROR(IFERROR(_xlfn.FORECAST.ETS(AW$5,tbl_Model[[#This Row],[H_2023_01]:[H_2025_12]],$H$5:$AQ$5),_xlfn.FORECAST.LINEAR(AW$5,tbl_Model[[#This Row],[H_2023_01]:[H_2025_12]],$H$5:$AQ$5)),0),0) -> 13.08832 | AX17: =MAX(IFERROR(IFERROR(_xlfn.FORECAST.ETS(AX$5,tbl_Model[[#This Row],[H_2023_01]:[H_2025_12]],$H$5:$AQ$5),_xlfn.FORECAST.LINEAR(AX$5,tbl_Model[[#This Row],[H_2023_01]:[H_2025_12]],$H$5:$AQ$5)),0),0) -> 13.288324 | AY17: =MAX(IFERROR(IFERROR(_xlfn.FORECAST.ETS(AY$5,tbl_Model[[#This Row],[H_2023_01]:[H_2025_12]],$H$5:$AQ$5),_xlfn.FORECAST.LINEAR(AY$5,tbl_Model[[#This Row],[H_2023_01]:[H_2025_12]],$H$5:$AQ$5)),0),0) -> 13.488328 | ... BC17: =MAX(IFERROR(IFERROR(_xlfn.FORECAST.ETS(BC$5,tbl_Model[[#This Row],[H_2023_01]:[H_2025_12]],$H$5:$AQ$5),_xlfn.FORECAST.LINEAR(BC$5,tbl_Model[[#This Row],[H_2023_01]:[H_2025_12]],$H$5:$AQ$5)),0),0) -> 14.288342 | BD17: =IFERROR(AR17/SUM(Model!$AR17:$BC17),1/12) -> 0.076382612 | BE17: =IFERROR(AS17/SUM(Model!$AR17:$BC17),1/12) -> 0.077646379 | BF17: =IFERROR(AT17/SUM(Model!$AR17:$BC17),1/12) -> 0.078910147 | BG17: =IFERROR(AU17/SUM(Model!$AR17:$BC17),1/12) -> 0.080173915 | BH17: =IFERROR(AV17/SUM(Model!$AR17:$BC17),1/12) -> 0.081437682 | BI17: =IFERROR(AW17/SUM(Model!$AR17:$BC17),1/12) -> 0.08270145 | BJ17: =IFERROR(AX17/SUM(Model!$AR17:$BC17),1/12) -> 0.083965217 | BK17: =IFERROR(AY17/SUM(Model!$AR17:$BC17),1/12) -> 0.085228985 | ... BO17: =IFERROR(BC17/SUM(Model!$AR17:$BC17),1/12) -> 0.090284055 | BP17: =_xlfn.XLOOKUP(tbl_Model[[#This Row],[country]],tbl_UnitsPerCountry[Country],tbl_UnitsPerCountry[Units2026],0) *SUMIFS(tbl_CollectionMix[Mix2026],tbl_CollectionMix[country],tbl_Model[[#This Row],[country]],tbl_CollectionMix[collection],tbl_Model[[#This Row],[collection]]) *IF(tbl_Model[[#This Row],[Type]]="Boutique", SUMIFS(tbl_ChannelMix[BoutiqueShare_2026_Effective],tbl_ChannelMix[Country],tbl_Model[[#This Row],[country]],tbl_ChannelMix[Collection],tbl_Model[[#This Row],[collection]]), 1-SUMIFS(tbl_ChannelMix[BoutiqueShare_2026_Effective],tbl_ChannelMix[Country],tbl_Model[[#This Row],[country]],tbl_ChannelMix[Collection],tbl_Model[[#This Row],[collection]])) -> 171.17834 | BQ17: {=IF(SUMIFS(tbl_SkuPrices[Units2025Actual],tbl_SkuPrices[Collection],tbl_Model[[#This Row],[collection]])=0, 0, SUMPRODUCT((tbl_SkuPrices[Collection]=tbl_Model[[#This Row],[collection]])*tbl_SkuPrices[BudgetedPrice2026]*tbl_SkuPrices[Units2025Actual]) /SUMIFS(tbl_SkuPrices[Units2025Actual],tbl_SkuPrices[Collection],tbl_Model[[#This Row],[collection]]))} -> 29113.63 | BR17: {=IF(SUMIFS(tbl_SkuPrices[Units2025Actual],tbl_SkuPrices[Collection],tbl_Model[[#This Row],[collection]])=0,0,SUMPRODUCT((tbl_SkuPrices[Collection]=tbl_Model[[#This Row],[collection]])*tbl_SkuPrices[BudgetedCost2026]*tbl_SkuPrices[Units2025Actual]) /SUMIFS(tbl_SkuPrices[Units2025Actual],tbl_SkuPrices[Collection],tbl_Model[[#This Row],[collection]]))} -> 6636.0593 | BS17: =IF(tbl_Model[[#This Row],[Type]]="Boutique", tbl_Model[[#This Row],[UnitListPrice]], tbl_Model[[#This Row],[UnitListPrice]]*(1-SUMIFS(tbl_MarketTerms[WholesaleMarginPct],tbl_MarketTerms[Country],tbl_Model[[#This Row],[country]]))) -> 29113.63 | BT17: =Model!$BP17*BD17 -> 13.075049 | BU17: =Model!$BP17*BE17 -> 13.291379 | BV17: =Model!$BP17*BF17 -> 13.507708 | BW17: =Model!$BP17*BG17 -> 13.724038 | BX17: =Model!$BP17*BH17 -> 13.940368 | BY17: =Model!$BP17*BI17 -> 14.156697 | BZ17: =Model!$BP17*BJ17 -> 14.373027 | CA17: =Model!$BP17*BK17 -> 14.589356 | ... CE17: =Model!$BP17*BO17 -> 15.454675 | CF17: =Model!$BS17*BT17 -> 380662.14 | CG17: =Model!$BS17*BU17 -> 386960.28 | CH17: =Model!$BS17*BV17 -> 393258.42 | CI17: =Model!$BS17*BW17 -> 399556.56 | CJ17: =Model!$BS17*BX17 -> 405854.7 | CK17: =Model!$BS17*BY17 -> 412152.84 | CL17: =Model!$BS17*BZ17 -> 418450.98 | CM17: =Model!$BS17*CA17 -> 424749.12 | ... CQ17: =Model!$BS17*CE17 -> 449941.69 | CR17: =Model!$BR17*BT17 -> 86766.801 | CS17: =Model!$BR17*BU17 -> 88202.377 | CT17: =Model!$BR17*BV17 -> 89637.953 | CU17: =Model!$BR17*BW17 -> 91073.529 | CV17: =Model!$BR17*BX17 -> 92509.106 | CW17: =Model!$BR17*BY17 -> 93944.682 | CX17: =Model!$BR17*BZ17 -> 95380.258 | CY17: =Model!$BR17*CA17 -> 96815.835 | ... DC17: =Model!$BR17*CE17 -> 102558.14 | DD17: =SUM(Model!$CF17:$CQ17) -> 4983622.9 | DE17: =SUM(Model!$CR17:$DC17) -> 1135949.6 | DF17: =IFERROR((Model!$DD17-Model!$DE17)/Model!$DD17,0) -> 0.77206349
B18: Boutique | C18: Heritage | D18: UAE | E18: 35 | F18: 810060.16 | G18: 176489.69 | H18: 1 | I18: 0 | J18: 1 | K18: 0 | L18: 1 | M18: 1 | N18: 0 | O18: 1 | P18: 9 | Q18: 3 | R18: 2 | S18: 0 | T18: 0 | U18: 1 | V18: 4 | W18: 0 | X18: 1 | Y18: 0 | Z18: 0 | AA18: 1 | AB18: 1 | AC18: 2 | AD18: 0 | AE18: 1 | AF18: 5 | AG18: 1 | AH18: 5 | AI18: 1 | AJ18: 3 | AK18: 4 | AL18: 0 | AM18: 1 | AN18: 6 | AO18: 0 | AP18: 1 | AQ18: 8 | AR18: =MAX(IFERROR(IFERROR(_xlfn.FORECAST.ETS(AR$5,tbl_Model[[#This Row],[H_2023_01]:[H_2025_12]],$H$5:$AQ$5),_xlfn.FORECAST.LINEAR(AR$5,tbl_Model[[#This Row],[H_2023_01]:[H_2025_12]],$H$5:$AQ$5)),0),0) -> 2.9600785 | AS18: =MAX(IFERROR(IFERROR(_xlfn.FORECAST.ETS(AS$5,tbl_Model[[#This Row],[H_2023_01]:[H_2025_12]],$H$5:$AQ$5),_xlfn.FORECAST.LINEAR(AS$5,tbl_Model[[#This Row],[H_2023_01]:[H_2025_12]],$H$5:$AQ$5)),0),0) -> 3.012131 | AT18: =MAX(IFERROR(IFERROR(_xlfn.FORECAST.ETS(AT$5,tbl_Model[[#This Row],[H_2023_01]:[H_2025_12]],$H$5:$AQ$5),_xlfn.FORECAST.LINEAR(AT$5,tbl_Model[[#This Row],[H_2023_01]:[H_2025_12]],$H$5:$AQ$5)),0),0) -> 3.0641834 | AU18: =MAX(IFERROR(IFERROR(_xlfn.FORECAST.ETS(AU$5,tbl_Model[[#This Row],[H_2023_01]:[H_2025_12]],$H$5:$AQ$5),_xlfn.FORECAST.LINEAR(AU$5,tbl_Model[[#This Row],[H_2023_01]:[H_2025_12]],$H$5:$AQ$5)),0),0) -> 3.1162359 | AV18: =MAX(IFERROR(IFERROR(_xlfn.FORECAST.ETS(AV$5,tbl_Model[[#This Row],[H_2023_01]:[H_2025_12]],$H$5:$AQ$5),_xlfn.FORECAST.LINEAR(AV$5,tbl_Model[[#This Row],[H_2023_01]:[H_2025_12]],$H$5:$AQ$5)),0),0) -> 3.1682884 | AW18: =MAX(IFERROR(IFERROR(_xlfn.FORECAST.ETS(AW$5,tbl_Model[[#This Row],[H_2023_01]:[H_2025_12]],$H$5:$AQ$5),_xlfn.FORECAST.LINEAR(AW$5,tbl_Model[[#This Row],[H_2023_01]:[H_2025_12]],$H$5:$AQ$5)),0),0) -> 3.2203408 | AX18: =MAX(IFERROR(IFERROR(_xlfn.FORECAST.ETS(AX$5,tbl_Model[[#This Row],[H_2023_01]:[H_2025_12]],$H$5:$AQ$5),_xlfn.FORECAST.LINEAR(AX$5,tbl_Model[[#This Row],[H_2023_01]:[H_2025_12]],$H$5:$AQ$5)),0),0) -> 3.2723933 | AY18: =MAX(IFERROR(IFERROR(_xlfn.FORECAST.ETS(AY$5,tbl_Model[[#This Row],[H_2023_01]:[H_2025_12]],$H$5:$AQ$5),_xlfn.FORECAST.LINEAR(AY$5,tbl_Model[[#This Row],[H_2023_01]:[H_2025_12]],$H$5:$AQ$5)),0),0) -> 3.3244458 | ... BC18: =MAX(IFERROR(IFERROR(_xlfn.FORECAST.ETS(BC$5,tbl_Model[[#This Row],[H_2023_01]:[H_2025_12]],$H$5:$AQ$5),_xlfn.FORECAST.LINEAR(BC$5,tbl_Model[[#This Row],[H_2023_01]:[H_2025_12]],$H$5:$AQ$5)),0),0) -> 3.5326556 | BD18: =IFERROR(AR18/SUM(Model!$AR18:$BC18),1/12) -> 0.075984387 | BE18: =IFERROR(AS18/SUM(Model!$AR18:$BC18),1/12) -> 0.077320559 | BF18: =IFERROR(AT18/SUM(Model!$AR18:$BC18),1/12) -> 0.078656731 | BG18: =IFERROR(AU18/SUM(Model!$AR18:$BC18),1/12) -> 0.079992903 | BH18: =IFERROR(AV18/SUM(Model!$AR18:$BC18),1/12) -> 0.081329075 | BI18: =IFERROR(AW18/SUM(Model!$AR18:$BC18),1/12) -> 0.082665247 | BJ18: =IFERROR(AX18/SUM(Model!$AR18:$BC18),1/12) -> 0.084001419 | BK18: =IFERROR(AY18/SUM(Model!$AR18:$BC18),1/12) -> 0.085337591 | ... BO18: =IFERROR(BC18/SUM(Model!$AR18:$BC18),1/12) -> 0.09068228 | BP18: =_xlfn.XLOOKUP(tbl_Model[[#This Row],[country]],tbl_UnitsPerCountry[Country],tbl_UnitsPerCountry[Units2026],0) *SUMIFS(tbl_CollectionMix[Mix2026],tbl_CollectionMix[country],tbl_Model[[#This Row],[country]],tbl_CollectionMix[collection],tbl_Model[[#This Row],[collection]]) *IF(tbl_Model[[#This Row],[Type]]="Boutique", SUMIFS(tbl_ChannelMix[BoutiqueShare_2026_Effective],tbl_ChannelMix[Country],tbl_Model[[#This Row],[country]],tbl_ChannelMix[Collection],tbl_Model[[#This Row],[collection]]), 1-SUMIFS(tbl_ChannelMix[BoutiqueShare_2026_Effective],tbl_ChannelMix[Country],tbl_Model[[#This Row],[country]],tbl_ChannelMix[Collection],tbl_Model[[#This Row],[collection]])) -> 38.615422 | BQ18: {=IF(SUMIFS(tbl_SkuPrices[Units2025Actual],tbl_SkuPrices[Collection],tbl_Model[[#This Row],[collection]])=0, 0, SUMPRODUCT((tbl_SkuPrices[Collection]=tbl_Model[[#This Row],[collection]])*tbl_SkuPrices[BudgetedPrice2026]*tbl_SkuPrices[Units2025Actual]) /SUMIFS(tbl_SkuPrices[Units2025Actual],tbl_SkuPrices[Collection],tbl_Model[[#This Row],[collection]]))} -> 24503.914 | BR18: {=IF(SUMIFS(tbl_SkuPrices[Units2025Actual],tbl_SkuPrices[Collection],tbl_Model[[#This Row],[collection]])=0,0,SUMPRODUCT((tbl_SkuPrices[Collection]=tbl_Model[[#This Row],[collection]])*tbl_SkuPrices[BudgetedCost2026]*tbl_SkuPrices[Units2025Actual]) /SUMIFS(tbl_SkuPrices[Units2025Actual],tbl_SkuPrices[Collection],tbl_Model[[#This Row],[collection]]))} -> 5272.126 | BS18: =IF(tbl_Model[[#This Row],[Type]]="Boutique", tbl_Model[[#This Row],[UnitListPrice]], tbl_Model[[#This Row],[UnitListPrice]]*(1-SUMIFS(tbl_MarketTerms[WholesaleMarginPct],tbl_MarketTerms[Country],tbl_Model[[#This Row],[country]]))) -> 24503.914 | BT18: =Model!$BP18*BD18 -> 2.9341692 | BU18: =Model!$BP18*BE18 -> 2.985766 | BV18: =Model!$BP18*BF18 -> 3.0373629 | BW18: =Model!$BP18*BG18 -> 3.0889597 | BX18: =Model!$BP18*BH18 -> 3.1405566 | BY18: =Model!$BP18*BI18 -> 3.1921534 | BZ18: =Model!$BP18*BJ18 -> 3.2437503 | CA18: =Model!$BP18*BK18 -> 3.2953471 | ... CE18: =Model!$BP18*BO18 -> 3.5017345 | CF18: =Model!$BS18*BT18 -> 71898.628 | CG18: =Model!$BS18*BU18 -> 73162.953 | CH18: =Model!$BS18*BV18 -> 74427.278 | CI18: =Model!$BS18*BW18 -> 75691.602 | CJ18: =Model!$BS18*BX18 -> 76955.927 | CK18: =Model!$BS18*BY18 -> 78220.252 | CL18: =Model!$BS18*BZ18 -> 79484.577 | CM18: =Model!$BS18*CA18 -> 80748.901 | ... CQ18: =Model!$BS18*CE18 -> 85806.2 | CR18: =Model!$BR18*BT18 -> 15469.309 | CS18: =Model!$BR18*BU18 -> 15741.335 | CT18: =Model!$BR18*BV18 -> 16013.36 | CU18: =Model!$BR18*BW18 -> 16285.385 | CV18: =Model!$BR18*BX18 -> 16557.41 | CW18: =Model!$BR18*BY18 -> 16829.435 | CX18: =Model!$BR18*BZ18 -> 17101.46 | CY18: =Model!$BR18*CA18 -> 17373.485 | ... DC18: =Model!$BR18*CE18 -> 18461.586 | DD18: =SUM(Model!$CF18:$CQ18) -> 946228.97 | DE18: =SUM(Model!$CR18:$DC18) -> 203585.37 | DF18: =IFERROR((Model!$DD18-Model!$DE18)/Model!$DD18,0) -> 0.78484555
... B566: Wholesale | C566: Terra | D566: Taiwan | E566: 27 | F566: 160198.55 | G566: 71787.12 | H566: 4 | I566: 2 | J566: 7 | K566: 0 | L566: 4 | M566: 12 | N566: 2 | O566: 0 | P566: 0 | Q566: 4 | R566: 0 | S566: 3 | T566: 2 | U566: 5 | V566: 1 | W566: 0 | X566: 0 | Y566: 3 | Z566: 0 | AA566: 0 | AB566: 0 | AC566: 0 | AD566: 6 | AE566: 6 | AF566: 9 | AG566: 0 | AH566: 0 | AI566: 0 | AJ566: 2 | AK566: 0 | AL566: 0 | AM566: 0 | AN566: 0 | AO566: 1 | AP566: 0 | AQ566: 15 | AR566: =MAX(IFERROR(IFERROR(_xlfn.FORECAST.ETS(AR$5,tbl_Model[[#This Row],[H_2023_01]:[H_2025_12]],$H$5:$AQ$5),_xlfn.FORECAST.LINEAR(AR$5,tbl_Model[[#This Row],[H_2023_01]:[H_2025_12]],$H$5:$AQ$5)),0),0) -> 2.2560061 | AS566: =MAX(IFERROR(IFERROR(_xlfn.FORECAST.ETS(AS$5,tbl_Model[[#This Row],[H_2023_01]:[H_2025_12]],$H$5:$AQ$5),_xlfn.FORECAST.LINEAR(AS$5,tbl_Model[[#This Row],[H_2023_01]:[H_2025_12]],$H$5:$AQ$5)),0),0) -> 2.2230061 | AT566: =MAX(IFERROR(IFERROR(_xlfn.FORECAST.ETS(AT$5,tbl_Model[[#This Row],[H_2023_01]:[H_2025_12]],$H$5:$AQ$5),_xlfn.FORECAST.LINEAR(AT$5,tbl_Model[[#This Row],[H_2023_01]:[H_2025_12]],$H$5:$AQ$5)),0),0) -> 2.1900061 | AU566: =MAX(IFERROR(IFERROR(_xlfn.FORECAST.ETS(AU$5,tbl_Model[[#This Row],[H_2023_01]:[H_2025_12]],$H$5:$AQ$5),_xlfn.FORECAST.LINEAR(AU$5,tbl_Model[[#This Row],[H_2023_01]:[H_2025_12]],$H$5:$AQ$5)),0),0) -> 2.1570062 | AV566: =MAX(IFERROR(IFERROR(_xlfn.FORECAST.ETS(AV$5,tbl_Model[[#This Row],[H_2023_01]:[H_2025_12]],$H$5:$AQ$5),_xlfn.FORECAST.LINEAR(AV$5,tbl_Model[[#This Row],[H_2023_01]:[H_2025_12]],$H$5:$AQ$5)),0),0) -> 2.1240062 | AW566: =MAX(IFERROR(IFERROR(_xlfn.FORECAST.ETS(AW$5,tbl_Model[[#This Row],[H_2023_01]:[H_2025_12]],$H$5:$AQ$5),_xlfn.FORECAST.LINEAR(AW$5,tbl_Model[[#This Row],[H_2023_01]:[H_2025_12]],$H$5:$AQ$5)),0),0) -> 2.0910062 | AX566: =MAX(IFERROR(IFERROR(_xlfn.FORECAST.ETS(AX$5,tbl_Model[[#This Row],[H_2023_01]:[H_2025_12]],$H$5:$AQ$5),_xlfn.FORECAST.LINEAR(AX$5,tbl_Model[[#This Row],[H_2023_01]:[H_2025_12]],$H$5:$AQ$5)),0),0) -> 2.0580063 | AY566: =MAX(IFERROR(IFERROR(_xlfn.FORECAST.ETS(AY$5,tbl_Model[[#This Row],[H_2023_01]:[H_2025_12]],$H$5:$AQ$5),_xlfn.FORECAST.LINEAR(AY$5,tbl_Model[[#This Row],[H_2023_01]:[H_2025_12]],$H$5:$AQ$5)),0),0) -> 2.0250063 | ... BC566: =MAX(IFERROR(IFERROR(_xlfn.FORECAST.ETS(BC$5,tbl_Model[[#This Row],[H_2023_01]:[H_2025_12]],$H$5:$AQ$5),_xlfn.FORECAST.LINEAR(BC$5,tbl_Model[[#This Row],[H_2023_01]:[H_2025_12]],$H$5:$AQ$5)),0),0) -> 1.8930064 | BD566: =IFERROR(AR566/SUM(Model!$AR566:$BC566),1/12) -> 0.090624218 | BE566: =IFERROR(AS566/SUM(Model!$AR566:$BC566),1/12) -> 0.089298603 | BF566: =IFERROR(AT566/SUM(Model!$AR566:$BC566),1/12) -> 0.087972987 | BG566: =IFERROR(AU566/SUM(Model!$AR566:$BC566),1/12) -> 0.086647372 | BH566: =IFERROR(AV566/SUM(Model!$AR566:$BC566),1/12) -> 0.085321756 | BI566: =IFERROR(AW566/SUM(Model!$AR566:$BC566),1/12) -> 0.083996141 | BJ566: =IFERROR(AX566/SUM(Model!$AR566:$BC566),1/12) -> 0.082670526 | BK566: =IFERROR(AY566/SUM(Model!$AR566:$BC566),1/12) -> 0.08134491 | ... BO566: =IFERROR(BC566/SUM(Model!$AR566:$BC566),1/12) -> 0.076042449 | BP566: =_xlfn.XLOOKUP(tbl_Model[[#This Row],[country]],tbl_UnitsPerCountry[Country],tbl_UnitsPerCountry[Units2026],0) *SUMIFS(tbl_CollectionMix[Mix2026],tbl_CollectionMix[country],tbl_Model[[#This Row],[country]],tbl_CollectionMix[collection],tbl_Model[[#This Row],[collection]]) *IF(tbl_Model[[#This Row],[Type]]="Boutique", SUMIFS(tbl_ChannelMix[BoutiqueShare_2026_Effective],tbl_ChannelMix[Country],tbl_Model[[#This Row],[country]],tbl_ChannelMix[Collection],tbl_Model[[#This Row],[collection]]), 1-SUMIFS(tbl_ChannelMix[BoutiqueShare_2026_Effective],tbl_ChannelMix[Country],tbl_Model[[#This Row],[country]],tbl_ChannelMix[Collection],tbl_Model[[#This Row],[collection]])) -> 27.074951 | BQ566: {=IF(SUMIFS(tbl_SkuPrices[Units2025Actual],tbl_SkuPrices[Collection],tbl_Model[[#This Row],[collection]])=0, 0, SUMPRODUCT((tbl_SkuPrices[Collection]=tbl_Model[[#This Row],[collection]])*tbl_SkuPrices[BudgetedPrice2026]*tbl_SkuPrices[Units2025Actual]) /SUMIFS(tbl_SkuPrices[Units2025Actual],tbl_SkuPrices[Collection],tbl_Model[[#This Row],[collection]]))} -> 9379.6906 | BR566: {=IF(SUMIFS(tbl_SkuPrices[Units2025Actual],tbl_SkuPrices[Collection],tbl_Model[[#This Row],[collection]])=0,0,SUMPRODUCT((tbl_SkuPrices[Collection]=tbl_Model[[#This Row],[collection]])*tbl_SkuPrices[BudgetedCost2026]*tbl_SkuPrices[Units2025Actual]) /SUMIFS(tbl_SkuPrices[Units2025Actual],tbl_SkuPrices[Collection],tbl_Model[[#This Row],[collection]]))} -> 2699.8138 | BS566: =IF(tbl_Model[[#This Row],[Type]]="Boutique", tbl_Model[[#This Row],[UnitListPrice]], tbl_Model[[#This Row],[UnitListPrice]]*(1-SUMIFS(tbl_MarketTerms[WholesaleMarginPct],tbl_MarketTerms[Country],tbl_Model[[#This Row],[country]]))) -> 6162.4567 | BT566: =Model!$BP566*BD566 -> 2.4536462 | BU566: =Model!$BP566*BE566 -> 2.4177553 | BV566: =Model!$BP566*BF566 -> 2.3818643 | BW566: =Model!$BP566*BG566 -> 2.3459733 | BX566: =Model!$BP566*BH566 -> 2.3100823 | BY566: =Model!$BP566*BI566 -> 2.2741914 | BZ566: =Model!$BP566*BJ566 -> 2.2383004 | CA566: =Model!$BP566*BK566 -> 2.2024094 | ... CE566: =Model!$BP566*BO566 -> 2.0588455 | CF566: =Model!$BS566*BT566 -> 15120.489 | CG566: =Model!$BS566*BU566 -> 14899.312 | CH566: =Model!$BS566*BV566 -> 14678.136 | CI566: =Model!$BS566*BW566 -> 14456.959 | CJ566: =Model!$BS566*BX566 -> 14235.783 | CK566: =Model!$BS566*BY566 -> 14014.606 | CL566: =Model!$BS566*BZ566 -> 13793.429 | CM566: =Model!$BS566*CA566 -> 13572.253 | ... CQ566: =Model!$BS566*CE566 -> 12687.547 | CR566: =Model!$BR566*BT566 -> 6624.388 | CS566: =Model!$BR566*BU566 -> 6527.489 | CT566: =Model!$BR566*BV566 -> 6430.5901 | CU566: =Model!$BR566*BW566 -> 6333.6912 | CV566: =Model!$BR566*BX566 -> 6236.7922 | CW566: =Model!$BR566*BY566 -> 6139.8933 | CX566: =Model!$BR566*BZ566 -> 6042.9943 | CY566: =Model!$BR566*CA566 -> 5946.0954 | ... DC566: =Model!$BR566*CE566 -> 5558.4996 | DD566: =SUM(Model!$CF566:$CQ566) -> 166848.21 | DE566: =SUM(Model!$CR566:$DC566) -> 73097.326 | DF566: =IFERROR((Model!$DD566-Model!$DE566)/Model!$DD566,0) -> 0.56189326

Sheet Budget Export
B2: BUDGET EXPORT TO SQL
