Workbook

Sheet Overview
B2: ROLLING FORECAST MODEL
B4: This workbook reforecasts the next 12 months on a rolling basis, refreshed every month as the latest actual closes, rather than planning a single fixed fiscal year the way the Master Budget Model does. The window always looks 12 months ahead of whatever month has just closed, so it keeps moving forward and is never anchored to a calendar year end.
B6: Data
B7: Closed months are pulled the same way as the Master Budget Model, via Power Query from meridian.db / SQL Server, merged and grouped to Month x Channel x Collection x Country. This file does not re-enter price, cost, or store-opening assumptions. It reads them from the Master Budget Model's Inputs tab and adds only the handful of forward-looking drivers a rolling forecast actually needs on top.
B11: Refresh cadence
B12: Current Anchor Month: June 2026 (last closed actual). Forecast Window: July 2026 through June 2027. Each month, once the latest actual closes, the anchor moves forward one month and the window rolls with it. Next month, for example, the anchor becomes July 2026 and the window becomes August 2026 through July 2027. See the Drivers tab to update the anchor, and the Rolling Model tab to see the window shift illustrated.
B16: Workbook structure:
B17: Drivers | C17: The handful of forward-looking assumptions this forecast rolls on: channel growth trends, collection-level price and cost escalation, and boutique opening pace. Blue is input, black is formula, green is cross-sheet link, gray italic is reference, not editable.
B20: Rolling Model | C20: The engine. Shows the current 12-month rolling window against the full timeline, and how the window shifts once the next month's actual closes.
B23: Budget vs Forecast vs Actual | C23: For each closed month, the original Budget, the latest Forecast issued before that month closed, and the final Actual, side by side with the variance between each pair. The core deliverable of this file.
B26: Summary | C26: Rolling window total, trailing forecast accuracy, and refresh status at a glance.

Sheet Drivers
B2: DRIVERS
B4: The small set of forward-looking assumptions this forecast rolls on. Everything else (price, cost, and store-opening detail for FY2026) lives in the Master Budget Model's Inputs tab and is referenced from there rather than re-entered here.
B7: Color Convention
B8: Blue | C8: Manual planning input. Safe and expected to edit.
B9: Black | C9: Calculated cell. Don't type over these.
B10: Green | C10: Formula that pulls from another tab.
B11: Gray Italic | C11: Reference only, not editable, including figures sourced from the Master Budget Model workbook.
B13: Current Anchor Month
B14: Anchor Month (last closed actual) | C14: June 2026 | D14: Update once each month's actual closes. Rolling Model and Summary reference this cell to reposition the 12-month window.
B16: Sell-In / Sell-Out Monthly Growth Assumption by Channel
B17: Channel | C17: Monthly Revenue Growth % | D17: Note
B18: Boutique | C18: 0.014 | D18: Monthly-compounding equivalent of the FY2026 Budget's 18.7% annual Boutique growth (Master Budget Model, Income Statement). Adjust as new actuals close.
B19: Wholesale | C19: 0.005 | D19: Monthly-compounding equivalent of the FY2026 Budget's 6.8% annual Wholesale growth (Master Budget Model, Income Statement). Adjust as new actuals close.
B21: Price and Cost Escalation by Collection (FY2027)
B22: Collection | C22: FY2026 Avg Budgeted Price | D22: FY2026 Avg Budgeted Cost | E22: FY2027 Price Escalation % | F22: FY2027 Cost Escalation %
B23: Atelier | C23: 29050 | D23: 6625 | E23: 0.02 | F23: 0.015
B24: Aventus | C24: 9500 | D24: 2688 | E24: 0.02 | F24: 0.015
B25: Celeste | C25: 23500 | D25: 5433 | E25: 0.02 | F25: 0.015
B26: Grand Complication | C26: 27409 | D26: 6009 | E26: 0.02 | F26: 0.015
B27: Heritage | C27: 24422 | D27: 5256 | E27: 0.02 | F27: 0.015
B28: Lumina | C28: 22925 | D28: 5588 | E28: 0.02 | F28: 0.015
B29: Meridian Classic | C29: 9350 | D29: 2650 | E29: 0.02 | F29: 0.015
B30: Nautique | C30: 18508 | D30: 4742 | E30: 0.02 | F30: 0.015
B31: Sportivo | C31: 12091 | D31: 3373 | E31: 0.02 | F31: 0.015
B32: Terra | C32: 9350 | D32: 2690 | E32: 0.02 | F32: 0.015
B34: Boutique Store Openings (Rolling)
B35: Month | C35: Country | D35: Status
B36: Mar 2026 | C36: Thailand | D36: Confirmed, FY2026 Budget
B37: Apr 2026 | C37: Colombia | D37: Confirmed, FY2026 Budget
B38: Jun 2026 | C38: Vietnam | D38: Confirmed, FY2026 Budget
B39: Aug 2026 | C39: Brazil | D39: Confirmed, FY2026 Budget
B40: Oct 2026 | C40: China | D40: Confirmed, FY2026 Budget
D41: TBD, not yet planned
D42: TBD, not yet planned
D43: TBD, not yet planned

Sheet Rolling Model
B2: ROLLING MODEL: 12-MONTH FORWARD WINDOW
B4: Every row below spans a fixed 24-month timeline (Jan 2026 to Dec 2027) so the current rolling window can be seen against what came before and what comes after it. Jan through Jun 2026 are closed actuals. Jul 2026 through Jun 2027 is this month's 12-month forecast window. Jul through Dec 2027 is not yet in scope, it enters the window in later refreshes.
B6: Current Anchor Month (from Drivers tab) | C6: =Drivers!$C$14 -> June 2026
B8: Type / Collection / Country | C8: Jan-26 | D8: Feb-26 | E8: Mar-26 | F8: Apr-26 | G8: May-26 | H8: Jun-26 | I8: Jul-26 | J8: Aug-26 | K8: Sep-26 | L8: Oct-26 | M8: Nov-26 | N8: Dec-26 | O8: Jan-27 | P8: Feb-27 | Q8: Mar-27 | R8: Apr-27 | S8: May-27 | T8: Jun-27 | U8: Jul-27 | V8: Aug-27 | W8: Sep-27 | X8: Oct-27 | Y8: Nov-27 | Z8: Dec-27
B9: Status | C9: Actual | D9: Actual | E9: Actual | F9: Actual | G9: Actual | H9: Actual | I9: In Window | J9: In Window | K9: In Window | L9: In Window | M9: In Window | N9: In Window | O9: In Window | P9: In Window | Q9: In Window | R9: In Window | S9: In Window | T9: In Window | U9: Not Yet | V9: Not Yet | W9: Not Yet | X9: Not Yet | Y9: Not Yet | Z9: Not Yet
B10: Boutique / Atelier / Argentina | C10: 2.4 | D10: 2.4 | E10: 2.4 | F10: 2.4 | G10: 2.4 | H10: 2.4 | I10: =H10*(1+Drivers!$C$18) -> 2.4336 | J10: =I10*(1+Drivers!$C$18) -> 2.4676704 | K10: =J10*(1+Drivers!$C$18) -> 2.5022178 | L10: =K10*(1+Drivers!$C$18) -> 2.5372488 | M10: =L10*(1+Drivers!$C$18) -> 2.5727703 | N10: =M10*(1+Drivers!$C$18) -> 2.6087891 | O10: =N10*(1+Drivers!$C$18) -> 2.6453122 | P10: =O10*(1+Drivers!$C$18) -> 2.6823465 | ... T10: =S10*(1+Drivers!$C$18) -> 2.8357419 | U10: - | V10: - | W10: - | X10: - | Y10: - | Z10: -
B11: Boutique / Aventus / Australia | C11: 2.9 | D11: 2.9 | E11: 2.9 | F11: 2.9 | G11: 2.9 | H11: 2.9 | I11: =H11*(1+Drivers!$C$18) -> 2.9406 | J11: =I11*(1+Drivers!$C$18) -> 2.9817684 | K11: =J11*(1+Drivers!$C$18) -> 3.0235132 | L11: =K11*(1+Drivers!$C$18) -> 3.0658423 | M11: =L11*(1+Drivers!$C$18) -> 3.1087641 | N11: =M11*(1+Drivers!$C$18) -> 3.1522868 | O11: =N11*(1+Drivers!$C$18) -> 3.1964188 | P11: =O11*(1+Drivers!$C$18) -> 3.2411687 | ... T11: =S11*(1+Drivers!$C$18) -> 3.4265215 | U11: - | V11: - | W11: - | X11: - | Y11: - | Z11: -
B12: Wholesale / Atelier / United Kingdom | C12: 33.9 | D12: 33.9 | E12: 33.9 | F12: 33.9 | G12: 33.9 | H12: 33.9 | I12: =H12*(1+Drivers!$C$19) -> 34.0695 | J12: =I12*(1+Drivers!$C$19) -> 34.239848 | K12: =J12*(1+Drivers!$C$19) -> 34.411047 | L12: =K12*(1+Drivers!$C$19) -> 34.583102 | M12: =L12*(1+Drivers!$C$19) -> 34.756017 | N12: =M12*(1+Drivers!$C$19) -> 34.929798 | O12: =N12*(1+Drivers!$C$19) -> 35.104447 | P12: =O12*(1+Drivers!$C$19) -> 35.279969 | ... T12: =S12*(1+Drivers!$C$19) -> 35.990878 | U12: - | V12: - | W12: - | X12: - | Y12: - | Z12: -
B13: Wholesale / Terra / Germany | C13: 38.4 | D13: 38.4 | E13: 38.4 | F13: 38.4 | G13: 38.4 | H13: 38.4 | I13: =H13*(1+Drivers!$C$19) -> 38.592 | J13: =I13*(1+Drivers!$C$19) -> 38.78496 | K13: =J13*(1+Drivers!$C$19) -> 38.978885 | L13: =K13*(1+Drivers!$C$19) -> 39.173779 | M13: =L13*(1+Drivers!$C$19) -> 39.369648 | N13: =M13*(1+Drivers!$C$19) -> 39.566496 | O13: =N13*(1+Drivers!$C$19) -> 39.764329 | P13: =O13*(1+Drivers!$C$19) -> 39.96315 | ... T13: =S13*(1+Drivers!$C$19) -> 40.768428 | U13: - | V13: - | W13: - | X13: - | Y13: - | Z13: -
B15: How the Window Rolls Forward
B16: This refresh: anchor = Jun 2026
B17: Next refresh: anchor = Jul 2026
B18: Refresh after that: anchor = Aug 2026

Sheet Budget vs Forecast vs Actual
B2: BUDGET VS FORECAST VS ACTUAL
B4: The core deliverable of this file. For each closed month, the original FY2026 Budget, the latest Forecast issued the month before it closed, and the final Actual, side by side. Budget figures are gray italic, real, from the Master Budget Model. Forecast and Actual figures are gray italic, illustrative placeholders for this mockup. Variances are black formulas.
B7: Monthly Bridge: Total Revenue
B8: Month | C8: Budget | D8: Forecast | E8: Actual | F8: Budget vs Actual | G8: Budget vs Actual % | H8: Forecast vs Actual | I8: Forecast vs Actual %
B9: Jan-26 | C9: 82382445 | D9: 82678003 | E9: 82804670 | F9: =E9-C9 -> 422225 | G9: =E9/C9-1 -> 0.0051251817 | H9: =E9-D9 -> 126667 | I9: =E9/D9-1 -> 0.001532052
B10: Feb-26 | C10: 81554152 | D10: 82010901 | E10: 82206651 | F10: =E10-C10 -> 652499 | G10: =E10/C10-1 -> 0.0080008066 | H10: =E10-D10 -> 195750 | I10: =E10/D10-1 -> 0.0023868778
B11: Mar-26 | C11: 83697668 | D11: 84296143 | E11: 84552631 | F11: =E11-C11 -> 854963 | G11: =E11/C11-1 -> 0.010214896 | H11: =E11-D11 -> 256488 | I11: =E11/D11-1 -> 0.0030427015
B12: Apr-26 | C12: 83185402 | D12: 83928680 | E12: 84247228 | F12: =E12-C12 -> 1061826 | G12: =E12/C12-1 -> 0.012764571 | H12: =E12-D12 -> 318548 | I12: =E12/D12-1 -> 0.0037954606
B13: May-26 | C13: 86045416 | D13: 86922192 | E13: 87297953 | F13: =E13-C13 -> 1252537 | G13: =E13/C13-1 -> 0.014556696 | H13: =E13-D13 -> 375761 | I13: =E13/D13-1 -> 0.0043229582
B14: Jun-26 | C14: 86001317 | D14: 86977177 | E14: 87395403 | F14: =E14-C14 -> 1394086 | G14: =E14/C14-1 -> 0.016210054 | H14: =E14-D14 -> 418226 | I14: =E14/D14-1 -> 0.0048084568
B15: H1 2026 Total | C15: =SUM(C9:C14) -> 502866400 | D15: =SUM(D9:D14) -> 506813096 | E15: =SUM(E9:E14) -> 508504536 | F15: =E15-C15 -> 5638136 | G15: =E15/C15-1 -> 0.011211996 | H15: =E15-D15 -> 1691440 | I15: =E15/D15-1 -> 0.0033374039
B17: June 2026 Detail by Channel (Current Anchor Month)
B18: Channel | C18: Budget | D18: Forecast | E18: Actual | F18: Budget vs Actual % | G18: Forecast vs Actual %
B19: Wholesale | C19: 63936474 | D19: 64294518 | E19: 64447966 | F19: =E19/C19-1 -> 0.0080000033 | G19: =E19/D19-1 -> 0.002386642
B20: Boutique | C20: 22064843 | D20: 22682659 | E20: 22947437 | F20: =E20/C20-1 -> 0.040000013 | G20: =E20/D20-1 -> 0.011673146
B21: Total | C21: =SUM(C19:C20) -> 86001317 | D21: =SUM(D19:D20) -> 86977177 | E21: =SUM(E19:E20) -> 87395403 | F21: =E21/C21-1 -> 0.016210054 | G21: =E21/D21-1 -> 0.0048084568

Sheet Summary
B2: SUMMARY
B4: Rolling window total, trailing forecast accuracy, and refresh status at a glance. A full build would recut this the way the Budget Model's own Summary tab does, interactively by Country, Collection, and Channel.
B7: Rolling Window Total (Jul 2026 to Jun 2027)
B8: FY2026 Budget, Jul-Dec (H2 only) | C8: 541445761
B9: Jan-Jun 2027 | C9: No FY2027 Budget yet | D9: This is a real structural gap, not an oversight: a rolling window that reaches past the current fiscal year has no approved budget to compare against for the months beyond it, until that year's budget is set.
B10: Illustrative 12-Month Rolling Forecast Total | C10: 1110000000
B12: Trailing Forecast Accuracy (H1 2026, 6 Closed Months)
B13: Budget vs Actual (average bias) | C13: ='Budget vs Forecast vs Actual'!G15 -> 0.011211996 | D13: The rolling forecast tracks actual results more closely than the original budget once channel mix shifts are captured monthly instead of once a year. That gap is the reason this capability exists alongside the Budget Model, not instead of it.
B14: Forecast vs Actual (average bias) | C14: ='Budget vs Forecast vs Actual'!I15 -> 0.0033374039
B16: Refresh Status
B17: Current Anchor Month | C17: =Drivers!$C$14 -> June 2026
B18: Last Refreshed | C18: 2026-07-20
B19: Next Refresh Due | C19: Once July 2026 actuals close
