Workbook
Name Slicer_month: #N/A

Sheet Overview
B2: FY2026 FORECASTS MODEL
B4: This workbook plans FY2026 revenue, cost, and margin from the ground up, by country, collection, and channel, starting from actual 2025 performance and letting you adjust the assumptions to plan for the new fiscal year.
B6: Data
B7: Every gray 'Query Data' cell in this workbook was pulled via Power Query from meridian.db / SQL Server on 2026-07-20. It is correct as of that date, not live. Two source facts, fact_boutique_sales (direct/boutique channel) and fact_sell_in (wholesale shipments), are each merged with their supporting dimensions (store or wholesale customer to geography, SKU to collection, date to month/year), then appended into one consolidated actuals table, tagged by channel. That table is grouped down to Month x Channel x Collection x Country, which is the grain the Model tab works at.
B11: Workbook structure:
C12: Every editable assumption in one place: units per country, price and cost per SKU, collection mix by country, planned new store openings for 2026, and the Boutique/Wholesale and Retail/Online channel splits. Blue is input, black is formula, green is cross-sheet link.
C15: Takes 2025 actuals and 2026 Inputs assumptions and builds FY2026 at Type x Collection x Country x Month grain: a statistical shape (FORECAST.ETS, floored at zero) blended with your manual overrides, priced and costed per SKU, rolled into budgeted units, revenue, COGS, and margin.
C18: The Model's output consolidated into a full P&L, 2025 Actual vs 2026 Budget, monthly and quarterly, down to net income.
C19: Budget sliced interactively by Mode, Collection, Type, Region, and Country. Topline or detailed view without touching the Model tab.
C20: The Model's output reshaped to match fact_budget's schema exactly, splitting each row into its four channel_id values (Boutique/Wholesale x Retail/Online) using each Country/Collection's Channel Mix shares. This table is used at the end of the process to update the Database with the Official Budget for 2026

Sheet Summary
D2: OVERVIEW | N2: REGIONAL SPLIT
E3: Budget | F3: Forecast | G3: Variance | H3: Margin vs BGT | I3: Mix Budget | J3: Mix Forecast | O3: Budget | P3: Forecast | Q3: Variance | R3: Margin vs BGT | S3: Mix Budget | T3: Mix Forecast
D4: TOPLINE | E4: =IFERROR(_xlfn.XLOOKUP($D4,'Detailed Forecast'!$D:$D,'Detailed Forecast'!AB:AB,""),"") -> 1.0443122e+09 | F4: =IFERROR(_xlfn.XLOOKUP($D4,'Detailed Forecast'!$D:$D,'Detailed Forecast'!AC:AC,""),"") -> 9.609565e+08 | G4: =F4/E4-1 -> -0.079818722 | H4: =IFERROR((((_xlfn.XLOOKUP(D4,'Detailed Forecast'!D:D,'Detailed Forecast'!AC:AC)-_xlfn.XLOOKUP(D4,'Detailed Forecast'!D:D,'Detailed Forecast'!S:S))/F4)-((_xlfn.XLOOKUP(D4,'Detailed Forecast'!D:D,'Detailed Forecast'!AB:AB)-_xlfn.XLOOKUP(D4,'Detailed Forecast'!D:D,'Detailed Forecast'!R:R))/E4))*100,"") -> -0.69939207 | I4: =E4/E$4 -> 1 | J4: =F4/F$4 -> 1 | N4: EMEA | O4: =IFERROR(_xlfn.XLOOKUP($N4,'Detailed Forecast'!$D:$D,'Detailed Forecast'!AB:AB,""),"") -> 4.9486286e+08 | P4: =IFERROR(_xlfn.XLOOKUP($N4,'Detailed Forecast'!$D:$D,'Detailed Forecast'!AC:AC,""),"") -> 4.5559987e+08 | Q4: =P4/O4-1 -> -0.079341147 | R4: =IFERROR((((_xlfn.XLOOKUP(N4,'Detailed Forecast'!D:D,'Detailed Forecast'!AC:AC)-_xlfn.XLOOKUP(N4,'Detailed Forecast'!D:D,'Detailed Forecast'!S:S))/P4)-((_xlfn.XLOOKUP(N4,'Detailed Forecast'!D:D,'Detailed Forecast'!AB:AB)-_xlfn.XLOOKUP(N4,'Detailed Forecast'!D:D,'Detailed Forecast'!R:R))/O4))*100,"") -> -0.45313549 | S4: =O4/E$4 -> 0.47386488 | T4: =P4/F$4 -> 0.47411082
N5: APAC | O5: =IFERROR(_xlfn.XLOOKUP($N5,'Detailed Forecast'!$D:$D,'Detailed Forecast'!AB:AB,""),"") -> 3.097853e+08 | P5: =IFERROR(_xlfn.XLOOKUP($N5,'Detailed Forecast'!$D:$D,'Detailed Forecast'!AC:AC,""),"") -> 2.8613527e+08 | Q5: =P5/O5-1 -> -0.07634328 | R5: =IFERROR((((_xlfn.XLOOKUP(N5,'Detailed Forecast'!D:D,'Detailed Forecast'!AC:AC)-_xlfn.XLOOKUP(N5,'Detailed Forecast'!D:D,'Detailed Forecast'!S:S))/P5)-((_xlfn.XLOOKUP(N5,'Detailed Forecast'!D:D,'Detailed Forecast'!AB:AB)-_xlfn.XLOOKUP(N5,'Detailed Forecast'!D:D,'Detailed Forecast'!R:R))/O5))*100,"") -> -0.98947799 | S5: =O5/E$4 -> 0.29664052 | T5: =P5/F$4 -> 0.2977609
D6: Boutique | E6: =IFERROR(_xlfn.XLOOKUP($D6,'Detailed Forecast'!$D:$D,'Detailed Forecast'!AB:AB,""),"") -> 2.6983289e+08 | F6: =IFERROR(_xlfn.XLOOKUP($D6,'Detailed Forecast'!$D:$D,'Detailed Forecast'!AC:AC,""),"") -> 2.5378155e+08 | G6: =F6/E6-1 -> -0.059486213 | H6: =IFERROR((((_xlfn.XLOOKUP(D6,'Detailed Forecast'!D:D,'Detailed Forecast'!AC:AC)-_xlfn.XLOOKUP(D6,'Detailed Forecast'!D:D,'Detailed Forecast'!S:S))/F6)-((_xlfn.XLOOKUP(D6,'Detailed Forecast'!D:D,'Detailed Forecast'!AB:AB)-_xlfn.XLOOKUP(D6,'Detailed Forecast'!D:D,'Detailed Forecast'!R:R))/E6))*100,"") -> -0.4673047 | I6: =E6/E$4 -> 0.25838337 | J6: =F6/F$4 -> 0.26409266 | N6: NA | O6: =IFERROR(_xlfn.XLOOKUP($N6,'Detailed Forecast'!$D:$D,'Detailed Forecast'!AB:AB,""),"") -> 1.6842559e+08 | P6: =IFERROR(_xlfn.XLOOKUP($N6,'Detailed Forecast'!$D:$D,'Detailed Forecast'!AC:AC,""),"") -> 1.5592378e+08 | Q6: =P6/O6-1 -> -0.074227494 | R6: =IFERROR((((_xlfn.XLOOKUP(N6,'Detailed Forecast'!D:D,'Detailed Forecast'!AC:AC)-_xlfn.XLOOKUP(N6,'Detailed Forecast'!D:D,'Detailed Forecast'!S:S))/P6)-((_xlfn.XLOOKUP(N6,'Detailed Forecast'!D:D,'Detailed Forecast'!AB:AB)-_xlfn.XLOOKUP(N6,'Detailed Forecast'!D:D,'Detailed Forecast'!R:R))/O6))*100,"") -> -0.74113366 | S6: =O6/E$4 -> 0.16127897 | T6: =P6/F$4 -> 0.16225894
D7: Wholesale | E7: =IFERROR(_xlfn.XLOOKUP($D7,'Detailed Forecast'!$D:$D,'Detailed Forecast'!AB:AB,""),"") -> 7.7447927e+08 | F7: =IFERROR(_xlfn.XLOOKUP($D7,'Detailed Forecast'!$D:$D,'Detailed Forecast'!AC:AC,""),"") -> 7.0712027e+08 | G7: =F7/E7-1 -> -0.086973277 | H7: =IFERROR((((_xlfn.XLOOKUP(D7,'Detailed Forecast'!D:D,'Detailed Forecast'!AC:AC)-_xlfn.XLOOKUP(D7,'Detailed Forecast'!D:D,'Detailed Forecast'!S:S))/F7)-((_xlfn.XLOOKUP(D7,'Detailed Forecast'!D:D,'Detailed Forecast'!AB:AB)-_xlfn.XLOOKUP(D7,'Detailed Forecast'!D:D,'Detailed Forecast'!R:R))/E7))*100,"") -> -0.87796981 | I7: =E7/E$4 -> 0.74161663 | J7: =F7/F$4 -> 0.73585045 | N7: LATAM | O7: =IFERROR(_xlfn.XLOOKUP($N7,'Detailed Forecast'!$D:$D,'Detailed Forecast'!AB:AB,""),"") -> 71238416 | P7: =IFERROR(_xlfn.XLOOKUP($N7,'Detailed Forecast'!$D:$D,'Detailed Forecast'!AC:AC,""),"") -> 63260771 | Q7: =P7/O7-1 -> -0.11198515 | R7: =IFERROR((((_xlfn.XLOOKUP(N7,'Detailed Forecast'!D:D,'Detailed Forecast'!AC:AC)-_xlfn.XLOOKUP(N7,'Detailed Forecast'!D:D,'Detailed Forecast'!S:S))/P7)-((_xlfn.XLOOKUP(N7,'Detailed Forecast'!D:D,'Detailed Forecast'!AB:AB)-_xlfn.XLOOKUP(N7,'Detailed Forecast'!D:D,'Detailed Forecast'!R:R))/O7))*100,"") -> -1.0964388 | S7: =O7/E$4 -> 0.068215634 | T7: =P7/F$4 -> 0.065831046
Q8: =IFERROR(#REF!/O8-1,"") | S8: =IFERROR(#REF!/Q8-1,"")
D9: Online | E9: =IFERROR(_xlfn.XLOOKUP($D9,'Detailed Forecast'!$D:$D,'Detailed Forecast'!AB:AB,""),"") -> 279632185 | F9: =IFERROR(_xlfn.XLOOKUP($D9,'Detailed Forecast'!$D:$D,'Detailed Forecast'!AC:AC,""),"") -> 2.6169573e+08 | G9: =F9/E9-1 -> -0.064143013 | H9: =IFERROR((((_xlfn.XLOOKUP(D9,'Detailed Forecast'!D:D,'Detailed Forecast'!AC:AC)-_xlfn.XLOOKUP(D9,'Detailed Forecast'!D:D,'Detailed Forecast'!S:S))/F9)-((_xlfn.XLOOKUP(D9,'Detailed Forecast'!D:D,'Detailed Forecast'!AB:AB)-_xlfn.XLOOKUP(D9,'Detailed Forecast'!D:D,'Detailed Forecast'!R:R))/E9))*100,"") -> -0.66097818 | I9: =E9/E$4 -> 0.26776686 | J9: =F9/F$4 -> 0.27232839 | N9: United States | O9: =IFERROR(_xlfn.XLOOKUP($N9,'Detailed Forecast'!$D:$D,'Detailed Forecast'!AB:AB,""),"") -> 92133696 | P9: =IFERROR(_xlfn.XLOOKUP($N9,'Detailed Forecast'!$D:$D,'Detailed Forecast'!AC:AC,""),"") -> 84835011 | Q9: =P9/O9-1 -> -0.07921841 | R9: =IFERROR((((_xlfn.XLOOKUP(N9,'Detailed Forecast'!D:D,'Detailed Forecast'!AC:AC)-_xlfn.XLOOKUP(N9,'Detailed Forecast'!D:D,'Detailed Forecast'!S:S))/P9)-((_xlfn.XLOOKUP(N9,'Detailed Forecast'!D:D,'Detailed Forecast'!AB:AB)-_xlfn.XLOOKUP(N9,'Detailed Forecast'!D:D,'Detailed Forecast'!R:R))/O9))*100,"") -> -0.68471785 | S9: =O9/E$4 -> 0.088224287 | T9: =P9/F$4 -> 0.088281843
D10: Retail | E10: =IFERROR(_xlfn.XLOOKUP($D10,'Detailed Forecast'!$D:$D,'Detailed Forecast'!AB:AB,""),"") -> 7.6467998e+08 | F10: =IFERROR(_xlfn.XLOOKUP($D10,'Detailed Forecast'!$D:$D,'Detailed Forecast'!AC:AC,""),"") -> 6.9923021e+08 | G10: =F10/E10-1 -> -0.08559105 | H10: =IFERROR((((_xlfn.XLOOKUP(D10,'Detailed Forecast'!D:D,'Detailed Forecast'!AC:AC)-_xlfn.XLOOKUP(D10,'Detailed Forecast'!D:D,'Detailed Forecast'!S:S))/F10)-((_xlfn.XLOOKUP(D10,'Detailed Forecast'!D:D,'Detailed Forecast'!AB:AB)-_xlfn.XLOOKUP(D10,'Detailed Forecast'!D:D,'Detailed Forecast'!R:R))/E10))*100,"") -> -0.70274096 | I10: =E10/E$4 -> 0.73223314 | J10: =F10/F$4 -> 0.72763982 | N10: Switzerland | O10: =IFERROR(_xlfn.XLOOKUP($N10,'Detailed Forecast'!$D:$D,'Detailed Forecast'!AB:AB,""),"") -> 79478848 | P10: =IFERROR(_xlfn.XLOOKUP($N10,'Detailed Forecast'!$D:$D,'Detailed Forecast'!AC:AC,""),"") -> 73968231 | Q10: =P10/O10-1 -> -0.069334385 | R10: =IFERROR((((_xlfn.XLOOKUP(N10,'Detailed Forecast'!D:D,'Detailed Forecast'!AC:AC)-_xlfn.XLOOKUP(N10,'Detailed Forecast'!D:D,'Detailed Forecast'!S:S))/P10)-((_xlfn.XLOOKUP(N10,'Detailed Forecast'!D:D,'Detailed Forecast'!AB:AB)-_xlfn.XLOOKUP(N10,'Detailed Forecast'!D:D,'Detailed Forecast'!R:R))/O10))*100,"") -> -1.0532419 | S10: =O10/E$4 -> 0.076106409 | T10: =P10/F$4 -> 0.076973548
N11: United Kingdom | O11: =IFERROR(_xlfn.XLOOKUP($N11,'Detailed Forecast'!$D:$D,'Detailed Forecast'!AB:AB,""),"") -> 79547549 | P11: =IFERROR(_xlfn.XLOOKUP($N11,'Detailed Forecast'!$D:$D,'Detailed Forecast'!AC:AC,""),"") -> 74448962 | Q11: =P11/O11-1 -> -0.064094838 | R11: =IFERROR((((_xlfn.XLOOKUP(N11,'Detailed Forecast'!D:D,'Detailed Forecast'!AC:AC)-_xlfn.XLOOKUP(N11,'Detailed Forecast'!D:D,'Detailed Forecast'!S:S))/P11)-((_xlfn.XLOOKUP(N11,'Detailed Forecast'!D:D,'Detailed Forecast'!AB:AB)-_xlfn.XLOOKUP(N11,'Detailed Forecast'!D:D,'Detailed Forecast'!R:R))/O11))*100,"") -> 0.24504496 | S11: =O11/E$4 -> 0.076172195 | T11: =P11/F$4 -> 0.077473811
D12: Atelier | E12: =IFERROR(_xlfn.XLOOKUP($D12,'Detailed Forecast'!$D:$D,'Detailed Forecast'!AB:AB,""),"") -> 1.8825674e+08 | F12: =IFERROR(_xlfn.XLOOKUP($D12,'Detailed Forecast'!$D:$D,'Detailed Forecast'!AC:AC,""),"") -> 1.7255059e+08 | G12: =F12/E12-1 -> -0.083429429 | H12: =IFERROR((((_xlfn.XLOOKUP(D12,'Detailed Forecast'!D:D,'Detailed Forecast'!AC:AC)-_xlfn.XLOOKUP(D12,'Detailed Forecast'!D:D,'Detailed Forecast'!S:S))/F12)-((_xlfn.XLOOKUP(D12,'Detailed Forecast'!D:D,'Detailed Forecast'!AB:AB)-_xlfn.XLOOKUP(D12,'Detailed Forecast'!D:D,'Detailed Forecast'!R:R))/E12))*100,"") -> -1.0359771 | I12: =E12/E$4 -> 0.18026865 | J12: =F12/F$4 -> 0.17956129 | N12: Germany | O12: =IFERROR(_xlfn.XLOOKUP($N12,'Detailed Forecast'!$D:$D,'Detailed Forecast'!AB:AB,""),"") -> 75904894 | P12: =IFERROR(_xlfn.XLOOKUP($N12,'Detailed Forecast'!$D:$D,'Detailed Forecast'!AC:AC,""),"") -> 67001147 | Q12: =P12/O12-1 -> -0.11730136 | R12: =IFERROR((((_xlfn.XLOOKUP(N12,'Detailed Forecast'!D:D,'Detailed Forecast'!AC:AC)-_xlfn.XLOOKUP(N12,'Detailed Forecast'!D:D,'Detailed Forecast'!S:S))/P12)-((_xlfn.XLOOKUP(N12,'Detailed Forecast'!D:D,'Detailed Forecast'!AB:AB)-_xlfn.XLOOKUP(N12,'Detailed Forecast'!D:D,'Detailed Forecast'!R:R))/O12))*100,"") -> -0.53177849 | S12: =O12/E$4 -> 0.072684104 | T12: =P12/F$4 -> 0.069723392
D13: Grand Complication | E13: =IFERROR(_xlfn.XLOOKUP($D13,'Detailed Forecast'!$D:$D,'Detailed Forecast'!AB:AB,""),"") -> 1.6983548e+08 | F13: =IFERROR(_xlfn.XLOOKUP($D13,'Detailed Forecast'!$D:$D,'Detailed Forecast'!AC:AC,""),"") -> 1.6143978e+08 | G13: =F13/E13-1 -> -0.049434314 | H13: =IFERROR((((_xlfn.XLOOKUP(D13,'Detailed Forecast'!D:D,'Detailed Forecast'!AC:AC)-_xlfn.XLOOKUP(D13,'Detailed Forecast'!D:D,'Detailed Forecast'!S:S))/F13)-((_xlfn.XLOOKUP(D13,'Detailed Forecast'!D:D,'Detailed Forecast'!AB:AB)-_xlfn.XLOOKUP(D13,'Detailed Forecast'!D:D,'Detailed Forecast'!R:R))/E13))*100,"") -> -0.18612334 | I13: =E13/E$4 -> 0.16262904 | J13: =F13/F$4 -> 0.16799905 | N13: Japan | O13: =IFERROR(_xlfn.XLOOKUP($N13,'Detailed Forecast'!$D:$D,'Detailed Forecast'!AB:AB,""),"") -> 74351402 | P13: =IFERROR(_xlfn.XLOOKUP($N13,'Detailed Forecast'!$D:$D,'Detailed Forecast'!AC:AC,""),"") -> 69655670 | Q13: =P13/O13-1 -> -0.063155928 | R13: =IFERROR((((_xlfn.XLOOKUP(N13,'Detailed Forecast'!D:D,'Detailed Forecast'!AC:AC)-_xlfn.XLOOKUP(N13,'Detailed Forecast'!D:D,'Detailed Forecast'!S:S))/P13)-((_xlfn.XLOOKUP(N13,'Detailed Forecast'!D:D,'Detailed Forecast'!AB:AB)-_xlfn.XLOOKUP(N13,'Detailed Forecast'!D:D,'Detailed Forecast'!R:R))/O13))*100,"") -> -0.99668322 | S13: =O13/E$4 -> 0.07119653 | T13: =P13/F$4 -> 0.072485768
D14: Celeste | E14: =IFERROR(_xlfn.XLOOKUP($D14,'Detailed Forecast'!$D:$D,'Detailed Forecast'!AB:AB,""),"") -> 1.5011745e+08 | F14: =IFERROR(_xlfn.XLOOKUP($D14,'Detailed Forecast'!$D:$D,'Detailed Forecast'!AC:AC,""),"") -> 1.367532e+08 | G14: =F14/E14-1 -> -0.08902529 | H14: =IFERROR((((_xlfn.XLOOKUP(D14,'Detailed Forecast'!D:D,'Detailed Forecast'!AC:AC)-_xlfn.XLOOKUP(D14,'Detailed Forecast'!D:D,'Detailed Forecast'!S:S))/F14)-((_xlfn.XLOOKUP(D14,'Detailed Forecast'!D:D,'Detailed Forecast'!AB:AB)-_xlfn.XLOOKUP(D14,'Detailed Forecast'!D:D,'Detailed Forecast'!R:R))/E14))*100,"") -> -0.39945765 | I14: =E14/E$4 -> 0.14374768 | J14: =F14/F$4 -> 0.14230946 | N14: France | O14: =IFERROR(_xlfn.XLOOKUP($N14,'Detailed Forecast'!$D:$D,'Detailed Forecast'!AB:AB,""),"") -> 71167772 | P14: =IFERROR(_xlfn.XLOOKUP($N14,'Detailed Forecast'!$D:$D,'Detailed Forecast'!AC:AC,""),"") -> 65700803 | Q14: =P14/O14-1 -> -0.076818044 | R14: =IFERROR((((_xlfn.XLOOKUP(N14,'Detailed Forecast'!D:D,'Detailed Forecast'!AC:AC)-_xlfn.XLOOKUP(N14,'Detailed Forecast'!D:D,'Detailed Forecast'!S:S))/P14)-((_xlfn.XLOOKUP(N14,'Detailed Forecast'!D:D,'Detailed Forecast'!AB:AB)-_xlfn.XLOOKUP(N14,'Detailed Forecast'!D:D,'Detailed Forecast'!R:R))/O14))*100,"") -> -0.39141237 | S14: =O14/E$4 -> 0.068147988 | T14: =P14/F$4 -> 0.068370216
D15: Heritage | E15: =IFERROR(_xlfn.XLOOKUP($D15,'Detailed Forecast'!$D:$D,'Detailed Forecast'!AB:AB,""),"") -> 1.3310788e+08 | F15: =IFERROR(_xlfn.XLOOKUP($D15,'Detailed Forecast'!$D:$D,'Detailed Forecast'!AC:AC,""),"") -> 1.2663828e+08 | G15: =F15/E15-1 -> -0.048604169 | H15: =IFERROR((((_xlfn.XLOOKUP(D15,'Detailed Forecast'!D:D,'Detailed Forecast'!AC:AC)-_xlfn.XLOOKUP(D15,'Detailed Forecast'!D:D,'Detailed Forecast'!S:S))/F15)-((_xlfn.XLOOKUP(D15,'Detailed Forecast'!D:D,'Detailed Forecast'!AB:AB)-_xlfn.XLOOKUP(D15,'Detailed Forecast'!D:D,'Detailed Forecast'!R:R))/E15))*100,"") -> -0.32150116 | I15: =E15/E$4 -> 0.12745985 | J15: =F15/F$4 -> 0.13178357 | N15: China | O15: =IFERROR(_xlfn.XLOOKUP($N15,'Detailed Forecast'!$D:$D,'Detailed Forecast'!AB:AB,""),"") -> 68853049 | P15: =IFERROR(_xlfn.XLOOKUP($N15,'Detailed Forecast'!$D:$D,'Detailed Forecast'!AC:AC,""),"") -> 63340833 | Q15: =P15/O15-1 -> -0.080057692 | R15: =IFERROR((((_xlfn.XLOOKUP(N15,'Detailed Forecast'!D:D,'Detailed Forecast'!AC:AC)-_xlfn.XLOOKUP(N15,'Detailed Forecast'!D:D,'Detailed Forecast'!S:S))/P15)-((_xlfn.XLOOKUP(N15,'Detailed Forecast'!D:D,'Detailed Forecast'!AB:AB)-_xlfn.XLOOKUP(N15,'Detailed Forecast'!D:D,'Detailed Forecast'!R:R))/O15))*100,"") -> -1.1957068 | S15: =O15/E$4 -> 0.065931483 | T15: =P15/F$4 -> 0.06591436
D16: Lumina | E16: =IFERROR(_xlfn.XLOOKUP($D16,'Detailed Forecast'!$D:$D,'Detailed Forecast'!AB:AB,""),"") -> 1.0227366e+08 | F16: =IFERROR(_xlfn.XLOOKUP($D16,'Detailed Forecast'!$D:$D,'Detailed Forecast'!AC:AC,""),"") -> 91777145 | G16: =F16/E16-1 -> -0.10263166 | H16: =IFERROR((((_xlfn.XLOOKUP(D16,'Detailed Forecast'!D:D,'Detailed Forecast'!AC:AC)-_xlfn.XLOOKUP(D16,'Detailed Forecast'!D:D,'Detailed Forecast'!S:S))/F16)-((_xlfn.XLOOKUP(D16,'Detailed Forecast'!D:D,'Detailed Forecast'!AB:AB)-_xlfn.XLOOKUP(D16,'Detailed Forecast'!D:D,'Detailed Forecast'!R:R))/E16))*100,"") -> -0.87072183 | I16: =E16/E$4 -> 0.097933993 | J16: =F16/F$4 -> 0.095506035 | N16: Mexico | O16: =IFERROR(_xlfn.XLOOKUP($N16,'Detailed Forecast'!$D:$D,'Detailed Forecast'!AB:AB,""),"") -> 46863360 | P16: =IFERROR(_xlfn.XLOOKUP($N16,'Detailed Forecast'!$D:$D,'Detailed Forecast'!AC:AC,""),"") -> 46356402 | Q16: =P16/O16-1 -> -0.010817801 | R16: =IFERROR((((_xlfn.XLOOKUP(N16,'Detailed Forecast'!D:D,'Detailed Forecast'!AC:AC)-_xlfn.XLOOKUP(N16,'Detailed Forecast'!D:D,'Detailed Forecast'!S:S))/P16)-((_xlfn.XLOOKUP(N16,'Detailed Forecast'!D:D,'Detailed Forecast'!AB:AB)-_xlfn.XLOOKUP(N16,'Detailed Forecast'!D:D,'Detailed Forecast'!R:R))/O16))*100,"") -> -0.81222264 | S16: =O16/E$4 -> 0.044874858 | T16: =P16/F$4 -> 0.048239855
D17: Nautique | E17: =IFERROR(_xlfn.XLOOKUP($D17,'Detailed Forecast'!$D:$D,'Detailed Forecast'!AB:AB,""),"") -> 87971574 | F17: =IFERROR(_xlfn.XLOOKUP($D17,'Detailed Forecast'!$D:$D,'Detailed Forecast'!AC:AC,""),"") -> 77485073 | G17: =F17/E17-1 -> -0.11920329 | H17: =IFERROR((((_xlfn.XLOOKUP(D17,'Detailed Forecast'!D:D,'Detailed Forecast'!AC:AC)-_xlfn.XLOOKUP(D17,'Detailed Forecast'!D:D,'Detailed Forecast'!S:S))/F17)-((_xlfn.XLOOKUP(D17,'Detailed Forecast'!D:D,'Detailed Forecast'!AB:AB)-_xlfn.XLOOKUP(D17,'Detailed Forecast'!D:D,'Detailed Forecast'!R:R))/E17))*100,"") -> -1.2288681 | I17: =E17/E$4 -> 0.084238772 | J17: =F17/F$4 -> 0.080633278 | N17: UAE | O17: =IFERROR(_xlfn.XLOOKUP($N17,'Detailed Forecast'!$D:$D,'Detailed Forecast'!AB:AB,""),"") -> 45173303 | P17: =IFERROR(_xlfn.XLOOKUP($N17,'Detailed Forecast'!$D:$D,'Detailed Forecast'!AC:AC,""),"") -> 39326181 | Q17: =P17/O17-1 -> -0.12943755 | R17: =IFERROR((((_xlfn.XLOOKUP(N17,'Detailed Forecast'!D:D,'Detailed Forecast'!AC:AC)-_xlfn.XLOOKUP(N17,'Detailed Forecast'!D:D,'Detailed Forecast'!S:S))/P17)-((_xlfn.XLOOKUP(N17,'Detailed Forecast'!D:D,'Detailed Forecast'!AB:AB)-_xlfn.XLOOKUP(N17,'Detailed Forecast'!D:D,'Detailed Forecast'!R:R))/O17))*100,"") -> -0.34066386 | S17: =O17/E$4 -> 0.043256514 | T17: =P17/F$4 -> 0.040923998
D18: Sportivo | E18: =IFERROR(_xlfn.XLOOKUP($D18,'Detailed Forecast'!$D:$D,'Detailed Forecast'!AB:AB,""),"") -> 86284486 | F18: =IFERROR(_xlfn.XLOOKUP($D18,'Detailed Forecast'!$D:$D,'Detailed Forecast'!AC:AC,""),"") -> 78731598 | G18: =F18/E18-1 -> -0.087534721 | H18: =IFERROR((((_xlfn.XLOOKUP(D18,'Detailed Forecast'!D:D,'Detailed Forecast'!AC:AC)-_xlfn.XLOOKUP(D18,'Detailed Forecast'!D:D,'Detailed Forecast'!S:S))/F18)-((_xlfn.XLOOKUP(D18,'Detailed Forecast'!D:D,'Detailed Forecast'!AB:AB)-_xlfn.XLOOKUP(D18,'Detailed Forecast'!D:D,'Detailed Forecast'!R:R))/E18))*100,"") -> -1.1829601 | I18: =E18/E$4 -> 0.082623271 | J18: =F18/F$4 -> 0.08193045 | N18: South Korea | O18: =IFERROR(_xlfn.XLOOKUP($N18,'Detailed Forecast'!$D:$D,'Detailed Forecast'!AB:AB,""),"") -> 43348060 | P18: =IFERROR(_xlfn.XLOOKUP($N18,'Detailed Forecast'!$D:$D,'Detailed Forecast'!AC:AC,""),"") -> 42499336 | Q18: =P18/O18-1 -> -0.019579288 | R18: =IFERROR((((_xlfn.XLOOKUP(N18,'Detailed Forecast'!D:D,'Detailed Forecast'!AC:AC)-_xlfn.XLOOKUP(N18,'Detailed Forecast'!D:D,'Detailed Forecast'!S:S))/P18)-((_xlfn.XLOOKUP(N18,'Detailed Forecast'!D:D,'Detailed Forecast'!AB:AB)-_xlfn.XLOOKUP(N18,'Detailed Forecast'!D:D,'Detailed Forecast'!R:R))/O18))*100,"") -> -0.98157208 | S18: =O18/E$4 -> 0.041508719 | T18: =P18/F$4 -> 0.044226077
D19: Terra | E19: =IFERROR(_xlfn.XLOOKUP($D19,'Detailed Forecast'!$D:$D,'Detailed Forecast'!AB:AB,""),"") -> 50051302 | F19: =IFERROR(_xlfn.XLOOKUP($D19,'Detailed Forecast'!$D:$D,'Detailed Forecast'!AC:AC,""),"") -> 45788310 | G19: =F19/E19-1 -> -0.085172446 | H19: =IFERROR((((_xlfn.XLOOKUP(D19,'Detailed Forecast'!D:D,'Detailed Forecast'!AC:AC)-_xlfn.XLOOKUP(D19,'Detailed Forecast'!D:D,'Detailed Forecast'!S:S))/F19)-((_xlfn.XLOOKUP(D19,'Detailed Forecast'!D:D,'Detailed Forecast'!AB:AB)-_xlfn.XLOOKUP(D19,'Detailed Forecast'!D:D,'Detailed Forecast'!R:R))/E19))*100,"") -> -1.7754882 | I19: =E19/E$4 -> 0.04792753 | J19: =F19/F$4 -> 0.047648682 | N19: Brazil | O19: =IFERROR(_xlfn.XLOOKUP($N19,'Detailed Forecast'!$D:$D,'Detailed Forecast'!AB:AB,""),"") -> 39604826 | P19: =IFERROR(_xlfn.XLOOKUP($N19,'Detailed Forecast'!$D:$D,'Detailed Forecast'!AC:AC,""),"") -> 30673535 | Q19: =P19/O19-1 -> -0.22551016 | R19: =IFERROR((((_xlfn.XLOOKUP(N19,'Detailed Forecast'!D:D,'Detailed Forecast'!AC:AC)-_xlfn.XLOOKUP(N19,'Detailed Forecast'!D:D,'Detailed Forecast'!S:S))/P19)-((_xlfn.XLOOKUP(N19,'Detailed Forecast'!D:D,'Detailed Forecast'!AB:AB)-_xlfn.XLOOKUP(N19,'Detailed Forecast'!D:D,'Detailed Forecast'!R:R))/O19))*100,"") -> -2.5631571 | S19: =O19/E$4 -> 0.037924318 | T19: =P19/F$4 -> 0.031919796
D20: Meridian Classic | E20: =IFERROR(_xlfn.XLOOKUP($D20,'Detailed Forecast'!$D:$D,'Detailed Forecast'!AB:AB,""),"") -> 43126677 | F20: =IFERROR(_xlfn.XLOOKUP($D20,'Detailed Forecast'!$D:$D,'Detailed Forecast'!AC:AC,""),"") -> 39351989 | G20: =F20/E20-1 -> -0.087525598 | H20: =IFERROR((((_xlfn.XLOOKUP(D20,'Detailed Forecast'!D:D,'Detailed Forecast'!AC:AC)-_xlfn.XLOOKUP(D20,'Detailed Forecast'!D:D,'Detailed Forecast'!S:S))/F20)-((_xlfn.XLOOKUP(D20,'Detailed Forecast'!D:D,'Detailed Forecast'!AB:AB)-_xlfn.XLOOKUP(D20,'Detailed Forecast'!D:D,'Detailed Forecast'!R:R))/E20))*100,"") -> -0.77977085 | I20: =E20/E$4 -> 0.04129673 | J20: =F20/F$4 -> 0.040950853 | N20: Hong Kong | O20: =IFERROR(_xlfn.XLOOKUP($N20,'Detailed Forecast'!$D:$D,'Detailed Forecast'!AB:AB,""),"") -> 37213204 | P20: =IFERROR(_xlfn.XLOOKUP($N20,'Detailed Forecast'!$D:$D,'Detailed Forecast'!AC:AC,""),"") -> 31591595 | Q20: =P20/O20-1 -> -0.15106489 | R20: =IFERROR((((_xlfn.XLOOKUP(N20,'Detailed Forecast'!D:D,'Detailed Forecast'!AC:AC)-_xlfn.XLOOKUP(N20,'Detailed Forecast'!D:D,'Detailed Forecast'!S:S))/P20)-((_xlfn.XLOOKUP(N20,'Detailed Forecast'!D:D,'Detailed Forecast'!AB:AB)-_xlfn.XLOOKUP(N20,'Detailed Forecast'!D:D,'Detailed Forecast'!R:R))/O20))*100,"") -> -0.10985521 | S20: =O20/E$4 -> 0.035634177 | T20: =P20/F$4 -> 0.032875156
D21: Aventus | E21: =IFERROR(_xlfn.XLOOKUP($D21,'Detailed Forecast'!$D:$D,'Detailed Forecast'!AB:AB,""),"") -> 33286916 | F21: =IFERROR(_xlfn.XLOOKUP($D21,'Detailed Forecast'!$D:$D,'Detailed Forecast'!AC:AC,""),"") -> 30661390 | G21: =F21/E21-1 -> -0.078875604 | H21: =IFERROR((((_xlfn.XLOOKUP(D21,'Detailed Forecast'!D:D,'Detailed Forecast'!AC:AC)-_xlfn.XLOOKUP(D21,'Detailed Forecast'!D:D,'Detailed Forecast'!S:S))/F21)-((_xlfn.XLOOKUP(D21,'Detailed Forecast'!D:D,'Detailed Forecast'!AB:AB)-_xlfn.XLOOKUP(D21,'Detailed Forecast'!D:D,'Detailed Forecast'!R:R))/E21))*100,"") -> -0.81463366 | I21: =E21/E$4 -> 0.031874488 | J21: =F21/F$4 -> 0.031907157 | N21: Netherlands | O21: =IFERROR(_xlfn.XLOOKUP($N21,'Detailed Forecast'!$D:$D,'Detailed Forecast'!AB:AB,""),"") -> 35176261 | P21: =IFERROR(_xlfn.XLOOKUP($N21,'Detailed Forecast'!$D:$D,'Detailed Forecast'!AC:AC,""),"") -> 31882422 | Q21: =P21/O21-1 -> -0.093638101 | R21: =IFERROR((((_xlfn.XLOOKUP(N21,'Detailed Forecast'!D:D,'Detailed Forecast'!AC:AC)-_xlfn.XLOOKUP(N21,'Detailed Forecast'!D:D,'Detailed Forecast'!S:S))/P21)-((_xlfn.XLOOKUP(N21,'Detailed Forecast'!D:D,'Detailed Forecast'!AB:AB)-_xlfn.XLOOKUP(N21,'Detailed Forecast'!D:D,'Detailed Forecast'!R:R))/O21))*100,"") -> -0.35982831 | S21: =O21/E$4 -> 0.033683665 | T21: =P21/F$4 -> 0.0331778
N22: Italy | O22: =IFERROR(_xlfn.XLOOKUP($N22,'Detailed Forecast'!$D:$D,'Detailed Forecast'!AB:AB,""),"") -> 32110359 | P22: =IFERROR(_xlfn.XLOOKUP($N22,'Detailed Forecast'!$D:$D,'Detailed Forecast'!AC:AC,""),"") -> 30217287 | Q22: =P22/O22-1 -> -0.058955177 | R22: =IFERROR((((_xlfn.XLOOKUP(N22,'Detailed Forecast'!D:D,'Detailed Forecast'!AC:AC)-_xlfn.XLOOKUP(N22,'Detailed Forecast'!D:D,'Detailed Forecast'!S:S))/P22)-((_xlfn.XLOOKUP(N22,'Detailed Forecast'!D:D,'Detailed Forecast'!AB:AB)-_xlfn.XLOOKUP(N22,'Detailed Forecast'!D:D,'Detailed Forecast'!R:R))/O22))*100,"") -> -0.56260833 | S22: =O22/E$4 -> 0.030747855 | T22: =P22/F$4 -> 0.03144501
D23: JAN | E23: =IFERROR(_xlfn.XLOOKUP($D23,'Detailed Forecast'!$D:$D,'Detailed Forecast'!AB:AB,""),"") -> 82382445 | F23: =IFERROR(_xlfn.XLOOKUP($D23,'Detailed Forecast'!$D:$D,'Detailed Forecast'!AC:AC,""),"") -> 70958559 | G23: =F23/E23-1 -> -0.13866894 | H23: =IFERROR((((_xlfn.XLOOKUP(D23,'Detailed Forecast'!D:D,'Detailed Forecast'!AC:AC)-_xlfn.XLOOKUP(D23,'Detailed Forecast'!D:D,'Detailed Forecast'!S:S))/F23)-((_xlfn.XLOOKUP(D23,'Detailed Forecast'!D:D,'Detailed Forecast'!AB:AB)-_xlfn.XLOOKUP(D23,'Detailed Forecast'!D:D,'Detailed Forecast'!R:R))/E23))*100,"") -> -0.45473569 | I23: =E23/E$4 -> 0.0788868 | J23: =F23/F$4 -> 0.073841593 | N23: Australia | O23: =IFERROR(_xlfn.XLOOKUP($N23,'Detailed Forecast'!$D:$D,'Detailed Forecast'!AB:AB,""),"") -> 30718394 | P23: =IFERROR(_xlfn.XLOOKUP($N23,'Detailed Forecast'!$D:$D,'Detailed Forecast'!AC:AC,""),"") -> 30441847 | Q23: =P23/O23-1 -> -0.0090026601 | R23: =IFERROR((((_xlfn.XLOOKUP(N23,'Detailed Forecast'!D:D,'Detailed Forecast'!AC:AC)-_xlfn.XLOOKUP(N23,'Detailed Forecast'!D:D,'Detailed Forecast'!S:S))/P23)-((_xlfn.XLOOKUP(N23,'Detailed Forecast'!D:D,'Detailed Forecast'!AB:AB)-_xlfn.XLOOKUP(N23,'Detailed Forecast'!D:D,'Detailed Forecast'!R:R))/O23))*100,"") -> -1.3866294 | S23: =O23/E$4 -> 0.029414954 | T23: =P23/F$4 -> 0.031678694
D24: FEB | E24: =IFERROR(_xlfn.XLOOKUP($D24,'Detailed Forecast'!$D:$D,'Detailed Forecast'!AB:AB,""),"") -> 81554153 | F24: =IFERROR(_xlfn.XLOOKUP($D24,'Detailed Forecast'!$D:$D,'Detailed Forecast'!AC:AC,""),"") -> 67748869 | G24: =F24/E24-1 -> -0.16927751 | H24: =IFERROR((((_xlfn.XLOOKUP(D24,'Detailed Forecast'!D:D,'Detailed Forecast'!AC:AC)-_xlfn.XLOOKUP(D24,'Detailed Forecast'!D:D,'Detailed Forecast'!S:S))/F24)-((_xlfn.XLOOKUP(D24,'Detailed Forecast'!D:D,'Detailed Forecast'!AB:AB)-_xlfn.XLOOKUP(D24,'Detailed Forecast'!D:D,'Detailed Forecast'!R:R))/E24))*100,"") -> -0.5296515 | I24: =E24/E$4 -> 0.078093654 | J24: =F24/F$4 -> 0.070501494 | N24: Canada | O24: =IFERROR(_xlfn.XLOOKUP($N24,'Detailed Forecast'!$D:$D,'Detailed Forecast'!AB:AB,""),"") -> 29428532 | P24: =IFERROR(_xlfn.XLOOKUP($N24,'Detailed Forecast'!$D:$D,'Detailed Forecast'!AC:AC,""),"") -> 24824576 | Q24: =P24/O24-1 -> -0.15644532 | R24: =IFERROR((((_xlfn.XLOOKUP(N24,'Detailed Forecast'!D:D,'Detailed Forecast'!AC:AC)-_xlfn.XLOOKUP(N24,'Detailed Forecast'!D:D,'Detailed Forecast'!S:S))/P24)-((_xlfn.XLOOKUP(N24,'Detailed Forecast'!D:D,'Detailed Forecast'!AB:AB)-_xlfn.XLOOKUP(N24,'Detailed Forecast'!D:D,'Detailed Forecast'!R:R))/O24))*100,"") -> -0.83715245 | S24: =O24/E$4 -> 0.028179823 | T24: =P24/F$4 -> 0.025833194
D25: MAR | E25: =IFERROR(_xlfn.XLOOKUP($D25,'Detailed Forecast'!$D:$D,'Detailed Forecast'!AB:AB,""),"") -> 83697668 | F25: =IFERROR(_xlfn.XLOOKUP($D25,'Detailed Forecast'!$D:$D,'Detailed Forecast'!AC:AC,""),"") -> 84591120 | G25: =F25/E25-1 -> 0.010674752 | H25: =IFERROR((((_xlfn.XLOOKUP(D25,'Detailed Forecast'!D:D,'Detailed Forecast'!AC:AC)-_xlfn.XLOOKUP(D25,'Detailed Forecast'!D:D,'Detailed Forecast'!S:S))/F25)-((_xlfn.XLOOKUP(D25,'Detailed Forecast'!D:D,'Detailed Forecast'!AB:AB)-_xlfn.XLOOKUP(D25,'Detailed Forecast'!D:D,'Detailed Forecast'!R:R))/E25))*100,"") -> -0.44111022 | I25: =E25/E$4 -> 0.080146216 | J25: =F25/F$4 -> 0.088028043 | N25: Saudi Arabia | O25: =IFERROR(_xlfn.XLOOKUP($N25,'Detailed Forecast'!$D:$D,'Detailed Forecast'!AB:AB,""),"") -> 26604173 | P25: =IFERROR(_xlfn.XLOOKUP($N25,'Detailed Forecast'!$D:$D,'Detailed Forecast'!AC:AC,""),"") -> 26882371 | Q25: =P25/O25-1 -> 0.010456926 | R25: =IFERROR((((_xlfn.XLOOKUP(N25,'Detailed Forecast'!D:D,'Detailed Forecast'!AC:AC)-_xlfn.XLOOKUP(N25,'Detailed Forecast'!D:D,'Detailed Forecast'!S:S))/P25)-((_xlfn.XLOOKUP(N25,'Detailed Forecast'!D:D,'Detailed Forecast'!AB:AB)-_xlfn.XLOOKUP(N25,'Detailed Forecast'!D:D,'Detailed Forecast'!R:R))/O25))*100,"") -> -0.49088479 | S25: =O25/E$4 -> 0.025475307 | T25: =P25/F$4 -> 0.027974597
D26: APR | E26: =IFERROR(_xlfn.XLOOKUP($D26,'Detailed Forecast'!$D:$D,'Detailed Forecast'!AB:AB,""),"") -> 83185402 | F26: =IFERROR(_xlfn.XLOOKUP($D26,'Detailed Forecast'!$D:$D,'Detailed Forecast'!AC:AC,""),"") -> 77673877 | G26: =F26/E26-1 -> -0.06625591 | H26: =IFERROR((((_xlfn.XLOOKUP(D26,'Detailed Forecast'!D:D,'Detailed Forecast'!AC:AC)-_xlfn.XLOOKUP(D26,'Detailed Forecast'!D:D,'Detailed Forecast'!S:S))/F26)-((_xlfn.XLOOKUP(D26,'Detailed Forecast'!D:D,'Detailed Forecast'!AB:AB)-_xlfn.XLOOKUP(D26,'Detailed Forecast'!D:D,'Detailed Forecast'!R:R))/E26))*100,"") -> -0.81113205 | I26: =E26/E$4 -> 0.079655686 | J26: =F26/F$4 -> 0.080829754 | N26: Singapore | O26: =IFERROR(_xlfn.XLOOKUP($N26,'Detailed Forecast'!$D:$D,'Detailed Forecast'!AB:AB,""),"") -> 25004398 | P26: =IFERROR(_xlfn.XLOOKUP($N26,'Detailed Forecast'!$D:$D,'Detailed Forecast'!AC:AC,""),"") -> 21263202 | Q26: =P26/O26-1 -> -0.1496215 | R26: =IFERROR((((_xlfn.XLOOKUP(N26,'Detailed Forecast'!D:D,'Detailed Forecast'!AC:AC)-_xlfn.XLOOKUP(N26,'Detailed Forecast'!D:D,'Detailed Forecast'!S:S))/P26)-((_xlfn.XLOOKUP(N26,'Detailed Forecast'!D:D,'Detailed Forecast'!AB:AB)-_xlfn.XLOOKUP(N26,'Detailed Forecast'!D:D,'Detailed Forecast'!R:R))/O26))*100,"") -> -0.819001 | S26: =O26/E$4 -> 0.023943413 | T26: =P26/F$4 -> 0.022127123
D27: MAY | E27: =IFERROR(_xlfn.XLOOKUP($D27,'Detailed Forecast'!$D:$D,'Detailed Forecast'!AB:AB,""),"") -> 86045416 | F27: =IFERROR(_xlfn.XLOOKUP($D27,'Detailed Forecast'!$D:$D,'Detailed Forecast'!AC:AC,""),"") -> 82028726 | G27: =F27/E27-1 -> -0.046681048 | H27: =IFERROR((((_xlfn.XLOOKUP(D27,'Detailed Forecast'!D:D,'Detailed Forecast'!AC:AC)-_xlfn.XLOOKUP(D27,'Detailed Forecast'!D:D,'Detailed Forecast'!S:S))/F27)-((_xlfn.XLOOKUP(D27,'Detailed Forecast'!D:D,'Detailed Forecast'!AB:AB)-_xlfn.XLOOKUP(D27,'Detailed Forecast'!D:D,'Detailed Forecast'!R:R))/E27))*100,"") -> -0.99937855 | I27: =E27/E$4 -> 0.082394344 | J27: =F27/F$4 -> 0.085361539 | N27: Spain | O27: =IFERROR(_xlfn.XLOOKUP($N27,'Detailed Forecast'!$D:$D,'Detailed Forecast'!AB:AB,""),"") -> 21095213 | P27: =IFERROR(_xlfn.XLOOKUP($N27,'Detailed Forecast'!$D:$D,'Detailed Forecast'!AC:AC,""),"") -> 19524891 | Q27: =P27/O27-1 -> -0.074439735 | R27: =IFERROR((((_xlfn.XLOOKUP(N27,'Detailed Forecast'!D:D,'Detailed Forecast'!AC:AC)-_xlfn.XLOOKUP(N27,'Detailed Forecast'!D:D,'Detailed Forecast'!S:S))/P27)-((_xlfn.XLOOKUP(N27,'Detailed Forecast'!D:D,'Detailed Forecast'!AB:AB)-_xlfn.XLOOKUP(N27,'Detailed Forecast'!D:D,'Detailed Forecast'!R:R))/O27))*100,"") -> -0.499148 | S27: =O27/E$4 -> 0.020200102 | T27: =P27/F$4 -> 0.020318184
D28: JUN | E28: =IFERROR(_xlfn.XLOOKUP($D28,'Detailed Forecast'!$D:$D,'Detailed Forecast'!AB:AB,""),"") -> 86001317 | F28: =IFERROR(_xlfn.XLOOKUP($D28,'Detailed Forecast'!$D:$D,'Detailed Forecast'!AC:AC,""),"") -> 79707905 | G28: =F28/E28-1 -> -0.073178091 | H28: =IFERROR((((_xlfn.XLOOKUP(D28,'Detailed Forecast'!D:D,'Detailed Forecast'!AC:AC)-_xlfn.XLOOKUP(D28,'Detailed Forecast'!D:D,'Detailed Forecast'!S:S))/F28)-((_xlfn.XLOOKUP(D28,'Detailed Forecast'!D:D,'Detailed Forecast'!AB:AB)-_xlfn.XLOOKUP(D28,'Detailed Forecast'!D:D,'Detailed Forecast'!R:R))/E28))*100,"") -> -0.91906178 | I28: =E28/E$4 -> 0.082352117 | J28: =F28/F$4 -> 0.082946424 | N28: Peru | O28: =IFERROR(_xlfn.XLOOKUP($N28,'Detailed Forecast'!$D:$D,'Detailed Forecast'!AB:AB,""),"") -> 11872331 | P28: =IFERROR(_xlfn.XLOOKUP($N28,'Detailed Forecast'!$D:$D,'Detailed Forecast'!AC:AC,""),"") -> 10638417 | Q28: =P28/O28-1 -> -0.10393189 | R28: =IFERROR((((_xlfn.XLOOKUP(N28,'Detailed Forecast'!D:D,'Detailed Forecast'!AC:AC)-_xlfn.XLOOKUP(N28,'Detailed Forecast'!D:D,'Detailed Forecast'!S:S))/P28)-((_xlfn.XLOOKUP(N28,'Detailed Forecast'!D:D,'Detailed Forecast'!AB:AB)-_xlfn.XLOOKUP(N28,'Detailed Forecast'!D:D,'Detailed Forecast'!R:R))/O28))*100,"") -> -0.3964698 | S28: =O28/E$4 -> 0.011368565 | T28: =P28/F$4 -> 0.011070655
D29: JUL | E29: =IFERROR(_xlfn.XLOOKUP($D29,'Detailed Forecast'!$D:$D,'Detailed Forecast'!AB:AB,""),"") -> 84448323 | F29: =IFERROR(_xlfn.XLOOKUP($D29,'Detailed Forecast'!$D:$D,'Detailed Forecast'!AC:AC,""),"") -> 77704543 | G29: =F29/E29-1 -> -0.079856886 | H29: =IFERROR((((_xlfn.XLOOKUP(D29,'Detailed Forecast'!D:D,'Detailed Forecast'!AC:AC)-_xlfn.XLOOKUP(D29,'Detailed Forecast'!D:D,'Detailed Forecast'!S:S))/F29)-((_xlfn.XLOOKUP(D29,'Detailed Forecast'!D:D,'Detailed Forecast'!AB:AB)-_xlfn.XLOOKUP(D29,'Detailed Forecast'!D:D,'Detailed Forecast'!R:R))/E29))*100,"") -> -0.69798759 | I29: =E29/E$4 -> 0.08086502 | J29: =F29/F$4 -> 0.080861666 | N29: Vietnam | O29: =IFERROR(_xlfn.XLOOKUP($N29,'Detailed Forecast'!$D:$D,'Detailed Forecast'!AB:AB,""),"") -> 12312228 | P29: =IFERROR(_xlfn.XLOOKUP($N29,'Detailed Forecast'!$D:$D,'Detailed Forecast'!AC:AC,""),"") -> 10223461 | Q29: =P29/O29-1 -> -0.16964978 | R29: =IFERROR((((_xlfn.XLOOKUP(N29,'Detailed Forecast'!D:D,'Detailed Forecast'!AC:AC)-_xlfn.XLOOKUP(N29,'Detailed Forecast'!D:D,'Detailed Forecast'!S:S))/P29)-((_xlfn.XLOOKUP(N29,'Detailed Forecast'!D:D,'Detailed Forecast'!AB:AB)-_xlfn.XLOOKUP(N29,'Detailed Forecast'!D:D,'Detailed Forecast'!R:R))/O29))*100,"") -> -2.7652271 | S29: =O29/E$4 -> 0.011789797 | T29: =P29/F$4 -> 0.010638839
D30: AUG | E30: =IFERROR(_xlfn.XLOOKUP($D30,'Detailed Forecast'!$D:$D,'Detailed Forecast'!AB:AB,""),"") -> 85293961 | F30: =IFERROR(_xlfn.XLOOKUP($D30,'Detailed Forecast'!$D:$D,'Detailed Forecast'!AC:AC,""),"") -> 78482651 | G30: =F30/E30-1 -> -0.079856886 | H30: =IFERROR((((_xlfn.XLOOKUP(D30,'Detailed Forecast'!D:D,'Detailed Forecast'!AC:AC)-_xlfn.XLOOKUP(D30,'Detailed Forecast'!D:D,'Detailed Forecast'!S:S))/F30)-((_xlfn.XLOOKUP(D30,'Detailed Forecast'!D:D,'Detailed Forecast'!AB:AB)-_xlfn.XLOOKUP(D30,'Detailed Forecast'!D:D,'Detailed Forecast'!R:R))/E30))*100,"") -> -0.69939151 | I30: =E30/E$4 -> 0.081674775 | J30: =F30/F$4 -> 0.081671388 | N30: Chile | O30: =IFERROR(_xlfn.XLOOKUP($N30,'Detailed Forecast'!$D:$D,'Detailed Forecast'!AB:AB,""),"") -> 8954264.8 | P30: =IFERROR(_xlfn.XLOOKUP($N30,'Detailed Forecast'!$D:$D,'Detailed Forecast'!AC:AC,""),"") -> 10048556 | Q30: =P30/O30-1 -> 0.12220892 | R30: =IFERROR((((_xlfn.XLOOKUP(N30,'Detailed Forecast'!D:D,'Detailed Forecast'!AC:AC)-_xlfn.XLOOKUP(N30,'Detailed Forecast'!D:D,'Detailed Forecast'!S:S))/P30)-((_xlfn.XLOOKUP(N30,'Detailed Forecast'!D:D,'Detailed Forecast'!AB:AB)-_xlfn.XLOOKUP(N30,'Detailed Forecast'!D:D,'Detailed Forecast'!R:R))/O30))*100,"") -> -0.80324476 | S30: =O30/E$4 -> 0.0085743183 | T30: =P30/F$4 -> 0.010456827
D31: SEP | E31: =IFERROR(_xlfn.XLOOKUP($D31,'Detailed Forecast'!$D:$D,'Detailed Forecast'!AB:AB,""),"") -> 87377353 | F31: =IFERROR(_xlfn.XLOOKUP($D31,'Detailed Forecast'!$D:$D,'Detailed Forecast'!AC:AC,""),"") -> 80399670 | G31: =F31/E31-1 -> -0.079856886 | H31: =IFERROR((((_xlfn.XLOOKUP(D31,'Detailed Forecast'!D:D,'Detailed Forecast'!AC:AC)-_xlfn.XLOOKUP(D31,'Detailed Forecast'!D:D,'Detailed Forecast'!S:S))/F31)-((_xlfn.XLOOKUP(D31,'Detailed Forecast'!D:D,'Detailed Forecast'!AB:AB)-_xlfn.XLOOKUP(D31,'Detailed Forecast'!D:D,'Detailed Forecast'!R:R))/E31))*100,"") -> -0.69840649 | I31: =E31/E$4 -> 0.083669765 | J31: =F31/F$4 -> 0.083666295 | N31: Taiwan | O31: =IFERROR(_xlfn.XLOOKUP($N31,'Detailed Forecast'!$D:$D,'Detailed Forecast'!AB:AB,""),"") -> 8349498.7 | P31: =IFERROR(_xlfn.XLOOKUP($N31,'Detailed Forecast'!$D:$D,'Detailed Forecast'!AC:AC,""),"") -> 8144660 | Q31: =P31/O31-1 -> -0.024533053 | R31: =IFERROR((((_xlfn.XLOOKUP(N31,'Detailed Forecast'!D:D,'Detailed Forecast'!AC:AC)-_xlfn.XLOOKUP(N31,'Detailed Forecast'!D:D,'Detailed Forecast'!S:S))/P31)-((_xlfn.XLOOKUP(N31,'Detailed Forecast'!D:D,'Detailed Forecast'!AB:AB)-_xlfn.XLOOKUP(N31,'Detailed Forecast'!D:D,'Detailed Forecast'!R:R))/O31))*100,"") -> -0.15503899 | S31: =O31/E$4 -> 0.0079952135 | T31: =P31/F$4 -> 0.0084755762
D32: OCT | E32: =IFERROR(_xlfn.XLOOKUP($D32,'Detailed Forecast'!$D:$D,'Detailed Forecast'!AB:AB,""),"") -> 90973952 | F32: =IFERROR(_xlfn.XLOOKUP($D32,'Detailed Forecast'!$D:$D,'Detailed Forecast'!AC:AC,""),"") -> 83709056 | G32: =F32/E32-1 -> -0.079856886 | H32: =IFERROR((((_xlfn.XLOOKUP(D32,'Detailed Forecast'!D:D,'Detailed Forecast'!AC:AC)-_xlfn.XLOOKUP(D32,'Detailed Forecast'!D:D,'Detailed Forecast'!S:S))/F32)-((_xlfn.XLOOKUP(D32,'Detailed Forecast'!D:D,'Detailed Forecast'!AB:AB)-_xlfn.XLOOKUP(D32,'Detailed Forecast'!D:D,'Detailed Forecast'!R:R))/E32))*100,"") -> -0.69918899 | I32: =E32/E$4 -> 0.087113754 | J32: =F32/F$4 -> 0.087110141 | N32: Argentina | O32: =IFERROR(_xlfn.XLOOKUP($N32,'Detailed Forecast'!$D:$D,'Detailed Forecast'!AB:AB,""),"") -> 7486142.7 | P32: =IFERROR(_xlfn.XLOOKUP($N32,'Detailed Forecast'!$D:$D,'Detailed Forecast'!AC:AC,""),"") -> 8755372.9 | Q32: =P32/O32-1 -> 0.16954395 | R32: =IFERROR((((_xlfn.XLOOKUP(N32,'Detailed Forecast'!D:D,'Detailed Forecast'!AC:AC)-_xlfn.XLOOKUP(N32,'Detailed Forecast'!D:D,'Detailed Forecast'!S:S))/P32)-((_xlfn.XLOOKUP(N32,'Detailed Forecast'!D:D,'Detailed Forecast'!AB:AB)-_xlfn.XLOOKUP(N32,'Detailed Forecast'!D:D,'Detailed Forecast'!R:R))/O32))*100,"") -> 0.30696892 | S32: =O32/E$4 -> 0.0071684913 | T32: =P32/F$4 -> 0.0091111022
D33: NOV | E33: =IFERROR(_xlfn.XLOOKUP($D33,'Detailed Forecast'!$D:$D,'Detailed Forecast'!AB:AB,""),"") -> 96279579 | F33: =IFERROR(_xlfn.XLOOKUP($D33,'Detailed Forecast'!$D:$D,'Detailed Forecast'!AC:AC,""),"") -> 88590991 | G33: =F33/E33-1 -> -0.079856886 | H33: =IFERROR((((_xlfn.XLOOKUP(D33,'Detailed Forecast'!D:D,'Detailed Forecast'!AC:AC)-_xlfn.XLOOKUP(D33,'Detailed Forecast'!D:D,'Detailed Forecast'!S:S))/F33)-((_xlfn.XLOOKUP(D33,'Detailed Forecast'!D:D,'Detailed Forecast'!AB:AB)-_xlfn.XLOOKUP(D33,'Detailed Forecast'!D:D,'Detailed Forecast'!R:R))/E33))*100,"") -> -0.69957538 | I33: =E33/E$4 -> 0.092194252 | J33: =F33/F$4 -> 0.092190428 | N33: Greece | O33: =IFERROR(_xlfn.XLOOKUP($N33,'Detailed Forecast'!$D:$D,'Detailed Forecast'!AB:AB,""),"") -> 7250288.4 | P33: =IFERROR(_xlfn.XLOOKUP($N33,'Detailed Forecast'!$D:$D,'Detailed Forecast'!AC:AC,""),"") -> 6155204.5 | Q33: =P33/O33-1 -> -0.15104005 | R33: =IFERROR((((_xlfn.XLOOKUP(N33,'Detailed Forecast'!D:D,'Detailed Forecast'!AC:AC)-_xlfn.XLOOKUP(N33,'Detailed Forecast'!D:D,'Detailed Forecast'!S:S))/P33)-((_xlfn.XLOOKUP(N33,'Detailed Forecast'!D:D,'Detailed Forecast'!AB:AB)-_xlfn.XLOOKUP(N33,'Detailed Forecast'!D:D,'Detailed Forecast'!R:R))/O33))*100,"") -> -0.49372532 | S33: =O33/E$4 -> 0.0069426448 | T33: =P33/F$4 -> 0.0064052894
D34: DEC | E34: =IFERROR(_xlfn.XLOOKUP($D34,'Detailed Forecast'!$D:$D,'Detailed Forecast'!AB:AB,""),"") -> 97072592 | F34: =IFERROR(_xlfn.XLOOKUP($D34,'Detailed Forecast'!$D:$D,'Detailed Forecast'!AC:AC,""),"") -> 89320677 | G34: =F34/E34-1 -> -0.079856886 | H34: =IFERROR((((_xlfn.XLOOKUP(D34,'Detailed Forecast'!D:D,'Detailed Forecast'!AC:AC)-_xlfn.XLOOKUP(D34,'Detailed Forecast'!D:D,'Detailed Forecast'!S:S))/F34)-((_xlfn.XLOOKUP(D34,'Detailed Forecast'!D:D,'Detailed Forecast'!AB:AB)-_xlfn.XLOOKUP(D34,'Detailed Forecast'!D:D,'Detailed Forecast'!R:R))/E34))*100,"") -> -0.69960101 | I34: =E34/E$4 -> 0.092953616 | J34: =F34/F$4 -> 0.092949761 | N34: Belgium | O34: =IFERROR(_xlfn.XLOOKUP($N34,'Detailed Forecast'!$D:$D,'Detailed Forecast'!AB:AB,""),"") -> 7101675.1 | P34: =IFERROR(_xlfn.XLOOKUP($N34,'Detailed Forecast'!$D:$D,'Detailed Forecast'!AC:AC,""),"") -> 6195889.5 | Q34: =P34/O34-1 -> -0.12754534 | R34: =IFERROR((((_xlfn.XLOOKUP(N34,'Detailed Forecast'!D:D,'Detailed Forecast'!AC:AC)-_xlfn.XLOOKUP(N34,'Detailed Forecast'!D:D,'Detailed Forecast'!S:S))/P34)-((_xlfn.XLOOKUP(N34,'Detailed Forecast'!D:D,'Detailed Forecast'!AB:AB)-_xlfn.XLOOKUP(N34,'Detailed Forecast'!D:D,'Detailed Forecast'!R:R))/O34))*100,"") -> -0.99190417 | S34: =O34/E$4 -> 0.0068003375 | T34: =P34/F$4 -> 0.0064476275
N35: Portugal | O35: =IFERROR(_xlfn.XLOOKUP($N35,'Detailed Forecast'!$D:$D,'Detailed Forecast'!AB:AB,""),"") -> 6598666.2 | P35: =IFERROR(_xlfn.XLOOKUP($N35,'Detailed Forecast'!$D:$D,'Detailed Forecast'!AC:AC,""),"") -> 8155816.6 | Q35: =P35/O35-1 -> 0.23597957 | R35: =IFERROR((((_xlfn.XLOOKUP(N35,'Detailed Forecast'!D:D,'Detailed Forecast'!AC:AC)-_xlfn.XLOOKUP(N35,'Detailed Forecast'!D:D,'Detailed Forecast'!S:S))/P35)-((_xlfn.XLOOKUP(N35,'Detailed Forecast'!D:D,'Detailed Forecast'!AB:AB)-_xlfn.XLOOKUP(N35,'Detailed Forecast'!D:D,'Detailed Forecast'!R:R))/O35))*100,"") -> -0.63818547 | S35: =O35/E$4 -> 0.0063186722 | T35: =P35/F$4 -> 0.008487186
N36: Thailand | O36: =IFERROR(_xlfn.XLOOKUP($N36,'Detailed Forecast'!$D:$D,'Detailed Forecast'!AB:AB,""),"") -> 5800820.7 | P36: =IFERROR(_xlfn.XLOOKUP($N36,'Detailed Forecast'!$D:$D,'Detailed Forecast'!AC:AC,""),"") -> 4956554.8 | Q36: =P36/O36-1 -> -0.1455425 | R36: =IFERROR((((_xlfn.XLOOKUP(N36,'Detailed Forecast'!D:D,'Detailed Forecast'!AC:AC)-_xlfn.XLOOKUP(N36,'Detailed Forecast'!D:D,'Detailed Forecast'!S:S))/P36)-((_xlfn.XLOOKUP(N36,'Detailed Forecast'!D:D,'Detailed Forecast'!AB:AB)-_xlfn.XLOOKUP(N36,'Detailed Forecast'!D:D,'Detailed Forecast'!R:R))/O36))*100,"") -> -0.21147053 | S36: =O36/E$4 -> 0.0055546808 | T36: =P36/F$4 -> 0.0051579387
N37: Austria | O37: =IFERROR(_xlfn.XLOOKUP($N37,'Detailed Forecast'!$D:$D,'Detailed Forecast'!AB:AB,""),"") -> 3991680.5 | P37: =IFERROR(_xlfn.XLOOKUP($N37,'Detailed Forecast'!$D:$D,'Detailed Forecast'!AC:AC,""),"") -> 2467948.6 | Q37: =P37/O37-1 -> -0.38172693 | R37: =IFERROR((((_xlfn.XLOOKUP(N37,'Detailed Forecast'!D:D,'Detailed Forecast'!AC:AC)-_xlfn.XLOOKUP(N37,'Detailed Forecast'!D:D,'Detailed Forecast'!S:S))/P37)-((_xlfn.XLOOKUP(N37,'Detailed Forecast'!D:D,'Detailed Forecast'!AB:AB)-_xlfn.XLOOKUP(N37,'Detailed Forecast'!D:D,'Detailed Forecast'!R:R))/O37))*100,"") -> -0.55776235 | S37: =O37/E$4 -> 0.0038223059 | T37: =P37/F$4 -> 0.0025682209
N38: Malaysia | O38: =IFERROR(_xlfn.XLOOKUP($N38,'Detailed Forecast'!$D:$D,'Detailed Forecast'!AB:AB,""),"") -> 3834242.8 | P38: =IFERROR(_xlfn.XLOOKUP($N38,'Detailed Forecast'!$D:$D,'Detailed Forecast'!AC:AC,""),"") -> 4090033.1 | Q38: =P38/O38-1 -> 0.066712083 | R38: =IFERROR((((_xlfn.XLOOKUP(N38,'Detailed Forecast'!D:D,'Detailed Forecast'!AC:AC)-_xlfn.XLOOKUP(N38,'Detailed Forecast'!D:D,'Detailed Forecast'!S:S))/P38)-((_xlfn.XLOOKUP(N38,'Detailed Forecast'!D:D,'Detailed Forecast'!AB:AB)-_xlfn.XLOOKUP(N38,'Detailed Forecast'!D:D,'Detailed Forecast'!R:R))/O38))*100,"") -> -1.1649871 | S38: =O38/E$4 -> 0.0036715485 | T38: =P38/F$4 -> 0.0042562105
N39: Estonia | O39: =IFERROR(_xlfn.XLOOKUP($N39,'Detailed Forecast'!$D:$D,'Detailed Forecast'!AB:AB,""),"") -> 3662176.3 | P39: =IFERROR(_xlfn.XLOOKUP($N39,'Detailed Forecast'!$D:$D,'Detailed Forecast'!AC:AC,""),"") -> 3439988.7 | Q39: =P39/O39-1 -> -0.060670928 | R39: =IFERROR((((_xlfn.XLOOKUP(N39,'Detailed Forecast'!D:D,'Detailed Forecast'!AC:AC)-_xlfn.XLOOKUP(N39,'Detailed Forecast'!D:D,'Detailed Forecast'!S:S))/P39)-((_xlfn.XLOOKUP(N39,'Detailed Forecast'!D:D,'Detailed Forecast'!AB:AB)-_xlfn.XLOOKUP(N39,'Detailed Forecast'!D:D,'Detailed Forecast'!R:R))/O39))*100,"") -> -1.6801556 | S39: =O39/E$4 -> 0.0035067832 | T39: =P39/F$4 -> 0.0035797549
N40: Colombia | O40: =IFERROR(_xlfn.XLOOKUP($N40,'Detailed Forecast'!$D:$D,'Detailed Forecast'!AB:AB,""),"") -> 3320851.4 | P40: =IFERROR(_xlfn.XLOOKUP($N40,'Detailed Forecast'!$D:$D,'Detailed Forecast'!AC:AC,""),"") -> 3191324.4 | Q40: =P40/O40-1 -> -0.039004163 | R40: =IFERROR((((_xlfn.XLOOKUP(N40,'Detailed Forecast'!D:D,'Detailed Forecast'!AC:AC)-_xlfn.XLOOKUP(N40,'Detailed Forecast'!D:D,'Detailed Forecast'!S:S))/P40)-((_xlfn.XLOOKUP(N40,'Detailed Forecast'!D:D,'Detailed Forecast'!AB:AB)-_xlfn.XLOOKUP(N40,'Detailed Forecast'!D:D,'Detailed Forecast'!R:R))/O40))*100,"") -> -1.3334719 | S40: =O40/E$4 -> 0.0031799413 | T40: =P40/F$4 -> 0.0033209873

Sheet Income Statement
B2: INCOME STATEMENT
B4: Color Convention | K4: EXPENSES COEFFICIENT | M4: Represents the manual input designed for this Forecast Model, which applies to Operating, Interests and Tax Expenses as a sourch of additional variation other than the Actuals vs Budget based on Sales
B5: Blue | C5: Manual input/used in Income Statement only
B6: Black | C6: Calculated cell
B7: Green | C7: Formula that pulls from another tab/used in Income Statement only
C9: 2026 BUDGET | D9: 2026 FORECAST | E9: % | G9: EXPENSES COEFFICIENT | H9: JAN | I9: FEB | J9: MAR | K9: APR | L9: MAY | M9: JUN | N9: JUL | O9: AUG | P9: SEP | Q9: OCT | R9: NOV | S9: DEC | U9: Q1 | V9: Q2 | W9: Q3 | X9: Q4
B10: Revenue
B11: Boutique Revenue | C11: =IFERROR(_xlfn.XLOOKUP(_xlfn.TEXTBEFORE(B11," "),'Detailed Forecast'!$D$7:$D$8,'Detailed Forecast'!$AB$10:$AB$11,0),0) -> 279632185 | D11: =SUM(U11,V11,W11,X11) -> 2.5378155e+08 | E11: =D11/C11-1 -> -0.092445118 | H11: =IFERROR(_xlfn.XLOOKUP(_xlfn.CONCAT(_xlfn.TEXTBEFORE($B11," ")," - ",H$9),Model!$D$64:$D$87,Model!$AA$64:$AA$87,0),0) -> 18523464 | I11: =IFERROR(_xlfn.XLOOKUP(_xlfn.CONCAT(_xlfn.TEXTBEFORE($B11," ")," - ",I$9),Model!$D$64:$D$87,Model!$AA$64:$AA$87,0),0) -> 17268734 | J11: =IFERROR(_xlfn.XLOOKUP(_xlfn.CONCAT(_xlfn.TEXTBEFORE($B11," ")," - ",J$9),Model!$D$64:$D$87,Model!$AA$64:$AA$87,0),0) -> 22083621 | K11: =IFERROR(_xlfn.XLOOKUP(_xlfn.CONCAT(_xlfn.TEXTBEFORE($B11," ")," - ",K$9),Model!$D$64:$D$87,Model!$AA$64:$AA$87,0),0) -> 21179108 | L11: =IFERROR(_xlfn.XLOOKUP(_xlfn.CONCAT(_xlfn.TEXTBEFORE($B11," ")," - ",L$9),Model!$D$64:$D$87,Model!$AA$64:$AA$87,0),0) -> 23141212 | M11: =IFERROR(_xlfn.XLOOKUP(_xlfn.CONCAT(_xlfn.TEXTBEFORE($B11," ")," - ",M$9),Model!$D$64:$D$87,Model!$AA$64:$AA$87,0),0) -> 20251165 | N11: =IFERROR(_xlfn.XLOOKUP(_xlfn.CONCAT(_xlfn.TEXTBEFORE($B11," ")," - ",N$9),Model!$D$64:$D$87,Model!$AA$64:$AA$87,0),0) -> 20877025 | O11: =IFERROR(_xlfn.XLOOKUP(_xlfn.CONCAT(_xlfn.TEXTBEFORE($B11," ")," - ",O$9),Model!$D$64:$D$87,Model!$AA$64:$AA$87,0),0) -> 20896814 | ... S11: =IFERROR(_xlfn.XLOOKUP(_xlfn.CONCAT(_xlfn.TEXTBEFORE($B11," ")," - ",S$9),Model!$D$64:$D$87,Model!$AA$64:$AA$87,0),0) -> 23247048 | U11: =SUM(H11:J11) -> 57875818 | V11: =SUM(K11:M11) -> 64571485 | W11: =SUM(N11:P11) -> 63454008 | X11: =SUM(Q11:S11) -> 67880243
B12: Wholesale Revenue | C12: =IFERROR(_xlfn.XLOOKUP(_xlfn.TEXTBEFORE(B12," "),'Detailed Forecast'!$D$7:$D$8,'Detailed Forecast'!$AB$10:$AB$11,0),0) -> 7.6467998e+08 | D12: =SUM(U12,V12,W12,X12) -> 7.0712027e+08 | E12: =D12/C12-1 -> -0.075272936 | H12: =IFERROR(_xlfn.XLOOKUP(_xlfn.CONCAT(_xlfn.TEXTBEFORE($B12," ")," - ",H$9),Model!$D$64:$D$87,Model!$AA$64:$AA$87,0),0) -> 52435095 | I12: =IFERROR(_xlfn.XLOOKUP(_xlfn.CONCAT(_xlfn.TEXTBEFORE($B12," ")," - ",I$9),Model!$D$64:$D$87,Model!$AA$64:$AA$87,0),0) -> 50480135 | J12: =IFERROR(_xlfn.XLOOKUP(_xlfn.CONCAT(_xlfn.TEXTBEFORE($B12," ")," - ",J$9),Model!$D$64:$D$87,Model!$AA$64:$AA$87,0),0) -> 62507499 | K12: =IFERROR(_xlfn.XLOOKUP(_xlfn.CONCAT(_xlfn.TEXTBEFORE($B12," ")," - ",K$9),Model!$D$64:$D$87,Model!$AA$64:$AA$87,0),0) -> 56494769 | L12: =IFERROR(_xlfn.XLOOKUP(_xlfn.CONCAT(_xlfn.TEXTBEFORE($B12," ")," - ",L$9),Model!$D$64:$D$87,Model!$AA$64:$AA$87,0),0) -> 58887513 | M12: =IFERROR(_xlfn.XLOOKUP(_xlfn.CONCAT(_xlfn.TEXTBEFORE($B12," ")," - ",M$9),Model!$D$64:$D$87,Model!$AA$64:$AA$87,0),0) -> 59456740 | N12: =IFERROR(_xlfn.XLOOKUP(_xlfn.CONCAT(_xlfn.TEXTBEFORE($B12," ")," - ",N$9),Model!$D$64:$D$87,Model!$AA$64:$AA$87,0),0) -> 56836694 | O12: =IFERROR(_xlfn.XLOOKUP(_xlfn.CONCAT(_xlfn.TEXTBEFORE($B12," ")," - ",O$9),Model!$D$64:$D$87,Model!$AA$64:$AA$87,0),0) -> 57589573 | ... S12: =IFERROR(_xlfn.XLOOKUP(_xlfn.CONCAT(_xlfn.TEXTBEFORE($B12," ")," - ",S$9),Model!$D$64:$D$87,Model!$AA$64:$AA$87,0),0) -> 66062231 | U12: =SUM(H12:J12) -> 1.6542273e+08 | V12: =SUM(K12:M12) -> 1.7483902e+08 | W12: =SUM(N12:P12) -> 1.7315757e+08 | X12: =SUM(Q12:S12) -> 1.9370094e+08
B13: Total Net Revenue | C13: =SUM(C11:C12) -> 1.0443122e+09 | D13: =Model!AA7 -> 9.609565e+08 | E13: =D13/C13-1 -> -0.079818722 | H13: =H11+H12 -> 70958559 | I13: =I11+I12 -> 67748869 | J13: =J11+J12 -> 84591120 | K13: =K11+K12 -> 77673877 | L13: =L11+L12 -> 82028726 | M13: =M11+M12 -> 79707905 | N13: =N11+N12 -> 77713719 | O13: =O11+O12 -> 78486387 | ... S13: =S11+S12 -> 89309279 | U13: =SUM(H13:J13) -> 2.2329855e+08 | V13: =SUM(K13:M13) -> 2.3941051e+08 | W13: =SUM(N13:P13) -> 2.3661158e+08 | X13: =SUM(Q13:S13) -> 2.6158119e+08
B15: Cost of Goods Sold
B16: Boutique COGS | C16: =IFERROR(_xlfn.XLOOKUP(_xlfn.TEXTBEFORE(B16," "),'Detailed Forecast'!$D$7:$D$8,'Detailed Forecast'!$R$10:$R$11,0),0) -> 96280930 | D16: =SUM(U16,V16,W16,X16) -> 62394552 | E16: =D16/C16-1 -> -0.35195316 | H16: =IFERROR(_xlfn.XLOOKUP(_xlfn.CONCAT(_xlfn.TEXTBEFORE($B16," ")," - ",H$9),Model!$D$64:$D$87,Model!$Z$64:$Z$87,0),0) -> 4507909.5 | I16: =IFERROR(_xlfn.XLOOKUP(_xlfn.CONCAT(_xlfn.TEXTBEFORE($B16," ")," - ",I$9),Model!$D$64:$D$87,Model!$Z$64:$Z$87,0),0) -> 4216923.3 | J16: =IFERROR(_xlfn.XLOOKUP(_xlfn.CONCAT(_xlfn.TEXTBEFORE($B16," ")," - ",J$9),Model!$D$64:$D$87,Model!$Z$64:$Z$87,0),0) -> 5415470 | K16: =IFERROR(_xlfn.XLOOKUP(_xlfn.CONCAT(_xlfn.TEXTBEFORE($B16," ")," - ",K$9),Model!$D$64:$D$87,Model!$Z$64:$Z$87,0),0) -> 5221563.1 | L16: =IFERROR(_xlfn.XLOOKUP(_xlfn.CONCAT(_xlfn.TEXTBEFORE($B16," ")," - ",L$9),Model!$D$64:$D$87,Model!$Z$64:$Z$87,0),0) -> 5739560.9 | M16: =IFERROR(_xlfn.XLOOKUP(_xlfn.CONCAT(_xlfn.TEXTBEFORE($B16," ")," - ",M$9),Model!$D$64:$D$87,Model!$Z$64:$Z$87,0),0) -> 5013162.8 | N16: =IFERROR(_xlfn.XLOOKUP(_xlfn.CONCAT(_xlfn.TEXTBEFORE($B16," ")," - ",N$9),Model!$D$64:$D$87,Model!$Z$64:$Z$87,0),0) -> 5129376.6 | O16: =IFERROR(_xlfn.XLOOKUP(_xlfn.CONCAT(_xlfn.TEXTBEFORE($B16," ")," - ",O$9),Model!$D$64:$D$87,Model!$Z$64:$Z$87,0),0) -> 5133526.3 | ... S16: =IFERROR(_xlfn.XLOOKUP(_xlfn.CONCAT(_xlfn.TEXTBEFORE($B16," ")," - ",S$9),Model!$D$64:$D$87,Model!$Z$64:$Z$87,0),0) -> 5713173.6 | U16: =SUM(H16:J16) -> 14140303 | V16: =SUM(K16:M16) -> 15974287 | W16: =SUM(N16:P16) -> 15594526 | X16: =SUM(Q16:S16) -> 16685436
B17: Wholesale COGS | C17: =IFERROR(_xlfn.XLOOKUP(_xlfn.TEXTBEFORE(B17," "),'Detailed Forecast'!$D$7:$D$8,'Detailed Forecast'!$R$10:$R$11,0),0) -> 2.4957106e+08 | D17: =SUM(U17,V17,W17,X17) -> 2.6256065e+08 | E17: =D17/C17-1 -> 0.052047661 | H17: =IFERROR(_xlfn.XLOOKUP(_xlfn.CONCAT(_xlfn.TEXTBEFORE($B17," ")," - ",H$9),Model!$D$64:$D$87,Model!$Z$64:$Z$87,0),0) -> 19345015 | I17: =IFERROR(_xlfn.XLOOKUP(_xlfn.CONCAT(_xlfn.TEXTBEFORE($B17," ")," - ",I$9),Model!$D$64:$D$87,Model!$Z$64:$Z$87,0),0) -> 18585005 | J17: =IFERROR(_xlfn.XLOOKUP(_xlfn.CONCAT(_xlfn.TEXTBEFORE($B17," ")," - ",J$9),Model!$D$64:$D$87,Model!$Z$64:$Z$87,0),0) -> 23042674 | K17: =IFERROR(_xlfn.XLOOKUP(_xlfn.CONCAT(_xlfn.TEXTBEFORE($B17," ")," - ",K$9),Model!$D$64:$D$87,Model!$Z$64:$Z$87,0),0) -> 21128744 | L17: =IFERROR(_xlfn.XLOOKUP(_xlfn.CONCAT(_xlfn.TEXTBEFORE($B17," ")," - ",L$9),Model!$D$64:$D$87,Model!$Z$64:$Z$87,0),0) -> 22251307 | M17: =IFERROR(_xlfn.XLOOKUP(_xlfn.CONCAT(_xlfn.TEXTBEFORE($B17," ")," - ",M$9),Model!$D$64:$D$87,Model!$Z$64:$Z$87,0),0) -> 22172927 | N17: =IFERROR(_xlfn.XLOOKUP(_xlfn.CONCAT(_xlfn.TEXTBEFORE($B17," ")," - ",N$9),Model!$D$64:$D$87,Model!$Z$64:$Z$87,0),0) -> 21085032 | O17: =IFERROR(_xlfn.XLOOKUP(_xlfn.CONCAT(_xlfn.TEXTBEFORE($B17," ")," - ",O$9),Model!$D$64:$D$87,Model!$Z$64:$Z$87,0),0) -> 21395222 | ... S17: =IFERROR(_xlfn.XLOOKUP(_xlfn.CONCAT(_xlfn.TEXTBEFORE($B17," ")," - ",S$9),Model!$D$64:$D$87,Model!$Z$64:$Z$87,0),0) -> 24484869 | U17: =SUM(H17:J17) -> 60972693 | V17: =SUM(K17:M17) -> 65552978 | W17: =SUM(N17:P17) -> 64289067 | X17: =SUM(Q17:S17) -> 71745911
B18: Total COGS | C18: =SUM(C16:C17) -> 3.4585199e+08 | D18: =Model!Z7 -> 3.2496738e+08 | E18: =D18/C18-1 -> -0.060385977 | H18: =H16+H17 -> 23852924 | I18: =I16+I17 -> 22801928 | J18: =J16+J17 -> 28458144 | K18: =K16+K17 -> 26350307 | L18: =L16+L17 -> 27990868 | M18: =M16+M17 -> 27186090 | N18: =N16+N17 -> 26214409 | O18: =O16+O17 -> 26528748 | ... S18: =S16+S17 -> 30198042 | U18: =SUM(H18:J18) -> 75112996 | V18: =SUM(K18:M18) -> 81527265 | W18: =SUM(N18:P18) -> 79883593 | X18: =SUM(Q18:S18) -> 88431347
B20: Gross Profit
B21: Gross Profit | C21: =C13-C18 -> 6.9846017e+08 | D21: =D13-D18 -> 6.3598912e+08 | E21: =D21/C21-1 -> -0.089441109 | H21: =H13-H18 -> 47105634 | I21: =I13-I18 -> 44946941 | J21: =J13-J18 -> 56132976 | K21: =K13-K18 -> 51323570 | L21: =L13-L18 -> 54037857 | M21: =M13-M18 -> 52521815 | N21: =N13-N18 -> 51499310 | O21: =O13-O18 -> 51957639 | ... S21: =S13-S18 -> 59111237 | U21: =SUM(H21:J21) -> 1.4818555e+08 | V21: =SUM(K21:M21) -> 1.5788324e+08 | W21: =SUM(N21:P21) -> 1.5672799e+08 | X21: =SUM(Q21:S21) -> 1.7314984e+08
B22: Gross Margin % | C22: =IF(C13=0,0,C21/C13) -> 0.66882317 | D22: =IF(D13=0,0,D21/D13) -> 0.66182925 | E22: =_xlfn.CONCAT(ROUND((D22-C22)*10000,0),"pp") -> -70pp | H22: =IF(H13=0,0,H21/H13) -> 0.66384711 | I22: =IF(I13=0,0,I21/I13) -> 0.66343456 | J22: =IF(J13=0,0,J21/J13) -> 0.66358001 | K22: =IF(K13=0,0,K21/K13) -> 0.66075715 | L22: =IF(L13=0,0,L21/L13) -> 0.65876749 | M22: =IF(M13=0,0,M21/M13) -> 0.65892856 | N22: =IF(N13=0,0,N21/N13) -> 0.66267978 | O22: =IF(O13=0,0,O21/O13) -> 0.66199555 | ... S22: =IF(S13=0,0,S21/S13) -> 0.66187116 | U22: =IF(U13=0,0,U21/U13) -> 0.66362076 | V22: =IF(V13=0,0,V21/V13) -> 0.65946664 | W22: =IF(W13=0,0,W21/W13) -> 0.66238511 | X22: =IF(X13=0,0,X21/X13) -> 0.66193537
B24: Operating Expenses
B25: Ammortisation & Depreciation | C25: =-C13*0.05 -> -52215608 | D25: =-$D$13*G25 -> -48047825 | E25: =D25/C25-1 -> -0.079818722 | G25: 0.05 | H25: =-H13*0.05 -> -3547927.9 | I25: =-I13*0.05 -> -3387443.4 | J25: =-J13*0.05 -> -4229556 | K25: =-K13*0.05 -> -3883693.9 | L25: =-L13*0.05 -> -4101436.3 | M25: =-M13*0.05 -> -3985395.3 | N25: =-N13*0.05 -> -3885686 | O25: =-O13*0.05 -> -3924319.4 | ... S25: =-S13*0.05 -> -4465464 | U25: =SUM(H25:J25) -> -11164927 | V25: =SUM(K25:M25) -> -11970525 | W25: =SUM(N25:P25) -> -11830579 | X25: =SUM(Q25:S25) -> -13079059
B26: Marketing | C26: =-C13*0.1 -> -1.0443122e+08 | D26: =-$D$13*G26 -> -96095650 | E26: =D26/C26-1 -> -0.079818722 | G26: 0.1 | H26: =-H13*0.1 -> -7095855.9 | I26: =-I13*0.1 -> -6774886.9 | J26: =-J13*0.1 -> -8459112 | K26: =-K13*0.1 -> -7767387.7 | L26: =-L13*0.1 -> -8202872.6 | M26: =-M13*0.1 -> -7970790.5 | N26: =-N13*0.1 -> -7771371.9 | O26: =-O13*0.1 -> -7848638.7 | ... S26: =-S13*0.1 -> -8930927.9 | U26: =SUM(H26:J26) -> -22329855 | V26: =SUM(K26:M26) -> -23941051 | W26: =SUM(N26:P26) -> -23661158 | X26: =SUM(Q26:S26) -> -26158119
B27: General & Administrative | C27: =-C13*0.05 -> -52215608 | D27: =-$D$13*G27 -> -38438260 | E27: =D27/C27-1 -> -0.26385498 | G27: 0.04 | H27: =-H13*0.05 -> -3547927.9 | I27: =-I13*0.05 -> -3387443.4 | J27: =-J13*0.05 -> -4229556 | K27: =-K13*0.05 -> -3883693.9 | L27: =-L13*0.05 -> -4101436.3 | M27: =-M13*0.05 -> -3985395.3 | N27: =-N13*0.05 -> -3885686 | O27: =-O13*0.05 -> -3924319.4 | ... S27: =-S13*0.05 -> -4465464 | U27: =SUM(H27:J27) -> -11164927 | V27: =SUM(K27:M27) -> -11970525 | W27: =SUM(N27:P27) -> -11830579 | X27: =SUM(Q27:S27) -> -13079059
B28: Salaries & Benefits | C28: =-C13*0.2 -> -2.0886243e+08 | D28: =-$D$13*G28 -> -1.7297217e+08 | E28: =D28/C28-1 -> -0.17183685 | G28: 0.18 | H28: =-H13*0.2 -> -14191712 | I28: =-I13*0.2 -> -13549774 | J28: =-J13*0.2 -> -16918224 | K28: =-K13*0.2 -> -15534775 | L28: =-L13*0.2 -> -16405745 | M28: =-M13*0.2 -> -15941581 | N28: =-N13*0.2 -> -15542744 | O28: =-O13*0.2 -> -15697277 | ... S28: =-S13*0.2 -> -17861856 | U28: =SUM(H28:J28) -> -44659709 | V28: =SUM(K28:M28) -> -47882102 | W28: =SUM(N28:P28) -> -47322316 | X28: =SUM(Q28:S28) -> -52316238
B30: Operating Result
B31: Operating Result | C31: =C21+SUM(C25:C28) -> 2.8073531e+08 | D31: =SUM(D25:D28,D21) -> 2.8043521e+08 | E31: =D31/C31-1 -> -0.0010689503 | H31: =H21+SUM(H25:H28) -> 18722211 | I31: =I21+SUM(I25:I28) -> 17847393 | J31: =J21+SUM(J25:J28) -> 22296528 | K31: =K21+SUM(K25:K28) -> 20254019 | L31: =L21+SUM(L25:L28) -> 21226367 | M31: =M21+SUM(M25:M28) -> 20638653 | N31: =N21+SUM(N25:N28) -> 20413822 | O31: =O21+SUM(O25:O28) -> 20563084 | ... S31: =S21+SUM(S25:S28) -> 23387525 | U31: =SUM(H31:J31) -> 58866132 | V31: =SUM(K31:M31) -> 62119039 | W31: =SUM(N31:P31) -> 62083355 | X31: =SUM(Q31:S31) -> 68517365
B32: Operating Margin % | C32: =IF(C13=0,0,C31/C13) -> 0.26882317 | D32: =IF(D13=0,0,D31/D13) -> 0.29182925 | E32: =_xlfn.CONCAT(ROUND((D32-C32)*10000,0),"pp") -> 230pp | H32: =IF(H13=0,0,H31/H13) -> 0.26384711 | I32: =IF(I13=0,0,I31/I13) -> 0.26343456 | J32: =IF(J13=0,0,J31/J13) -> 0.26358001 | K32: =IF(K13=0,0,K31/K13) -> 0.26075715 | L32: =IF(L13=0,0,L31/L13) -> 0.25876749 | M32: =IF(M13=0,0,M31/M13) -> 0.25892856 | N32: =IF(N13=0,0,N31/N13) -> 0.26267978 | O32: =IF(O13=0,0,O31/O13) -> 0.26199555 | ... S32: =IF(S13=0,0,S31/S13) -> 0.26187116 | U32: =IF(U13=0,0,U31/U13) -> 0.26362076 | V32: =IF(V13=0,0,V31/V13) -> 0.25946664 | W32: =IF(W13=0,0,W31/W13) -> 0.26238511 | X32: =IF(X13=0,0,X31/X13) -> 0.26193537
B34: Interests & Taxes
B35: Net Interests Expenses | C35: =-C31*0.09 -> -25266178 | D35: =-$D$31*G35 -> -28043521 | E35: =D35/C35-1 -> 0.10992339 | G35: 0.1 | H35: =-H31*0.09 -> -1684999 | I35: =-I31*0.09 -> -1606265.4 | J35: =-J31*0.09 -> -2006687.5 | K35: =-K31*0.09 -> -1822861.7 | L35: =-L31*0.09 -> -1910373 | M35: =-M31*0.09 -> -1857478.8 | N35: =-N31*0.09 -> -1837244 | O35: =-O31*0.09 -> -1850677.6 | ... S35: =-S31*0.09 -> -2104877.2 | U35: =-U31*0.09 -> -5297951.9 | V35: =-V31*0.09 -> -5590713.5 | W35: =-W31*0.09 -> -5587502 | X35: =-X31*0.09 -> -6166562.9
B36: Corporate Tax | C36: =-(C31-C35)*0.25 -> -76500371 | D36: =-$D$31*G36 -> -70108804 | E36: =D36/C36-1 -> -0.083549496 | G36: 0.25 | H36: =-(H31-H35)*0.25 -> -5101802.4 | I36: =-(I31-I35)*0.25 -> -4863414.7 | J36: =-(J31-J35)*0.25 -> -6075803.9 | K36: =-(K31-K35)*0.25 -> -5519220.2 | L36: =-(L31-L35)*0.25 -> -5784185.1 | M36: =-(M31-M35)*0.25 -> -5624033 | N36: =-(N31-N35)*0.25 -> -5562766.6 | O36: =-(O31-O35)*0.25 -> -5603440.5 | ... S36: =-(S31-S35)*0.25 -> -6373100.5 | U36: =-(U31-U35)*0.25 -> -16041021 | V36: =-(V31-V35)*0.25 -> -16927438 | W36: =-(W31-W35)*0.25 -> -16917714 | X36: =-(X31-X35)*0.25 -> -18670982
B38: Net Income
B39: =B38 -> Net Income | C39: =C31+C35+C36 -> 1.7896876e+08 | D39: =D31+D35+D36 -> 1.8228289e+08 | E39: =D39/C39-1 -> 0.018517933 | H39: =H31+H35+H36 -> 11935409 | I39: =I31+I35+I36 -> 11377713 | J39: =J31+J35+J36 -> 14214037 | K39: =K31+K35+K36 -> 12911937 | L39: =L31+L35+L36 -> 13531809 | M39: =M31+M35+M36 -> 13157141 | N39: =N31+N35+N36 -> 13013812 | O39: =O31+O35+O36 -> 13108966 | ... S39: =S31+S35+S36 -> 14909547 | U39: =U31+U35+U36 -> 37527159 | V39: =V31+V35+V36 -> 39600888 | W39: =W31+W35+W36 -> 39578139 | X39: =X31+X35+X36 -> 43679820
B40: Net Income Margin % | C40: =IF(C13=0,0,C39/C13) -> 0.17137477 | D40: =IF(D13=0,0,D39/D13) -> 0.18968901 | E40: =_xlfn.CONCAT(ROUND((D40-C40)*10000,0),"pp") -> 183pp | H40: =IF(H13=0,0,H39/H13) -> 0.16820253 | I40: =IF(I13=0,0,I39/I13) -> 0.16793953 | J40: =IF(J13=0,0,J39/J13) -> 0.16803226 | K40: =IF(K13=0,0,K39/K13) -> 0.16623269 | L40: =IF(L13=0,0,L39/L13) -> 0.16496427 | M40: =IF(M13=0,0,M39/M13) -> 0.16506696 | N40: =IF(N13=0,0,N39/N13) -> 0.16745836 | O40: =IF(O13=0,0,O39/O13) -> 0.16702216 | ... S40: =IF(S13=0,0,S39/S13) -> 0.16694287 | U40: =IF(U13=0,0,U39/U13) -> 0.16805823 | V40: =IF(V13=0,0,V39/V13) -> 0.16540998 | W40: =IF(W13=0,0,W39/W13) -> 0.16727051 | X40: =IF(X13=0,0,X39/X13) -> 0.1669838

Sheet Detailed Forecast
D2: UNITS | P2: COGS | Z2: REVENUE
F3: LY | G3: ACTUALS | H3: BUDGET | I3: FORECAST | J3: vs LY | K3: vs ACTUALS | L3: vs BUDGET | P3: LY | Q3: ACTUALS | R3: BUDGET | S3: FORECAST | T3: vs LY | U3: vs ACTUALS | V3: vs BUDGET | Z3: LY | AA3: ACTUALS | AB3: BUDGET | AC3: FORECAST | AD3: vs LY | AE3: vs ACTUALS | AF3: vs BUDGET
D5: TOPLINE | F5: =IFERROR(_xlfn.XLOOKUP($D5,Model!$D:$D,Model!G:G,""),"") -> 70972 | G5: =IFERROR(_xlfn.XLOOKUP($D5,Model!$D:$D,Model!H:H,""),"") -> 32888 | H5: =IFERROR(_xlfn.XLOOKUP($D5,Model!$D:$D,Model!I:I,""),"") -> 74712.84 | I5: =IFERROR(_xlfn.XLOOKUP($D5,Model!$D:$D,Model!Y:Y,""),"") -> 68038.152 | J5: =IFERROR(I5/F5-1,"") -> -0.04133811 | K5: =IFERROR(I5/G5-1,"") -> 1.0687835 | L5: =IFERROR(I5/H5-1,"") -> -0.089337902 | P5: =IFERROR(_xlfn.XLOOKUP($D5,Model!$D:$D,Model!J:J,""),"") -> 3.2230053e+08 | Q5: =IFERROR(_xlfn.XLOOKUP($D5,Model!$D:$D,Model!K:K,""),"") -> 1.5664026e+08 | R5: =IFERROR(_xlfn.XLOOKUP($D5,Model!$D:$D,Model!L:L,""),"") -> 3.4585199e+08 | S5: =IFERROR(_xlfn.XLOOKUP($D5,Model!$D:$D,Model!Z:Z,""),"") -> 3.2496738e+08 | T5: =IFERROR(S5/P5-1,"") -> 0.0082744156 | U5: =IFERROR(S5/Q5-1,"") -> 1.0746095 | V5: =IFERROR(S5/R5-1,"") -> -0.060385977 | Z5: =IFERROR(_xlfn.XLOOKUP($D5,Model!$D:$D,Model!M:M,""),"") -> 9.5278736e+08 | AA5: =IFERROR(_xlfn.XLOOKUP($D5,Model!$D:$D,Model!N:N,""),"") -> 4.6270906e+08 | AB5: =IFERROR(_xlfn.XLOOKUP($D5,Model!$D:$D,Model!O:O,""),"") -> 1.0443122e+09 | AC5: =IFERROR(_xlfn.XLOOKUP($D5,Model!$D:$D,Model!AA:AA,""),"") -> 9.609565e+08 | AD5: =IFERROR(AC5/Z5-1,"") -> 0.0085739407 | AE5: =IFERROR(AC5/AA5-1,"") -> 1.076805 | AF5: =IFERROR(AC5/AB5-1,"") -> -0.079818722
D7: Boutique | F7: =IFERROR(_xlfn.XLOOKUP($D7,Model!$D:$D,Model!G:G,""),"") -> 12157 | G7: =IFERROR(_xlfn.XLOOKUP($D7,Model!$D:$D,Model!H:H,""),"") -> 6281 | H7: =IFERROR(_xlfn.XLOOKUP($D7,Model!$D:$D,Model!I:I,""),"") -> 14048.2 | I7: =IFERROR(_xlfn.XLOOKUP($D7,Model!$D:$D,Model!Y:Y,""),"") -> 13001.249 | J7: =IFERROR(I7/F7-1,"") -> 0.069445474 | K7: =IFERROR(I7/G7-1,"") -> 1.0699329 | L7: =IFERROR(I7/H7-1,"") -> -0.074525659 | P7: =IFERROR(_xlfn.XLOOKUP($D7,Model!$D:$D,Model!J:J,""),"") -> 55404604 | Q7: =IFERROR(_xlfn.XLOOKUP($D7,Model!$D:$D,Model!K:K,""),"") -> 30114590 | R7: =IFERROR(_xlfn.XLOOKUP($D7,Model!$D:$D,Model!L:L,""),"") -> 65079980 | S7: =IFERROR(_xlfn.XLOOKUP($D7,Model!$D:$D,Model!Z:Z,""),"") -> 62394552 | T7: =IFERROR(S7/P7-1,"") -> 0.12616186 | U7: =IFERROR(S7/Q7-1,"") -> 1.0719044 | V7: =IFERROR(S7/R7-1,"") -> -0.04126351 | Z7: =IFERROR(_xlfn.XLOOKUP($D7,Model!$D:$D,Model!M:M,""),"") -> 2.2739209e+08 | AA7: =IFERROR(_xlfn.XLOOKUP($D7,Model!$D:$D,Model!N:N,""),"") -> 1.224473e+08 | AB7: =IFERROR(_xlfn.XLOOKUP($D7,Model!$D:$D,Model!O:O,""),"") -> 2.6983289e+08 | AC7: =IFERROR(_xlfn.XLOOKUP($D7,Model!$D:$D,Model!AA:AA,""),"") -> 2.5378155e+08 | AD7: =IFERROR(AC7/Z7-1,"") -> 0.11605271 | AE7: =IFERROR(AC7/AA7-1,"") -> 1.0725777 | AF7: =IFERROR(AC7/AB7-1,"") -> -0.059486213
D8: Wholesale | F8: =IFERROR(_xlfn.XLOOKUP($D8,Model!$D:$D,Model!G:G,""),"") -> 58815 | G8: =IFERROR(_xlfn.XLOOKUP($D8,Model!$D:$D,Model!H:H,""),"") -> 26607 | H8: =IFERROR(_xlfn.XLOOKUP($D8,Model!$D:$D,Model!I:I,""),"") -> 60664.64 | I8: =IFERROR(_xlfn.XLOOKUP($D8,Model!$D:$D,Model!Y:Y,""),"") -> 55035.456 | J8: =IFERROR(I8/F8-1,"") -> -0.064261562 | K8: =IFERROR(I8/G8-1,"") -> 1.0684578 | L8: =IFERROR(I8/H8-1,"") -> -0.092791843 | P8: =IFERROR(_xlfn.XLOOKUP($D8,Model!$D:$D,Model!J:J,""),"") -> 2.6689593e+08 | Q8: =IFERROR(_xlfn.XLOOKUP($D8,Model!$D:$D,Model!K:K,""),"") -> 1.2652567e+08 | R8: =IFERROR(_xlfn.XLOOKUP($D8,Model!$D:$D,Model!L:L,""),"") -> 2.8077201e+08 | S8: =IFERROR(_xlfn.XLOOKUP($D8,Model!$D:$D,Model!Z:Z,""),"") -> 2.6256065e+08 | T8: =IFERROR(S8/P8-1,"") -> -0.016243323 | U8: =IFERROR(S8/Q8-1,"") -> 1.0751571 | V8: =IFERROR(S8/R8-1,"") -> -0.064861734 | Z8: =IFERROR(_xlfn.XLOOKUP($D8,Model!$D:$D,Model!M:M,""),"") -> 7.2539527e+08 | AA8: =IFERROR(_xlfn.XLOOKUP($D8,Model!$D:$D,Model!N:N,""),"") -> 3.4026175e+08 | AB8: =IFERROR(_xlfn.XLOOKUP($D8,Model!$D:$D,Model!O:O,""),"") -> 7.7447927e+08 | AC8: =IFERROR(_xlfn.XLOOKUP($D8,Model!$D:$D,Model!AA:AA,""),"") -> 7.0712027e+08 | AD8: =IFERROR(AC8/Z8-1,"") -> -0.025193161 | AE8: =IFERROR(AC8/AA8-1,"") -> 1.0781656 | AF8: =IFERROR(AC8/AB8-1,"") -> -0.086973277
D10: Online | F10: =IFERROR(_xlfn.XLOOKUP($D10,Model!$D:$D,Model!G:G,""),"") -> 19882 | G10: =IFERROR(_xlfn.XLOOKUP($D10,Model!$D:$D,Model!H:H,""),"") -> 9297 | H10: =IFERROR(_xlfn.XLOOKUP($D10,Model!$D:$D,Model!I:I,""),"") -> 20751.5 | I10: =IFERROR(_xlfn.XLOOKUP($D10,Model!$D:$D,Model!Y:Y,""),"") -> 19247.496 | J10: =IFERROR(I10/F10-1,"") -> -0.031913506 | K10: =IFERROR(I10/G10-1,"") -> 1.070291 | L10: =IFERROR(I10/H10-1,"") -> -0.072476897 | P10: =IFERROR(_xlfn.XLOOKUP($D10,Model!$D:$D,Model!J:J,""),"") -> 90554517 | Q10: =IFERROR(_xlfn.XLOOKUP($D10,Model!$D:$D,Model!K:K,""),"") -> 44231114 | R10: =IFERROR(_xlfn.XLOOKUP($D10,Model!$D:$D,Model!L:L,""),"") -> 96280930 | S10: =IFERROR(_xlfn.XLOOKUP($D10,Model!$D:$D,Model!Z:Z,""),"") -> 91834932 | T10: =IFERROR(S10/P10-1,"") -> 0.014139716 | U10: =IFERROR(S10/Q10-1,"") -> 1.0762518 | V10: =IFERROR(S10/R10-1,"") -> -0.04617734 | Z10: =IFERROR(_xlfn.XLOOKUP($D10,Model!$D:$D,Model!M:M,""),"") -> 2.5839883e+08 | AA10: =IFERROR(_xlfn.XLOOKUP($D10,Model!$D:$D,Model!N:N,""),"") -> 1.2581854e+08 | AB10: =IFERROR(_xlfn.XLOOKUP($D10,Model!$D:$D,Model!O:O,""),"") -> 279632185 | AC10: =IFERROR(_xlfn.XLOOKUP($D10,Model!$D:$D,Model!AA:AA,""),"") -> 2.6169573e+08 | AD10: =IFERROR(AC10/Z10-1,"") -> 0.012758982 | AE10: =IFERROR(AC10/AA10-1,"") -> 1.0799458 | AF10: =IFERROR(AC10/AB10-1,"") -> -0.064143013
D11: Retail | F11: =IFERROR(_xlfn.XLOOKUP($D11,Model!$D:$D,Model!G:G,""),"") -> 51090 | G11: =IFERROR(_xlfn.XLOOKUP($D11,Model!$D:$D,Model!H:H,""),"") -> 23591 | H11: =IFERROR(_xlfn.XLOOKUP($D11,Model!$D:$D,Model!I:I,""),"") -> 53961.34 | I11: =IFERROR(_xlfn.XLOOKUP($D11,Model!$D:$D,Model!Y:Y,""),"") -> 48789.425 | J11: =IFERROR(I11/F11-1,"") -> -0.045029846 | K11: =IFERROR(I11/G11-1,"") -> 1.0681372 | L11: =IFERROR(I11/H11-1,"") -> -0.095844818 | P11: =IFERROR(_xlfn.XLOOKUP($D11,Model!$D:$D,Model!J:J,""),"") -> 2.3174601e+08 | Q11: =IFERROR(_xlfn.XLOOKUP($D11,Model!$D:$D,Model!K:K,""),"") -> 1.1240915e+08 | R11: =IFERROR(_xlfn.XLOOKUP($D11,Model!$D:$D,Model!L:L,""),"") -> 2.4957106e+08 | S11: =IFERROR(_xlfn.XLOOKUP($D11,Model!$D:$D,Model!Z:Z,""),"") -> 2.3312379e+08 | T11: =IFERROR(S11/P11-1,"") -> 0.0059451923 | U11: =IFERROR(S11/Q11-1,"") -> 1.0738863 | V11: =IFERROR(S11/R11-1,"") -> -0.06590216 | Z11: =IFERROR(_xlfn.XLOOKUP($D11,Model!$D:$D,Model!M:M,""),"") -> 6.9438853e+08 | AA11: =IFERROR(_xlfn.XLOOKUP($D11,Model!$D:$D,Model!N:N,""),"") -> 3.3689052e+08 | AB11: =IFERROR(_xlfn.XLOOKUP($D11,Model!$D:$D,Model!O:O,""),"") -> 7.6467998e+08 | AC11: =IFERROR(_xlfn.XLOOKUP($D11,Model!$D:$D,Model!AA:AA,""),"") -> 6.9923021e+08 | AD11: =IFERROR(AC11/Z11-1,"") -> 0.0069725893 | AE11: =IFERROR(AC11/AA11-1,"") -> 1.0755414 | AF11: =IFERROR(AC11/AB11-1,"") -> -0.08559105
D13: Atelier | F13: =IFERROR(_xlfn.XLOOKUP($D13,Model!$D:$D,Model!G:G,""),"") -> 8364 | G13: =IFERROR(_xlfn.XLOOKUP($D13,Model!$D:$D,Model!H:H,""),"") -> 3849 | H13: =IFERROR(_xlfn.XLOOKUP($D13,Model!$D:$D,Model!I:I,""),"") -> 8807.23 | I13: =IFERROR(_xlfn.XLOOKUP($D13,Model!$D:$D,Model!Y:Y,""),"") -> 8012.856 | J13: =IFERROR(I13/F13-1,"") -> -0.041982785 | K13: =IFERROR(I13/G13-1,"") -> 1.081802 | L13: =IFERROR(I13/H13-1,"") -> -0.090195671 | P13: =IFERROR(_xlfn.XLOOKUP($D13,Model!$D:$D,Model!J:J,""),"") -> 54387432 | Q13: =IFERROR(_xlfn.XLOOKUP($D13,Model!$D:$D,Model!K:K,""),"") -> 26590825 | R13: =IFERROR(_xlfn.XLOOKUP($D13,Model!$D:$D,Model!L:L,""),"") -> 58445307 | S13: =IFERROR(_xlfn.XLOOKUP($D13,Model!$D:$D,Model!Z:Z,""),"") -> 55356833 | T13: =IFERROR(S13/P13-1,"") -> 0.017823982 | U13: =IFERROR(S13/Q13-1,"") -> 1.081802 | V13: =IFERROR(S13/R13-1,"") -> -0.052843832 | Z13: =IFERROR(_xlfn.XLOOKUP($D13,Model!$D:$D,Model!M:M,""),"") -> 1.7146439e+08 | AA13: =IFERROR(_xlfn.XLOOKUP($D13,Model!$D:$D,Model!N:N,""),"") -> 82923695 | AB13: =IFERROR(_xlfn.XLOOKUP($D13,Model!$D:$D,Model!O:O,""),"") -> 1.8825674e+08 | AC13: =IFERROR(_xlfn.XLOOKUP($D13,Model!$D:$D,Model!AA:AA,""),"") -> 1.7255059e+08 | AD13: =IFERROR(AC13/Z13-1,"") -> 0.0063348631 | AE13: =IFERROR(AC13/AA13-1,"") -> 1.0808358 | AF13: =IFERROR(AC13/AB13-1,"") -> -0.083429429
D14: Grand Complication | F14: =IFERROR(_xlfn.XLOOKUP($D14,Model!$D:$D,Model!G:G,""),"") -> 8001 | G14: =IFERROR(_xlfn.XLOOKUP($D14,Model!$D:$D,Model!H:H,""),"") -> 3725 | H14: =IFERROR(_xlfn.XLOOKUP($D14,Model!$D:$D,Model!I:I,""),"") -> 8418.48 | I14: =IFERROR(_xlfn.XLOOKUP($D14,Model!$D:$D,Model!Y:Y,""),"") -> 7833.521 | J14: =IFERROR(I14/F14-1,"") -> -0.020932256 | K14: =IFERROR(I14/G14-1,"") -> 1.1029587 | L14: =IFERROR(I14/H14-1,"") -> -0.069485107 | P14: =IFERROR(_xlfn.XLOOKUP($D14,Model!$D:$D,Model!J:J,""),"") -> 47303983 | Q14: =IFERROR(_xlfn.XLOOKUP($D14,Model!$D:$D,Model!K:K,""),"") -> 23065048 | R14: =IFERROR(_xlfn.XLOOKUP($D14,Model!$D:$D,Model!L:L,""),"") -> 50711240 | S14: =IFERROR(_xlfn.XLOOKUP($D14,Model!$D:$D,Model!Z:Z,""),"") -> 48504842 | T14: =IFERROR(S14/P14-1,"") -> 0.025385994 | U14: =IFERROR(S14/Q14-1,"") -> 1.1029587 | V14: =IFERROR(S14/R14-1,"") -> -0.043509058 | Z14: =IFERROR(_xlfn.XLOOKUP($D14,Model!$D:$D,Model!M:M,""),"") -> 1.5501977e+08 | AA14: =IFERROR(_xlfn.XLOOKUP($D14,Model!$D:$D,Model!N:N,""),"") -> 76785014 | AB14: =IFERROR(_xlfn.XLOOKUP($D14,Model!$D:$D,Model!O:O,""),"") -> 1.6983548e+08 | AC14: =IFERROR(_xlfn.XLOOKUP($D14,Model!$D:$D,Model!AA:AA,""),"") -> 1.6143978e+08 | AD14: =IFERROR(AC14/Z14-1,"") -> 0.041414164 | AE14: =IFERROR(AC14/AA14-1,"") -> 1.1024908 | AF14: =IFERROR(AC14/AB14-1,"") -> -0.049434314
D15: Celeste | F15: =IFERROR(_xlfn.XLOOKUP($D15,Model!$D:$D,Model!G:G,""),"") -> 8450 | G15: =IFERROR(_xlfn.XLOOKUP($D15,Model!$D:$D,Model!H:H,""),"") -> 3897 | H15: =IFERROR(_xlfn.XLOOKUP($D15,Model!$D:$D,Model!I:I,""),"") -> 8899.85 | I15: =IFERROR(_xlfn.XLOOKUP($D15,Model!$D:$D,Model!Y:Y,""),"") -> 8030.5069 | J15: =IFERROR(I15/F15-1,"") -> -0.049644151 | K15: =IFERROR(I15/G15-1,"") -> 1.0606895 | L15: =IFERROR(I15/H15-1,"") -> -0.097680643 | P15: =IFERROR(_xlfn.XLOOKUP($D15,Model!$D:$D,Model!J:J,""),"") -> 44817048 | Q15: =IFERROR(_xlfn.XLOOKUP($D15,Model!$D:$D,Model!K:K,""),"") -> 21588337 | R15: =IFERROR(_xlfn.XLOOKUP($D15,Model!$D:$D,Model!L:L,""),"") -> 48234695 | S15: =IFERROR(_xlfn.XLOOKUP($D15,Model!$D:$D,Model!Z:Z,""),"") -> 44486858 | T15: =IFERROR(S15/P15-1,"") -> -0.0073675033 | U15: =IFERROR(S15/Q15-1,"") -> 1.0606895 | V15: =IFERROR(S15/R15-1,"") -> -0.077700016 | Z15: =IFERROR(_xlfn.XLOOKUP($D15,Model!$D:$D,Model!M:M,""),"") -> 1.3686594e+08 | AA15: =IFERROR(_xlfn.XLOOKUP($D15,Model!$D:$D,Model!N:N,""),"") -> 66253229 | AB15: =IFERROR(_xlfn.XLOOKUP($D15,Model!$D:$D,Model!O:O,""),"") -> 1.5011745e+08 | AC15: =IFERROR(_xlfn.XLOOKUP($D15,Model!$D:$D,Model!AA:AA,""),"") -> 1.367532e+08 | AD15: =IFERROR(AC15/Z15-1,"") -> -0.00082372969 | AE15: =IFERROR(AC15/AA15-1,"") -> 1.0640986 | AF15: =IFERROR(AC15/AB15-1,"") -> -0.08902529
D16: Heritage | F16: =IFERROR(_xlfn.XLOOKUP($D16,Model!$D:$D,Model!G:G,""),"") -> 7333 | G16: =IFERROR(_xlfn.XLOOKUP($D16,Model!$D:$D,Model!H:H,""),"") -> 3435 | H16: =IFERROR(_xlfn.XLOOKUP($D16,Model!$D:$D,Model!I:I,""),"") -> 7719.8 | I16: =IFERROR(_xlfn.XLOOKUP($D16,Model!$D:$D,Model!Y:Y,""),"") -> 7341.7481 | J16: =IFERROR(I16/F16-1,"") -> 0.0011929721 | K16: =IFERROR(I16/G16-1,"") -> 1.1373357 | L16: =IFERROR(I16/H16-1,"") -> -0.048971727 | P16: =IFERROR(_xlfn.XLOOKUP($D16,Model!$D:$D,Model!J:J,""),"") -> 38028274 | Q16: =IFERROR(_xlfn.XLOOKUP($D16,Model!$D:$D,Model!K:K,""),"") -> 18307257 | R16: =IFERROR(_xlfn.XLOOKUP($D16,Model!$D:$D,Model!L:L,""),"") -> 40699789 | S16: =IFERROR(_xlfn.XLOOKUP($D16,Model!$D:$D,Model!Z:Z,""),"") -> 39128753 | T16: =IFERROR(S16/P16-1,"") -> 0.028938454 | U16: =IFERROR(S16/Q16-1,"") -> 1.1373357 | V16: =IFERROR(S16/R16-1,"") -> -0.038600591 | Z16: =IFERROR(_xlfn.XLOOKUP($D16,Model!$D:$D,Model!M:M,""),"") -> 1.2156724e+08 | AA16: =IFERROR(_xlfn.XLOOKUP($D16,Model!$D:$D,Model!N:N,""),"") -> 59362888 | AB16: =IFERROR(_xlfn.XLOOKUP($D16,Model!$D:$D,Model!O:O,""),"") -> 1.3310788e+08 | AC16: =IFERROR(_xlfn.XLOOKUP($D16,Model!$D:$D,Model!AA:AA,""),"") -> 1.2663828e+08 | AD16: =IFERROR(AC16/Z16-1,"") -> 0.041713866 | AE16: =IFERROR(AC16/AA16-1,"") -> 1.1332904 | AF16: =IFERROR(AC16/AB16-1,"") -> -0.048604169
D17: Lumina | F17: =IFERROR(_xlfn.XLOOKUP($D17,Model!$D:$D,Model!G:G,""),"") -> 5792 | G17: =IFERROR(_xlfn.XLOOKUP($D17,Model!$D:$D,Model!H:H,""),"") -> 2621 | H17: =IFERROR(_xlfn.XLOOKUP($D17,Model!$D:$D,Model!I:I,""),"") -> 6093.08 | I17: =IFERROR(_xlfn.XLOOKUP($D17,Model!$D:$D,Model!Y:Y,""),"") -> 5374.8478 | J17: =IFERROR(I17/F17-1,"") -> -0.07202214 | K17: =IFERROR(I17/G17-1,"") -> 1.0506859 | L17: =IFERROR(I17/H17-1,"") -> -0.11787671 | P17: =IFERROR(_xlfn.XLOOKUP($D17,Model!$D:$D,Model!J:J,""),"") -> 31738325 | Q17: =IFERROR(_xlfn.XLOOKUP($D17,Model!$D:$D,Model!K:K,""),"") -> 15312709 | R17: =IFERROR(_xlfn.XLOOKUP($D17,Model!$D:$D,Model!L:L,""),"") -> 34102421 | S17: =IFERROR(_xlfn.XLOOKUP($D17,Model!$D:$D,Model!Z:Z,""),"") -> 31401556 | T17: =IFERROR(S17/P17-1,"") -> -0.010610786 | U17: =IFERROR(S17/Q17-1,"") -> 1.0506859 | V17: =IFERROR(S17/R17-1,"") -> -0.079198613 | Z17: =IFERROR(_xlfn.XLOOKUP($D17,Model!$D:$D,Model!M:M,""),"") -> 93372771 | AA17: =IFERROR(_xlfn.XLOOKUP($D17,Model!$D:$D,Model!N:N,""),"") -> 44711923 | AB17: =IFERROR(_xlfn.XLOOKUP($D17,Model!$D:$D,Model!O:O,""),"") -> 1.0227366e+08 | AC17: =IFERROR(_xlfn.XLOOKUP($D17,Model!$D:$D,Model!AA:AA,""),"") -> 91777145 | AD17: =IFERROR(AC17/Z17-1,"") -> -0.017088775 | AE17: =IFERROR(AC17/AA17-1,"") -> 1.0526325 | AF17: =IFERROR(AC17/AB17-1,"") -> -0.10263166
D18: Nautique | F18: =IFERROR(_xlfn.XLOOKUP($D18,Model!$D:$D,Model!G:G,""),"") -> 6227 | G18: =IFERROR(_xlfn.XLOOKUP($D18,Model!$D:$D,Model!H:H,""),"") -> 2798 | H18: =IFERROR(_xlfn.XLOOKUP($D18,Model!$D:$D,Model!I:I,""),"") -> 6553.44 | I18: =IFERROR(_xlfn.XLOOKUP($D18,Model!$D:$D,Model!Y:Y,""),"") -> 5764.6258 | J18: =IFERROR(I18/F18-1,"") -> -0.074253131 | K18: =IFERROR(I18/G18-1,"") -> 1.0602665 | L18: =IFERROR(I18/H18-1,"") -> -0.12036644 | P18: =IFERROR(_xlfn.XLOOKUP($D18,Model!$D:$D,Model!J:J,""),"") -> 29046636 | Q18: =IFERROR(_xlfn.XLOOKUP($D18,Model!$D:$D,Model!K:K,""),"") -> 13766712 | R18: =IFERROR(_xlfn.XLOOKUP($D18,Model!$D:$D,Model!L:L,""),"") -> 31120583 | S18: =IFERROR(_xlfn.XLOOKUP($D18,Model!$D:$D,Model!Z:Z,""),"") -> 28363096 | T18: =IFERROR(S18/P18-1,"") -> -0.02353251 | U18: =IFERROR(S18/Q18-1,"") -> 1.0602665 | V18: =IFERROR(S18/R18-1,"") -> -0.088606519 | Z18: =IFERROR(_xlfn.XLOOKUP($D18,Model!$D:$D,Model!M:M,""),"") -> 80446487 | AA18: =IFERROR(_xlfn.XLOOKUP($D18,Model!$D:$D,Model!N:N,""),"") -> 37656145 | AB18: =IFERROR(_xlfn.XLOOKUP($D18,Model!$D:$D,Model!O:O,""),"") -> 87971574 | AC18: =IFERROR(_xlfn.XLOOKUP($D18,Model!$D:$D,Model!AA:AA,""),"") -> 77485073 | AD18: =IFERROR(AC18/Z18-1,"") -> -0.036812231 | AE18: =IFERROR(AC18/AA18-1,"") -> 1.0577006 | AF18: =IFERROR(AC18/AB18-1,"") -> -0.11920329
D19: Sportivo | F19: =IFERROR(_xlfn.XLOOKUP($D19,Model!$D:$D,Model!G:G,""),"") -> 9290 | G19: =IFERROR(_xlfn.XLOOKUP($D19,Model!$D:$D,Model!H:H,""),"") -> 4307 | H19: =IFERROR(_xlfn.XLOOKUP($D19,Model!$D:$D,Model!I:I,""),"") -> 9784.7 | I19: =IFERROR(_xlfn.XLOOKUP($D19,Model!$D:$D,Model!Y:Y,""),"") -> 8850.088 | J19: =IFERROR(I19/F19-1,"") -> -0.047353286 | K19: =IFERROR(I19/G19-1,"") -> 1.0548149 | L19: =IFERROR(I19/H19-1,"") -> -0.095517699 | P19: =IFERROR(_xlfn.XLOOKUP($D19,Model!$D:$D,Model!J:J,""),"") -> 30719559 | Q19: =IFERROR(_xlfn.XLOOKUP($D19,Model!$D:$D,Model!K:K,""),"") -> 15079270 | R19: =IFERROR(_xlfn.XLOOKUP($D19,Model!$D:$D,Model!L:L,""),"") -> 32936866 | S19: =IFERROR(_xlfn.XLOOKUP($D19,Model!$D:$D,Model!Z:Z,""),"") -> 30985110 | T19: =IFERROR(S19/P19-1,"") -> 0.0086443722 | U19: =IFERROR(S19/Q19-1,"") -> 1.0548149 | V19: =IFERROR(S19/R19-1,"") -> -0.059257488 | Z19: =IFERROR(_xlfn.XLOOKUP($D19,Model!$D:$D,Model!M:M,""),"") -> 78662775 | AA19: =IFERROR(_xlfn.XLOOKUP($D19,Model!$D:$D,Model!N:N,""),"") -> 38333077 | AB19: =IFERROR(_xlfn.XLOOKUP($D19,Model!$D:$D,Model!O:O,""),"") -> 86284486 | AC19: =IFERROR(_xlfn.XLOOKUP($D19,Model!$D:$D,Model!AA:AA,""),"") -> 78731598 | AD19: =IFERROR(AC19/Z19-1,"") -> 0.00087490541 | AE19: =IFERROR(AC19/AA19-1,"") -> 1.0538815 | AF19: =IFERROR(AC19/AB19-1,"") -> -0.087534721
... D41: LATAM | F41: =IFERROR(_xlfn.XLOOKUP($D41,Model!$D:$D,Model!G:G,""),"") -> 4797 | G41: =IFERROR(_xlfn.XLOOKUP($D41,Model!$D:$D,Model!H:H,""),"") -> 2190 | H41: =IFERROR(_xlfn.XLOOKUP($D41,Model!$D:$D,Model!I:I,""),"") -> 5162.5 | I41: =IFERROR(_xlfn.XLOOKUP($D41,Model!$D:$D,Model!Y:Y,""),"") -> 4547.6166 | J41: =IFERROR(I41/F41-1,"") -> -0.051987376 | K41: =IFERROR(I41/G41-1,"") -> 1.0765372 | L41: =IFERROR(I41/H41-1,"") -> -0.11910575 | P41: =IFERROR(_xlfn.XLOOKUP($D41,Model!$D:$D,Model!J:J,""),"") -> 22077630 | Q41: =IFERROR(_xlfn.XLOOKUP($D41,Model!$D:$D,Model!K:K,""),"") -> 10603643 | R41: =IFERROR(_xlfn.XLOOKUP($D41,Model!$D:$D,Model!L:L,""),"") -> 24068477 | S41: =IFERROR(_xlfn.XLOOKUP($D41,Model!$D:$D,Model!Z:Z,""),"") -> 22066781 | T41: =IFERROR(S41/P41-1,"") -> -0.00049141783 | U41: =IFERROR(S41/Q41-1,"") -> 1.0810565 | V41: =IFERROR(S41/R41-1,"") -> -0.083166728 | Z41: =IFERROR(_xlfn.XLOOKUP($D41,Model!$D:$D,Model!M:M,""),"") -> 62691296 | AA41: =IFERROR(_xlfn.XLOOKUP($D41,Model!$D:$D,Model!N:N,""),"") -> 30382045 | AB41: =IFERROR(_xlfn.XLOOKUP($D41,Model!$D:$D,Model!O:O,""),"") -> 71238416 | AC41: =IFERROR(_xlfn.XLOOKUP($D41,Model!$D:$D,Model!AA:AA,""),"") -> 63260771 | AD41: =IFERROR(AC41/Z41-1,"") -> 0.0090838065 | AE41: =IFERROR(AC41/AA41-1,"") -> 1.0821762 | AF41: =IFERROR(AC41/AB41-1,"") -> -0.11198515
J42: =IFERROR(I42/F42-1,"") | K42: =IFERROR(I42/G42-1,"") | L42: =IFERROR(I42/H42-1,"") | T42: =IFERROR(S42/P42-1,"") | U42: =IFERROR(S42/Q42-1,"") | V42: =IFERROR(S42/R42-1,"") | AD42: =IFERROR(AC42/Z42-1,"") | AE42: =IFERROR(AC42/AA42-1,"") | AF42: =IFERROR(AC42/AB42-1,"")
D44: United States | F44: =IFERROR(_xlfn.XLOOKUP($D44,Model!$D:$D,Model!G:G,""),"") -> 6142 | G44: =IFERROR(_xlfn.XLOOKUP($D44,Model!$D:$D,Model!H:H,""),"") -> 2807 | H44: =IFERROR(_xlfn.XLOOKUP($D44,Model!$D:$D,Model!I:I,""),"") -> 6450.01 | I44: =IFERROR(_xlfn.XLOOKUP($D44,Model!$D:$D,Model!Y:Y,""),"") -> 5856.3812 | J44: =IFERROR(I44/F44-1,"") -> -0.046502578 | K44: =IFERROR(I44/G44-1,"") -> 1.0863488 | L44: =IFERROR(I44/H44-1,"") -> -0.092035335 | P44: =IFERROR(_xlfn.XLOOKUP($D44,Model!$D:$D,Model!J:J,""),"") -> 28055616 | Q44: =IFERROR(_xlfn.XLOOKUP($D44,Model!$D:$D,Model!K:K,""),"") -> 13531538 | R44: =IFERROR(_xlfn.XLOOKUP($D44,Model!$D:$D,Model!L:L,""),"") -> 30017449 | S44: =IFERROR(_xlfn.XLOOKUP($D44,Model!$D:$D,Model!Z:Z,""),"") -> 28220395 | T44: =IFERROR(S44/P44-1,"") -> 0.005873316 | U44: =IFERROR(S44/Q44-1,"") -> 1.0855275 | V44: =IFERROR(S44/R44-1,"") -> -0.059866983 | Z44: =IFERROR(_xlfn.XLOOKUP($D44,Model!$D:$D,Model!M:M,""),"") -> 84694710 | AA44: =IFERROR(_xlfn.XLOOKUP($D44,Model!$D:$D,Model!N:N,""),"") -> 40577151 | AB44: =IFERROR(_xlfn.XLOOKUP($D44,Model!$D:$D,Model!O:O,""),"") -> 92133696 | AC44: =IFERROR(_xlfn.XLOOKUP($D44,Model!$D:$D,Model!AA:AA,""),"") -> 84835011 | AD44: =IFERROR(AC44/Z44-1,"") -> 0.0016565451 | AE44: =IFERROR(AC44/AA44-1,"") -> 1.0907089 | AF44: =IFERROR(AC44/AB44-1,"") -> -0.07921841
D45: Switzerland | F45: =IFERROR(_xlfn.XLOOKUP($D45,Model!$D:$D,Model!G:G,""),"") -> 5057 | G45: =IFERROR(_xlfn.XLOOKUP($D45,Model!$D:$D,Model!H:H,""),"") -> 2322 | H45: =IFERROR(_xlfn.XLOOKUP($D45,Model!$D:$D,Model!I:I,""),"") -> 5309.91 | I45: =IFERROR(_xlfn.XLOOKUP($D45,Model!$D:$D,Model!Y:Y,""),"") -> 4900.0918 | J45: =IFERROR(I45/F45-1,"") -> -0.031027919 | K45: =IFERROR(I45/G45-1,"") -> 1.1102893 | L45: =IFERROR(I45/H45-1,"") -> -0.077179874 | P45: =IFERROR(_xlfn.XLOOKUP($D45,Model!$D:$D,Model!J:J,""),"") -> 22912708 | Q45: =IFERROR(_xlfn.XLOOKUP($D45,Model!$D:$D,Model!K:K,""),"") -> 11091311 | R45: =IFERROR(_xlfn.XLOOKUP($D45,Model!$D:$D,Model!L:L,""),"") -> 24604173 | S45: =IFERROR(_xlfn.XLOOKUP($D45,Model!$D:$D,Model!Z:Z,""),"") -> 23677322 | T45: =IFERROR(S45/P45-1,"") -> 0.033370732 | U45: =IFERROR(S45/Q45-1,"") -> 1.1347631 | V45: =IFERROR(S45/R45-1,"") -> -0.03767047 | Z45: =IFERROR(_xlfn.XLOOKUP($D45,Model!$D:$D,Model!M:M,""),"") -> 72731826 | AA45: =IFERROR(_xlfn.XLOOKUP($D45,Model!$D:$D,Model!N:N,""),"") -> 34698382 | AB45: =IFERROR(_xlfn.XLOOKUP($D45,Model!$D:$D,Model!O:O,""),"") -> 79478848 | AC45: =IFERROR(_xlfn.XLOOKUP($D45,Model!$D:$D,Model!AA:AA,""),"") -> 73968231 | AD45: =IFERROR(AC45/Z45-1,"") -> 0.016999513 | AE45: =IFERROR(AC45/AA45-1,"") -> 1.1317487 | AF45: =IFERROR(AC45/AB45-1,"") -> -0.069334385
D46: United Kingdom | F46: =IFERROR(_xlfn.XLOOKUP($D46,Model!$D:$D,Model!G:G,""),"") -> 5223 | G46: =IFERROR(_xlfn.XLOOKUP($D46,Model!$D:$D,Model!H:H,""),"") -> 2403 | H46: =IFERROR(_xlfn.XLOOKUP($D46,Model!$D:$D,Model!I:I,""),"") -> 5479.95 | I46: =IFERROR(_xlfn.XLOOKUP($D46,Model!$D:$D,Model!Y:Y,""),"") -> 4974.4145 | J46: =IFERROR(I46/F46-1,"") -> -0.047594387 | K46: =IFERROR(I46/G46-1,"") -> 1.0700851 | L46: =IFERROR(I46/H46-1,"") -> -0.092251843 | P46: =IFERROR(_xlfn.XLOOKUP($D46,Model!$D:$D,Model!J:J,""),"") -> 23561007 | Q46: =IFERROR(_xlfn.XLOOKUP($D46,Model!$D:$D,Model!K:K,""),"") -> 11429032 | R46: =IFERROR(_xlfn.XLOOKUP($D46,Model!$D:$D,Model!L:L,""),"") -> 25388842 | S46: =IFERROR(_xlfn.XLOOKUP($D46,Model!$D:$D,Model!Z:Z,""),"") -> 23579115 | T46: =IFERROR(S46/P46-1,"") -> 0.00076855184 | U46: =IFERROR(S46/Q46-1,"") -> 1.0630893 | V46: =IFERROR(S46/R46-1,"") -> -0.071280413 | Z46: =IFERROR(_xlfn.XLOOKUP($D46,Model!$D:$D,Model!M:M,""),"") -> 72561125 | AA46: =IFERROR(_xlfn.XLOOKUP($D46,Model!$D:$D,Model!N:N,""),"") -> 36171551 | AB46: =IFERROR(_xlfn.XLOOKUP($D46,Model!$D:$D,Model!O:O,""),"") -> 79547549 | AC46: =IFERROR(_xlfn.XLOOKUP($D46,Model!$D:$D,Model!AA:AA,""),"") -> 74448962 | AD46: =IFERROR(AC46/Z46-1,"") -> 0.026017186 | AE46: =IFERROR(AC46/AA46-1,"") -> 1.0582187 | AF46: =IFERROR(AC46/AB46-1,"") -> -0.064094838
D47: Germany | F47: =IFERROR(_xlfn.XLOOKUP($D47,Model!$D:$D,Model!G:G,""),"") -> 5124 | G47: =IFERROR(_xlfn.XLOOKUP($D47,Model!$D:$D,Model!H:H,""),"") -> 2304 | H47: =IFERROR(_xlfn.XLOOKUP($D47,Model!$D:$D,Model!I:I,""),"") -> 5380.09 | I47: =IFERROR(_xlfn.XLOOKUP($D47,Model!$D:$D,Model!Y:Y,""),"") -> 4736.2734 | J47: =IFERROR(I47/F47-1,"") -> -0.075668737 | K47: =IFERROR(I47/G47-1,"") -> 1.0556742 | L47: =IFERROR(I47/H47-1,"") -> -0.11966651 | P47: =IFERROR(_xlfn.XLOOKUP($D47,Model!$D:$D,Model!J:J,""),"") -> 23145018 | Q47: =IFERROR(_xlfn.XLOOKUP($D47,Model!$D:$D,Model!K:K,""),"") -> 10849389 | R47: =IFERROR(_xlfn.XLOOKUP($D47,Model!$D:$D,Model!L:L,""),"") -> 24918761 | S47: =IFERROR(_xlfn.XLOOKUP($D47,Model!$D:$D,Model!Z:Z,""),"") -> 22352054 | T47: =IFERROR(S47/P47-1,"") -> -0.034260665 | U47: =IFERROR(S47/Q47-1,"") -> 1.0602131 | V47: =IFERROR(S47/R47-1,"") -> -0.10300299 | Z47: =IFERROR(_xlfn.XLOOKUP($D47,Model!$D:$D,Model!M:M,""),"") -> 69251898 | AA47: =IFERROR(_xlfn.XLOOKUP($D47,Model!$D:$D,Model!N:N,""),"") -> 32463769 | AB47: =IFERROR(_xlfn.XLOOKUP($D47,Model!$D:$D,Model!O:O,""),"") -> 75904894 | AC47: =IFERROR(_xlfn.XLOOKUP($D47,Model!$D:$D,Model!AA:AA,""),"") -> 67001147 | AD47: =IFERROR(AC47/Z47-1,"") -> -0.032500931 | AE47: =IFERROR(AC47/AA47-1,"") -> 1.0638745 | AF47: =IFERROR(AC47/AB47-1,"") -> -0.11730136
D48: Japan | F48: =IFERROR(_xlfn.XLOOKUP($D48,Model!$D:$D,Model!G:G,""),"") -> 5228 | G48: =IFERROR(_xlfn.XLOOKUP($D48,Model!$D:$D,Model!H:H,""),"") -> 2376 | H48: =IFERROR(_xlfn.XLOOKUP($D48,Model!$D:$D,Model!I:I,""),"") -> 5490.11 | I48: =IFERROR(_xlfn.XLOOKUP($D48,Model!$D:$D,Model!Y:Y,""),"") -> 5127.2734 | J48: =IFERROR(I48/F48-1,"") -> -0.019266755 | K48: =IFERROR(I48/G48-1,"") -> 1.1579434 | L48: =IFERROR(I48/H48-1,"") -> -0.06608913 | P48: =IFERROR(_xlfn.XLOOKUP($D48,Model!$D:$D,Model!J:J,""),"") -> 23751720 | Q48: =IFERROR(_xlfn.XLOOKUP($D48,Model!$D:$D,Model!K:K,""),"") -> 11178834 | R48: =IFERROR(_xlfn.XLOOKUP($D48,Model!$D:$D,Model!L:L,""),"") -> 25324670 | S48: =IFERROR(_xlfn.XLOOKUP($D48,Model!$D:$D,Model!Z:Z,""),"") -> 24419513 | T48: =IFERROR(S48/P48-1,"") -> 0.028115585 | U48: =IFERROR(S48/Q48-1,"") -> 1.1844419 | V48: =IFERROR(S48/R48-1,"") -> -0.035742091 | Z48: =IFERROR(_xlfn.XLOOKUP($D48,Model!$D:$D,Model!M:M,""),"") -> 68446214 | AA48: =IFERROR(_xlfn.XLOOKUP($D48,Model!$D:$D,Model!N:N,""),"") -> 31831200 | AB48: =IFERROR(_xlfn.XLOOKUP($D48,Model!$D:$D,Model!O:O,""),"") -> 74351402 | AC48: =IFERROR(_xlfn.XLOOKUP($D48,Model!$D:$D,Model!AA:AA,""),"") -> 69655670 | AD48: =IFERROR(AC48/Z48-1,"") -> 0.017670172 | AE48: =IFERROR(AC48/AA48-1,"") -> 1.1882829 | AF48: =IFERROR(AC48/AB48-1,"") -> -0.063155928
D49: France | F49: =IFERROR(_xlfn.XLOOKUP($D49,Model!$D:$D,Model!G:G,""),"") -> 4904 | G49: =IFERROR(_xlfn.XLOOKUP($D49,Model!$D:$D,Model!H:H,""),"") -> 2289 | H49: =IFERROR(_xlfn.XLOOKUP($D49,Model!$D:$D,Model!I:I,""),"") -> 5149.95 | I49: =IFERROR(_xlfn.XLOOKUP($D49,Model!$D:$D,Model!Y:Y,""),"") -> 4693.8714 | J49: =IFERROR(I49/F49-1,"") -> -0.042848411 | K49: =IFERROR(I49/G49-1,"") -> 1.050621 | L49: =IFERROR(I49/H49-1,"") -> -0.088559813 | P49: =IFERROR(_xlfn.XLOOKUP($D49,Model!$D:$D,Model!J:J,""),"") -> 22195409 | Q49: =IFERROR(_xlfn.XLOOKUP($D49,Model!$D:$D,Model!K:K,""),"") -> 10788101 | R49: =IFERROR(_xlfn.XLOOKUP($D49,Model!$D:$D,Model!L:L,""),"") -> 23718828 | S49: =IFERROR(_xlfn.XLOOKUP($D49,Model!$D:$D,Model!Z:Z,""),"") -> 22153955 | T49: =IFERROR(S49/P49-1,"") -> -0.0018676737 | U49: =IFERROR(S49/Q49-1,"") -> 1.0535547 | V49: =IFERROR(S49/R49-1,"") -> -0.065975979 | Z49: =IFERROR(_xlfn.XLOOKUP($D49,Model!$D:$D,Model!M:M,""),"") -> 65526892 | AA49: =IFERROR(_xlfn.XLOOKUP($D49,Model!$D:$D,Model!N:N,""),"") -> 31957386 | AB49: =IFERROR(_xlfn.XLOOKUP($D49,Model!$D:$D,Model!O:O,""),"") -> 71167772 | AC49: =IFERROR(_xlfn.XLOOKUP($D49,Model!$D:$D,Model!AA:AA,""),"") -> 65700803 | AD49: =IFERROR(AC49/Z49-1,"") -> 0.0026540504 | AE49: =IFERROR(AC49/AA49-1,"") -> 1.0558879 | AF49: =IFERROR(AC49/AB49-1,"") -> -0.076818044
D50: China | F50: =IFERROR(_xlfn.XLOOKUP($D50,Model!$D:$D,Model!G:G,""),"") -> 4710 | G50: =IFERROR(_xlfn.XLOOKUP($D50,Model!$D:$D,Model!H:H,""),"") -> 2264 | H50: =IFERROR(_xlfn.XLOOKUP($D50,Model!$D:$D,Model!I:I,""),"") -> 5000.07 | I50: =IFERROR(_xlfn.XLOOKUP($D50,Model!$D:$D,Model!Y:Y,""),"") -> 4593.8846 | J50: =IFERROR(I50/F50-1,"") -> -0.024652958 | K50: =IFERROR(I50/G50-1,"") -> 1.029101 | L50: =IFERROR(I50/H50-1,"") -> -0.081235949 | P50: =IFERROR(_xlfn.XLOOKUP($D50,Model!$D:$D,Model!J:J,""),"") -> 21129130 | Q50: =IFERROR(_xlfn.XLOOKUP($D50,Model!$D:$D,Model!K:K,""),"") -> 10681052 | R50: =IFERROR(_xlfn.XLOOKUP($D50,Model!$D:$D,Model!L:L,""),"") -> 22723840 | S50: =IFERROR(_xlfn.XLOOKUP($D50,Model!$D:$D,Model!Z:Z,""),"") -> 21661992 | T50: =IFERROR(S50/P50-1,"") -> 0.02521934 | U50: =IFERROR(S50/Q50-1,"") -> 1.0280767 | V50: =IFERROR(S50/R50-1,"") -> -0.046728349 | Z50: =IFERROR(_xlfn.XLOOKUP($D50,Model!$D:$D,Model!M:M,""),"") -> 61225099 | AA50: =IFERROR(_xlfn.XLOOKUP($D50,Model!$D:$D,Model!N:N,""),"") -> 31154928 | AB50: =IFERROR(_xlfn.XLOOKUP($D50,Model!$D:$D,Model!O:O,""),"") -> 68853049 | AC50: =IFERROR(_xlfn.XLOOKUP($D50,Model!$D:$D,Model!AA:AA,""),"") -> 63340833 | AD50: =IFERROR(AC50/Z50-1,"") -> 0.034556641 | AE50: =IFERROR(AC50/AA50-1,"") -> 1.033092 | AF50: =IFERROR(AC50/AB50-1,"") -> -0.080057692
D51: Mexico | F51: =IFERROR(_xlfn.XLOOKUP($D51,Model!$D:$D,Model!G:G,""),"") -> 3111 | G51: =IFERROR(_xlfn.XLOOKUP($D51,Model!$D:$D,Model!H:H,""),"") -> 1518 | H51: =IFERROR(_xlfn.XLOOKUP($D51,Model!$D:$D,Model!I:I,""),"") -> 3269.99 | I51: =IFERROR(_xlfn.XLOOKUP($D51,Model!$D:$D,Model!Y:Y,""),"") -> 3193.2099 | J51: =IFERROR(I51/F51-1,"") -> 0.026425561 | K51: =IFERROR(I51/G51-1,"") -> 1.1035638 | L51: =IFERROR(I51/H51-1,"") -> -0.023480219 | P51: =IFERROR(_xlfn.XLOOKUP($D51,Model!$D:$D,Model!J:J,""),"") -> 14362563 | Q51: =IFERROR(_xlfn.XLOOKUP($D51,Model!$D:$D,Model!K:K,""),"") -> 7360193.9 | R51: =IFERROR(_xlfn.XLOOKUP($D51,Model!$D:$D,Model!L:L,""),"") -> 15342834 | S51: =IFERROR(_xlfn.XLOOKUP($D51,Model!$D:$D,Model!Z:Z,""),"") -> 15553375 | T51: =IFERROR(S51/P51-1,"") -> 0.082910867 | U51: =IFERROR(S51/Q51-1,"") -> 1.1131746 | V51: =IFERROR(S51/R51-1,"") -> 0.013722463 | Z51: =IFERROR(_xlfn.XLOOKUP($D51,Model!$D:$D,Model!M:M,""),"") -> 43124315 | AA51: =IFERROR(_xlfn.XLOOKUP($D51,Model!$D:$D,Model!N:N,""),"") -> 21821683 | AB51: =IFERROR(_xlfn.XLOOKUP($D51,Model!$D:$D,Model!O:O,""),"") -> 46863360 | AC51: =IFERROR(_xlfn.XLOOKUP($D51,Model!$D:$D,Model!AA:AA,""),"") -> 46356402 | AD51: =IFERROR(AC51/Z51-1,"") -> 0.074948128 | AE51: =IFERROR(AC51/AA51-1,"") -> 1.1243275 | AF51: =IFERROR(AC51/AB51-1,"") -> -0.010817801
D52: UAE | F52: =IFERROR(_xlfn.XLOOKUP($D52,Model!$D:$D,Model!G:G,""),"") -> 3093 | G52: =IFERROR(_xlfn.XLOOKUP($D52,Model!$D:$D,Model!H:H,""),"") -> 1361 | H52: =IFERROR(_xlfn.XLOOKUP($D52,Model!$D:$D,Model!I:I,""),"") -> 3250.03 | I52: =IFERROR(_xlfn.XLOOKUP($D52,Model!$D:$D,Model!Y:Y,""),"") -> 2785.167 | J52: =IFERROR(I52/F52-1,"") -> -0.099525702 | K52: =IFERROR(I52/G52-1,"") -> 1.0464122 | L52: =IFERROR(I52/H52-1,"") -> -0.14303345 | P52: =IFERROR(_xlfn.XLOOKUP($D52,Model!$D:$D,Model!J:J,""),"") -> 14027140 | Q52: =IFERROR(_xlfn.XLOOKUP($D52,Model!$D:$D,Model!K:K,""),"") -> 6462043.7 | R52: =IFERROR(_xlfn.XLOOKUP($D52,Model!$D:$D,Model!L:L,""),"") -> 15050590 | S52: =IFERROR(_xlfn.XLOOKUP($D52,Model!$D:$D,Model!Z:Z,""),"") -> 13236448 | T52: =IFERROR(S52/P52-1,"") -> -0.056368742 | U52: =IFERROR(S52/Q52-1,"") -> 1.0483378 | V52: =IFERROR(S52/R52-1,"") -> -0.12053624 | Z52: =IFERROR(_xlfn.XLOOKUP($D52,Model!$D:$D,Model!M:M,""),"") -> 41436160 | AA52: =IFERROR(_xlfn.XLOOKUP($D52,Model!$D:$D,Model!N:N,""),"") -> 19168326 | AB52: =IFERROR(_xlfn.XLOOKUP($D52,Model!$D:$D,Model!O:O,""),"") -> 45173303 | AC52: =IFERROR(_xlfn.XLOOKUP($D52,Model!$D:$D,Model!AA:AA,""),"") -> 39326181 | AD52: =IFERROR(AC52/Z52-1,"") -> -0.050921189 | AE52: =IFERROR(AC52/AA52-1,"") -> 1.0516231 | AF52: =IFERROR(AC52/AB52-1,"") -> -0.12943755
D53: South Korea | F53: =IFERROR(_xlfn.XLOOKUP($D53,Model!$D:$D,Model!G:G,""),"") -> 3011 | G53: =IFERROR(_xlfn.XLOOKUP($D53,Model!$D:$D,Model!H:H,""),"") -> 1537 | H53: =IFERROR(_xlfn.XLOOKUP($D53,Model!$D:$D,Model!I:I,""),"") -> 3159.91 | I53: =IFERROR(_xlfn.XLOOKUP($D53,Model!$D:$D,Model!Y:Y,""),"") -> 3113.5012 | J53: =IFERROR(I53/F53-1,"") -> 0.034042248 | K53: =IFERROR(I53/G53-1,"") -> 1.0257002 | L53: =IFERROR(I53/H53-1,"") -> -0.014686745 | P53: =IFERROR(_xlfn.XLOOKUP($D53,Model!$D:$D,Model!J:J,""),"") -> 13782697 | Q53: =IFERROR(_xlfn.XLOOKUP($D53,Model!$D:$D,Model!K:K,""),"") -> 7316804.6 | R53: =IFERROR(_xlfn.XLOOKUP($D53,Model!$D:$D,Model!L:L,""),"") -> 14708709 | S53: =IFERROR(_xlfn.XLOOKUP($D53,Model!$D:$D,Model!Z:Z,""),"") -> 14837885 | T53: =IFERROR(S53/P53-1,"") -> 0.076558859 | U53: =IFERROR(S53/Q53-1,"") -> 1.0279187 | V53: =IFERROR(S53/R53-1,"") -> 0.00878225 | Z53: =IFERROR(_xlfn.XLOOKUP($D53,Model!$D:$D,Model!M:M,""),"") -> 39951287 | AA53: =IFERROR(_xlfn.XLOOKUP($D53,Model!$D:$D,Model!N:N,""),"") -> 20962778 | AB53: =IFERROR(_xlfn.XLOOKUP($D53,Model!$D:$D,Model!O:O,""),"") -> 43348060 | AC53: =IFERROR(_xlfn.XLOOKUP($D53,Model!$D:$D,Model!AA:AA,""),"") -> 42499336 | AD53: =IFERROR(AC53/Z53-1,"") -> 0.063778905 | AE53: =IFERROR(AC53/AA53-1,"") -> 1.0273714 | AF53: =IFERROR(AC53/AB53-1,"") -> -0.019579288
D54: Brazil | F54: =IFERROR(_xlfn.XLOOKUP($D54,Model!$D:$D,Model!G:G,""),"") -> 2709 | G54: =IFERROR(_xlfn.XLOOKUP($D54,Model!$D:$D,Model!H:H,""),"") -> 1136 | H54: =IFERROR(_xlfn.XLOOKUP($D54,Model!$D:$D,Model!I:I,""),"") -> 2999.96 | I54: =IFERROR(_xlfn.XLOOKUP($D54,Model!$D:$D,Model!Y:Y,""),"") -> 2389.8867 | J54: =IFERROR(I54/F54-1,"") -> -0.11779745 | K54: =IFERROR(I54/G54-1,"") -> 1.1037735 | L54: =IFERROR(I54/H54-1,"") -> -0.20336047 | P54: =IFERROR(_xlfn.XLOOKUP($D54,Model!$D:$D,Model!J:J,""),"") -> 12554571 | Q54: =IFERROR(_xlfn.XLOOKUP($D54,Model!$D:$D,Model!K:K,""),"") -> 5566194.9 | R54: =IFERROR(_xlfn.XLOOKUP($D54,Model!$D:$D,Model!L:L,""),"") -> 14084345 | S54: =IFERROR(_xlfn.XLOOKUP($D54,Model!$D:$D,Model!Z:Z,""),"") -> 11694393 | T54: =IFERROR(S54/P54-1,"") -> -0.06851511 | U54: =IFERROR(S54/Q54-1,"") -> 1.1009672 | V54: =IFERROR(S54/R54-1,"") -> -0.16968855 | Z54: =IFERROR(_xlfn.XLOOKUP($D54,Model!$D:$D,Model!M:M,""),"") -> 33244194 | AA54: =IFERROR(_xlfn.XLOOKUP($D54,Model!$D:$D,Model!N:N,""),"") -> 14655709 | AB54: =IFERROR(_xlfn.XLOOKUP($D54,Model!$D:$D,Model!O:O,""),"") -> 39604826 | AC54: =IFERROR(_xlfn.XLOOKUP($D54,Model!$D:$D,Model!AA:AA,""),"") -> 30673535 | AD54: =IFERROR(AC54/Z54-1,"") -> -0.077326547 | AE54: =IFERROR(AC54/AA54-1,"") -> 1.092941 | AF54: =IFERROR(AC54/AB54-1,"") -> -0.22551016
D55: Hong Kong | F55: =IFERROR(_xlfn.XLOOKUP($D55,Model!$D:$D,Model!G:G,""),"") -> 2613 | G55: =IFERROR(_xlfn.XLOOKUP($D55,Model!$D:$D,Model!H:H,""),"") -> 1113 | H55: =IFERROR(_xlfn.XLOOKUP($D55,Model!$D:$D,Model!I:I,""),"") -> 2740.01 | I55: =IFERROR(_xlfn.XLOOKUP($D55,Model!$D:$D,Model!Y:Y,""),"") -> 2284.6759 | J55: =IFERROR(I55/F55-1,"") -> -0.12565024 | K55: =IFERROR(I55/G55-1,"") -> 1.0527187 | L55: =IFERROR(I55/H55-1,"") -> -0.16617971 | P55: =IFERROR(_xlfn.XLOOKUP($D55,Model!$D:$D,Model!J:J,""),"") -> 11856393 | Q55: =IFERROR(_xlfn.XLOOKUP($D55,Model!$D:$D,Model!K:K,""),"") -> 5315856.6 | R55: =IFERROR(_xlfn.XLOOKUP($D55,Model!$D:$D,Model!L:L,""),"") -> 12793907 | S55: =IFERROR(_xlfn.XLOOKUP($D55,Model!$D:$D,Model!Z:Z,""),"") -> 10895902 | T55: =IFERROR(S55/P55-1,"") -> -0.081010414 | U55: =IFERROR(S55/Q55-1,"") -> 1.0496982 | V55: =IFERROR(S55/R55-1,"") -> -0.14835227 | Z55: =IFERROR(_xlfn.XLOOKUP($D55,Model!$D:$D,Model!M:M,""),"") -> 33911293 | AA55: =IFERROR(_xlfn.XLOOKUP($D55,Model!$D:$D,Model!N:N,""),"") -> 15385841 | AB55: =IFERROR(_xlfn.XLOOKUP($D55,Model!$D:$D,Model!O:O,""),"") -> 37213204 | AC55: =IFERROR(_xlfn.XLOOKUP($D55,Model!$D:$D,Model!AA:AA,""),"") -> 31591595 | AD55: =IFERROR(AC55/Z55-1,"") -> -0.068404888 | AE55: =IFERROR(AC55/AA55-1,"") -> 1.0532902 | AF55: =IFERROR(AC55/AB55-1,"") -> -0.15106489
... D75: Colombia | F75: =IFERROR(_xlfn.XLOOKUP($D75,Model!$D:$D,Model!G:G,""),"") -> 280 | G75: =IFERROR(_xlfn.XLOOKUP($D75,Model!$D:$D,Model!H:H,""),"") -> 137 | H75: =IFERROR(_xlfn.XLOOKUP($D75,Model!$D:$D,Model!I:I,""),"") -> 262.5 | I75: =IFERROR(_xlfn.XLOOKUP($D75,Model!$D:$D,Model!Y:Y,""),"") -> 255.59701 | J75: =IFERROR(I75/F75-1,"") -> -0.087153518 | K75: =IFERROR(I75/G75-1,"") -> 0.86567164 | L75: =IFERROR(I75/H75-1,"") -> -0.026297086 | P75: =IFERROR(_xlfn.XLOOKUP($D75,Model!$D:$D,Model!J:J,""),"") -> 1287280.2 | Q75: =IFERROR(_xlfn.XLOOKUP($D75,Model!$D:$D,Model!K:K,""),"") -> 633972.65 | R75: =IFERROR(_xlfn.XLOOKUP($D75,Model!$D:$D,Model!L:L,""),"") -> 1253727 | S75: =IFERROR(_xlfn.XLOOKUP($D75,Model!$D:$D,Model!Z:Z,""),"") -> 1247381.8 | T75: =IFERROR(S75/P75-1,"") -> -0.030994353 | U75: =IFERROR(S75/Q75-1,"") -> 0.96756406 | V75: =IFERROR(S75/R75-1,"") -> -0.0050610366 | Z75: =IFERROR(_xlfn.XLOOKUP($D75,Model!$D:$D,Model!M:M,""),"") -> 3357002.9 | AA75: =IFERROR(_xlfn.XLOOKUP($D75,Model!$D:$D,Model!N:N,""),"") -> 1600808 | AB75: =IFERROR(_xlfn.XLOOKUP($D75,Model!$D:$D,Model!O:O,""),"") -> 3320851.4 | AC75: =IFERROR(_xlfn.XLOOKUP($D75,Model!$D:$D,Model!AA:AA,""),"") -> 3191324.4 | AD75: =IFERROR(AC75/Z75-1,"") -> -0.049353112 | AE75: =IFERROR(AC75/AA75-1,"") -> 0.99357096 | AF75: =IFERROR(AC75/AB75-1,"") -> -0.039004163

Sheet Model
E2: Pivot Tables from DB | S2: Forecast Model
D3: Tag for lookups | E3: Pivot tables with consolidated values for Actuals and Budgtet transformed in PowerQuery from the database. These tables below display LY actuals, TY actuals (YTD) and TY Budget and can be refreshed anytime the Company Database is updated with new data. | S3: Average delta based on available actuals data: actuals variance vs budget computed at channel/country/collection level month after month | Y3: Forecast based on Actuals where available and a calculated estimate for subsequent months
Y4: Non-actuals months are computed based on the effect of the actuals trend on the master budget
G5: Sum of units | J5: Sum of cogs | M5: Sum of revenue | S5: Sum of units | T5: Sum of cogs | U5: Sum of revenue | Y5: Forecast
G6: 2025 Actuals | H6: 2026 Actuals | I6: 2026 Budget | J6: 2025 Actuals | K6: 2026 Actuals | L6: 2026 Budget | M6: 2025 Actuals | N6: 2026 Actuals | O6: 2026 Budget | S6: Units | T6: Cogs | U6: Revenue | Y6: Units | Z6: Cogs | AA6: Revenue
D7: TOPLINE | E7: TOTAL | F7: TOTAL | G7: =SUM(G56:G57) -> 70972 | H7: =SUM(H56:H57) -> 32888 | I7: =SUM(I56:I57) -> 74712.84 | J7: =SUM(J56:J57) -> 3.2230053e+08 | K7: =SUM(K56:K57) -> 1.5664026e+08 | L7: =SUM(L56:L57) -> 3.4585199e+08 | M7: =SUM(M56:M57) -> 9.5278736e+08 | N7: =SUM(N56:N57) -> 4.6270906e+08 | O7: =SUM(O56:O57) -> 1.0443122e+09 | S7: =IFERROR(SUMPRODUCT(H$13:H$24,$W$13:$W$24)/SUMPRODUCT(I$13:I$24,$W$13:$W$24)-1,"") -> -0.089359254 | T7: =IFERROR(SUMPRODUCT(K$13:K$24,$W$13:$W$24)/SUMPRODUCT(L$13:L$24,$W$13:$W$24)-1,"") -> -0.060415529 | U7: =IFERROR(SUMPRODUCT(N$13:N$24,$W$13:$W$24)/SUMPRODUCT(O$13:O$24,$W$13:$W$24)-1,"") -> -0.079856886 | Y7: =IFERROR(AVERAGE(Y25,Y55,Y88,Y217,Y284,Y679),"") -> 68038.152 | Z7: =IFERROR(AVERAGE(Z25,Z55,Z88,Z217,Z284,Z679),"") -> 3.2496738e+08 | AA7: =IFERROR(AVERAGE(AA25,AA55,AA88,AA217,AA284,AA679),"") -> 9.609565e+08
E9: MONTHS
G10: Column Labels
G11: Sum of units | J11: Sum of cogs | M11: Sum of revenue | S11: Average Delta | W11: Actuals | Y11: Forecast
F12: Row Labels | G12: 2025 Actuals | H12: 2026 Actuals | I12: 2026 Budget | J12: 2025 Actuals | K12: 2026 Actuals | L12: 2026 Budget | M12: 2025 Actuals | N12: 2026 Actuals | O12: 2026 Budget | S12: Units | T12: Cogs | U12: Revenue | W12: Multiplier | Y12: Units | Z12: Cogs | AA12: Revenue
C13: 1 | D13: =_xlfn.XLOOKUP(F13,$C$13:$C$24,$E$13:$E$24,"") -> JAN | E13: JAN | F13: 1 | G13: 4774 | H13: 5014 | I13: 5899.24 | J13: 21647908 | K13: 23852924 | L13: 27318474 | M13: 63896491 | N13: 70958559 | O13: 82382445 | S13: =IFERROR(SUMPRODUCT(H$13:H$24,$W$13:$W$24)/SUMPRODUCT(I$13:I$24,$W$13:$W$24)-1,"") -> -0.089359254 | T13: =IFERROR(SUMPRODUCT(K$13:K$24,$W$13:$W$24)/SUMPRODUCT(L$13:L$24,$W$13:$W$24)-1,"") -> -0.060415529 | U13: =IFERROR(SUMPRODUCT(N$13:N$24,$W$13:$W$24)/SUMPRODUCT(O$13:O$24,$W$13:$W$24)-1,"") -> -0.079856886 | W13: =IFERROR(IF(H13>0,1,0),"") -> 1 | Y13: =IFERROR(IF($W13=1,H13,I13*(1+S13)),"") -> 5014 | Z13: =IFERROR(IF($W13=1,K13,L13*(1+T13)),"") -> 23852924 | AA13: =IFERROR(IF($W13=1,N13,O13*(1+U13)),"") -> 70958559
C14: 2 | D14: =_xlfn.XLOOKUP(F14,$C$13:$C$24,$E$13:$E$24,"") -> FEB | E14: FEB | F14: 2 | G14: 4611 | H14: 4820 | I14: 5857.91 | J14: 20788430 | K14: 22801928 | L14: 27016357 | M14: 61428994 | N14: 67748869 | O14: 81554153 | S14: =IFERROR(SUMPRODUCT(H$13:H$24,$W$13:$W$24)/SUMPRODUCT(I$13:I$24,$W$13:$W$24)-1,"") -> -0.089359254 | T14: =IFERROR(SUMPRODUCT(K$13:K$24,$W$13:$W$24)/SUMPRODUCT(L$13:L$24,$W$13:$W$24)-1,"") -> -0.060415529 | U14: =IFERROR(SUMPRODUCT(N$13:N$24,$W$13:$W$24)/SUMPRODUCT(O$13:O$24,$W$13:$W$24)-1,"") -> -0.079856886 | W14: =IFERROR(IF(H14>0,1,0),"") -> 1 | Y14: =IFERROR(IF($W14=1,H14,I14*(1+S14)),"") -> 4820 | Z14: =IFERROR(IF($W14=1,K14,L14*(1+T14)),"") -> 22801928 | AA14: =IFERROR(IF($W14=1,N14,O14*(1+U14)),"") -> 67748869
C15: 3 | D15: =_xlfn.XLOOKUP(F15,$C$13:$C$24,$E$13:$E$24,"") -> MAR | E15: MAR | F15: 3 | G15: 5638 | H15: 5909 | I15: 6047.01 | J15: 25836655 | K15: 28458144 | L15: 27788370 | M15: 76771853 | N15: 84591120 | O15: 83697668 | S15: =IFERROR(SUMPRODUCT(H$13:H$24,$W$13:$W$24)/SUMPRODUCT(I$13:I$24,$W$13:$W$24)-1,"") -> -0.089359254 | T15: =IFERROR(SUMPRODUCT(K$13:K$24,$W$13:$W$24)/SUMPRODUCT(L$13:L$24,$W$13:$W$24)-1,"") -> -0.060415529 | U15: =IFERROR(SUMPRODUCT(N$13:N$24,$W$13:$W$24)/SUMPRODUCT(O$13:O$24,$W$13:$W$24)-1,"") -> -0.079856886 | W15: =IFERROR(IF(H15>0,1,0),"") -> 1 | Y15: =IFERROR(IF($W15=1,H15,I15*(1+S15)),"") -> 5909 | Z15: =IFERROR(IF($W15=1,K15,L15*(1+T15)),"") -> 28458144 | AA15: =IFERROR(IF($W15=1,N15,O15*(1+U15)),"") -> 84591120
C16: 4 | D16: =_xlfn.XLOOKUP(F16,$C$13:$C$24,$E$13:$E$24,"") -> APR | E16: APR | F16: 4 | G16: 5275 | H16: 5525 | I16: 5956.7 | J16: 23926461 | K16: 26350307 | L16: 27545309 | M16: 71107882 | N16: 77673877 | O16: 83185402 | S16: =IFERROR(SUMPRODUCT(H$13:H$24,$W$13:$W$24)/SUMPRODUCT(I$13:I$24,$W$13:$W$24)-1,"") -> -0.089359254 | T16: =IFERROR(SUMPRODUCT(K$13:K$24,$W$13:$W$24)/SUMPRODUCT(L$13:L$24,$W$13:$W$24)-1,"") -> -0.060415529 | U16: =IFERROR(SUMPRODUCT(N$13:N$24,$W$13:$W$24)/SUMPRODUCT(O$13:O$24,$W$13:$W$24)-1,"") -> -0.079856886 | W16: =IFERROR(IF(H16>0,1,0),"") -> 1 | Y16: =IFERROR(IF($W16=1,H16,I16*(1+S16)),"") -> 5525 | Z16: =IFERROR(IF($W16=1,K16,L16*(1+T16)),"") -> 26350307 | AA16: =IFERROR(IF($W16=1,N16,O16*(1+U16)),"") -> 77673877
C17: 5 | D17: =_xlfn.XLOOKUP(F17,$C$13:$C$24,$E$13:$E$24,"") -> MAY | E17: MAY | F17: 5 | G17: 5661 | H17: 5934 | I17: 6163.41 | J17: 25432682 | K17: 27990868 | L17: 28501574 | M17: 75443430 | N17: 82028726 | O17: 86045416 | S17: =IFERROR(SUMPRODUCT(H$13:H$24,$W$13:$W$24)/SUMPRODUCT(I$13:I$24,$W$13:$W$24)-1,"") -> -0.089359254 | T17: =IFERROR(SUMPRODUCT(K$13:K$24,$W$13:$W$24)/SUMPRODUCT(L$13:L$24,$W$13:$W$24)-1,"") -> -0.060415529 | U17: =IFERROR(SUMPRODUCT(N$13:N$24,$W$13:$W$24)/SUMPRODUCT(O$13:O$24,$W$13:$W$24)-1,"") -> -0.079856886 | W17: =IFERROR(IF(H17>0,1,0),"") -> 1 | Y17: =IFERROR(IF($W17=1,H17,I17*(1+S17)),"") -> 5934 | Z17: =IFERROR(IF($W17=1,K17,L17*(1+T17)),"") -> 27990868 | AA17: =IFERROR(IF($W17=1,N17,O17*(1+U17)),"") -> 82028726
C18: 6 | D18: =_xlfn.XLOOKUP(F18,$C$13:$C$24,$E$13:$E$24,"") -> JUN | E18: JUN | F18: 6 | G18: 5432 | H18: 5686 | I18: 6190.96 | J18: 24717459 | K18: 27186090 | L18: 28542188 | M18: 72981103 | N18: 79707905 | O18: 86001317 | S18: =IFERROR(SUMPRODUCT(H$13:H$24,$W$13:$W$24)/SUMPRODUCT(I$13:I$24,$W$13:$W$24)-1,"") -> -0.089359254 | T18: =IFERROR(SUMPRODUCT(K$13:K$24,$W$13:$W$24)/SUMPRODUCT(L$13:L$24,$W$13:$W$24)-1,"") -> -0.060415529 | U18: =IFERROR(SUMPRODUCT(N$13:N$24,$W$13:$W$24)/SUMPRODUCT(O$13:O$24,$W$13:$W$24)-1,"") -> -0.079856886 | W18: =IFERROR(IF(H18>0,1,0),"") -> 1 | Y18: =IFERROR(IF($W18=1,H18,I18*(1+S18)),"") -> 5686 | Z18: =IFERROR(IF($W18=1,K18,L18*(1+T18)),"") -> 27186090 | AA18: =IFERROR(IF($W18=1,N18,O18*(1+U18)),"") -> 79707905
C19: 7 | D19: =_xlfn.XLOOKUP(F19,$C$13:$C$24,$E$13:$E$24,"") -> JUL | E19: JUL | F19: 7 | G19: 5395 | I19: 5996.83 | J19: 24477665 | L19: 27897645 | M19: 72015413 | O19: 84448323 | S19: =IFERROR(SUMPRODUCT(H$13:H$24,$W$13:$W$24)/SUMPRODUCT(I$13:I$24,$W$13:$W$24)-1,"") -> -0.089359254 | T19: =IFERROR(SUMPRODUCT(K$13:K$24,$W$13:$W$24)/SUMPRODUCT(L$13:L$24,$W$13:$W$24)-1,"") -> -0.060415529 | U19: =IFERROR(SUMPRODUCT(N$13:N$24,$W$13:$W$24)/SUMPRODUCT(O$13:O$24,$W$13:$W$24)-1,"") -> -0.079856886 | W19: =IFERROR(IF(H19>0,1,0),"") -> 0 | Y19: =IFERROR(IF($W19=1,H19,I19*(1+S19)),"") -> 5460.9577 | Z19: =IFERROR(IF($W19=1,K19,L19*(1+T19)),"") -> 26212194 | AA19: =IFERROR(IF($W19=1,N19,O19*(1+U19)),"") -> 77704543
C20: 8 | D20: =_xlfn.XLOOKUP(F20,$C$13:$C$24,$E$13:$E$24,"") -> AUG | E20: AUG | F20: 8 | G20: 5237 | I20: 6113.95 | J20: 23570792 | L20: 28233677 | M20: 69657165 | O20: 85293961 | S20: =IFERROR(SUMPRODUCT(H$13:H$24,$W$13:$W$24)/SUMPRODUCT(I$13:I$24,$W$13:$W$24)-1,"") -> -0.089359254 | T20: =IFERROR(SUMPRODUCT(K$13:K$24,$W$13:$W$24)/SUMPRODUCT(L$13:L$24,$W$13:$W$24)-1,"") -> -0.060415529 | U20: =IFERROR(SUMPRODUCT(N$13:N$24,$W$13:$W$24)/SUMPRODUCT(O$13:O$24,$W$13:$W$24)-1,"") -> -0.079856886 | W20: =IFERROR(IF(H20>0,1,0),"") -> 0 | Y20: =IFERROR(IF($W20=1,H20,I20*(1+S20)),"") -> 5567.612 | Z20: =IFERROR(IF($W20=1,K20,L20*(1+T20)),"") -> 26527925 | AA20: =IFERROR(IF($W20=1,N20,O20*(1+U20)),"") -> 78482651
C21: 9 | D21: =_xlfn.XLOOKUP(F21,$C$13:$C$24,$E$13:$E$24,"") -> SEP | E21: SEP | F21: 9 | G21: 5659 | I21: 6238 | J21: 25703164 | L21: 28882578 | M21: 76302534 | O21: 87377353 | S21: =IFERROR(SUMPRODUCT(H$13:H$24,$W$13:$W$24)/SUMPRODUCT(I$13:I$24,$W$13:$W$24)-1,"") -> -0.089359254 | T21: =IFERROR(SUMPRODUCT(K$13:K$24,$W$13:$W$24)/SUMPRODUCT(L$13:L$24,$W$13:$W$24)-1,"") -> -0.060415529 | U21: =IFERROR(SUMPRODUCT(N$13:N$24,$W$13:$W$24)/SUMPRODUCT(O$13:O$24,$W$13:$W$24)-1,"") -> -0.079856886 | W21: =IFERROR(IF(H21>0,1,0),"") -> 0 | Y21: =IFERROR(IF($W21=1,H21,I21*(1+S21)),"") -> 5680.577 | Z21: =IFERROR(IF($W21=1,K21,L21*(1+T21)),"") -> 27137622 | AA21: =IFERROR(IF($W21=1,N21,O21*(1+U21)),"") -> 80399670
C22: 10 | D22: =_xlfn.XLOOKUP(F22,$C$13:$C$24,$E$13:$E$24,"") -> OCT | E22: OCT | F22: 10 | G22: 6213 | I22: 6459.37 | J22: 28382120 | L22: 30105126 | M22: 83728323 | O22: 90973952 | S22: =IFERROR(SUMPRODUCT(H$13:H$24,$W$13:$W$24)/SUMPRODUCT(I$13:I$24,$W$13:$W$24)-1,"") -> -0.089359254 | T22: =IFERROR(SUMPRODUCT(K$13:K$24,$W$13:$W$24)/SUMPRODUCT(L$13:L$24,$W$13:$W$24)-1,"") -> -0.060415529 | U22: =IFERROR(SUMPRODUCT(N$13:N$24,$W$13:$W$24)/SUMPRODUCT(O$13:O$24,$W$13:$W$24)-1,"") -> -0.079856886 | W22: =IFERROR(IF(H22>0,1,0),"") -> 0 | Y22: =IFERROR(IF($W22=1,H22,I22*(1+S22)),"") -> 5882.1655 | Z22: =IFERROR(IF($W22=1,K22,L22*(1+T22)),"") -> 28286309 | AA22: =IFERROR(IF($W22=1,N22,O22*(1+U22)),"") -> 83709056
C23: 11 | D23: =_xlfn.XLOOKUP(F23,$C$13:$C$24,$E$13:$E$24,"") -> NOV | E23: NOV | F23: 11 | G23: 7883 | I23: 6858.17 | J23: 35862040 | L23: 31878473 | M23: 1.0569689e+08 | O23: 96279579 | S23: =IFERROR(SUMPRODUCT(H$13:H$24,$W$13:$W$24)/SUMPRODUCT(I$13:I$24,$W$13:$W$24)-1,"") -> -0.089359254 | T23: =IFERROR(SUMPRODUCT(K$13:K$24,$W$13:$W$24)/SUMPRODUCT(L$13:L$24,$W$13:$W$24)-1,"") -> -0.060415529 | U23: =IFERROR(SUMPRODUCT(N$13:N$24,$W$13:$W$24)/SUMPRODUCT(O$13:O$24,$W$13:$W$24)-1,"") -> -0.079856886 | W23: =IFERROR(IF(H23>0,1,0),"") -> 0 | Y23: =IFERROR(IF($W23=1,H23,I23*(1+S23)),"") -> 6245.329 | Z23: =IFERROR(IF($W23=1,K23,L23*(1+T23)),"") -> 29952518 | AA23: =IFERROR(IF($W23=1,N23,O23*(1+U23)),"") -> 88590991
C24: 12 | D24: =_xlfn.XLOOKUP(F24,$C$13:$C$24,$E$13:$E$24,"") -> DEC | E24: DEC | F24: 12 | G24: 9194 | I24: 6931.29 | J24: 41955154 | L24: 32142219 | M24: 1.2375728e+08 | O24: 97072592 | S24: =IFERROR(SUMPRODUCT(H$13:H$24,$W$13:$W$24)/SUMPRODUCT(I$13:I$24,$W$13:$W$24)-1,"") -> -0.089359254 | T24: =IFERROR(SUMPRODUCT(K$13:K$24,$W$13:$W$24)/SUMPRODUCT(L$13:L$24,$W$13:$W$24)-1,"") -> -0.060415529 | U24: =IFERROR(SUMPRODUCT(N$13:N$24,$W$13:$W$24)/SUMPRODUCT(O$13:O$24,$W$13:$W$24)-1,"") -> -0.079856886 | W24: =IFERROR(IF(H24>0,1,0),"") -> 0 | Y24: =IFERROR(IF($W24=1,H24,I24*(1+S24)),"") -> 6311.9151 | Z24: =IFERROR(IF($W24=1,K24,L24*(1+T24)),"") -> 30200330 | AA24: =IFERROR(IF($W24=1,N24,O24*(1+U24)),"") -> 89320677
Y25: =IFERROR(SUM(Y13:Y24),"") -> 68036.556 | Z25: =IFERROR(SUM(Z13:Z24),"") -> 3.2495716e+08 | AA25: =IFERROR(SUM(AA13:AA24),"") -> 9.6091664e+08
E27: MODE
G28: Values | H28: scenario
G29: Sum of units | J29: Sum of cogs | M29: Sum of revenue | S29: Sum of units | T29: Sum of cogs | U29: Sum of revenue | W29: Actuals | Y29: Forecast
E30: channel_mode | F30: month | G30: 2025 Actuals | H30: 2026 Actuals | I30: 2026 Budget | J30: 2025 Actuals | K30: 2026 Actuals | L30: 2026 Budget | M30: 2025 Actuals | N30: 2026 Actuals | O30: 2026 Budget | S30: vs LY | T30: vs LY | U30: vs LY | W30: Multiplier | Y30: Units | Z30: Cogs | AA30: Revenue
D31: =_xlfn.CONCAT(E31," - ",_xlfn.XLOOKUP(F31,$C$13:$C$24,$E$13:$E$24,"")) -> Online - JAN | E31: Online | F31: 1 | G31: 1281 | H31: 1329 | I31: 1637.99 | J31: 5771942.6 | K31: 6276082.8 | L31: 7605108.6 | M31: 16348083 | N31: 17871607 | O31: 22056516 | S31: =IFERROR(SUMPRODUCT(H$31:H$42,$W$31:$W$42)/SUMPRODUCT(I$31:I$42,$W$31:$W$42)-1,"") -> -0.072476897 | T31: =IFERROR(SUMPRODUCT(K$31:K$42,$W$31:$W$42)/SUMPRODUCT(L$31:L$42,$W$31:$W$42)-1,"") -> -0.04617734 | U31: =IFERROR(SUMPRODUCT(N$31:N$42,$W$31:$W$42)/SUMPRODUCT(O$31:O$42,$W$31:$W$42)-1,"") -> -0.064143013 | W31: =IFERROR(_xlfn.XLOOKUP(F31,$F$13:$F$24,$W$13:$W$24),"") -> 1 | Y31: =IFERROR(IF($W31=1,H31,I31*(1+S31)),"") -> 1329 | Z31: =IFERROR(IF($W31=1,K31,L31*(1+T31)),"") -> 6276082.8 | AA31: =IFERROR(IF($W31=1,N31,O31*(1+U31)),"") -> 17871607
D32: =_xlfn.CONCAT(E32," - ",_xlfn.XLOOKUP(F32,$C$13:$C$24,$E$13:$E$24,"")) -> Online - FEB | E32: Online | F32: 2 | G32: 1257 | H32: 1301 | I32: 1625.34 | J32: 5744184.2 | K32: 6226354.2 | L32: 7520042.6 | M32: 16477242 | N32: 17903891 | O32: 21826770 | S32: =IFERROR(SUMPRODUCT(H$31:H$42,$W$31:$W$42)/SUMPRODUCT(I$31:I$42,$W$31:$W$42)-1,"") -> -0.072476897 | T32: =IFERROR(SUMPRODUCT(K$31:K$42,$W$31:$W$42)/SUMPRODUCT(L$31:L$42,$W$31:$W$42)-1,"") -> -0.04617734 | U32: =IFERROR(SUMPRODUCT(N$31:N$42,$W$31:$W$42)/SUMPRODUCT(O$31:O$42,$W$31:$W$42)-1,"") -> -0.064143013 | W32: =IFERROR(_xlfn.XLOOKUP(F32,$F$13:$F$24,$W$13:$W$24),"") -> 1 | Y32: =IFERROR(IF($W32=1,H32,I32*(1+S32)),"") -> 1301 | Z32: =IFERROR(IF($W32=1,K32,L32*(1+T32)),"") -> 6226354.2 | AA32: =IFERROR(IF($W32=1,N32,O32*(1+U32)),"") -> 17903891
D33: =_xlfn.CONCAT(E33," - ",_xlfn.XLOOKUP(F33,$C$13:$C$24,$E$13:$E$24,"")) -> Online - MAR | E33: Online | F33: 3 | G33: 1704 | H33: 1784 | I33: 1674.47 | J33: 7708123.3 | K33: 8472420.8 | L33: 7727928.4 | M33: 22061995 | N33: 24266022 | O33: 22369643 | S33: =IFERROR(SUMPRODUCT(H$31:H$42,$W$31:$W$42)/SUMPRODUCT(I$31:I$42,$W$31:$W$42)-1,"") -> -0.072476897 | T33: =IFERROR(SUMPRODUCT(K$31:K$42,$W$31:$W$42)/SUMPRODUCT(L$31:L$42,$W$31:$W$42)-1,"") -> -0.04617734 | U33: =IFERROR(SUMPRODUCT(N$31:N$42,$W$31:$W$42)/SUMPRODUCT(O$31:O$42,$W$31:$W$42)-1,"") -> -0.064143013 | W33: =IFERROR(_xlfn.XLOOKUP(F33,$F$13:$F$24,$W$13:$W$24),"") -> 1 | Y33: =IFERROR(IF($W33=1,H33,I33*(1+S33)),"") -> 1784 | Z33: =IFERROR(IF($W33=1,K33,L33*(1+T33)),"") -> 8472420.8 | AA33: =IFERROR(IF($W33=1,N33,O33*(1+U33)),"") -> 24266022
D34: =_xlfn.CONCAT(E34," - ",_xlfn.XLOOKUP(F34,$C$13:$C$24,$E$13:$E$24,"")) -> Online - APR | E34: Online | F34: 4 | G34: 1544 | H34: 1591 | I34: 1668.65 | J34: 7121781 | K34: 7750423.7 | L34: 7718325.5 | M34: 20482796 | N34: 22040328 | O34: 22381004 | S34: =IFERROR(SUMPRODUCT(H$31:H$42,$W$31:$W$42)/SUMPRODUCT(I$31:I$42,$W$31:$W$42)-1,"") -> -0.072476897 | T34: =IFERROR(SUMPRODUCT(K$31:K$42,$W$31:$W$42)/SUMPRODUCT(L$31:L$42,$W$31:$W$42)-1,"") -> -0.04617734 | U34: =IFERROR(SUMPRODUCT(N$31:N$42,$W$31:$W$42)/SUMPRODUCT(O$31:O$42,$W$31:$W$42)-1,"") -> -0.064143013 | W34: =IFERROR(_xlfn.XLOOKUP(F34,$F$13:$F$24,$W$13:$W$24),"") -> 1 | Y34: =IFERROR(IF($W34=1,H34,I34*(1+S34)),"") -> 1591 | Z34: =IFERROR(IF($W34=1,K34,L34*(1+T34)),"") -> 7750423.7 | AA34: =IFERROR(IF($W34=1,N34,O34*(1+U34)),"") -> 22040328
D35: =_xlfn.CONCAT(E35," - ",_xlfn.XLOOKUP(F35,$C$13:$C$24,$E$13:$E$24,"")) -> Online - MAY | E35: Online | F35: 5 | G35: 1541 | H35: 1598 | I35: 1701.1 | J35: 6938714.6 | K35: 7577503.9 | L35: 7867807.4 | M35: 19926068 | N35: 21501038 | O35: 22812014 | S35: =IFERROR(SUMPRODUCT(H$31:H$42,$W$31:$W$42)/SUMPRODUCT(I$31:I$42,$W$31:$W$42)-1,"") -> -0.072476897 | T35: =IFERROR(SUMPRODUCT(K$31:K$42,$W$31:$W$42)/SUMPRODUCT(L$31:L$42,$W$31:$W$42)-1,"") -> -0.04617734 | U35: =IFERROR(SUMPRODUCT(N$31:N$42,$W$31:$W$42)/SUMPRODUCT(O$31:O$42,$W$31:$W$42)-1,"") -> -0.064143013 | W35: =IFERROR(_xlfn.XLOOKUP(F35,$F$13:$F$24,$W$13:$W$24),"") -> 1 | Y35: =IFERROR(IF($W35=1,H35,I35*(1+S35)),"") -> 1598 | Z35: =IFERROR(IF($W35=1,K35,L35*(1+T35)),"") -> 7577503.9 | AA35: =IFERROR(IF($W35=1,N35,O35*(1+U35)),"") -> 21501038
D36: =_xlfn.CONCAT(E36," - ",_xlfn.XLOOKUP(F36,$C$13:$C$24,$E$13:$E$24,"")) -> Online - JUN | E36: Online | F36: 6 | G36: 1648 | H36: 1694 | I36: 1715.92 | J36: 7347806.6 | K36: 7928328.7 | L36: 7933258.9 | M36: 20713714 | N36: 22235653 | O36: 22996110 | S36: =IFERROR(SUMPRODUCT(H$31:H$42,$W$31:$W$42)/SUMPRODUCT(I$31:I$42,$W$31:$W$42)-1,"") -> -0.072476897 | T36: =IFERROR(SUMPRODUCT(K$31:K$42,$W$31:$W$42)/SUMPRODUCT(L$31:L$42,$W$31:$W$42)-1,"") -> -0.04617734 | U36: =IFERROR(SUMPRODUCT(N$31:N$42,$W$31:$W$42)/SUMPRODUCT(O$31:O$42,$W$31:$W$42)-1,"") -> -0.064143013 | W36: =IFERROR(_xlfn.XLOOKUP(F36,$F$13:$F$24,$W$13:$W$24),"") -> 1 | Y36: =IFERROR(IF($W36=1,H36,I36*(1+S36)),"") -> 1694 | Z36: =IFERROR(IF($W36=1,K36,L36*(1+T36)),"") -> 7928328.7 | AA36: =IFERROR(IF($W36=1,N36,O36*(1+U36)),"") -> 22235653
D37: =_xlfn.CONCAT(E37," - ",_xlfn.XLOOKUP(F37,$C$13:$C$24,$E$13:$E$24,"")) -> Online - JUL | E37: Online | F37: 7 | G37: 1499 | I37: 1670.63 | J37: 6785638.5 | L37: 7781691 | M37: 19176293 | O37: 22644062 | S37: =IFERROR(SUMPRODUCT(H$31:H$42,$W$31:$W$42)/SUMPRODUCT(I$31:I$42,$W$31:$W$42)-1,"") -> -0.072476897 | T37: =IFERROR(SUMPRODUCT(K$31:K$42,$W$31:$W$42)/SUMPRODUCT(L$31:L$42,$W$31:$W$42)-1,"") -> -0.04617734 | U37: =IFERROR(SUMPRODUCT(N$31:N$42,$W$31:$W$42)/SUMPRODUCT(O$31:O$42,$W$31:$W$42)-1,"") -> -0.064143013 | W37: =IFERROR(_xlfn.XLOOKUP(F37,$F$13:$F$24,$W$13:$W$24),"") -> 0 | Y37: =IFERROR(IF($W37=1,H37,I37*(1+S37)),"") -> 1549.5479 | Z37: =IFERROR(IF($W37=1,K37,L37*(1+T37)),"") -> 7422353.2 | AA37: =IFERROR(IF($W37=1,N37,O37*(1+U37)),"") -> 21191604
D38: =_xlfn.CONCAT(E38," - ",_xlfn.XLOOKUP(F38,$C$13:$C$24,$E$13:$E$24,"")) -> Online - AUG | E38: Online | F38: 8 | G38: 1393 | I38: 1696.2 | J38: 6265641.7 | L38: 7846625.3 | M38: 18268063 | O38: 22794431 | S38: =IFERROR(SUMPRODUCT(H$31:H$42,$W$31:$W$42)/SUMPRODUCT(I$31:I$42,$W$31:$W$42)-1,"") -> -0.072476897 | T38: =IFERROR(SUMPRODUCT(K$31:K$42,$W$31:$W$42)/SUMPRODUCT(L$31:L$42,$W$31:$W$42)-1,"") -> -0.04617734 | U38: =IFERROR(SUMPRODUCT(N$31:N$42,$W$31:$W$42)/SUMPRODUCT(O$31:O$42,$W$31:$W$42)-1,"") -> -0.064143013 | W38: =IFERROR(_xlfn.XLOOKUP(F38,$F$13:$F$24,$W$13:$W$24),"") -> 0 | Y38: =IFERROR(IF($W38=1,H38,I38*(1+S38)),"") -> 1573.2647 | Z38: =IFERROR(IF($W38=1,K38,L38*(1+T38)),"") -> 7484289 | AA38: =IFERROR(IF($W38=1,N38,O38*(1+U38)),"") -> 21332328
D39: =_xlfn.CONCAT(E39," - ",_xlfn.XLOOKUP(F39,$C$13:$C$24,$E$13:$E$24,"")) -> Online - SEP | E39: Online | F39: 9 | G39: 1524 | I39: 1716.61 | J39: 7028101.7 | L39: 7975527.8 | M39: 20230699 | O39: 23213531 | S39: =IFERROR(SUMPRODUCT(H$31:H$42,$W$31:$W$42)/SUMPRODUCT(I$31:I$42,$W$31:$W$42)-1,"") -> -0.072476897 | T39: =IFERROR(SUMPRODUCT(K$31:K$42,$W$31:$W$42)/SUMPRODUCT(L$31:L$42,$W$31:$W$42)-1,"") -> -0.04617734 | U39: =IFERROR(SUMPRODUCT(N$31:N$42,$W$31:$W$42)/SUMPRODUCT(O$31:O$42,$W$31:$W$42)-1,"") -> -0.064143013 | W39: =IFERROR(_xlfn.XLOOKUP(F39,$F$13:$F$24,$W$13:$W$24),"") -> 0 | Y39: =IFERROR(IF($W39=1,H39,I39*(1+S39)),"") -> 1592.1954 | Z39: =IFERROR(IF($W39=1,K39,L39*(1+T39)),"") -> 7607239.2 | AA39: =IFERROR(IF($W39=1,N39,O39*(1+U39)),"") -> 21724545
D40: =_xlfn.CONCAT(E40," - ",_xlfn.XLOOKUP(F40,$C$13:$C$24,$E$13:$E$24,"")) -> Online - OCT | E40: Online | F40: 10 | G40: 1694 | I40: 1811.87 | J40: 7791120.9 | L40: 8455356.3 | M40: 22125290 | O40: 24609713 | S40: =IFERROR(SUMPRODUCT(H$31:H$42,$W$31:$W$42)/SUMPRODUCT(I$31:I$42,$W$31:$W$42)-1,"") -> -0.072476897 | T40: =IFERROR(SUMPRODUCT(K$31:K$42,$W$31:$W$42)/SUMPRODUCT(L$31:L$42,$W$31:$W$42)-1,"") -> -0.04617734 | U40: =IFERROR(SUMPRODUCT(N$31:N$42,$W$31:$W$42)/SUMPRODUCT(O$31:O$42,$W$31:$W$42)-1,"") -> -0.064143013 | W40: =IFERROR(_xlfn.XLOOKUP(F40,$F$13:$F$24,$W$13:$W$24),"") -> 0 | Y40: =IFERROR(IF($W40=1,H40,I40*(1+S40)),"") -> 1680.5513 | Z40: =IFERROR(IF($W40=1,K40,L40*(1+T40)),"") -> 8064910.5 | AA40: =IFERROR(IF($W40=1,N40,O40*(1+U40)),"") -> 23031172
D41: =_xlfn.CONCAT(E41," - ",_xlfn.XLOOKUP(F41,$C$13:$C$24,$E$13:$E$24,"")) -> Online - NOV | E41: Online | F41: 11 | G41: 2365 | I41: 1901.92 | J41: 10791633 | L41: 8867978.9 | M41: 30550026 | O41: 25804337 | S41: =IFERROR(SUMPRODUCT(H$31:H$42,$W$31:$W$42)/SUMPRODUCT(I$31:I$42,$W$31:$W$42)-1,"") -> -0.072476897 | T41: =IFERROR(SUMPRODUCT(K$31:K$42,$W$31:$W$42)/SUMPRODUCT(L$31:L$42,$W$31:$W$42)-1,"") -> -0.04617734 | U41: =IFERROR(SUMPRODUCT(N$31:N$42,$W$31:$W$42)/SUMPRODUCT(O$31:O$42,$W$31:$W$42)-1,"") -> -0.064143013 | W41: =IFERROR(_xlfn.XLOOKUP(F41,$F$13:$F$24,$W$13:$W$24),"") -> 0 | Y41: =IFERROR(IF($W41=1,H41,I41*(1+S41)),"") -> 1764.0747 | Z41: =IFERROR(IF($W41=1,K41,L41*(1+T41)),"") -> 8458479.2 | AA41: =IFERROR(IF($W41=1,N41,O41*(1+U41)),"") -> 24149169
D42: =_xlfn.CONCAT(E42," - ",_xlfn.XLOOKUP(F42,$C$13:$C$24,$E$13:$E$24,"")) -> Online - DEC | E42: Online | F42: 12 | G42: 2432 | I42: 1930.8 | J42: 11259829 | L42: 8981278.8 | M42: 32038559 | O42: 26124054 | S42: =IFERROR(SUMPRODUCT(H$31:H$42,$W$31:$W$42)/SUMPRODUCT(I$31:I$42,$W$31:$W$42)-1,"") -> -0.072476897 | T42: =IFERROR(SUMPRODUCT(K$31:K$42,$W$31:$W$42)/SUMPRODUCT(L$31:L$42,$W$31:$W$42)-1,"") -> -0.04617734 | U42: =IFERROR(SUMPRODUCT(N$31:N$42,$W$31:$W$42)/SUMPRODUCT(O$31:O$42,$W$31:$W$42)-1,"") -> -0.064143013 | W42: =IFERROR(_xlfn.XLOOKUP(F42,$F$13:$F$24,$W$13:$W$24),"") -> 0 | Y42: =IFERROR(IF($W42=1,H42,I42*(1+S42)),"") -> 1790.8616 | Z42: =IFERROR(IF($W42=1,K42,L42*(1+T42)),"") -> 8566547.2 | AA42: =IFERROR(IF($W42=1,N42,O42*(1+U42)),"") -> 24448378
D43: =_xlfn.CONCAT(E43," - ",_xlfn.XLOOKUP(F43,$C$13:$C$24,$E$13:$E$24,"")) -> Retail - JAN | E43: Retail | F43: 1 | G43: 3493 | H43: 3685 | I43: 4261.25 | J43: 15875965 | K43: 17576842 | L43: 19713366 | M43: 47548409 | N43: 53086952 | O43: 60325928 | S43: =IFERROR(SUMPRODUCT(H$43:H$54,$W$43:$W$54)/SUMPRODUCT(I$43:I$54,$W$43:$W$54)-1,"") -> -0.095844818 | T43: =IFERROR(SUMPRODUCT(K$43:K$54,$W$43:$W$54)/SUMPRODUCT(L$43:L$54,$W$43:$W$54)-1,"") -> -0.06590216 | U43: =IFERROR(SUMPRODUCT(N$43:N$54,$W$43:$W$54)/SUMPRODUCT(O$43:O$54,$W$43:$W$54)-1,"") -> -0.08559105 | W43: =IFERROR(_xlfn.XLOOKUP(F43,$F$13:$F$24,$W$13:$W$24),"") -> 1 | Y43: =IFERROR(IF($W43=1,H43,I43*(1+S43)),"") -> 3685 | Z43: =IFERROR(IF($W43=1,K43,L43*(1+T43)),"") -> 17576842 | AA43: =IFERROR(IF($W43=1,N43,O43*(1+U43)),"") -> 53086952
D44: =_xlfn.CONCAT(E44," - ",_xlfn.XLOOKUP(F44,$C$13:$C$24,$E$13:$E$24,"")) -> Retail - FEB | E44: Retail | F44: 2 | G44: 3354 | H44: 3519 | I44: 4232.57 | J44: 15044246 | K44: 16575574 | L44: 19496314 | M44: 44951752 | N44: 49844977 | O44: 59727383 | S44: =IFERROR(SUMPRODUCT(H$43:H$54,$W$43:$W$54)/SUMPRODUCT(I$43:I$54,$W$43:$W$54)-1,"") -> -0.095844818 | T44: =IFERROR(SUMPRODUCT(K$43:K$54,$W$43:$W$54)/SUMPRODUCT(L$43:L$54,$W$43:$W$54)-1,"") -> -0.06590216 | U44: =IFERROR(SUMPRODUCT(N$43:N$54,$W$43:$W$54)/SUMPRODUCT(O$43:O$54,$W$43:$W$54)-1,"") -> -0.08559105 | W44: =IFERROR(_xlfn.XLOOKUP(F44,$F$13:$F$24,$W$13:$W$24),"") -> 1 | Y44: =IFERROR(IF($W44=1,H44,I44*(1+S44)),"") -> 3519 | Z44: =IFERROR(IF($W44=1,K44,L44*(1+T44)),"") -> 16575574 | AA44: =IFERROR(IF($W44=1,N44,O44*(1+U44)),"") -> 49844977
D45: =_xlfn.CONCAT(E45," - ",_xlfn.XLOOKUP(F45,$C$13:$C$24,$E$13:$E$24,"")) -> Retail - MAR | E45: Retail | F45: 3 | G45: 3934 | H45: 4125 | I45: 4372.54 | J45: 18128532 | K45: 19985723 | L45: 20060441 | M45: 54709858 | N45: 60325098 | O45: 61328025 | S45: =IFERROR(SUMPRODUCT(H$43:H$54,$W$43:$W$54)/SUMPRODUCT(I$43:I$54,$W$43:$W$54)-1,"") -> -0.095844818 | T45: =IFERROR(SUMPRODUCT(K$43:K$54,$W$43:$W$54)/SUMPRODUCT(L$43:L$54,$W$43:$W$54)-1,"") -> -0.06590216 | U45: =IFERROR(SUMPRODUCT(N$43:N$54,$W$43:$W$54)/SUMPRODUCT(O$43:O$54,$W$43:$W$54)-1,"") -> -0.08559105 | W45: =IFERROR(_xlfn.XLOOKUP(F45,$F$13:$F$24,$W$13:$W$24),"") -> 1 | Y45: =IFERROR(IF($W45=1,H45,I45*(1+S45)),"") -> 4125 | Z45: =IFERROR(IF($W45=1,K45,L45*(1+T45)),"") -> 19985723 | AA45: =IFERROR(IF($W45=1,N45,O45*(1+U45)),"") -> 60325098
D46: =_xlfn.CONCAT(E46," - ",_xlfn.XLOOKUP(F46,$C$13:$C$24,$E$13:$E$24,"")) -> Retail - APR | E46: Retail | F46: 4 | G46: 3731 | H46: 3934 | I46: 4288.05 | J46: 16804680 | K46: 18599883 | L46: 19826983 | M46: 50625086 | N46: 55633549 | O46: 60804398 | S46: =IFERROR(SUMPRODUCT(H$43:H$54,$W$43:$W$54)/SUMPRODUCT(I$43:I$54,$W$43:$W$54)-1,"") -> -0.095844818 | T46: =IFERROR(SUMPRODUCT(K$43:K$54,$W$43:$W$54)/SUMPRODUCT(L$43:L$54,$W$43:$W$54)-1,"") -> -0.06590216 | U46: =IFERROR(SUMPRODUCT(N$43:N$54,$W$43:$W$54)/SUMPRODUCT(O$43:O$54,$W$43:$W$54)-1,"") -> -0.08559105 | W46: =IFERROR(_xlfn.XLOOKUP(F46,$F$13:$F$24,$W$13:$W$24),"") -> 1 | Y46: =IFERROR(IF($W46=1,H46,I46*(1+S46)),"") -> 3934 | Z46: =IFERROR(IF($W46=1,K46,L46*(1+T46)),"") -> 18599883 | AA46: =IFERROR(IF($W46=1,N46,O46*(1+U46)),"") -> 55633549
D47: =_xlfn.CONCAT(E47," - ",_xlfn.XLOOKUP(F47,$C$13:$C$24,$E$13:$E$24,"")) -> Retail - MAY | E47: Retail | F47: 5 | G47: 4120 | H47: 4336 | I47: 4462.31 | J47: 18493968 | K47: 20413364 | L47: 20633767 | M47: 55517362 | N47: 60527688 | O47: 63233401 | S47: =IFERROR(SUMPRODUCT(H$43:H$54,$W$43:$W$54)/SUMPRODUCT(I$43:I$54,$W$43:$W$54)-1,"") -> -0.095844818 | T47: =IFERROR(SUMPRODUCT(K$43:K$54,$W$43:$W$54)/SUMPRODUCT(L$43:L$54,$W$43:$W$54)-1,"") -> -0.06590216 | U47: =IFERROR(SUMPRODUCT(N$43:N$54,$W$43:$W$54)/SUMPRODUCT(O$43:O$54,$W$43:$W$54)-1,"") -> -0.08559105 | W47: =IFERROR(_xlfn.XLOOKUP(F47,$F$13:$F$24,$W$13:$W$24),"") -> 1 | Y47: =IFERROR(IF($W47=1,H47,I47*(1+S47)),"") -> 4336 | Z47: =IFERROR(IF($W47=1,K47,L47*(1+T47)),"") -> 20413364 | AA47: =IFERROR(IF($W47=1,N47,O47*(1+U47)),"") -> 60527688
D48: =_xlfn.CONCAT(E48," - ",_xlfn.XLOOKUP(F48,$C$13:$C$24,$E$13:$E$24,"")) -> Retail - JUN | E48: Retail | F48: 6 | G48: 3784 | H48: 3992 | I48: 4475.04 | J48: 17369653 | K48: 19257761 | L48: 20608929 | M48: 52267389 | N48: 57472253 | O48: 63005208 | S48: =IFERROR(SUMPRODUCT(H$43:H$54,$W$43:$W$54)/SUMPRODUCT(I$43:I$54,$W$43:$W$54)-1,"") -> -0.095844818 | T48: =IFERROR(SUMPRODUCT(K$43:K$54,$W$43:$W$54)/SUMPRODUCT(L$43:L$54,$W$43:$W$54)-1,"") -> -0.06590216 | U48: =IFERROR(SUMPRODUCT(N$43:N$54,$W$43:$W$54)/SUMPRODUCT(O$43:O$54,$W$43:$W$54)-1,"") -> -0.08559105 | W48: =IFERROR(_xlfn.XLOOKUP(F48,$F$13:$F$24,$W$13:$W$24),"") -> 1 | Y48: =IFERROR(IF($W48=1,H48,I48*(1+S48)),"") -> 3992 | Z48: =IFERROR(IF($W48=1,K48,L48*(1+T48)),"") -> 19257761 | AA48: =IFERROR(IF($W48=1,N48,O48*(1+U48)),"") -> 57472253
D49: =_xlfn.CONCAT(E49," - ",_xlfn.XLOOKUP(F49,$C$13:$C$24,$E$13:$E$24,"")) -> Retail - JUL | E49: Retail | F49: 7 | G49: 3896 | I49: 4326.2 | J49: 17692027 | L49: 20115954 | M49: 52839120 | O49: 61804261 | S49: =IFERROR(SUMPRODUCT(H$43:H$54,$W$43:$W$54)/SUMPRODUCT(I$43:I$54,$W$43:$W$54)-1,"") -> -0.095844818 | T49: =IFERROR(SUMPRODUCT(K$43:K$54,$W$43:$W$54)/SUMPRODUCT(L$43:L$54,$W$43:$W$54)-1,"") -> -0.06590216 | U49: =IFERROR(SUMPRODUCT(N$43:N$54,$W$43:$W$54)/SUMPRODUCT(O$43:O$54,$W$43:$W$54)-1,"") -> -0.08559105 | W49: =IFERROR(_xlfn.XLOOKUP(F49,$F$13:$F$24,$W$13:$W$24),"") -> 0 | Y49: =IFERROR(IF($W49=1,H49,I49*(1+S49)),"") -> 3911.5561 | Z49: =IFERROR(IF($W49=1,K49,L49*(1+T49)),"") -> 18790269 | AA49: =IFERROR(IF($W49=1,N49,O49*(1+U49)),"") -> 56514370
D50: =_xlfn.CONCAT(E50," - ",_xlfn.XLOOKUP(F50,$C$13:$C$24,$E$13:$E$24,"")) -> Retail - AUG | E50: Retail | F50: 8 | G50: 3844 | I50: 4417.75 | J50: 17305150 | L50: 20387052 | M50: 51389102 | O50: 62499530 | S50: =IFERROR(SUMPRODUCT(H$43:H$54,$W$43:$W$54)/SUMPRODUCT(I$43:I$54,$W$43:$W$54)-1,"") -> -0.095844818 | T50: =IFERROR(SUMPRODUCT(K$43:K$54,$W$43:$W$54)/SUMPRODUCT(L$43:L$54,$W$43:$W$54)-1,"") -> -0.06590216 | U50: =IFERROR(SUMPRODUCT(N$43:N$54,$W$43:$W$54)/SUMPRODUCT(O$43:O$54,$W$43:$W$54)-1,"") -> -0.08559105 | W50: =IFERROR(_xlfn.XLOOKUP(F50,$F$13:$F$24,$W$13:$W$24),"") -> 0 | Y50: =IFERROR(IF($W50=1,H50,I50*(1+S50)),"") -> 3994.3316 | Z50: =IFERROR(IF($W50=1,K50,L50*(1+T50)),"") -> 19043501 | AA50: =IFERROR(IF($W50=1,N50,O50*(1+U50)),"") -> 57150130
D51: =_xlfn.CONCAT(E51," - ",_xlfn.XLOOKUP(F51,$C$13:$C$24,$E$13:$E$24,"")) -> Retail - SEP | E51: Retail | F51: 9 | G51: 4135 | I51: 4521.39 | J51: 18675062 | L51: 20907051 | M51: 56071835 | O51: 64163823 | S51: =IFERROR(SUMPRODUCT(H$43:H$54,$W$43:$W$54)/SUMPRODUCT(I$43:I$54,$W$43:$W$54)-1,"") -> -0.095844818 | T51: =IFERROR(SUMPRODUCT(K$43:K$54,$W$43:$W$54)/SUMPRODUCT(L$43:L$54,$W$43:$W$54)-1,"") -> -0.06590216 | U51: =IFERROR(SUMPRODUCT(N$43:N$54,$W$43:$W$54)/SUMPRODUCT(O$43:O$54,$W$43:$W$54)-1,"") -> -0.08559105 | W51: =IFERROR(_xlfn.XLOOKUP(F51,$F$13:$F$24,$W$13:$W$24),"") -> 0 | Y51: =IFERROR(IF($W51=1,H51,I51*(1+S51)),"") -> 4088.0382 | Z51: =IFERROR(IF($W51=1,K51,L51*(1+T51)),"") -> 19529231 | AA51: =IFERROR(IF($W51=1,N51,O51*(1+U51)),"") -> 58671974
D52: =_xlfn.CONCAT(E52," - ",_xlfn.XLOOKUP(F52,$C$13:$C$24,$E$13:$E$24,"")) -> Retail - OCT | E52: Retail | F52: 10 | G52: 4519 | I52: 4647.5 | J52: 20590999 | L52: 21649770 | M52: 61603033 | O52: 66364239 | S52: =IFERROR(SUMPRODUCT(H$43:H$54,$W$43:$W$54)/SUMPRODUCT(I$43:I$54,$W$43:$W$54)-1,"") -> -0.095844818 | T52: =IFERROR(SUMPRODUCT(K$43:K$54,$W$43:$W$54)/SUMPRODUCT(L$43:L$54,$W$43:$W$54)-1,"") -> -0.06590216 | U52: =IFERROR(SUMPRODUCT(N$43:N$54,$W$43:$W$54)/SUMPRODUCT(O$43:O$54,$W$43:$W$54)-1,"") -> -0.08559105 | W52: =IFERROR(_xlfn.XLOOKUP(F52,$F$13:$F$24,$W$13:$W$24),"") -> 0 | Y52: =IFERROR(IF($W52=1,H52,I52*(1+S52)),"") -> 4202.0612 | Z52: =IFERROR(IF($W52=1,K52,L52*(1+T52)),"") -> 20223003 | AA52: =IFERROR(IF($W52=1,N52,O52*(1+U52)),"") -> 60684054
D53: =_xlfn.CONCAT(E53," - ",_xlfn.XLOOKUP(F53,$C$13:$C$24,$E$13:$E$24,"")) -> Retail - NOV | E53: Retail | F53: 11 | G53: 5518 | I53: 4956.25 | J53: 25070407 | L53: 23010494 | M53: 75146864 | O53: 70475241 | S53: =IFERROR(SUMPRODUCT(H$43:H$54,$W$43:$W$54)/SUMPRODUCT(I$43:I$54,$W$43:$W$54)-1,"") -> -0.095844818 | T53: =IFERROR(SUMPRODUCT(K$43:K$54,$W$43:$W$54)/SUMPRODUCT(L$43:L$54,$W$43:$W$54)-1,"") -> -0.06590216 | U53: =IFERROR(SUMPRODUCT(N$43:N$54,$W$43:$W$54)/SUMPRODUCT(O$43:O$54,$W$43:$W$54)-1,"") -> -0.08559105 | W53: =IFERROR(_xlfn.XLOOKUP(F53,$F$13:$F$24,$W$13:$W$24),"") -> 0 | Y53: =IFERROR(IF($W53=1,H53,I53*(1+S53)),"") -> 4481.2191 | Z53: =IFERROR(IF($W53=1,K53,L53*(1+T53)),"") -> 21494052 | AA53: =IFERROR(IF($W53=1,N53,O53*(1+U53)),"") -> 64443192
D54: =_xlfn.CONCAT(E54," - ",_xlfn.XLOOKUP(F54,$C$13:$C$24,$E$13:$E$24,"")) -> Retail - DEC | E54: Retail | F54: 12 | G54: 6762 | I54: 5000.49 | J54: 30695325 | L54: 23160940 | M54: 91718718 | O54: 70948538 | S54: =IFERROR(SUMPRODUCT(H$43:H$54,$W$43:$W$54)/SUMPRODUCT(I$43:I$54,$W$43:$W$54)-1,"") -> -0.095844818 | T54: =IFERROR(SUMPRODUCT(K$43:K$54,$W$43:$W$54)/SUMPRODUCT(L$43:L$54,$W$43:$W$54)-1,"") -> -0.06590216 | U54: =IFERROR(SUMPRODUCT(N$43:N$54,$W$43:$W$54)/SUMPRODUCT(O$43:O$54,$W$43:$W$54)-1,"") -> -0.08559105 | W54: =IFERROR(_xlfn.XLOOKUP(F54,$F$13:$F$24,$W$13:$W$24),"") -> 0 | Y54: =IFERROR(IF($W54=1,H54,I54*(1+S54)),"") -> 4521.2189 | Z54: =IFERROR(IF($W54=1,K54,L54*(1+T54)),"") -> 21634584 | AA54: =IFERROR(IF($W54=1,N54,O54*(1+U54)),"") -> 64875978
E55: Grand Total | G55: 70972 | H55: 32888 | I55: 74712.84 | J55: 3.2230053e+08 | K55: 1.5664026e+08 | L55: 3.4585199e+08 | M55: 9.5278736e+08 | N55: 4.6270906e+08 | O55: 1.0443122e+09 | Y55: =IFERROR(SUM(Y31:Y54),"") -> 68036.921 | Z55: =IFERROR(SUM(Z31:Z54),"") -> 3.2495872e+08 | AA55: =IFERROR(SUM(AA31:AA54),"") -> 9.6092595e+08
D56: =E56 -> Online | E56: Online | G56: =SUMIF($E$31:$E$54,$E56,G$31:G$54) -> 19882 | H56: =SUMIF($E$31:$E$54,$E56,H$31:H$54) -> 9297 | I56: =SUMIF($E$31:$E$54,$E56,I$31:I$54) -> 20751.5 | J56: =SUMIF($E$31:$E$54,$E56,J$31:J$54) -> 90554517 | K56: =SUMIF($E$31:$E$54,$E56,K$31:K$54) -> 44231114 | L56: =SUMIF($E$31:$E$54,$E56,L$31:L$54) -> 96280930 | M56: =SUMIF($E$31:$E$54,$E56,M$31:M$54) -> 2.5839883e+08 | N56: =SUMIF($E$31:$E$54,$E56,N$31:N$54) -> 1.2581854e+08 | O56: =SUMIF($E$31:$E$54,$E56,O$31:O$54) -> 279632185 | Y56: =IFERROR(SUMIF($E$31:$E$54,$E56,Y$31:Y$54),"") -> 19247.496 | Z56: =IFERROR(SUMIF($E$31:$E$54,$E56,Z$31:Z$54),"") -> 91834932 | AA56: =IFERROR(SUMIF($E$31:$E$54,$E56,AA$31:AA$54),"") -> 2.6169573e+08
D57: =E57 -> Retail | E57: Retail | G57: =SUMIF($E$31:$E$54,$E57,G$31:G$54) -> 51090 | H57: =SUMIF($E$31:$E$54,$E57,H$31:H$54) -> 23591 | I57: =SUMIF($E$31:$E$54,$E57,I$31:I$54) -> 53961.34 | J57: =SUMIF($E$31:$E$54,$E57,J$31:J$54) -> 2.3174601e+08 | K57: =SUMIF($E$31:$E$54,$E57,K$31:K$54) -> 1.1240915e+08 | L57: =SUMIF($E$31:$E$54,$E57,L$31:L$54) -> 2.4957106e+08 | M57: =SUMIF($E$31:$E$54,$E57,M$31:M$54) -> 6.9438853e+08 | N57: =SUMIF($E$31:$E$54,$E57,N$31:N$54) -> 3.3689052e+08 | O57: =SUMIF($E$31:$E$54,$E57,O$31:O$54) -> 7.6467998e+08 | Y57: =IFERROR(SUMIF($E$31:$E$54,$E57,Y$31:Y$54),"") -> 48789.425 | Z57: =IFERROR(SUMIF($E$31:$E$54,$E57,Z$31:Z$54),"") -> 2.3312379e+08 | AA57: =IFERROR(SUMIF($E$31:$E$54,$E57,AA$31:AA$54),"") -> 6.9923021e+08
E60: TYPE
G61: Values | H61: scenario
G62: Sum of units | J62: Sum of cogs | M62: Sum of revenue | S62: Sum of units | T62: Sum of cogs | U62: Sum of revenue | W62: Actuals | Y62: Forecast
E63: channel_type | F63: month | G63: 2025 Actuals | H63: 2026 Actuals | I63: 2026 Budget | J63: 2025 Actuals | K63: 2026 Actuals | L63: 2026 Budget | M63: 2025 Actuals | N63: 2026 Actuals | O63: 2026 Budget | S63: vs LY | T63: vs LY | U63: vs LY | W63: Multiplier | Y63: Units | Z63: Cogs | AA63: Revenue
D64: =_xlfn.CONCAT(E64," - ",_xlfn.XLOOKUP(F64,$C$13:$C$24,$E$13:$E$24,"")) -> Boutique - JAN | E64: Boutique | F64: 1 | G64: 817 | H64: 942 | I64: 1103.75 | J64: 3745173 | K64: 4507909.5 | L64: 5097746.1 | M64: 15394471 | N64: 18523464 | O64: 21111266 | S64: =IFERROR(SUMPRODUCT(H$64:H$75,$W$64:$W$75)/SUMPRODUCT(I$64:I$75,$W$64:$W$75)-1,"") -> -0.074525659 | T64: =IFERROR(SUMPRODUCT(K$64:K$75,$W$64:$W$75)/SUMPRODUCT(L$64:L$75,$W$64:$W$75)-1,"") -> -0.04126351 | U64: =IFERROR(SUMPRODUCT(N$64:N$75,$W$64:$W$75)/SUMPRODUCT(O$64:O$75,$W$64:$W$75)-1,"") -> -0.059486213 | W64: =IFERROR(_xlfn.XLOOKUP(F64,$F$13:$F$24,$W$13:$W$24),"") -> 1 | Y64: =IFERROR(IF($W64=1,H64,I64*(1+S64)),"") -> 942 | Z64: =IFERROR(IF($W64=1,K64,L64*(1+T64)),"") -> 4507909.5 | AA64: =IFERROR(IF($W64=1,N64,O64*(1+U64)),"") -> 18523464
D65: =_xlfn.CONCAT(E65," - ",_xlfn.XLOOKUP(F65,$C$13:$C$24,$E$13:$E$24,"")) -> Boutique - FEB | E65: Boutique | F65: 2 | G65: 800 | H65: 903 | I65: 1112.54 | J65: 3564359.2 | K65: 4216923.3 | L65: 5138279.2 | M65: 14599967 | N65: 17268734 | O65: 21277833 | S65: =IFERROR(SUMPRODUCT(H$64:H$75,$W$64:$W$75)/SUMPRODUCT(I$64:I$75,$W$64:$W$75)-1,"") -> -0.074525659 | T65: =IFERROR(SUMPRODUCT(K$64:K$75,$W$64:$W$75)/SUMPRODUCT(L$64:L$75,$W$64:$W$75)-1,"") -> -0.04126351 | U65: =IFERROR(SUMPRODUCT(N$64:N$75,$W$64:$W$75)/SUMPRODUCT(O$64:O$75,$W$64:$W$75)-1,"") -> -0.059486213 | W65: =IFERROR(_xlfn.XLOOKUP(F65,$F$13:$F$24,$W$13:$W$24),"") -> 1 | Y65: =IFERROR(IF($W65=1,H65,I65*(1+S65)),"") -> 903 | Z65: =IFERROR(IF($W65=1,K65,L65*(1+T65)),"") -> 4216923.3 | AA65: =IFERROR(IF($W65=1,N65,O65*(1+U65)),"") -> 17268734
D66: =_xlfn.CONCAT(E66," - ",_xlfn.XLOOKUP(F66,$C$13:$C$24,$E$13:$E$24,"")) -> Boutique - MAR | E66: Boutique | F66: 3 | G66: 984 | H66: 1121 | I66: 1129.02 | J66: 4509779 | K66: 5415470 | L66: 5225691.8 | M66: 18534339 | N66: 22083621 | O66: 21673858 | S66: =IFERROR(SUMPRODUCT(H$64:H$75,$W$64:$W$75)/SUMPRODUCT(I$64:I$75,$W$64:$W$75)-1,"") -> -0.074525659 | T66: =IFERROR(SUMPRODUCT(K$64:K$75,$W$64:$W$75)/SUMPRODUCT(L$64:L$75,$W$64:$W$75)-1,"") -> -0.04126351 | U66: =IFERROR(SUMPRODUCT(N$64:N$75,$W$64:$W$75)/SUMPRODUCT(O$64:O$75,$W$64:$W$75)-1,"") -> -0.059486213 | W66: =IFERROR(_xlfn.XLOOKUP(F66,$F$13:$F$24,$W$13:$W$24),"") -> 1 | Y66: =IFERROR(IF($W66=1,H66,I66*(1+S66)),"") -> 1121 | Z66: =IFERROR(IF($W66=1,K66,L66*(1+T66)),"") -> 5415470 | AA66: =IFERROR(IF($W66=1,N66,O66*(1+U66)),"") -> 22083621
D67: =_xlfn.CONCAT(E67," - ",_xlfn.XLOOKUP(F67,$C$13:$C$24,$E$13:$E$24,"")) -> Boutique - APR | E67: Boutique | F67: 4 | G67: 953 | H67: 1095 | I67: 1126.35 | J67: 4342130.8 | K67: 5221563.1 | L67: 5218285.2 | M67: 17850387 | N67: 21179108 | O67: 21642805 | S67: =IFERROR(SUMPRODUCT(H$64:H$75,$W$64:$W$75)/SUMPRODUCT(I$64:I$75,$W$64:$W$75)-1,"") -> -0.074525659 | T67: =IFERROR(SUMPRODUCT(K$64:K$75,$W$64:$W$75)/SUMPRODUCT(L$64:L$75,$W$64:$W$75)-1,"") -> -0.04126351 | U67: =IFERROR(SUMPRODUCT(N$64:N$75,$W$64:$W$75)/SUMPRODUCT(O$64:O$75,$W$64:$W$75)-1,"") -> -0.059486213 | W67: =IFERROR(_xlfn.XLOOKUP(F67,$F$13:$F$24,$W$13:$W$24),"") -> 1 | Y67: =IFERROR(IF($W67=1,H67,I67*(1+S67)),"") -> 1095 | Z67: =IFERROR(IF($W67=1,K67,L67*(1+T67)),"") -> 5221563.1 | AA67: =IFERROR(IF($W67=1,N67,O67*(1+U67)),"") -> 21179108
D68: =_xlfn.CONCAT(E68," - ",_xlfn.XLOOKUP(F68,$C$13:$C$24,$E$13:$E$24,"")) -> Boutique - MAY | E68: Boutique | F68: 5 | G68: 1015 | H68: 1176 | I68: 1167.3 | J68: 4691765.1 | K68: 5739560.9 | L68: 5408958.6 | M68: 19307382 | N68: 23141212 | O68: 22421323 | S68: =IFERROR(SUMPRODUCT(H$64:H$75,$W$64:$W$75)/SUMPRODUCT(I$64:I$75,$W$64:$W$75)-1,"") -> -0.074525659 | T68: =IFERROR(SUMPRODUCT(K$64:K$75,$W$64:$W$75)/SUMPRODUCT(L$64:L$75,$W$64:$W$75)-1,"") -> -0.04126351 | U68: =IFERROR(SUMPRODUCT(N$64:N$75,$W$64:$W$75)/SUMPRODUCT(O$64:O$75,$W$64:$W$75)-1,"") -> -0.059486213 | W68: =IFERROR(_xlfn.XLOOKUP(F68,$F$13:$F$24,$W$13:$W$24),"") -> 1 | Y68: =IFERROR(IF($W68=1,H68,I68*(1+S68)),"") -> 1176 | Z68: =IFERROR(IF($W68=1,K68,L68*(1+T68)),"") -> 5739560.9 | AA68: =IFERROR(IF($W68=1,N68,O68*(1+U68)),"") -> 23141212
D69: =_xlfn.CONCAT(E69," - ",_xlfn.XLOOKUP(F69,$C$13:$C$24,$E$13:$E$24,"")) -> Boutique - JUN | E69: Boutique | F69: 6 | G69: 897 | H69: 1044 | I69: 1147.83 | J69: 4086208 | K69: 5013162.8 | L69: 5321744.6 | M69: 16773256 | N69: 20251165 | O69: 22064843 | S69: =IFERROR(SUMPRODUCT(H$64:H$75,$W$64:$W$75)/SUMPRODUCT(I$64:I$75,$W$64:$W$75)-1,"") -> -0.074525659 | T69: =IFERROR(SUMPRODUCT(K$64:K$75,$W$64:$W$75)/SUMPRODUCT(L$64:L$75,$W$64:$W$75)-1,"") -> -0.04126351 | U69: =IFERROR(SUMPRODUCT(N$64:N$75,$W$64:$W$75)/SUMPRODUCT(O$64:O$75,$W$64:$W$75)-1,"") -> -0.059486213 | W69: =IFERROR(_xlfn.XLOOKUP(F69,$F$13:$F$24,$W$13:$W$24),"") -> 1 | Y69: =IFERROR(IF($W69=1,H69,I69*(1+S69)),"") -> 1044 | Z69: =IFERROR(IF($W69=1,K69,L69*(1+T69)),"") -> 5013162.8 | AA69: =IFERROR(IF($W69=1,N69,O69*(1+U69)),"") -> 20251165
D70: =_xlfn.CONCAT(E70," - ",_xlfn.XLOOKUP(F70,$C$13:$C$24,$E$13:$E$24,"")) -> Boutique - JUL | E70: Boutique | F70: 7 | G70: 889 | I70: 1153.63 | J70: 4026732.6 | L70: 5350142.3 | M70: 16501416 | O70: 22197469 | S70: =IFERROR(SUMPRODUCT(H$64:H$75,$W$64:$W$75)/SUMPRODUCT(I$64:I$75,$W$64:$W$75)-1,"") -> -0.074525659 | T70: =IFERROR(SUMPRODUCT(K$64:K$75,$W$64:$W$75)/SUMPRODUCT(L$64:L$75,$W$64:$W$75)-1,"") -> -0.04126351 | U70: =IFERROR(SUMPRODUCT(N$64:N$75,$W$64:$W$75)/SUMPRODUCT(O$64:O$75,$W$64:$W$75)-1,"") -> -0.059486213 | W70: =IFERROR(_xlfn.XLOOKUP(F70,$F$13:$F$24,$W$13:$W$24),"") -> 0 | Y70: =IFERROR(IF($W70=1,H70,I70*(1+S70)),"") -> 1067.655 | Z70: =IFERROR(IF($W70=1,K70,L70*(1+T70)),"") -> 5129376.6 | AA70: =IFERROR(IF($W70=1,N70,O70*(1+U70)),"") -> 20877025
D71: =_xlfn.CONCAT(E71," - ",_xlfn.XLOOKUP(F71,$C$13:$C$24,$E$13:$E$24,"")) -> Boutique - AUG | E71: Boutique | F71: 8 | G71: 915 | I71: 1154.58 | J71: 4170840.7 | L71: 5354470.6 | M71: 17103811 | O71: 22218509 | S71: =IFERROR(SUMPRODUCT(H$64:H$75,$W$64:$W$75)/SUMPRODUCT(I$64:I$75,$W$64:$W$75)-1,"") -> -0.074525659 | T71: =IFERROR(SUMPRODUCT(K$64:K$75,$W$64:$W$75)/SUMPRODUCT(L$64:L$75,$W$64:$W$75)-1,"") -> -0.04126351 | U71: =IFERROR(SUMPRODUCT(N$64:N$75,$W$64:$W$75)/SUMPRODUCT(O$64:O$75,$W$64:$W$75)-1,"") -> -0.059486213 | W71: =IFERROR(_xlfn.XLOOKUP(F71,$F$13:$F$24,$W$13:$W$24),"") -> 0 | Y71: =IFERROR(IF($W71=1,H71,I71*(1+S71)),"") -> 1068.5342 | Z71: =IFERROR(IF($W71=1,K71,L71*(1+T71)),"") -> 5133526.3 | AA71: =IFERROR(IF($W71=1,N71,O71*(1+U71)),"") -> 20896814
D72: =_xlfn.CONCAT(E72," - ",_xlfn.XLOOKUP(F72,$C$13:$C$24,$E$13:$E$24,"")) -> Boutique - SEP | E72: Boutique | F72: 9 | G72: 1007 | I72: 1199.44 | J72: 4634475.9 | L72: 5561093.2 | M72: 19004314 | O72: 23051409 | S72: =IFERROR(SUMPRODUCT(H$64:H$75,$W$64:$W$75)/SUMPRODUCT(I$64:I$75,$W$64:$W$75)-1,"") -> -0.074525659 | T72: =IFERROR(SUMPRODUCT(K$64:K$75,$W$64:$W$75)/SUMPRODUCT(L$64:L$75,$W$64:$W$75)-1,"") -> -0.04126351 | U72: =IFERROR(SUMPRODUCT(N$64:N$75,$W$64:$W$75)/SUMPRODUCT(O$64:O$75,$W$64:$W$75)-1,"") -> -0.059486213 | W72: =IFERROR(_xlfn.XLOOKUP(F72,$F$13:$F$24,$W$13:$W$24),"") -> 0 | Y72: =IFERROR(IF($W72=1,H72,I72*(1+S72)),"") -> 1110.0509 | Z72: =IFERROR(IF($W72=1,K72,L72*(1+T72)),"") -> 5331623 | AA72: =IFERROR(IF($W72=1,N72,O72*(1+U72)),"") -> 21680168
D73: =_xlfn.CONCAT(E73," - ",_xlfn.XLOOKUP(F73,$C$13:$C$24,$E$13:$E$24,"")) -> Boutique - OCT | E73: Boutique | F73: 10 | G73: 1029 | I73: 1206.67 | J73: 4669616.7 | L73: 5585665.5 | M73: 19092309 | O73: 23154524 | S73: =IFERROR(SUMPRODUCT(H$64:H$75,$W$64:$W$75)/SUMPRODUCT(I$64:I$75,$W$64:$W$75)-1,"") -> -0.074525659 | T73: =IFERROR(SUMPRODUCT(K$64:K$75,$W$64:$W$75)/SUMPRODUCT(L$64:L$75,$W$64:$W$75)-1,"") -> -0.04126351 | U73: =IFERROR(SUMPRODUCT(N$64:N$75,$W$64:$W$75)/SUMPRODUCT(O$64:O$75,$W$64:$W$75)-1,"") -> -0.059486213 | W73: =IFERROR(_xlfn.XLOOKUP(F73,$F$13:$F$24,$W$13:$W$24),"") -> 0 | Y73: =IFERROR(IF($W73=1,H73,I73*(1+S73)),"") -> 1116.7421 | Z73: =IFERROR(IF($W73=1,K73,L73*(1+T73)),"") -> 5355181.4 | AA73: =IFERROR(IF($W73=1,N73,O73*(1+U73)),"") -> 21777149
D74: =_xlfn.CONCAT(E74," - ",_xlfn.XLOOKUP(F74,$C$13:$C$24,$E$13:$E$24,"")) -> Boutique - NOV | E74: Boutique | F74: 11 | G74: 1317 | I74: 1263.25 | J74: 5945340.7 | L74: 5858837.5 | M74: 24342931 | O74: 24301659 | S74: =IFERROR(SUMPRODUCT(H$64:H$75,$W$64:$W$75)/SUMPRODUCT(I$64:I$75,$W$64:$W$75)-1,"") -> -0.074525659 | T74: =IFERROR(SUMPRODUCT(K$64:K$75,$W$64:$W$75)/SUMPRODUCT(L$64:L$75,$W$64:$W$75)-1,"") -> -0.04126351 | U74: =IFERROR(SUMPRODUCT(N$64:N$75,$W$64:$W$75)/SUMPRODUCT(O$64:O$75,$W$64:$W$75)-1,"") -> -0.059486213 | W74: =IFERROR(_xlfn.XLOOKUP(F74,$F$13:$F$24,$W$13:$W$24),"") -> 0 | Y74: =IFERROR(IF($W74=1,H74,I74*(1+S74)),"") -> 1169.1055 | Z74: =IFERROR(IF($W74=1,K74,L74*(1+T74)),"") -> 5617081.3 | AA74: =IFERROR(IF($W74=1,N74,O74*(1+U74)),"") -> 22856046
D75: =_xlfn.CONCAT(E75," - ",_xlfn.XLOOKUP(F75,$C$13:$C$24,$E$13:$E$24,"")) -> Boutique - DEC | E75: Boutique | F75: 12 | G75: 1534 | I75: 1283.84 | J75: 7018182.2 | L75: 5959065.5 | M75: 28887503 | O75: 24717392 | S75: =IFERROR(SUMPRODUCT(H$64:H$75,$W$64:$W$75)/SUMPRODUCT(I$64:I$75,$W$64:$W$75)-1,"") -> -0.074525659 | T75: =IFERROR(SUMPRODUCT(K$64:K$75,$W$64:$W$75)/SUMPRODUCT(L$64:L$75,$W$64:$W$75)-1,"") -> -0.04126351 | U75: =IFERROR(SUMPRODUCT(N$64:N$75,$W$64:$W$75)/SUMPRODUCT(O$64:O$75,$W$64:$W$75)-1,"") -> -0.059486213 | W75: =IFERROR(_xlfn.XLOOKUP(F75,$F$13:$F$24,$W$13:$W$24),"") -> 0 | Y75: =IFERROR(IF($W75=1,H75,I75*(1+S75)),"") -> 1188.161 | Z75: =IFERROR(IF($W75=1,K75,L75*(1+T75)),"") -> 5713173.6 | AA75: =IFERROR(IF($W75=1,N75,O75*(1+U75)),"") -> 23247048
D76: =_xlfn.CONCAT(E76," - ",_xlfn.XLOOKUP(F76,$C$13:$C$24,$E$13:$E$24,"")) -> Wholesale - JAN | E76: Wholesale | F76: 1 | G76: 3957 | H76: 4072 | I76: 4795.49 | J76: 17902735 | K76: 19345015 | L76: 22220728 | M76: 48502020 | N76: 52435095 | O76: 61271179 | S76: =IFERROR(SUMPRODUCT(H$76:H$87,$W$76:$W$87)/SUMPRODUCT(I$76:I$87,$W$76:$W$87)-1,"") -> -0.092791843 | T76: =IFERROR(SUMPRODUCT(K$76:K$87,$W$76:$W$87)/SUMPRODUCT(L$76:L$87,$W$76:$W$87)-1,"") -> -0.064861734 | U76: =IFERROR(SUMPRODUCT(N$76:N$87,$W$76:$W$87)/SUMPRODUCT(O$76:O$87,$W$76:$W$87)-1,"") -> -0.086973277 | W76: =IFERROR(_xlfn.XLOOKUP(F76,$F$13:$F$24,$W$13:$W$24),"") -> 1 | Y76: =IFERROR(IF($W76=1,H76,I76*(1+S76)),"") -> 4072 | Z76: =IFERROR(IF($W76=1,K76,L76*(1+T76)),"") -> 19345015 | AA76: =IFERROR(IF($W76=1,N76,O76*(1+U76)),"") -> 52435095
D77: =_xlfn.CONCAT(E77," - ",_xlfn.XLOOKUP(F77,$C$13:$C$24,$E$13:$E$24,"")) -> Wholesale - FEB | E77: Wholesale | F77: 2 | G77: 3811 | H77: 3917 | I77: 4745.37 | J77: 17224071 | K77: 18585005 | L77: 21878077 | M77: 46829027 | N77: 50480135 | O77: 60276319 | S77: =IFERROR(SUMPRODUCT(H$76:H$87,$W$76:$W$87)/SUMPRODUCT(I$76:I$87,$W$76:$W$87)-1,"") -> -0.092791843 | T77: =IFERROR(SUMPRODUCT(K$76:K$87,$W$76:$W$87)/SUMPRODUCT(L$76:L$87,$W$76:$W$87)-1,"") -> -0.064861734 | U77: =IFERROR(SUMPRODUCT(N$76:N$87,$W$76:$W$87)/SUMPRODUCT(O$76:O$87,$W$76:$W$87)-1,"") -> -0.086973277 | W77: =IFERROR(_xlfn.XLOOKUP(F77,$F$13:$F$24,$W$13:$W$24),"") -> 1 | Y77: =IFERROR(IF($W77=1,H77,I77*(1+S77)),"") -> 3917 | Z77: =IFERROR(IF($W77=1,K77,L77*(1+T77)),"") -> 18585005 | AA77: =IFERROR(IF($W77=1,N77,O77*(1+U77)),"") -> 50480135
D78: =_xlfn.CONCAT(E78," - ",_xlfn.XLOOKUP(F78,$C$13:$C$24,$E$13:$E$24,"")) -> Wholesale - MAR | E78: Wholesale | F78: 3 | G78: 4654 | H78: 4788 | I78: 4917.99 | J78: 21326876 | K78: 23042674 | L78: 22562678 | M78: 58237514 | N78: 62507499 | O78: 62023811 | S78: =IFERROR(SUMPRODUCT(H$76:H$87,$W$76:$W$87)/SUMPRODUCT(I$76:I$87,$W$76:$W$87)-1,"") -> -0.092791843 | T78: =IFERROR(SUMPRODUCT(K$76:K$87,$W$76:$W$87)/SUMPRODUCT(L$76:L$87,$W$76:$W$87)-1,"") -> -0.064861734 | U78: =IFERROR(SUMPRODUCT(N$76:N$87,$W$76:$W$87)/SUMPRODUCT(O$76:O$87,$W$76:$W$87)-1,"") -> -0.086973277 | W78: =IFERROR(_xlfn.XLOOKUP(F78,$F$13:$F$24,$W$13:$W$24),"") -> 1 | Y78: =IFERROR(IF($W78=1,H78,I78*(1+S78)),"") -> 4788 | Z78: =IFERROR(IF($W78=1,K78,L78*(1+T78)),"") -> 23042674 | AA78: =IFERROR(IF($W78=1,N78,O78*(1+U78)),"") -> 62507499
D79: =_xlfn.CONCAT(E79," - ",_xlfn.XLOOKUP(F79,$C$13:$C$24,$E$13:$E$24,"")) -> Wholesale - APR | E79: Wholesale | F79: 4 | G79: 4322 | H79: 4430 | I79: 4830.35 | J79: 19584330 | K79: 21128744 | L79: 22327024 | M79: 53257495 | N79: 56494769 | O79: 61542597 | S79: =IFERROR(SUMPRODUCT(H$76:H$87,$W$76:$W$87)/SUMPRODUCT(I$76:I$87,$W$76:$W$87)-1,"") -> -0.092791843 | T79: =IFERROR(SUMPRODUCT(K$76:K$87,$W$76:$W$87)/SUMPRODUCT(L$76:L$87,$W$76:$W$87)-1,"") -> -0.064861734 | U79: =IFERROR(SUMPRODUCT(N$76:N$87,$W$76:$W$87)/SUMPRODUCT(O$76:O$87,$W$76:$W$87)-1,"") -> -0.086973277 | W79: =IFERROR(_xlfn.XLOOKUP(F79,$F$13:$F$24,$W$13:$W$24),"") -> 1 | Y79: =IFERROR(IF($W79=1,H79,I79*(1+S79)),"") -> 4430 | Z79: =IFERROR(IF($W79=1,K79,L79*(1+T79)),"") -> 21128744 | AA79: =IFERROR(IF($W79=1,N79,O79*(1+U79)),"") -> 56494769
D80: =_xlfn.CONCAT(E80," - ",_xlfn.XLOOKUP(F80,$C$13:$C$24,$E$13:$E$24,"")) -> Wholesale - MAY | E80: Wholesale | F80: 5 | G80: 4646 | H80: 4758 | I80: 4996.11 | J80: 20740917 | K80: 22251307 | L80: 23092615 | M80: 56136048 | N80: 58887513 | O80: 63624093 | S80: =IFERROR(SUMPRODUCT(H$76:H$87,$W$76:$W$87)/SUMPRODUCT(I$76:I$87,$W$76:$W$87)-1,"") -> -0.092791843 | T80: =IFERROR(SUMPRODUCT(K$76:K$87,$W$76:$W$87)/SUMPRODUCT(L$76:L$87,$W$76:$W$87)-1,"") -> -0.064861734 | U80: =IFERROR(SUMPRODUCT(N$76:N$87,$W$76:$W$87)/SUMPRODUCT(O$76:O$87,$W$76:$W$87)-1,"") -> -0.086973277 | W80: =IFERROR(_xlfn.XLOOKUP(F80,$F$13:$F$24,$W$13:$W$24),"") -> 1 | Y80: =IFERROR(IF($W80=1,H80,I80*(1+S80)),"") -> 4758 | Z80: =IFERROR(IF($W80=1,K80,L80*(1+T80)),"") -> 22251307 | AA80: =IFERROR(IF($W80=1,N80,O80*(1+U80)),"") -> 58887513
D81: =_xlfn.CONCAT(E81," - ",_xlfn.XLOOKUP(F81,$C$13:$C$24,$E$13:$E$24,"")) -> Wholesale - JUN | E81: Wholesale | F81: 6 | G81: 4535 | H81: 4642 | I81: 5043.13 | J81: 20631251 | K81: 22172927 | L81: 23220443 | M81: 56207847 | N81: 59456740 | O81: 63936474 | S81: =IFERROR(SUMPRODUCT(H$76:H$87,$W$76:$W$87)/SUMPRODUCT(I$76:I$87,$W$76:$W$87)-1,"") -> -0.092791843 | T81: =IFERROR(SUMPRODUCT(K$76:K$87,$W$76:$W$87)/SUMPRODUCT(L$76:L$87,$W$76:$W$87)-1,"") -> -0.064861734 | U81: =IFERROR(SUMPRODUCT(N$76:N$87,$W$76:$W$87)/SUMPRODUCT(O$76:O$87,$W$76:$W$87)-1,"") -> -0.086973277 | W81: =IFERROR(_xlfn.XLOOKUP(F81,$F$13:$F$24,$W$13:$W$24),"") -> 1 | Y81: =IFERROR(IF($W81=1,H81,I81*(1+S81)),"") -> 4642 | Z81: =IFERROR(IF($W81=1,K81,L81*(1+T81)),"") -> 22172927 | AA81: =IFERROR(IF($W81=1,N81,O81*(1+U81)),"") -> 59456740
D82: =_xlfn.CONCAT(E82," - ",_xlfn.XLOOKUP(F82,$C$13:$C$24,$E$13:$E$24,"")) -> Wholesale - JUL | E82: Wholesale | F82: 7 | G82: 4506 | I82: 4843.2 | J82: 20450933 | L82: 22547503 | M82: 55513997 | O82: 62250855 | S82: =IFERROR(SUMPRODUCT(H$76:H$87,$W$76:$W$87)/SUMPRODUCT(I$76:I$87,$W$76:$W$87)-1,"") -> -0.092791843 | T82: =IFERROR(SUMPRODUCT(K$76:K$87,$W$76:$W$87)/SUMPRODUCT(L$76:L$87,$W$76:$W$87)-1,"") -> -0.064861734 | U82: =IFERROR(SUMPRODUCT(N$76:N$87,$W$76:$W$87)/SUMPRODUCT(O$76:O$87,$W$76:$W$87)-1,"") -> -0.086973277 | W82: =IFERROR(_xlfn.XLOOKUP(F82,$F$13:$F$24,$W$13:$W$24),"") -> 0 | Y82: =IFERROR(IF($W82=1,H82,I82*(1+S82)),"") -> 4393.7905 | Z82: =IFERROR(IF($W82=1,K82,L82*(1+T82)),"") -> 21085032 | AA82: =IFERROR(IF($W82=1,N82,O82*(1+U82)),"") -> 56836694
D83: =_xlfn.CONCAT(E83," - ",_xlfn.XLOOKUP(F83,$C$13:$C$24,$E$13:$E$24,"")) -> Wholesale - AUG | E83: Wholesale | F83: 8 | G83: 4322 | I83: 4959.37 | J83: 19399951 | L83: 22879207 | M83: 52553355 | O83: 63075452 | S83: =IFERROR(SUMPRODUCT(H$76:H$87,$W$76:$W$87)/SUMPRODUCT(I$76:I$87,$W$76:$W$87)-1,"") -> -0.092791843 | T83: =IFERROR(SUMPRODUCT(K$76:K$87,$W$76:$W$87)/SUMPRODUCT(L$76:L$87,$W$76:$W$87)-1,"") -> -0.064861734 | U83: =IFERROR(SUMPRODUCT(N$76:N$87,$W$76:$W$87)/SUMPRODUCT(O$76:O$87,$W$76:$W$87)-1,"") -> -0.086973277 | W83: =IFERROR(_xlfn.XLOOKUP(F83,$F$13:$F$24,$W$13:$W$24),"") -> 0 | Y83: =IFERROR(IF($W83=1,H83,I83*(1+S83)),"") -> 4499.1809 | Z83: =IFERROR(IF($W83=1,K83,L83*(1+T83)),"") -> 21395222 | AA83: =IFERROR(IF($W83=1,N83,O83*(1+U83)),"") -> 57589573
D84: =_xlfn.CONCAT(E84," - ",_xlfn.XLOOKUP(F84,$C$13:$C$24,$E$13:$E$24,"")) -> Wholesale - SEP | E84: Wholesale | F84: 9 | G84: 4652 | I84: 5038.56 | J84: 21068688 | L84: 23321485 | M84: 57298220 | O84: 64325944 | S84: =IFERROR(SUMPRODUCT(H$76:H$87,$W$76:$W$87)/SUMPRODUCT(I$76:I$87,$W$76:$W$87)-1,"") -> -0.092791843 | T84: =IFERROR(SUMPRODUCT(K$76:K$87,$W$76:$W$87)/SUMPRODUCT(L$76:L$87,$W$76:$W$87)-1,"") -> -0.064861734 | U84: =IFERROR(SUMPRODUCT(N$76:N$87,$W$76:$W$87)/SUMPRODUCT(O$76:O$87,$W$76:$W$87)-1,"") -> -0.086973277 | W84: =IFERROR(_xlfn.XLOOKUP(F84,$F$13:$F$24,$W$13:$W$24),"") -> 0 | Y84: =IFERROR(IF($W84=1,H84,I84*(1+S84)),"") -> 4571.0227 | Z84: =IFERROR(IF($W84=1,K84,L84*(1+T84)),"") -> 21808813 | AA84: =IFERROR(IF($W84=1,N84,O84*(1+U84)),"") -> 58731306
D85: =_xlfn.CONCAT(E85," - ",_xlfn.XLOOKUP(F85,$C$13:$C$24,$E$13:$E$24,"")) -> Wholesale - OCT | E85: Wholesale | F85: 10 | G85: 5184 | I85: 5252.7 | J85: 23712503 | L85: 24519461 | M85: 64636014 | O85: 67819428 | S85: =IFERROR(SUMPRODUCT(H$76:H$87,$W$76:$W$87)/SUMPRODUCT(I$76:I$87,$W$76:$W$87)-1,"") -> -0.092791843 | T85: =IFERROR(SUMPRODUCT(K$76:K$87,$W$76:$W$87)/SUMPRODUCT(L$76:L$87,$W$76:$W$87)-1,"") -> -0.064861734 | U85: =IFERROR(SUMPRODUCT(N$76:N$87,$W$76:$W$87)/SUMPRODUCT(O$76:O$87,$W$76:$W$87)-1,"") -> -0.086973277 | W85: =IFERROR(_xlfn.XLOOKUP(F85,$F$13:$F$24,$W$13:$W$24),"") -> 0 | Y85: =IFERROR(IF($W85=1,H85,I85*(1+S85)),"") -> 4765.2923 | Z85: =IFERROR(IF($W85=1,K85,L85*(1+T85)),"") -> 22929086 | AA85: =IFERROR(IF($W85=1,N85,O85*(1+U85)),"") -> 61920950
D86: =_xlfn.CONCAT(E86," - ",_xlfn.XLOOKUP(F86,$C$13:$C$24,$E$13:$E$24,"")) -> Wholesale - NOV | E86: Wholesale | F86: 11 | G86: 6566 | I86: 5594.92 | J86: 29916699 | L86: 26019635 | M86: 81353959 | O86: 71977919 | S86: =IFERROR(SUMPRODUCT(H$76:H$87,$W$76:$W$87)/SUMPRODUCT(I$76:I$87,$W$76:$W$87)-1,"") -> -0.092791843 | T86: =IFERROR(SUMPRODUCT(K$76:K$87,$W$76:$W$87)/SUMPRODUCT(L$76:L$87,$W$76:$W$87)-1,"") -> -0.064861734 | U86: =IFERROR(SUMPRODUCT(N$76:N$87,$W$76:$W$87)/SUMPRODUCT(O$76:O$87,$W$76:$W$87)-1,"") -> -0.086973277 | W86: =IFERROR(_xlfn.XLOOKUP(F86,$F$13:$F$24,$W$13:$W$24),"") -> 0 | Y86: =IFERROR(IF($W86=1,H86,I86*(1+S86)),"") -> 5075.7571 | Z86: =IFERROR(IF($W86=1,K86,L86*(1+T86)),"") -> 24331956 | AA86: =IFERROR(IF($W86=1,N86,O86*(1+U86)),"") -> 65717764
D87: =_xlfn.CONCAT(E87," - ",_xlfn.XLOOKUP(F87,$C$13:$C$24,$E$13:$E$24,"")) -> Wholesale - DEC | E87: Wholesale | F87: 12 | G87: 7660 | I87: 5647.45 | J87: 34936972 | L87: 26183154 | M87: 94869774 | O87: 72355200 | S87: =IFERROR(SUMPRODUCT(H$76:H$87,$W$76:$W$87)/SUMPRODUCT(I$76:I$87,$W$76:$W$87)-1,"") -> -0.092791843 | T87: =IFERROR(SUMPRODUCT(K$76:K$87,$W$76:$W$87)/SUMPRODUCT(L$76:L$87,$W$76:$W$87)-1,"") -> -0.064861734 | U87: =IFERROR(SUMPRODUCT(N$76:N$87,$W$76:$W$87)/SUMPRODUCT(O$76:O$87,$W$76:$W$87)-1,"") -> -0.086973277 | W87: =IFERROR(_xlfn.XLOOKUP(F87,$F$13:$F$24,$W$13:$W$24),"") -> 0 | Y87: =IFERROR(IF($W87=1,H87,I87*(1+S87)),"") -> 5123.4127 | Z87: =IFERROR(IF($W87=1,K87,L87*(1+T87)),"") -> 24484869 | AA87: =IFERROR(IF($W87=1,N87,O87*(1+U87)),"") -> 66062231
E88: Grand Total | G88: 70972 | H88: 32888 | I88: 74712.84 | J88: 3.2230053e+08 | K88: 1.5664026e+08 | L88: 3.4585199e+08 | M88: 9.5278736e+08 | N88: 4.6270906e+08 | O88: 1.0443122e+09 | Y88: =IFERROR(SUM(Y64:Y87),"") -> 68036.705 | Z88: =IFERROR(SUM(Z64:Z87),"") -> 3.249552e+08 | AA88: =IFERROR(SUM(AA64:AA87),"") -> 9.6090182e+08
D89: =E89 -> Boutique | E89: Boutique | G89: =SUMIF($E$64:$E$87,$E89,G$64:G$87) -> 12157 | H89: =SUMIF($E$64:$E$87,$E89,H$64:H$87) -> 6281 | I89: =SUMIF($E$64:$E$87,$E89,I$64:I$87) -> 14048.2 | J89: =SUMIF($E$64:$E$87,$E89,J$64:J$87) -> 55404604 | K89: =SUMIF($E$64:$E$87,$E89,K$64:K$87) -> 30114590 | L89: =SUMIF($E$64:$E$87,$E89,L$64:L$87) -> 65079980 | M89: =SUMIF($E$64:$E$87,$E89,M$64:M$87) -> 2.2739209e+08 | N89: =SUMIF($E$64:$E$87,$E89,N$64:N$87) -> 1.224473e+08 | O89: =SUMIF($E$64:$E$87,$E89,O$64:O$87) -> 2.6983289e+08 | Y89: =IFERROR(SUMIF($E$64:$E$87,$E89,Y$64:Y$87),"") -> 13001.249 | Z89: =IFERROR(SUMIF($E$64:$E$87,$E89,Z$64:Z$87),"") -> 62394552 | AA89: =IFERROR(SUMIF($E$64:$E$87,$E89,AA$64:AA$87),"") -> 2.5378155e+08
D90: =E90 -> Wholesale | E90: Wholesale | G90: =SUMIF($E$64:$E$87,$E90,G$64:G$87) -> 58815 | H90: =SUMIF($E$64:$E$87,$E90,H$64:H$87) -> 26607 | I90: =SUMIF($E$64:$E$87,$E90,I$64:I$87) -> 60664.64 | J90: =SUMIF($E$64:$E$87,$E90,J$64:J$87) -> 2.6689593e+08 | K90: =SUMIF($E$64:$E$87,$E90,K$64:K$87) -> 1.2652567e+08 | L90: =SUMIF($E$64:$E$87,$E90,L$64:L$87) -> 2.8077201e+08 | M90: =SUMIF($E$64:$E$87,$E90,M$64:M$87) -> 7.2539527e+08 | N90: =SUMIF($E$64:$E$87,$E90,N$64:N$87) -> 3.4026175e+08 | O90: =SUMIF($E$64:$E$87,$E90,O$64:O$87) -> 7.7447927e+08 | Y90: =IFERROR(SUMIF($E$64:$E$87,$E90,Y$64:Y$87),"") -> 55035.456 | Z90: =IFERROR(SUMIF($E$64:$E$87,$E90,Z$64:Z$87),"") -> 2.6256065e+08 | AA90: =IFERROR(SUMIF($E$64:$E$87,$E90,AA$64:AA$87),"") -> 7.0712027e+08
E93: COLLECTION
G94: Values | H94: scenario
G95: Sum of units | J95: Sum of cogs | M95: Sum of revenue | S95: Sum of units | T95: Sum of cogs | U95: Sum of revenue | W95: Actuals | Y95: Forecast
E96: collection | F96: month | G96: 2025 Actuals | H96: 2026 Actuals | I96: 2026 Budget | J96: 2025 Actuals | K96: 2026 Actuals | L96: 2026 Budget | M96: 2025 Actuals | N96: 2026 Actuals | O96: 2026 Budget | S96: vs LY | T96: vs LY | U96: vs LY | W96: Multiplier | Y96: Units | Z96: Cogs | AA96: Revenue
E97: Atelier | F97: 1 | G97: 563 | H97: 594 | I97: 674.54 | J97: 3655716 | K97: 4078101.5 | L97: 4476287.9 | M97: 11434328 | N97: 12755481 | O97: 14384504 | S97: =IFERROR(SUMPRODUCT(H$97:H$108,$W$97:$W$108)/SUMPRODUCT(I$97:I$108,$W$97:$W$108)-1,"") -> -0.090195671 | T97: =IFERROR(SUMPRODUCT(K$97:K$108,$W$97:$W$108)/SUMPRODUCT(L$97:L$108,$W$97:$W$108)-1,"") -> -0.052843832 | U97: =IFERROR(SUMPRODUCT(N$97:N$108,$W$97:$W$108)/SUMPRODUCT(O$97:O$108,$W$97:$W$108)-1,"") -> -0.083429429 | W97: =IFERROR(_xlfn.XLOOKUP(F97,$F$13:$F$24,$W$13:$W$24),"") -> 1 | Y97: =IFERROR(IF($W97=1,H97,I97*(1+S97)),"") -> 594 | Z97: =IFERROR(IF($W97=1,K97,L97*(1+T97)),"") -> 4078101.5 | AA97: =IFERROR(IF($W97=1,N97,O97*(1+U97)),"") -> 12755481
E98: Atelier | F98: 2 | G98: 533 | H98: 552 | I98: 680.09 | J98: 3462143.9 | K98: 3785627.2 | L98: 4513118.1 | M98: 10835320 | N98: 11866432 | O98: 14556324 | S98: =IFERROR(SUMPRODUCT(H$97:H$108,$W$97:$W$108)/SUMPRODUCT(I$97:I$108,$W$97:$W$108)-1,"") -> -0.090195671 | T98: =IFERROR(SUMPRODUCT(K$97:K$108,$W$97:$W$108)/SUMPRODUCT(L$97:L$108,$W$97:$W$108)-1,"") -> -0.052843832 | U98: =IFERROR(SUMPRODUCT(N$97:N$108,$W$97:$W$108)/SUMPRODUCT(O$97:O$108,$W$97:$W$108)-1,"") -> -0.083429429 | W98: =IFERROR(_xlfn.XLOOKUP(F98,$F$13:$F$24,$W$13:$W$24),"") -> 1 | Y98: =IFERROR(IF($W98=1,H98,I98*(1+S98)),"") -> 552 | Z98: =IFERROR(IF($W98=1,K98,L98*(1+T98)),"") -> 3785627.2 | AA98: =IFERROR(IF($W98=1,N98,O98*(1+U98)),"") -> 11866432
E99: Atelier | F99: 3 | G99: 715 | H99: 757 | I99: 704.93 | J99: 4628276.9 | K99: 5185998.1 | L99: 4677957.8 | M99: 14509446 | N99: 16174790 | O99: 15071258 | S99: =IFERROR(SUMPRODUCT(H$97:H$108,$W$97:$W$108)/SUMPRODUCT(I$97:I$108,$W$97:$W$108)-1,"") -> -0.090195671 | T99: =IFERROR(SUMPRODUCT(K$97:K$108,$W$97:$W$108)/SUMPRODUCT(L$97:L$108,$W$97:$W$108)-1,"") -> -0.052843832 | U99: =IFERROR(SUMPRODUCT(N$97:N$108,$W$97:$W$108)/SUMPRODUCT(O$97:O$108,$W$97:$W$108)-1,"") -> -0.083429429 | W99: =IFERROR(_xlfn.XLOOKUP(F99,$F$13:$F$24,$W$13:$W$24),"") -> 1 | Y99: =IFERROR(IF($W99=1,H99,I99*(1+S99)),"") -> 757 | Z99: =IFERROR(IF($W99=1,K99,L99*(1+T99)),"") -> 5185998.1 | AA99: =IFERROR(IF($W99=1,N99,O99*(1+U99)),"") -> 16174790
E100: Atelier | F100: 4 | G100: 582 | H100: 609 | I100: 709 | J100: 3846761.7 | K100: 4285572.7 | L100: 4704966.6 | M100: 12210727 | N100: 13367118 | O100: 15145232 | S100: =IFERROR(SUMPRODUCT(H$97:H$108,$W$97:$W$108)/SUMPRODUCT(I$97:I$108,$W$97:$W$108)-1,"") -> -0.090195671 | T100: =IFERROR(SUMPRODUCT(K$97:K$108,$W$97:$W$108)/SUMPRODUCT(L$97:L$108,$W$97:$W$108)-1,"") -> -0.052843832 | U100: =IFERROR(SUMPRODUCT(N$97:N$108,$W$97:$W$108)/SUMPRODUCT(O$97:O$108,$W$97:$W$108)-1,"") -> -0.083429429 | W100: =IFERROR(_xlfn.XLOOKUP(F100,$F$13:$F$24,$W$13:$W$24),"") -> 1 | Y100: =IFERROR(IF($W100=1,H100,I100*(1+S100)),"") -> 609 | Z100: =IFERROR(IF($W100=1,K100,L100*(1+T100)),"") -> 4285572.7 | AA100: =IFERROR(IF($W100=1,N100,O100*(1+U100)),"") -> 13367118
E101: Atelier | F101: 5 | G101: 691 | H101: 719 | I101: 732.06 | J101: 4536445.3 | K101: 5003365.3 | L101: 4857994.1 | M101: 14502226 | N101: 15695833 | O101: 15684895 | S101: =IFERROR(SUMPRODUCT(H$97:H$108,$W$97:$W$108)/SUMPRODUCT(I$97:I$108,$W$97:$W$108)-1,"") -> -0.090195671 | T101: =IFERROR(SUMPRODUCT(K$97:K$108,$W$97:$W$108)/SUMPRODUCT(L$97:L$108,$W$97:$W$108)-1,"") -> -0.052843832 | U101: =IFERROR(SUMPRODUCT(N$97:N$108,$W$97:$W$108)/SUMPRODUCT(O$97:O$108,$W$97:$W$108)-1,"") -> -0.083429429 | W101: =IFERROR(_xlfn.XLOOKUP(F101,$F$13:$F$24,$W$13:$W$24),"") -> 1 | Y101: =IFERROR(IF($W101=1,H101,I101*(1+S101)),"") -> 719 | Z101: =IFERROR(IF($W101=1,K101,L101*(1+T101)),"") -> 5003365.3 | AA101: =IFERROR(IF($W101=1,N101,O101*(1+U101)),"") -> 15695833
E102: Atelier | F102: 6 | G102: 584 | H102: 618 | I102: 729.96 | J102: 3781876 | K102: 4252160 | L102: 4844058.4 | M102: 11851089 | N102: 13064040 | O102: 15629484 | S102: =IFERROR(SUMPRODUCT(H$97:H$108,$W$97:$W$108)/SUMPRODUCT(I$97:I$108,$W$97:$W$108)-1,"") -> -0.090195671 | T102: =IFERROR(SUMPRODUCT(K$97:K$108,$W$97:$W$108)/SUMPRODUCT(L$97:L$108,$W$97:$W$108)-1,"") -> -0.052843832 | U102: =IFERROR(SUMPRODUCT(N$97:N$108,$W$97:$W$108)/SUMPRODUCT(O$97:O$108,$W$97:$W$108)-1,"") -> -0.083429429 | W102: =IFERROR(_xlfn.XLOOKUP(F102,$F$13:$F$24,$W$13:$W$24),"") -> 1 | Y102: =IFERROR(IF($W102=1,H102,I102*(1+S102)),"") -> 618 | Z102: =IFERROR(IF($W102=1,K102,L102*(1+T102)),"") -> 4252160 | AA102: =IFERROR(IF($W102=1,N102,O102*(1+U102)),"") -> 13064040
E103: Atelier | F103: 7 | G103: 655 | I103: 715.19 | J103: 4261121.1 | L103: 4746043.7 | M103: 13375016 | O103: 15289199 | S103: =IFERROR(SUMPRODUCT(H$97:H$108,$W$97:$W$108)/SUMPRODUCT(I$97:I$108,$W$97:$W$108)-1,"") -> -0.090195671 | T103: =IFERROR(SUMPRODUCT(K$97:K$108,$W$97:$W$108)/SUMPRODUCT(L$97:L$108,$W$97:$W$108)-1,"") -> -0.052843832 | U103: =IFERROR(SUMPRODUCT(N$97:N$108,$W$97:$W$108)/SUMPRODUCT(O$97:O$108,$W$97:$W$108)-1,"") -> -0.083429429 | W103: =IFERROR(_xlfn.XLOOKUP(F103,$F$13:$F$24,$W$13:$W$24),"") -> 0 | Y103: =IFERROR(IF($W103=1,H103,I103*(1+S103)),"") -> 650.68296 | Z103: =IFERROR(IF($W103=1,K103,L103*(1+T103)),"") -> 4495244.6 | AA103: =IFERROR(IF($W103=1,N103,O103*(1+U103)),"") -> 14013629
E104: Atelier | F104: 8 | G104: 620 | I104: 712.85 | J104: 3991183.7 | L104: 4730515.4 | M104: 12640736 | O104: 15253137 | S104: =IFERROR(SUMPRODUCT(H$97:H$108,$W$97:$W$108)/SUMPRODUCT(I$97:I$108,$W$97:$W$108)-1,"") -> -0.090195671 | T104: =IFERROR(SUMPRODUCT(K$97:K$108,$W$97:$W$108)/SUMPRODUCT(L$97:L$108,$W$97:$W$108)-1,"") -> -0.052843832 | U104: =IFERROR(SUMPRODUCT(N$97:N$108,$W$97:$W$108)/SUMPRODUCT(O$97:O$108,$W$97:$W$108)-1,"") -> -0.083429429 | W104: =IFERROR(_xlfn.XLOOKUP(F104,$F$13:$F$24,$W$13:$W$24),"") -> 0 | Y104: =IFERROR(IF($W104=1,H104,I104*(1+S104)),"") -> 648.55402 | Z104: =IFERROR(IF($W104=1,K104,L104*(1+T104)),"") -> 4480536.8 | AA104: =IFERROR(IF($W104=1,N104,O104*(1+U104)),"") -> 13980577
E105: Atelier | F105: 9 | G105: 660 | I105: 744.37 | J105: 4269556.3 | L105: 4939684 | M105: 13724616 | O105: 15935277 | S105: =IFERROR(SUMPRODUCT(H$97:H$108,$W$97:$W$108)/SUMPRODUCT(I$97:I$108,$W$97:$W$108)-1,"") -> -0.090195671 | T105: =IFERROR(SUMPRODUCT(K$97:K$108,$W$97:$W$108)/SUMPRODUCT(L$97:L$108,$W$97:$W$108)-1,"") -> -0.052843832 | U105: =IFERROR(SUMPRODUCT(N$97:N$108,$W$97:$W$108)/SUMPRODUCT(O$97:O$108,$W$97:$W$108)-1,"") -> -0.083429429 | W105: =IFERROR(_xlfn.XLOOKUP(F105,$F$13:$F$24,$W$13:$W$24),"") -> 0 | Y105: =IFERROR(IF($W105=1,H105,I105*(1+S105)),"") -> 677.23105 | Z105: =IFERROR(IF($W105=1,K105,L105*(1+T105)),"") -> 4678652.1 | AA105: =IFERROR(IF($W105=1,N105,O105*(1+U105)),"") -> 14605806
E106: Atelier | F106: 10 | G106: 757 | I106: 796.99 | J106: 4909078.5 | L106: 5288873.5 | M106: 15406675 | O106: 16971808 | S106: =IFERROR(SUMPRODUCT(H$97:H$108,$W$97:$W$108)/SUMPRODUCT(I$97:I$108,$W$97:$W$108)-1,"") -> -0.090195671 | T106: =IFERROR(SUMPRODUCT(K$97:K$108,$W$97:$W$108)/SUMPRODUCT(L$97:L$108,$W$97:$W$108)-1,"") -> -0.052843832 | U106: =IFERROR(SUMPRODUCT(N$97:N$108,$W$97:$W$108)/SUMPRODUCT(O$97:O$108,$W$97:$W$108)-1,"") -> -0.083429429 | W106: =IFERROR(_xlfn.XLOOKUP(F106,$F$13:$F$24,$W$13:$W$24),"") -> 0 | Y106: =IFERROR(IF($W106=1,H106,I106*(1+S106)),"") -> 725.10495 | Z106: =IFERROR(IF($W106=1,K106,L106*(1+T106)),"") -> 5009389.1 | AA106: =IFERROR(IF($W106=1,N106,O106*(1+U106)),"") -> 15555860
E107: Atelier | F107: 11 | G107: 943 | I107: 805.61 | J107: 6123942.9 | L107: 5346076.3 | M107: 19242329 | O107: 17212024 | S107: =IFERROR(SUMPRODUCT(H$97:H$108,$W$97:$W$108)/SUMPRODUCT(I$97:I$108,$W$97:$W$108)-1,"") -> -0.090195671 | T107: =IFERROR(SUMPRODUCT(K$97:K$108,$W$97:$W$108)/SUMPRODUCT(L$97:L$108,$W$97:$W$108)-1,"") -> -0.052843832 | U107: =IFERROR(SUMPRODUCT(N$97:N$108,$W$97:$W$108)/SUMPRODUCT(O$97:O$108,$W$97:$W$108)-1,"") -> -0.083429429 | W107: =IFERROR(_xlfn.XLOOKUP(F107,$F$13:$F$24,$W$13:$W$24),"") -> 0 | Y107: =IFERROR(IF($W107=1,H107,I107*(1+S107)),"") -> 732.94747 | Z107: =IFERROR(IF($W107=1,K107,L107*(1+T107)),"") -> 5063569.1 | AA107: =IFERROR(IF($W107=1,N107,O107*(1+U107)),"") -> 15776035
...
